Workbook

Sheet Empezar aquí
A2: Homologación de Farmacia: empezar aquí
A3: Neuquén, San Juan y Salta + SAP · 284 ítems únicos del master · incorporación de SAP al 25/09/2026.
A4: ="SAP: "&B43&" coincidencias de confianza alta · "&SUM(B44:B46)&" ítems para revisar · "&B47&" sin candidato. Empezá por la hoja Master vs SAP." -> SAP: 170 coincidencias de confianza alta · 97 ítems para revisar · 17 sin candidato. Empezá por la hoja Master vs SAP.
A5: Base / sistema | B5: Ítems del master | C5: Homologados | D5: Sin equivalente confirmado | E5: Pendientes de resolver
A6: Neuquén | B6: =COUNTA(Neuquén!A8:A291) -> 284 | C6: =COUNTIFS(Neuquén!O8:O291,"Homologado") -> 0 | D6: =COUNTIFS(Neuquén!O8:O291,"Sin equivalente confirmado") -> 0 | E6: =B6-C6-D6 -> 284
A7: San Juan | B7: =COUNTA('San Juan'!A8:A291) -> 284 | C7: =COUNTIFS('San Juan'!O8:O291,"Homologado") -> 0 | D7: =COUNTIFS('San Juan'!O8:O291,"Sin equivalente confirmado") -> 0 | E7: =B7-C7-D7 -> 284
A8: Salta | B8: =COUNTA(Salta!A8:A291) -> 284 | C8: =COUNTIFS(Salta!O8:O291,"Homologado") -> 0 | D8: =COUNTIFS(Salta!O8:O291,"Sin equivalente confirmado") -> 0 | E8: =B8-C8-D8 -> 284
A9: SAP (cruce único) | B9: =COUNTA('Master vs SAP'!A8:A291) -> 284 | C9: =COUNTIFS('Master vs SAP'!O8:O291,"Homologado") -> 0 | D9: =COUNTIFS('Master vs SAP'!O8:O291,"Sin equivalente confirmado") -> 0 | E9: =B9-C9-D9 -> 284
A10: Resultado del cruce de Salta | B10: Cuenta ítems del master, no códigos únicos ni aprobaciones. Un código puede aparecer en más de un componente.
A11: Clasificación | B11: Cantidad | C11: Qué significa
A12: Coincidencia | B12: =COUNTIFS(Salta!$F$8:$F$291,A12) -> 120 | C12: Las características explícitas coinciden. La base todavía debe validar.
A13: Revisar presentación | B13: =COUNTIFS(Salta!$F$8:$F$291,A13) -> 8 | C13: Mismo ítem o familia, pero cambia dosis, concentración, volumen, forma o calibre.
A14: Revisar datos | B14: =COUNTIFS(Salta!$F$8:$F$291,A14) -> 61 | C14: Falta un dato o hay una unidad/denominación ambigua. No se presume que coincida.
A15: Revisar grupo | B15: =COUNTIFS(Salta!$F$8:$F$291,A15) -> 22 | C15: El master agrupa variantes o componentes. Hay que confirmar cobertura y códigos.
A16: Sin coincidencia | B16: =COUNTIFS(Salta!$F$8:$F$291,A16) -> 73 | C16: No se identificó candidato en este inventario; no prueba ausencia en AVAIN.
A18: Cómo usar este archivo | B18: Cada base y SAP tienen su revisión independiente. El catálogo enlaza todos los códigos por el ID común.
A19: 1. Abrí la hoja a revisar | B19: Abrí Neuquén, San Juan, Salta o Master vs SAP. D/E: candidatos. F: clasificación. G: confianza. H: detalle de lo que debe revisarse.
A20: 2. Revisá las diferencias | B20: Filtrá F por Revisar presentación para ver las diferencias comprobadas. Revisar datos indica información faltante o ambigua.
A21: 3. Completá el amarillo | B21: I: decisión. J/K: código y nombre confirmados. L/M: validadores de producto y código. N: fecha. En SAP, usar los datos del material SAP.
A22: 4. Verificá el cierre | B22: O indica qué falta. Sin equivalente exige validadores y fecha, con J/K vacíos. En Master vs SAP elegí Sin equivalente en SAP.
A23: 5. Consultá el catálogo | B23: Catálogo común integra las tres bases y SAP: P:R reciben códigos de bases homologados; S:V muestran candidatos SAP; W recibe el SAP homologado.
A25: Cómo leer la confianza | B25: Describe la evidencia del cruce; no reemplaza la validación del producto y del código.
A26: Alta | B26: Coincidencia respaldada por la descripción disponible. En Salta y SAP, coinciden los atributos que explicita el ítem del master.
A27: Media | B27: Candidato plausible, pero falta información, hay variantes agrupadas o una diferencia de volumen/presentación que requiere resolver.
A28: Baja / Sin coincidencia | B28: Baja: hay una incompatibilidad importante o evidencia débil. Sin coincidencia: no hay candidato respaldado; revisar observaciones.
A29: Origen de la confianza | B29: Salta/SAP: evaluados en sus respectivos cruces. Neuquén/San Juan: confianza histórica ajustada ante conflictos; se conserva el valor original.
A30: Marcas y presentaciones | B30: Una marca distinta, con el mismo ítem, sólo va en observaciones. Una diferencia real de presentación se clasifica Revisar presentación.
... A42: Resultado inicial SAP | B42: Un solo cruce contra Ítem que pide el master. No se reutilizan coincidencias de las bases para inferir SAP.
A43: Coincidencia | B43: =COUNTIFS('Master vs SAP'!$F$8:$F$291,A43) -> 170 | C43: Los atributos explícitos coinciden. Los responsables de producto y SAP todavía deben validar.
A44: Revisar presentación | B44: =COUNTIFS('Master vs SAP'!$F$8:$F$291,A44) -> 9 | C44: Mismo ítem o familia, pero cambia dosis, concentración, volumen, forma o calibre.
A45: Revisar datos | B45: =COUNTIFS('Master vs SAP'!$F$8:$F$291,A45) -> 44 | C45: Falta un dato o hay una unidad/denominación ambigua. No se presume que coincida.
A46: Revisar grupo | B46: =COUNTIFS('Master vs SAP'!$F$8:$F$291,A46) -> 44 | C46: El master agrupa variantes o componentes. Hay que confirmar cobertura y códigos.
A47: Sin coincidencia | B47: =COUNTIFS('Master vs SAP'!$F$8:$F$291,A47) -> 17 | C47: No se identificó candidato en la hoja SAP recibida; no prueba ausencia en todo SAP.
A49: Varios materiales SAP | B49: Puede haber varios códigos para un ítem: duplicados, marcas o variantes. D/E conservan el mismo orden; H indica qué elegir o confirmar.
A50: Trazabilidad completa | B50: El catálogo relaciona las cuatro codificaciones por ID común. Un candidato de confianza alta sigue pendiente hasta completar su validación.

Sheet Catálogo común
A2: Catálogo común · Neuquén, San Juan, Salta y SAP
A3: Una fila por ID del master. Para revisar, usá la hoja de la provincia o la hoja Master vs SAP.
A4: D:O = candidatos de las bases · P:R = códigos de bases homologados · S:V = candidatos SAP · W = código SAP homologado.
A5: La clasificación del cruce no equivale a aprobación. Códigos múltiples y nombres se muestran en el mismo orden.
D6: Neuquén · cruce inicial | H6: San Juan · cruce inicial | L6: Salta · cruce inicial | P6: Sólo códigos homologados | S6: SAP · cruce único con el master | W6: Sólo código homologado
A7: ID común propuesto | B7: Tipo de ítem | C7: Nombre común propuesto (master) | D7: Códigos Base Neuquén | E7: Nomenclatura Base Neuquén | F7: Confianza Neuquén | G7: Clasificación Neuquén | H7: Códigos Base San Juan | I7: Nomenclatura Base San Juan | J7: Confianza San Juan | K7: Clasificación San Juan | L7: Códigos Base Salta | M7: Nomenclatura Base Salta | N7: Confianza Salta | O7: Clasificación Salta | P7: Código Neuquén confirmado | Q7: Código San Juan confirmado | R7: Código Salta confirmado | S7: Códigos SAP | T7: Nomenclatura SAP | U7: Nivel de confianza SAP | V7: Clasificación SAP | W7: Código SAP confirmado
A8: M01-001 | B8: Medicación | C8: Ácido acetilsalicílico 100 mg | D8: =IF(VLOOKUP($A8,Neuquén!$A$8:$O$291,4,FALSE)="","",VLOOKUP($A8,Neuquén!$A$8:$O$291,4,FALSE)) -> 23 | E8: =IF(VLOOKUP($A8,Neuquén!$A$8:$O$291,5,FALSE)="","",VLOOKUP($A8,Neuquén!$A$8:$O$291,5,FALSE)) -> ASPIRINA | F8: =IF(VLOOKUP($A8,Neuquén!$A$8:$O$291,7,FALSE)="","",VLOOKUP($A8,Neuquén!$A$8:$O$291,7,FALSE)) -> Alta | G8: =IF(VLOOKUP($A8,Neuquén!$A$8:$O$291,6,FALSE)="","",VLOOKUP($A8,Neuquén!$A$8:$O$291,6,FALSE)) -> Coincidencia por validar | H8: =IF(VLOOKUP($A8,'San Juan'!$A$8:$O$291,4,FALSE)="","",VLOOKUP($A8,'San Juan'!$A$8:$O$291,4,FALSE)) -> MED4 | I8: =IF(VLOOKUP($A8,'San Juan'!$A$8:$O$291,5,FALSE)="","",VLOOKUP($A8,'San Juan'!$A$8:$O$291,5,FALSE)) -> Acido Acetil Salicílico Comp x 100 mg | J8: =IF(VLOOKUP($A8,'San Juan'!$A$8:$O$291,7,FALSE)="","",VLOOKUP($A8,'San Juan'!$A$8:$O$291,7,FALSE)) -> Alta | K8: =IF(VLOOKUP($A8,'San Juan'!$A$8:$O$291,6,FALSE)="","",VLOOKUP($A8,'San Juan'!$A$8:$O$291,6,FALSE)) -> Coincidencia por validar | L8: =IF(VLOOKUP($A8,Salta!$A$8:$O$291,4,FALSE)="","",VLOOKUP($A8,Salta!$A$8:$O$291,4,FALSE)) -> 410 | M8: =IF(VLOOKUP($A8,Salta!$A$8:$O$291,5,FALSE)="","",VLOOKUP($A8,Salta!$A$8:$O$291,5,FALSE)) -> Aspirina comprimidos 100mg | N8: =IF(VLOOKUP($A8,Salta!$A$8:$O$291,7,FALSE)="","",VLOOKUP($A8,Salta!$A$8:$O$291,7,FALSE)) -> Alta | O8: =IF(VLOOKUP($A8,Salta!$A$8:$O$291,6,FALSE)="","",VLOOKUP($A8,Salta!$A$8:$O$291,6,FALSE)) -> Coincidencia | P8: =IF(VLOOKUP($A8,Neuquén!$A$8:$O$291,15,FALSE)="Homologado",VLOOKUP($A8,Neuquén!$A$8:$O$291,10,FALSE),"") | Q8: =IF(VLOOKUP($A8,'San Juan'!$A$8:$O$291,15,FALSE)="Homologado",VLOOKUP($A8,'San Juan'!$A$8:$O$291,10,FALSE),"") | R8: =IF(VLOOKUP($A8,Salta!$A$8:$O$291,15,FALSE)="Homologado",VLOOKUP($A8,Salta!$A$8:$O$291,10,FALSE),"") | S8: =IF(VLOOKUP($A8,'Master vs SAP'!$A$8:$O$291,4,FALSE)="","",VLOOKUP($A8,'Master vs SAP'!$A$8:$O$291,4,FALSE)) -> 1001237 1000802 1000136 | T8: =IF(VLOOKUP($A8,'Master vs SAP'!$A$8:$O$291,5,FALSE)="","",VLOOKUP($A8,'Master vs SAP'!$A$8:$O$291,5,FALSE)) -> ACIDO ACETILSALICILICO 100MG ACIDO ACETILSALICILICO 100MG x 20 COMP ASPIRINA DE 100 MG | U8: =IF(VLOOKUP($A8,'Master vs SAP'!$A$8:$O$291,7,FALSE)="","",VLOOKUP($A8,'Master vs SAP'!$A$8:$O$291,7,FALSE)) -> Alta | V8: =IF(VLOOKUP($A8,'Master vs SAP'!$A$8:$O$291,6,FALSE)="","",VLOOKUP($A8,'Master vs SAP'!$A$8:$O$291,6,FALSE)) -> Coincidencia | W8: =IF(VLOOKUP($A8,'Master vs SAP'!$A$8:$O$291,15,FALSE)="Homologado",VLOOKUP($A8,'Master vs SAP'!$A$8:$O$291,10,FALSE),"")
A9: M01-002 | B9: Medicación | C9: Diclofenac 75 mg comp. | D9: =IF(VLOOKUP($A9,Neuquén!$A$8:$O$291,4,FALSE)="","",VLOOKUP($A9,Neuquén!$A$8:$O$291,4,FALSE)) -> 83 | E9: =IF(VLOOKUP($A9,Neuquén!$A$8:$O$291,5,FALSE)="","",VLOOKUP($A9,Neuquén!$A$8:$O$291,5,FALSE)) -> DICLOFENAC75COMP | F9: =IF(VLOOKUP($A9,Neuquén!$A$8:$O$291,7,FALSE)="","",VLOOKUP($A9,Neuquén!$A$8:$O$291,7,FALSE)) -> Alta | G9: =IF(VLOOKUP($A9,Neuquén!$A$8:$O$291,6,FALSE)="","",VLOOKUP($A9,Neuquén!$A$8:$O$291,6,FALSE)) -> Coincidencia por validar | H9: =IF(VLOOKUP($A9,'San Juan'!$A$8:$O$291,4,FALSE)="","",VLOOKUP($A9,'San Juan'!$A$8:$O$291,4,FALSE)) -> DES001 | I9: =IF(VLOOKUP($A9,'San Juan'!$A$8:$O$291,5,FALSE)="","",VLOOKUP($A9,'San Juan'!$A$8:$O$291,5,FALSE)) -> Diclofenac Comp x 75mg | J9: =IF(VLOOKUP($A9,'San Juan'!$A$8:$O$291,7,FALSE)="","",VLOOKUP($A9,'San Juan'!$A$8:$O$291,7,FALSE)) -> Alta | K9: =IF(VLOOKUP($A9,'San Juan'!$A$8:$O$291,6,FALSE)="","",VLOOKUP($A9,'San Juan'!$A$8:$O$291,6,FALSE)) -> Coincidencia por validar | L9: =IF(VLOOKUP($A9,Salta!$A$8:$O$291,4,FALSE)="","",VLOOKUP($A9,Salta!$A$8:$O$291,4,FALSE)) -> 99 | M9: =IF(VLOOKUP($A9,Salta!$A$8:$O$291,5,FALSE)="","",VLOOKUP($A9,Salta!$A$8:$O$291,5,FALSE)) -> Diclofenac Sódico Comprimidos x75mg | N9: =IF(VLOOKUP($A9,Salta!$A$8:$O$291,7,FALSE)="","",VLOOKUP($A9,Salta!$A$8:$O$291,7,FALSE)) -> Alta | O9: =IF(VLOOKUP($A9,Salta!$A$8:$O$291,6,FALSE)="","",VLOOKUP($A9,Salta!$A$8:$O$291,6,FALSE)) -> Coincidencia | P9: =IF(VLOOKUP($A9,Neuquén!$A$8:$O$291,15,FALSE)="Homologado",VLOOKUP($A9,Neuquén!$A$8:$O$291,10,FALSE),"") | Q9: =IF(VLOOKUP($A9,'San Juan'!$A$8:$O$291,15,FALSE)="Homologado",VLOOKUP($A9,'San Juan'!$A$8:$O$291,10,FALSE),"") | R9: =IF(VLOOKUP($A9,Salta!$A$8:$O$291,15,FALSE)="Homologado",VLOOKUP($A9,Salta!$A$8:$O$291,10,FALSE),"") | S9: =IF(VLOOKUP($A9,'Master vs SAP'!$A$8:$O$291,4,FALSE)="","",VLOOKUP($A9,'Master vs SAP'!$A$8:$O$291,4,FALSE)) -> 1000125 | T9: =IF(VLOOKUP($A9,'Master vs SAP'!$A$8:$O$291,5,FALSE)="","",VLOOKUP($A9,'Master vs SAP'!$A$8:$O$291,5,FALSE)) -> DICLOFENAC 75 MG COMPRIMIDOS | U9: =IF(VLOOKUP($A9,'Master vs SAP'!$A$8:$O$291,7,FALSE)="","",VLOOKUP($A9,'Master vs SAP'!$A$8:$O$291,7,FALSE)) -> Alta | V9: =IF(VLOOKUP($A9,'Master vs SAP'!$A$8:$O$291,6,FALSE)="","",VLOOKUP($A9,'Master vs SAP'!$A$8:$O$291,6,FALSE)) -> Coincidencia | W9: =IF(VLOOKUP($A9,'Master vs SAP'!$A$8:$O$291,15,FALSE)="Homologado",VLOOKUP($A9,'Master vs SAP'!$A$8:$O$291,10,FALSE),"")
A10: M01-003 | B10: Medicación | C10: Diclofenac 75 mg/3 ml amp. | D10: =IF(VLOOKUP($A10,Neuquén!$A$8:$O$291,4,FALSE)="","",VLOOKUP($A10,Neuquén!$A$8:$O$291,4,FALSE)) -> 89 | E10: =IF(VLOOKUP($A10,Neuquén!$A$8:$O$291,5,FALSE)="","",VLOOKUP($A10,Neuquén!$A$8:$O$291,5,FALSE)) -> DICLOFENACSODICO75MGAMPOLLA | F10: =IF(VLOOKUP($A10,Neuquén!$A$8:$O$291,7,FALSE)="","",VLOOKUP($A10,Neuquén!$A$8:$O$291,7,FALSE)) -> Media | G10: =IF(VLOOKUP($A10,Neuquén!$A$8:$O$291,6,FALSE)="","",VLOOKUP($A10,Neuquén!$A$8:$O$291,6,FALSE)) -> Equivalencia a revisar | H10: =IF(VLOOKUP($A10,'San Juan'!$A$8:$O$291,4,FALSE)="","",VLOOKUP($A10,'San Juan'!$A$8:$O$291,4,FALSE)) -> MED62 | I10: =IF(VLOOKUP($A10,'San Juan'!$A$8:$O$291,5,FALSE)="","",VLOOKUP($A10,'San Juan'!$A$8:$O$291,5,FALSE)) -> Diclofenac 75mg Amp x 3ml | J10: =IF(VLOOKUP($A10,'San Juan'!$A$8:$O$291,7,FALSE)="","",VLOOKUP($A10,'San Juan'!$A$8:$O$291,7,FALSE)) -> Alta | K10: =IF(VLOOKUP($A10,'San Juan'!$A$8:$O$291,6,FALSE)="","",VLOOKUP($A10,'San Juan'!$A$8:$O$291,6,FALSE)) -> Coincidencia por validar | L10: =IF(VLOOKUP($A10,Salta!$A$8:$O$291,4,FALSE)="","",VLOOKUP($A10,Salta!$A$8:$O$291,4,FALSE)) -> 97 | M10: =IF(VLOOKUP($A10,Salta!$A$8:$O$291,5,FALSE)="","",VLOOKUP($A10,Salta!$A$8:$O$291,5,FALSE)) -> Diclofenac inyectable 1 amp=3ml x 75mg | N10: =IF(VLOOKUP($A10,Salta!$A$8:$O$291,7,FALSE)="","",VLOOKUP($A10,Salta!$A$8:$O$291,7,FALSE)) -> Alta | O10: =IF(VLOOKUP($A10,Salta!$A$8:$O$291,6,FALSE)="","",VLOOKUP($A10,Salta!$A$8:$O$291,6,FALSE)) -> Coincidencia | P10: =IF(VLOOKUP($A10,Neuquén!$A$8:$O$291,15,FALSE)="Homologado",VLOOKUP($A10,Neuquén!$A$8:$O$291,10,FALSE),"") | Q10: =IF(VLOOKUP($A10,'San Juan'!$A$8:$O$291,15,FALSE)="Homologado",VLOOKUP($A10,'San Juan'!$A$8:$O$291,10,FALSE),"") | R10: =IF(VLOOKUP($A10,Salta!$A$8:$O$291,15,FALSE)="Homologado",VLOOKUP($A10,Salta!$A$8:$O$291,10,FALSE),"") | S10: =IF(VLOOKUP($A10,'Master vs SAP'!$A$8:$O$291,4,FALSE)="","",VLOOKUP($A10,'Master vs SAP'!$A$8:$O$291,4,FALSE)) -> 1000045 | T10: =IF(VLOOKUP($A10,'Master vs SAP'!$A$8:$O$291,5,FALSE)="","",VLOOKUP($A10,'Master vs SAP'!$A$8:$O$291,5,FALSE)) -> DICLOFENAC 75MG AMPOLLA 3ML | U10: =IF(VLOOKUP($A10,'Master vs SAP'!$A$8:$O$291,7,FALSE)="","",VLOOKUP($A10,'Master vs SAP'!$A$8:$O$291,7,FALSE)) -> Alta | V10: =IF(VLOOKUP($A10,'Master vs SAP'!$A$8:$O$291,6,FALSE)="","",VLOOKUP($A10,'Master vs SAP'!$A$8:$O$291,6,FALSE)) -> Coincidencia | W10: =IF(VLOOKUP($A10,'Master vs SAP'!$A$8:$O$291,15,FALSE)="Homologado",VLOOKUP($A10,'Master vs SAP'!$A$8:$O$291,10,FALSE),"")
A11: M01-004 | B11: Medicación | C11: Diclofenac + Pridinol comp. | D11: =IF(VLOOKUP($A11,Neuquén!$A$8:$O$291,4,FALSE)="","",VLOOKUP($A11,Neuquén!$A$8:$O$291,4,FALSE)) -> 82 | E11: =IF(VLOOKUP($A11,Neuquén!$A$8:$O$291,5,FALSE)="","",VLOOKUP($A11,Neuquén!$A$8:$O$291,5,FALSE)) -> DICLOFENAC+PRIDINOL | F11: =IF(VLOOKUP($A11,Neuquén!$A$8:$O$291,7,FALSE)="","",VLOOKUP($A11,Neuquén!$A$8:$O$291,7,FALSE)) -> Alta | G11: =IF(VLOOKUP($A11,Neuquén!$A$8:$O$291,6,FALSE)="","",VLOOKUP($A11,Neuquén!$A$8:$O$291,6,FALSE)) -> Coincidencia por validar | H11: =IF(VLOOKUP($A11,'San Juan'!$A$8:$O$291,4,FALSE)="","",VLOOKUP($A11,'San Juan'!$A$8:$O$291,4,FALSE)) -> MED61 | I11: =IF(VLOOKUP($A11,'San Juan'!$A$8:$O$291,5,FALSE)="","",VLOOKUP($A11,'San Juan'!$A$8:$O$291,5,FALSE)) -> Diclofenac + Pridinol Comp x 50/4 mg | J11: =IF(VLOOKUP($A11,'San Juan'!$A$8:$O$291,7,FALSE)="","",VLOOKUP($A11,'San Juan'!$A$8:$O$291,7,FALSE)) -> Alta | K11: =IF(VLOOKUP($A11,'San Juan'!$A$8:$O$291,6,FALSE)="","",VLOOKUP($A11,'San Juan'!$A$8:$O$291,6,FALSE)) -> Coincidencia por validar | L11: =IF(VLOOKUP($A11,Salta!$A$8:$O$291,4,FALSE)="","",VLOOKUP($A11,Salta!$A$8:$O$291,4,FALSE)) -> 96 | M11: =IF(VLOOKUP($A11,Salta!$A$8:$O$291,5,FALSE)="","",VLOOKUP($A11,Salta!$A$8:$O$291,5,FALSE)) -> Diclofenac + Pridinol Compromidos x50/4mg | N11: =IF(VLOOKUP($A11,Salta!$A$8:$O$291,7,FALSE)="","",VLOOKUP($A11,Salta!$A$8:$O$291,7,FALSE)) -> Alta | O11: =IF(VLOOKUP($A11,Salta!$A$8:$O$291,6,FALSE)="","",VLOOKUP($A11,Salta!$A$8:$O$291,6,FALSE)) -> Coincidencia | P11: =IF(VLOOKUP($A11,Neuquén!$A$8:$O$291,15,FALSE)="Homologado",VLOOKUP($A11,Neuquén!$A$8:$O$291,10,FALSE),"") | Q11: =IF(VLOOKUP($A11,'San Juan'!$A$8:$O$291,15,FALSE)="Homologado",VLOOKUP($A11,'San Juan'!$A$8:$O$291,10,FALSE),"") | R11: =IF(VLOOKUP($A11,Salta!$A$8:$O$291,15,FALSE)="Homologado",VLOOKUP($A11,Salta!$A$8:$O$291,10,FALSE),"") | S11: =IF(VLOOKUP($A11,'Master vs SAP'!$A$8:$O$291,4,FALSE)="","",VLOOKUP($A11,'Master vs SAP'!$A$8:$O$291,4,FALSE)) -> 1000889 | T11: =IF(VLOOKUP($A11,'Master vs SAP'!$A$8:$O$291,5,FALSE)="","",VLOOKUP($A11,'Master vs SAP'!$A$8:$O$291,5,FALSE)) -> DICLOFENAC+PRIDINOL COMPRIMIDOS | U11: =IF(VLOOKUP($A11,'Master vs SAP'!$A$8:$O$291,7,FALSE)="","",VLOOKUP($A11,'Master vs SAP'!$A$8:$O$291,7,FALSE)) -> Alta | V11: =IF(VLOOKUP($A11,'Master vs SAP'!$A$8:$O$291,6,FALSE)="","",VLOOKUP($A11,'Master vs SAP'!$A$8:$O$291,6,FALSE)) -> Coincidencia | W11: =IF(VLOOKUP($A11,'Master vs SAP'!$A$8:$O$291,15,FALSE)="Homologado",VLOOKUP($A11,'Master vs SAP'!$A$8:$O$291,10,FALSE),"")
A12: M01-005 | B12: Medicación | C12: Ibuprofeno 600 mg | D12: =IF(VLOOKUP($A12,Neuquén!$A$8:$O$291,4,FALSE)="","",VLOOKUP($A12,Neuquén!$A$8:$O$291,4,FALSE)) -> 396 | E12: =IF(VLOOKUP($A12,Neuquén!$A$8:$O$291,5,FALSE)="","",VLOOKUP($A12,Neuquén!$A$8:$O$291,5,FALSE)) -> IBUPROFENO600MGCOMPRECUBIERTOS | F12: =IF(VLOOKUP($A12,Neuquén!$A$8:$O$291,7,FALSE)="","",VLOOKUP($A12,Neuquén!$A$8:$O$291,7,FALSE)) -> Media | G12: =IF(VLOOKUP($A12,Neuquén!$A$8:$O$291,6,FALSE)="","",VLOOKUP($A12,Neuquén!$A$8:$O$291,6,FALSE)) -> Equivalencia a revisar | H12: =IF(VLOOKUP($A12,'San Juan'!$A$8:$O$291,4,FALSE)="","",VLOOKUP($A12,'San Juan'!$A$8:$O$291,4,FALSE)) -> MED102 | I12: =IF(VLOOKUP($A12,'San Juan'!$A$8:$O$291,5,FALSE)="","",VLOOKUP($A12,'San Juan'!$A$8:$O$291,5,FALSE)) -> Ibuprofeno Comp x 600 mg | J12: =IF(VLOOKUP($A12,'San Juan'!$A$8:$O$291,7,FALSE)="","",VLOOKUP($A12,'San Juan'!$A$8:$O$291,7,FALSE)) -> Alta | K12: =IF(VLOOKUP($A12,'San Juan'!$A$8:$O$291,6,FALSE)="","",VLOOKUP($A12,'San Juan'!$A$8:$O$291,6,FALSE)) -> Coincidencia por validar | L12: =IF(VLOOKUP($A12,Salta!$A$8:$O$291,4,FALSE)="","",VLOOKUP($A12,Salta!$A$8:$O$291,4,FALSE)) -> 150 | M12: =IF(VLOOKUP($A12,Salta!$A$8:$O$291,5,FALSE)="","",VLOOKUP($A12,Salta!$A$8:$O$291,5,FALSE)) -> Ibuprofeno Comprimidos x 600mg | N12: =IF(VLOOKUP($A12,Salta!$A$8:$O$291,7,FALSE)="","",VLOOKUP($A12,Salta!$A$8:$O$291,7,FALSE)) -> Alta | O12: =IF(VLOOKUP($A12,Salta!$A$8:$O$291,6,FALSE)="","",VLOOKUP($A12,Salta!$A$8:$O$291,6,FALSE)) -> Coincidencia | P12: =IF(VLOOKUP($A12,Neuquén!$A$8:$O$291,15,FALSE)="Homologado",VLOOKUP($A12,Neuquén!$A$8:$O$291,10,FALSE),"") | Q12: =IF(VLOOKUP($A12,'San Juan'!$A$8:$O$291,15,FALSE)="Homologado",VLOOKUP($A12,'San Juan'!$A$8:$O$291,10,FALSE),"") | R12: =IF(VLOOKUP($A12,Salta!$A$8:$O$291,15,FALSE)="Homologado",VLOOKUP($A12,Salta!$A$8:$O$291,10,FALSE),"") | S12: =IF(VLOOKUP($A12,'Master vs SAP'!$A$8:$O$291,4,FALSE)="","",VLOOKUP($A12,'Master vs SAP'!$A$8:$O$291,4,FALSE)) -> 1000124 | T12: =IF(VLOOKUP($A12,'Master vs SAP'!$A$8:$O$291,5,FALSE)="","",VLOOKUP($A12,'Master vs SAP'!$A$8:$O$291,5,FALSE)) -> IBUPROFENO COMP 600MG | U12: =IF(VLOOKUP($A12,'Master vs SAP'!$A$8:$O$291,7,FALSE)="","",VLOOKUP($A12,'Master vs SAP'!$A$8:$O$291,7,FALSE)) -> Alta | V12: =IF(VLOOKUP($A12,'Master vs SAP'!$A$8:$O$291,6,FALSE)="","",VLOOKUP($A12,'Master vs SAP'!$A$8:$O$291,6,FALSE)) -> Coincidencia | W12: =IF(VLOOKUP($A12,'Master vs SAP'!$A$8:$O$291,15,FALSE)="Homologado",VLOOKUP($A12,'Master vs SAP'!$A$8:$O$291,10,FALSE),"")
A13: M01-006 | B13: Medicación | C13: Ketorolac 10 mg SL | D13: =IF(VLOOKUP($A13,Neuquén!$A$8:$O$291,4,FALSE)="","",VLOOKUP($A13,Neuquén!$A$8:$O$291,4,FALSE)) -> 147 | E13: =IF(VLOOKUP($A13,Neuquén!$A$8:$O$291,5,FALSE)="","",VLOOKUP($A13,Neuquén!$A$8:$O$291,5,FALSE)) -> KETOROLAC | F13: =IF(VLOOKUP($A13,Neuquén!$A$8:$O$291,7,FALSE)="","",VLOOKUP($A13,Neuquén!$A$8:$O$291,7,FALSE)) -> Media | G13: =IF(VLOOKUP($A13,Neuquén!$A$8:$O$291,6,FALSE)="","",VLOOKUP($A13,Neuquén!$A$8:$O$291,6,FALSE)) -> Código compartido: revisar | H13: =IF(VLOOKUP($A13,'San Juan'!$A$8:$O$291,4,FALSE)="","",VLOOKUP($A13,'San Juan'!$A$8:$O$291,4,FALSE)) -> MED110 | I13: =IF(VLOOKUP($A13,'San Juan'!$A$8:$O$291,5,FALSE)="","",VLOOKUP($A13,'San Juan'!$A$8:$O$291,5,FALSE)) -> Ketorolac Comp SL X 10 mg | J13: =IF(VLOOKUP($A13,'San Juan'!$A$8:$O$291,7,FALSE)="","",VLOOKUP($A13,'San Juan'!$A$8:$O$291,7,FALSE)) -> Alta | K13: =IF(VLOOKUP($A13,'San Juan'!$A$8:$O$291,6,FALSE)="","",VLOOKUP($A13,'San Juan'!$A$8:$O$291,6,FALSE)) -> Coincidencia por validar | L13: =IF(VLOOKUP($A13,Salta!$A$8:$O$291,4,FALSE)="","",VLOOKUP($A13,Salta!$A$8:$O$291,4,FALSE)) -> 162 | M13: =IF(VLOOKUP($A13,Salta!$A$8:$O$291,5,FALSE)="","",VLOOKUP($A13,Salta!$A$8:$O$291,5,FALSE)) -> Ketorolac S/L Comprimidos x 10mg sl | N13: =IF(VLOOKUP($A13,Salta!$A$8:$O$291,7,FALSE)="","",VLOOKUP($A13,Salta!$A$8:$O$291,7,FALSE)) -> Alta | O13: =IF(VLOOKUP($A13,Salta!$A$8:$O$291,6,FALSE)="","",VLOOKUP($A13,Salta!$A$8:$O$291,6,FALSE)) -> Coincidencia | P13: =IF(VLOOKUP($A13,Neuquén!$A$8:$O$291,15,FALSE)="Homologado",VLOOKUP($A13,Neuquén!$A$8:$O$291,10,FALSE),"") | Q13: =IF(VLOOKUP($A13,'San Juan'!$A$8:$O$291,15,FALSE)="Homologado",VLOOKUP($A13,'San Juan'!$A$8:$O$291,10,FALSE),"") | R13: =IF(VLOOKUP($A13,Salta!$A$8:$O$291,15,FALSE)="Homologado",VLOOKUP($A13,Salta!$A$8:$O$291,10,FALSE),"") | S13: =IF(VLOOKUP($A13,'Master vs SAP'!$A$8:$O$291,4,FALSE)="","",VLOOKUP($A13,'Master vs SAP'!$A$8:$O$291,4,FALSE)) -> 1000129 | T13: =IF(VLOOKUP($A13,'Master vs SAP'!$A$8:$O$291,5,FALSE)="","",VLOOKUP($A13,'Master vs SAP'!$A$8:$O$291,5,FALSE)) -> KETOROLAC 10MG SUBLINGUAL | U13: =IF(VLOOKUP($A13,'Master vs SAP'!$A$8:$O$291,7,FALSE)="","",VLOOKUP($A13,'Master vs SAP'!$A$8:$O$291,7,FALSE)) -> Alta | V13: =IF(VLOOKUP($A13,'Master vs SAP'!$A$8:$O$291,6,FALSE)="","",VLOOKUP($A13,'Master vs SAP'!$A$8:$O$291,6,FALSE)) -> Coincidencia | W13: =IF(VLOOKUP($A13,'Master vs SAP'!$A$8:$O$291,15,FALSE)="Homologado",VLOOKUP($A13,'Master vs SAP'!$A$8:$O$291,10,FALSE),"")
A14: M01-007 | B14: Medicación | C14: Ketorolac 30 mg/1 ml amp. | D14: =IF(VLOOKUP($A14,Neuquén!$A$8:$O$291,4,FALSE)="","",VLOOKUP($A14,Neuquén!$A$8:$O$291,4,FALSE)) -> 147 | E14: =IF(VLOOKUP($A14,Neuquén!$A$8:$O$291,5,FALSE)="","",VLOOKUP($A14,Neuquén!$A$8:$O$291,5,FALSE)) -> KETOROLAC | F14: =IF(VLOOKUP($A14,Neuquén!$A$8:$O$291,7,FALSE)="","",VLOOKUP($A14,Neuquén!$A$8:$O$291,7,FALSE)) -> Media | G14: =IF(VLOOKUP($A14,Neuquén!$A$8:$O$291,6,FALSE)="","",VLOOKUP($A14,Neuquén!$A$8:$O$291,6,FALSE)) -> Código compartido: revisar | H14: =IF(VLOOKUP($A14,'San Juan'!$A$8:$O$291,4,FALSE)="","",VLOOKUP($A14,'San Juan'!$A$8:$O$291,4,FALSE)) -> MED109 | I14: =IF(VLOOKUP($A14,'San Juan'!$A$8:$O$291,5,FALSE)="","",VLOOKUP($A14,'San Juan'!$A$8:$O$291,5,FALSE)) -> Ketorolac 30mg Amp x 1 ml | J14: =IF(VLOOKUP($A14,'San Juan'!$A$8:$O$291,7,FALSE)="","",VLOOKUP($A14,'San Juan'!$A$8:$O$291,7,FALSE)) -> Alta | K14: =IF(VLOOKUP($A14,'San Juan'!$A$8:$O$291,6,FALSE)="","",VLOOKUP($A14,'San Juan'!$A$8:$O$291,6,FALSE)) -> Coincidencia por validar | L14: =IF(VLOOKUP($A14,Salta!$A$8:$O$291,4,FALSE)="","",VLOOKUP($A14,Salta!$A$8:$O$291,4,FALSE)) -> 160 | M14: =IF(VLOOKUP($A14,Salta!$A$8:$O$291,5,FALSE)="","",VLOOKUP($A14,Salta!$A$8:$O$291,5,FALSE)) -> Ketorolac 1 amp=30 mgr x 1ml | N14: =IF(VLOOKUP($A14,Salta!$A$8:$O$291,7,FALSE)="","",VLOOKUP($A14,Salta!$A$8:$O$291,7,FALSE)) -> Alta | O14: =IF(VLOOKUP($A14,Salta!$A$8:$O$291,6,FALSE)="","",VLOOKUP($A14,Salta!$A$8:$O$291,6,FALSE)) -> Coincidencia | P14: =IF(VLOOKUP($A14,Neuquén!$A$8:$O$291,15,FALSE)="Homologado",VLOOKUP($A14,Neuquén!$A$8:$O$291,10,FALSE),"") | Q14: =IF(VLOOKUP($A14,'San Juan'!$A$8:$O$291,15,FALSE)="Homologado",VLOOKUP($A14,'San Juan'!$A$8:$O$291,10,FALSE),"") | R14: =IF(VLOOKUP($A14,Salta!$A$8:$O$291,15,FALSE)="Homologado",VLOOKUP($A14,Salta!$A$8:$O$291,10,FALSE),"") | S14: =IF(VLOOKUP($A14,'Master vs SAP'!$A$8:$O$291,4,FALSE)="","",VLOOKUP($A14,'Master vs SAP'!$A$8:$O$291,4,FALSE)) -> 1000196 | T14: =IF(VLOOKUP($A14,'Master vs SAP'!$A$8:$O$291,5,FALSE)="","",VLOOKUP($A14,'Master vs SAP'!$A$8:$O$291,5,FALSE)) -> KETOROLAC 30 MG/1ML AMP | U14: =IF(VLOOKUP($A14,'Master vs SAP'!$A$8:$O$291,7,FALSE)="","",VLOOKUP($A14,'Master vs SAP'!$A$8:$O$291,7,FALSE)) -> Alta | V14: =IF(VLOOKUP($A14,'Master vs SAP'!$A$8:$O$291,6,FALSE)="","",VLOOKUP($A14,'Master vs SAP'!$A$8:$O$291,6,FALSE)) -> Coincidencia | W14: =IF(VLOOKUP($A14,'Master vs SAP'!$A$8:$O$291,15,FALSE)="Homologado",VLOOKUP($A14,'Master vs SAP'!$A$8:$O$291,10,FALSE),"")
A15: M01-008 | B15: Medicación | C15: Paracetamol 500 mg | D15: =IF(VLOOKUP($A15,Neuquén!$A$8:$O$291,4,FALSE)="","",VLOOKUP($A15,Neuquén!$A$8:$O$291,4,FALSE)) -> 179 | E15: =IF(VLOOKUP($A15,Neuquén!$A$8:$O$291,5,FALSE)="","",VLOOKUP($A15,Neuquén!$A$8:$O$291,5,FALSE)) -> PARACETAMOL500MG | F15: =IF(VLOOKUP($A15,Neuquén!$A$8:$O$291,7,FALSE)="","",VLOOKUP($A15,Neuquén!$A$8:$O$291,7,FALSE)) -> Alta | G15: =IF(VLOOKUP($A15,Neuquén!$A$8:$O$291,6,FALSE)="","",VLOOKUP($A15,Neuquén!$A$8:$O$291,6,FALSE)) -> Coincidencia por validar | H15: =IF(VLOOKUP($A15,'San Juan'!$A$8:$O$291,4,FALSE)="","",VLOOKUP($A15,'San Juan'!$A$8:$O$291,4,FALSE)) -> MED150 | I15: =IF(VLOOKUP($A15,'San Juan'!$A$8:$O$291,5,FALSE)="","",VLOOKUP($A15,'San Juan'!$A$8:$O$291,5,FALSE)) -> Paracetamol Comp x 1 gr | J15: =IF(VLOOKUP($A15,'San Juan'!$A$8:$O$291,7,FALSE)="","",VLOOKUP($A15,'San Juan'!$A$8:$O$291,7,FALSE)) -> Baja | K15: =IF(VLOOKUP($A15,'San Juan'!$A$8:$O$291,6,FALSE)="","",VLOOKUP($A15,'San Juan'!$A$8:$O$291,6,FALSE)) -> Revisar presentación | L15: =IF(VLOOKUP($A15,Salta!$A$8:$O$291,4,FALSE)="","",VLOOKUP($A15,Salta!$A$8:$O$291,4,FALSE)) -> 198 | M15: =IF(VLOOKUP($A15,Salta!$A$8:$O$291,5,FALSE)="","",VLOOKUP($A15,Salta!$A$8:$O$291,5,FALSE)) -> Paracetamol comprimidos 500mg | N15: =IF(VLOOKUP($A15,Salta!$A$8:$O$291,7,FALSE)="","",VLOOKUP($A15,Salta!$A$8:$O$291,7,FALSE)) -> Alta | O15: =IF(VLOOKUP($A15,Salta!$A$8:$O$291,6,FALSE)="","",VLOOKUP($A15,Salta!$A$8:$O$291,6,FALSE)) -> Coincidencia | P15: =IF(VLOOKUP($A15,Neuquén!$A$8:$O$291,15,FALSE)="Homologado",VLOOKUP($A15,Neuquén!$A$8:$O$291,10,FALSE),"") | Q15: =IF(VLOOKUP($A15,'San Juan'!$A$8:$O$291,15,FALSE)="Homologado",VLOOKUP($A15,'San Juan'!$A$8:$O$291,10,FALSE),"") | R15: =IF(VLOOKUP($A15,Salta!$A$8:$O$291,15,FALSE)="Homologado",VLOOKUP($A15,Salta!$A$8:$O$291,10,FALSE),"") | S15: =IF(VLOOKUP($A15,'Master vs SAP'!$A$8:$O$291,4,FALSE)="","",VLOOKUP($A15,'Master vs SAP'!$A$8:$O$291,4,FALSE)) -> 1000470 | T15: =IF(VLOOKUP($A15,'Master vs SAP'!$A$8:$O$291,5,FALSE)="","",VLOOKUP($A15,'Master vs SAP'!$A$8:$O$291,5,FALSE)) -> PARACETAMOL COMP 1 GRAMO | U15: =IF(VLOOKUP($A15,'Master vs SAP'!$A$8:$O$291,7,FALSE)="","",VLOOKUP($A15,'Master vs SAP'!$A$8:$O$291,7,FALSE)) -> Baja | V15: =IF(VLOOKUP($A15,'Master vs SAP'!$A$8:$O$291,6,FALSE)="","",VLOOKUP($A15,'Master vs SAP'!$A$8:$O$291,6,FALSE)) -> Revisar presentación | W15: =IF(VLOOKUP($A15,'Master vs SAP'!$A$8:$O$291,15,FALSE)="Homologado",VLOOKUP($A15,'Master vs SAP'!$A$8:$O$291,10,FALSE),"")
A16: M01-009 | B16: Medicación | C16: Dipirona 500 mg comp. | D16: =IF(VLOOKUP($A16,Neuquén!$A$8:$O$291,4,FALSE)="","",VLOOKUP($A16,Neuquén!$A$8:$O$291,4,FALSE)) -> 94 | E16: =IF(VLOOKUP($A16,Neuquén!$A$8:$O$291,5,FALSE)="","",VLOOKUP($A16,Neuquén!$A$8:$O$291,5,FALSE)) -> DIPIRONACOMP | F16: =IF(VLOOKUP($A16,Neuquén!$A$8:$O$291,7,FALSE)="","",VLOOKUP($A16,Neuquén!$A$8:$O$291,7,FALSE)) -> Media | G16: =IF(VLOOKUP($A16,Neuquén!$A$8:$O$291,6,FALSE)="","",VLOOKUP($A16,Neuquén!$A$8:$O$291,6,FALSE)) -> Equivalencia a revisar | H16: =IF(VLOOKUP($A16,'San Juan'!$A$8:$O$291,4,FALSE)="","",VLOOKUP($A16,'San Juan'!$A$8:$O$291,4,FALSE)) | I16: =IF(VLOOKUP($A16,'San Juan'!$A$8:$O$291,5,FALSE)="","",VLOOKUP($A16,'San Juan'!$A$8:$O$291,5,FALSE)) | J16: =IF(VLOOKUP($A16,'San Juan'!$A$8:$O$291,7,FALSE)="","",VLOOKUP($A16,'San Juan'!$A$8:$O$291,7,FALSE)) -> Sin coincidencia | K16: =IF(VLOOKUP($A16,'San Juan'!$A$8:$O$291,6,FALSE)="","",VLOOKUP($A16,'San Juan'!$A$8:$O$291,6,FALSE)) -> Sin código encontrado | L16: =IF(VLOOKUP($A16,Salta!$A$8:$O$291,4,FALSE)="","",VLOOKUP($A16,Salta!$A$8:$O$291,4,FALSE)) -> 105 | M16: =IF(VLOOKUP($A16,Salta!$A$8:$O$291,5,FALSE)="","",VLOOKUP($A16,Salta!$A$8:$O$291,5,FALSE)) -> Dipirona comprimidos x500mg | N16: =IF(VLOOKUP($A16,Salta!$A$8:$O$291,7,FALSE)="","",VLOOKUP($A16,Salta!$A$8:$O$291,7,FALSE)) -> Alta | O16: =IF(VLOOKUP($A16,Salta!$A$8:$O$291,6,FALSE)="","",VLOOKUP($A16,Salta!$A$8:$O$291,6,FALSE)) -> Coincidencia | P16: =IF(VLOOKUP($A16,Neuquén!$A$8:$O$291,15,FALSE)="Homologado",VLOOKUP($A16,Neuquén!$A$8:$O$291,10,FALSE),"") | Q16: =IF(VLOOKUP($A16,'San Juan'!$A$8:$O$291,15,FALSE)="Homologado",VLOOKUP($A16,'San Juan'!$A$8:$O$291,10,FALSE),"") | R16: =IF(VLOOKUP($A16,Salta!$A$8:$O$291,15,FALSE)="Homologado",VLOOKUP($A16,Salta!$A$8:$O$291,10,FALSE),"") | S16: =IF(VLOOKUP($A16,'Master vs SAP'!$A$8:$O$291,4,FALSE)="","",VLOOKUP($A16,'Master vs SAP'!$A$8:$O$291,4,FALSE)) -> 1005149 | T16: =IF(VLOOKUP($A16,'Master vs SAP'!$A$8:$O$291,5,FALSE)="","",VLOOKUP($A16,'Master vs SAP'!$A$8:$O$291,5,FALSE)) -> DIPIRONA 500MG COMPRIMIDOS | U16: =IF(VLOOKUP($A16,'Master vs SAP'!$A$8:$O$291,7,FALSE)="","",VLOOKUP($A16,'Master vs SAP'!$A$8:$O$291,7,FALSE)) -> Alta | V16: =IF(VLOOKUP($A16,'Master vs SAP'!$A$8:$O$291,6,FALSE)="","",VLOOKUP($A16,'Master vs SAP'!$A$8:$O$291,6,FALSE)) -> Coincidencia | W16: =IF(VLOOKUP($A16,'Master vs SAP'!$A$8:$O$291,15,FALSE)="Homologado",VLOOKUP($A16,'Master vs SAP'!$A$8:$O$291,10,FALSE),"")
A17: M01-010 | B17: Medicación | C17: Dipirona 1 g/2 ml amp. | D17: =IF(VLOOKUP($A17,Neuquén!$A$8:$O$291,4,FALSE)="","",VLOOKUP($A17,Neuquén!$A$8:$O$291,4,FALSE)) -> 93 | E17: =IF(VLOOKUP($A17,Neuquén!$A$8:$O$291,5,FALSE)="","",VLOOKUP($A17,Neuquén!$A$8:$O$291,5,FALSE)) -> DIPIRONAAMP | F17: =IF(VLOOKUP($A17,Neuquén!$A$8:$O$291,7,FALSE)="","",VLOOKUP($A17,Neuquén!$A$8:$O$291,7,FALSE)) -> Media | G17: =IF(VLOOKUP($A17,Neuquén!$A$8:$O$291,6,FALSE)="","",VLOOKUP($A17,Neuquén!$A$8:$O$291,6,FALSE)) -> Equivalencia a revisar | H17: =IF(VLOOKUP($A17,'San Juan'!$A$8:$O$291,4,FALSE)="","",VLOOKUP($A17,'San Juan'!$A$8:$O$291,4,FALSE)) | I17: =IF(VLOOKUP($A17,'San Juan'!$A$8:$O$291,5,FALSE)="","",VLOOKUP($A17,'San Juan'!$A$8:$O$291,5,FALSE)) | J17: =IF(VLOOKUP($A17,'San Juan'!$A$8:$O$291,7,FALSE)="","",VLOOKUP($A17,'San Juan'!$A$8:$O$291,7,FALSE)) -> Sin coincidencia | K17: =IF(VLOOKUP($A17,'San Juan'!$A$8:$O$291,6,FALSE)="","",VLOOKUP($A17,'San Juan'!$A$8:$O$291,6,FALSE)) -> Sin código encontrado | L17: =IF(VLOOKUP($A17,Salta!$A$8:$O$291,4,FALSE)="","",VLOOKUP($A17,Salta!$A$8:$O$291,4,FALSE)) -> 106 | M17: =IF(VLOOKUP($A17,Salta!$A$8:$O$291,5,FALSE)="","",VLOOKUP($A17,Salta!$A$8:$O$291,5,FALSE)) -> Dipirona inyectable 1amp=2ml 1gr | N17: =IF(VLOOKUP($A17,Salta!$A$8:$O$291,7,FALSE)="","",VLOOKUP($A17,Salta!$A$8:$O$291,7,FALSE)) -> Alta | O17: =IF(VLOOKUP($A17,Salta!$A$8:$O$291,6,FALSE)="","",VLOOKUP($A17,Salta!$A$8:$O$291,6,FALSE)) -> Coincidencia | P17: =IF(VLOOKUP($A17,Neuquén!$A$8:$O$291,15,FALSE)="Homologado",VLOOKUP($A17,Neuquén!$A$8:$O$291,10,FALSE),"") | Q17: =IF(VLOOKUP($A17,'San Juan'!$A$8:$O$291,15,FALSE)="Homologado",VLOOKUP($A17,'San Juan'!$A$8:$O$291,10,FALSE),"") | R17: =IF(VLOOKUP($A17,Salta!$A$8:$O$291,15,FALSE)="Homologado",VLOOKUP($A17,Salta!$A$8:$O$291,10,FALSE),"") | S17: =IF(VLOOKUP($A17,'Master vs SAP'!$A$8:$O$291,4,FALSE)="","",VLOOKUP($A17,'Master vs SAP'!$A$8:$O$291,4,FALSE)) -> 1000022 | T17: =IF(VLOOKUP($A17,'Master vs SAP'!$A$8:$O$291,5,FALSE)="","",VLOOKUP($A17,'Master vs SAP'!$A$8:$O$291,5,FALSE)) -> DIPIRONA 1G AMPOLLA DE 2ML INYECTABLE | U17: =IF(VLOOKUP($A17,'Master vs SAP'!$A$8:$O$291,7,FALSE)="","",VLOOKUP($A17,'Master vs SAP'!$A$8:$O$291,7,FALSE)) -> Alta | V17: =IF(VLOOKUP($A17,'Master vs SAP'!$A$8:$O$291,6,FALSE)="","",VLOOKUP($A17,'Master vs SAP'!$A$8:$O$291,6,FALSE)) -> Coincidencia | W17: =IF(VLOOKUP($A17,'Master vs SAP'!$A$8:$O$291,15,FALSE)="Homologado",VLOOKUP($A17,'Master vs SAP'!$A$8:$O$291,10,FALSE),"")
A18: M01-011 | B18: Medicación | C18: Tramadol 100 mg/2 ml amp. | D18: =IF(VLOOKUP($A18,Neuquén!$A$8:$O$291,4,FALSE)="","",VLOOKUP($A18,Neuquén!$A$8:$O$291,4,FALSE)) -> 327 | E18: =IF(VLOOKUP($A18,Neuquén!$A$8:$O$291,5,FALSE)="","",VLOOKUP($A18,Neuquén!$A$8:$O$291,5,FALSE)) -> TRAMADOL100MGAMP | F18: =IF(VLOOKUP($A18,Neuquén!$A$8:$O$291,7,FALSE)="","",VLOOKUP($A18,Neuquén!$A$8:$O$291,7,FALSE)) -> Alta | G18: =IF(VLOOKUP($A18,Neuquén!$A$8:$O$291,6,FALSE)="","",VLOOKUP($A18,Neuquén!$A$8:$O$291,6,FALSE)) -> Coincidencia por validar | H18: =IF(VLOOKUP($A18,'San Juan'!$A$8:$O$291,4,FALSE)="","",VLOOKUP($A18,'San Juan'!$A$8:$O$291,4,FALSE)) -> MED181 | I18: =IF(VLOOKUP($A18,'San Juan'!$A$8:$O$291,5,FALSE)="","",VLOOKUP($A18,'San Juan'!$A$8:$O$291,5,FALSE)) -> Tramadol 50mg/2ml amp | J18: =IF(VLOOKUP($A18,'San Juan'!$A$8:$O$291,7,FALSE)="","",VLOOKUP($A18,'San Juan'!$A$8:$O$291,7,FALSE)) -> Baja | K18: =IF(VLOOKUP($A18,'San Juan'!$A$8:$O$291,6,FALSE)="","",VLOOKUP($A18,'San Juan'!$A$8:$O$291,6,FALSE)) -> Revisar presentación | L18: =IF(VLOOKUP($A18,Salta!$A$8:$O$291,4,FALSE)="","",VLOOKUP($A18,Salta!$A$8:$O$291,4,FALSE)) -> 240 | M18: =IF(VLOOKUP($A18,Salta!$A$8:$O$291,5,FALSE)="","",VLOOKUP($A18,Salta!$A$8:$O$291,5,FALSE)) -> Tramadol clorhidrato 1 amp=2ml/100mg | N18: =IF(VLOOKUP($A18,Salta!$A$8:$O$291,7,FALSE)="","",VLOOKUP($A18,Salta!$A$8:$O$291,7,FALSE)) -> Alta | O18: =IF(VLOOKUP($A18,Salta!$A$8:$O$291,6,FALSE)="","",VLOOKUP($A18,Salta!$A$8:$O$291,6,FALSE)) -> Coincidencia | P18: =IF(VLOOKUP($A18,Neuquén!$A$8:$O$291,15,FALSE)="Homologado",VLOOKUP($A18,Neuquén!$A$8:$O$291,10,FALSE),"") | Q18: =IF(VLOOKUP($A18,'San Juan'!$A$8:$O$291,15,FALSE)="Homologado",VLOOKUP($A18,'San Juan'!$A$8:$O$291,10,FALSE),"") | R18: =IF(VLOOKUP($A18,Salta!$A$8:$O$291,15,FALSE)="Homologado",VLOOKUP($A18,Salta!$A$8:$O$291,10,FALSE),"") | S18: =IF(VLOOKUP($A18,'Master vs SAP'!$A$8:$O$291,4,FALSE)="","",VLOOKUP($A18,'Master vs SAP'!$A$8:$O$291,4,FALSE)) -> 1000635 | T18: =IF(VLOOKUP($A18,'Master vs SAP'!$A$8:$O$291,5,FALSE)="","",VLOOKUP($A18,'Master vs SAP'!$A$8:$O$291,5,FALSE)) -> TRAMADOL 50MG AMPOLLA | U18: =IF(VLOOKUP($A18,'Master vs SAP'!$A$8:$O$291,7,FALSE)="","",VLOOKUP($A18,'Master vs SAP'!$A$8:$O$291,7,FALSE)) -> Baja | V18: =IF(VLOOKUP($A18,'Master vs SAP'!$A$8:$O$291,6,FALSE)="","",VLOOKUP($A18,'Master vs SAP'!$A$8:$O$291,6,FALSE)) -> Revisar presentación | W18: =IF(VLOOKUP($A18,'Master vs SAP'!$A$8:$O$291,15,FALSE)="Homologado",VLOOKUP($A18,'Master vs SAP'!$A$8:$O$291,10,FALSE),"")
A19: M01-012 | B19: Medicación | C19: Tramadol + Paracetamol comp. | D19: =IF(VLOOKUP($A19,Neuquén!$A$8:$O$291,4,FALSE)="","",VLOOKUP($A19,Neuquén!$A$8:$O$291,4,FALSE)) -> 484 | E19: =IF(VLOOKUP($A19,Neuquén!$A$8:$O$291,5,FALSE)="","",VLOOKUP($A19,Neuquén!$A$8:$O$291,5,FALSE)) -> Tramadol+Paracetamol | F19: =IF(VLOOKUP($A19,Neuquén!$A$8:$O$291,7,FALSE)="","",VLOOKUP($A19,Neuquén!$A$8:$O$291,7,FALSE)) -> Alta | G19: =IF(VLOOKUP($A19,Neuquén!$A$8:$O$291,6,FALSE)="","",VLOOKUP($A19,Neuquén!$A$8:$O$291,6,FALSE)) -> Coincidencia por validar | H19: =IF(VLOOKUP($A19,'San Juan'!$A$8:$O$291,4,FALSE)="","",VLOOKUP($A19,'San Juan'!$A$8:$O$291,4,FALSE)) | I19: =IF(VLOOKUP($A19,'San Juan'!$A$8:$O$291,5,FALSE)="","",VLOOKUP($A19,'San Juan'!$A$8:$O$291,5,FALSE)) | J19: =IF(VLOOKUP($A19,'San Juan'!$A$8:$O$291,7,FALSE)="","",VLOOKUP($A19,'San Juan'!$A$8:$O$291,7,FALSE)) -> Sin coincidencia | K19: =IF(VLOOKUP($A19,'San Juan'!$A$8:$O$291,6,FALSE)="","",VLOOKUP($A19,'San Juan'!$A$8:$O$291,6,FALSE)) -> Sin código encontrado | L19: =IF(VLOOKUP($A19,Salta!$A$8:$O$291,4,FALSE)="","",VLOOKUP($A19,Salta!$A$8:$O$291,4,FALSE)) -> 343 | M19: =IF(VLOOKUP($A19,Salta!$A$8:$O$291,5,FALSE)="","",VLOOKUP($A19,Salta!$A$8:$O$291,5,FALSE)) -> Tramadol clorhidrato + Paracetamol Comprimidos | N19: =IF(VLOOKUP($A19,Salta!$A$8:$O$291,7,FALSE)="","",VLOOKUP($A19,Salta!$A$8:$O$291,7,FALSE)) -> Alta | O19: =IF(VLOOKUP($A19,Salta!$A$8:$O$291,6,FALSE)="","",VLOOKUP($A19,Salta!$A$8:$O$291,6,FALSE)) -> Coincidencia | P19: =IF(VLOOKUP($A19,Neuquén!$A$8:$O$291,15,FALSE)="Homologado",VLOOKUP($A19,Neuquén!$A$8:$O$291,10,FALSE),"") | Q19: =IF(VLOOKUP($A19,'San Juan'!$A$8:$O$291,15,FALSE)="Homologado",VLOOKUP($A19,'San Juan'!$A$8:$O$291,10,FALSE),"") | R19: =IF(VLOOKUP($A19,Salta!$A$8:$O$291,15,FALSE)="Homologado",VLOOKUP($A19,Salta!$A$8:$O$291,10,FALSE),"") | S19: =IF(VLOOKUP($A19,'Master vs SAP'!$A$8:$O$291,4,FALSE)="","",VLOOKUP($A19,'Master vs SAP'!$A$8:$O$291,4,FALSE)) -> 1000673 | T19: =IF(VLOOKUP($A19,'Master vs SAP'!$A$8:$O$291,5,FALSE)="","",VLOOKUP($A19,'Master vs SAP'!$A$8:$O$291,5,FALSE)) -> TRAMADOL + PARACETAMOL COMP. | U19: =IF(VLOOKUP($A19,'Master vs SAP'!$A$8:$O$291,7,FALSE)="","",VLOOKUP($A19,'Master vs SAP'!$A$8:$O$291,7,FALSE)) -> Alta | V19: =IF(VLOOKUP($A19,'Master vs SAP'!$A$8:$O$291,6,FALSE)="","",VLOOKUP($A19,'Master vs SAP'!$A$8:$O$291,6,FALSE)) -> Coincidencia | W19: =IF(VLOOKUP($A19,'Master vs SAP'!$A$8:$O$291,15,FALSE)="Homologado",VLOOKUP($A19,'Master vs SAP'!$A$8:$O$291,10,FALSE),"")
... A291: K-290 | B291: Componentes de kit | C291: Antiparras | D291: =IF(VLOOKUP($A291,Neuquén!$A$8:$O$291,4,FALSE)="","",VLOOKUP($A291,Neuquén!$A$8:$O$291,4,FALSE)) -> 1002 | E291: =IF(VLOOKUP($A291,Neuquén!$A$8:$O$291,5,FALSE)="","",VLOOKUP($A291,Neuquén!$A$8:$O$291,5,FALSE)) -> ANTIPARRA | F291: =IF(VLOOKUP($A291,Neuquén!$A$8:$O$291,7,FALSE)="","",VLOOKUP($A291,Neuquén!$A$8:$O$291,7,FALSE)) -> Sin coincidencia | G291: =IF(VLOOKUP($A291,Neuquén!$A$8:$O$291,6,FALSE)="","",VLOOKUP($A291,Neuquén!$A$8:$O$291,6,FALSE)) -> Código compartido: revisar | H291: =IF(VLOOKUP($A291,'San Juan'!$A$8:$O$291,4,FALSE)="","",VLOOKUP($A291,'San Juan'!$A$8:$O$291,4,FALSE)) | I291: =IF(VLOOKUP($A291,'San Juan'!$A$8:$O$291,5,FALSE)="","",VLOOKUP($A291,'San Juan'!$A$8:$O$291,5,FALSE)) | J291: =IF(VLOOKUP($A291,'San Juan'!$A$8:$O$291,7,FALSE)="","",VLOOKUP($A291,'San Juan'!$A$8:$O$291,7,FALSE)) -> Sin coincidencia | K291: =IF(VLOOKUP($A291,'San Juan'!$A$8:$O$291,6,FALSE)="","",VLOOKUP($A291,'San Juan'!$A$8:$O$291,6,FALSE)) -> Sin código encontrado | L291: =IF(VLOOKUP($A291,Salta!$A$8:$O$291,4,FALSE)="","",VLOOKUP($A291,Salta!$A$8:$O$291,4,FALSE)) -> 273 | M291: =IF(VLOOKUP($A291,Salta!$A$8:$O$291,5,FALSE)="","",VLOOKUP($A291,Salta!$A$8:$O$291,5,FALSE)) -> Antiparras transparentes | N291: =IF(VLOOKUP($A291,Salta!$A$8:$O$291,7,FALSE)="","",VLOOKUP($A291,Salta!$A$8:$O$291,7,FALSE)) -> Alta | O291: =IF(VLOOKUP($A291,Salta!$A$8:$O$291,6,FALSE)="","",VLOOKUP($A291,Salta!$A$8:$O$291,6,FALSE)) -> Coincidencia | P291: =IF(VLOOKUP($A291,Neuquén!$A$8:$O$291,15,FALSE)="Homologado",VLOOKUP($A291,Neuquén!$A$8:$O$291,10,FALSE),"") | Q291: =IF(VLOOKUP($A291,'San Juan'!$A$8:$O$291,15,FALSE)="Homologado",VLOOKUP($A291,'San Juan'!$A$8:$O$291,10,FALSE),"") | R291: =IF(VLOOKUP($A291,Salta!$A$8:$O$291,15,FALSE)="Homologado",VLOOKUP($A291,Salta!$A$8:$O$291,10,FALSE),"") | S291: =IF(VLOOKUP($A291,'Master vs SAP'!$A$8:$O$291,4,FALSE)="","",VLOOKUP($A291,'Master vs SAP'!$A$8:$O$291,4,FALSE)) -> 2000010 | T291: =IF(VLOOKUP($A291,'Master vs SAP'!$A$8:$O$291,5,FALSE)="","",VLOOKUP($A291,'Master vs SAP'!$A$8:$O$291,5,FALSE)) -> ANTIPARRA DE PLASTICO | U291: =IF(VLOOKUP($A291,'Master vs SAP'!$A$8:$O$291,7,FALSE)="","",VLOOKUP($A291,'Master vs SAP'!$A$8:$O$291,7,FALSE)) -> Alta | V291: =IF(VLOOKUP($A291,'Master vs SAP'!$A$8:$O$291,6,FALSE)="","",VLOOKUP($A291,'Master vs SAP'!$A$8:$O$291,6,FALSE)) -> Coincidencia | W291: =IF(VLOOKUP($A291,'Master vs SAP'!$A$8:$O$291,15,FALSE)="Homologado",VLOOKUP($A291,'Master vs SAP'!$A$8:$O$291,10,FALSE),"")

Sheet Neuquén
A2: Revisión de Neuquén
A3: 284 ítems del master. Esta hoja registra únicamente las decisiones de Neuquén.
A4: 1. Comparar C con D/E. 2. Leer clasificación, confianza y observaciones en F:H. 3. Completar el amarillo I:N.
A5: Confianza del relevamiento original, ajustada cuando se detectó un conflicto. La confianza histórica íntegra está en Datos originales.
A6: Comparación con el master · propuestas pendientes de validación | I6: Completar por la base | O6: Estado actual
A7: ID común | B7: Tipo de ítem | C7: Ítem que pide el master | D7: Códigos Base Neuquén | E7: Nomenclatura Base Neuquén | F7: Clasificación del cruce | G7: Nivel de confianza | H7: Observaciones y qué revisar | I7: Decisión de la base | J7: Código AVAIN confirmado | K7: Nombre AVAIN confirmado | L7: Validó el producto (nombre) | M7: Validó el código AVAIN (nombre) | N7: Fecha de validación | O7: Estado de esta base
A8: M02-001 | B8: Medicación | C8: Midazolam 15 mg/3 ml | D8: 330 | E8: MIDAZOLAM5MGAMP | F8: Revisar presentación | G8: Baja | H8: Master midazolam 15 mg/3 ml; Neuquén dice 5 mg ampolla. No informa volumen. Confirmar cantidad total por ampolla y concentración; no sumar ampollas para homologar. Confianza histórica: Media; ajustada a Baja por el hallazgo indicado. Fuente: master original, fila 22. | I8: Pendiente | O8: =IF(I8="Pendiente","Pendiente",IF(I8="Equivalente confirmado",IF(OR(J8="",K8=""),"Falta código o nombre",IF(OR(L8="",M8=""),"Falta validación",IF(OR(NOT(ISNUMBER(N8)),N8<=0),"Falta fecha","Homologado"))),IF(I8="Sin equivalente en AVAIN",IF(OR(J8<>"",K8<>""),"Quitar código y nombre",IF(OR(L8="",M8=""),"Falta validación",IF(OR(NOT(ISNUMBER(N8)),N8<=0),"Falta fecha","Sin equivalente confirmado"))),"Revisar decisión"))) -> Pendiente
A9: M02-007 | B9: Medicación | C9: Succinilcolina 100 mg | D9: 262 | E9: SUCCINILCOLINA500MG | F9: Revisar presentación | G9: Baja | H9: Master succinilcolina 100 mg; Neuquén registra 500 mg. Misma sustancia, presentación de dosis distinta. Confianza histórica: Media; ajustada a Baja por el hallazgo indicado. Fuente: master original, fila 179. | I9: Pendiente | O9: =IF(I9="Pendiente","Pendiente",IF(I9="Equivalente confirmado",IF(OR(J9="",K9=""),"Falta código o nombre",IF(OR(L9="",M9=""),"Falta validación",IF(OR(NOT(ISNUMBER(N9)),N9<=0),"Falta fecha","Homologado"))),IF(I9="Sin equivalente en AVAIN",IF(OR(J9<>"",K9<>""),"Quitar código y nombre",IF(OR(L9="",M9=""),"Falta validación",IF(OR(NOT(ISNUMBER(N9)),N9<=0),"Falta fecha","Sin equivalente confirmado"))),"Revisar decisión"))) -> Pendiente
A10: M05-005 | B10: Medicación | C10: Solución hipertónica nasal (Hypersol) | D10: 123 | E10: GLUCOSADO HIPERTONICO AMP | F10: Producto distinto | G10: Baja | H10: El master pide solución hipertónica nasal. El código 123 dice glucosado hipertónico en ampolla. Buscar la solución nasal. Confianza histórica: Sin coincidencia; ajustada a Baja por el hallazgo indicado. Fuente: master original, fila 6. | I10: Pendiente | O10: =IF(I10="Pendiente","Pendiente",IF(I10="Equivalente confirmado",IF(OR(J10="",K10=""),"Falta código o nombre",IF(OR(L10="",M10=""),"Falta validación",IF(OR(NOT(ISNUMBER(N10)),N10<=0),"Falta fecha","Homologado"))),IF(I10="Sin equivalente en AVAIN",IF(OR(J10<>"",K10<>""),"Quitar código y nombre",IF(OR(L10="",M10=""),"Falta validación",IF(OR(NOT(ISNUMBER(N10)),N10<=0),"Falta fecha","Sin equivalente confirmado"))),"Revisar decisión"))) -> Pendiente
A11: M08-006 | B11: Medicación | C11: Omeprazol 40 mg fco. amp. | D11: 170 | E11: OMEPRAZOL 20 MG COMP | F11: Revisar presentación | G11: Baja | H11: Mismo principio activo, dosis y forma distintas: master omeprazol 40 mg en frasco ampolla; código 170, 20 mg en comprimidos. Buscar la presentación correcta. Confianza histórica: Sin coincidencia; ajustada a Baja por el hallazgo indicado. Fuente: master original, fila 11. | I11: Pendiente | O11: =IF(I11="Pendiente","Pendiente",IF(I11="Equivalente confirmado",IF(OR(J11="",K11=""),"Falta código o nombre",IF(OR(L11="",M11=""),"Falta validación",IF(OR(NOT(ISNUMBER(N11)),N11<=0),"Falta fecha","Homologado"))),IF(I11="Sin equivalente en AVAIN",IF(OR(J11<>"",K11<>""),"Quitar código y nombre",IF(OR(L11="",M11=""),"Falta validación",IF(OR(NOT(ISNUMBER(N11)),N11<=0),"Falta fecha","Sin equivalente confirmado"))),"Revisar decisión"))) -> Pendiente
A12: M09-003 | B12: Medicación | C12: Lorazepam 4 mg/1 ml amp. | D12: 329 | E12: LORAZEPAMSUBLINGUALCOMP | F12: Revisar presentación | G12: Baja | H12: Master lorazepam 4 mg/1 ml ampolla; Neuquén registra comprimidos sublinguales. Forma distinta; falta la presentación inyectable requerida. Fuente: master original, fila 196. | I12: Pendiente | O12: =IF(I12="Pendiente","Pendiente",IF(I12="Equivalente confirmado",IF(OR(J12="",K12=""),"Falta código o nombre",IF(OR(L12="",M12=""),"Falta validación",IF(OR(NOT(ISNUMBER(N12)),N12<=0),"Falta fecha","Homologado"))),IF(I12="Sin equivalente en AVAIN",IF(OR(J12<>"",K12<>""),"Quitar código y nombre",IF(OR(L12="",M12=""),"Falta validación",IF(OR(NOT(ISNUMBER(N12)),N12<=0),"Falta fecha","Sin equivalente confirmado"))),"Revisar decisión"))) -> Pendiente
A13: M11-013 | B13: Medicación | C13: Aciclovir 400 mg | D13: 1 | E13: ACICLOVIR 5% | F13: Revisar presentación | G13: Baja | H13: Master aciclovir 400 mg; Neuquén registra 5% tópico según la observación original. Forma y concentración distintas. Buscar la presentación oral requerida. Confianza histórica: Sin coincidencia; ajustada a Baja por el hallazgo indicado. Fuente: master original, fila 33. | I13: Pendiente | O13: =IF(I13="Pendiente","Pendiente",IF(I13="Equivalente confirmado",IF(OR(J13="",K13=""),"Falta código o nombre",IF(OR(L13="",M13=""),"Falta validación",IF(OR(NOT(ISNUMBER(N13)),N13<=0),"Falta fecha","Homologado"))),IF(I13="Sin equivalente en AVAIN",IF(OR(J13<>"",K13<>""),"Quitar código y nombre",IF(OR(L13="",M13=""),"Falta validación",IF(OR(NOT(ISNUMBER(N13)),N13<=0),"Falta fecha","Sin equivalente confirmado"))),"Revisar decisión"))) -> Pendiente
A14: M13-007 | B14: Medicación | C14: Insulina corriente humana | D14: 389 | E14: INSULINA HUMALOG MIX 25 100 U/ML X 3ML | F14: Producto distinto | G14: Baja | H14: Master insulina corriente humana; Neuquén registra Humalog Mix 25. No se trata sólo de una marca: la formulación es distinta. Confianza histórica: Sin coincidencia; ajustada a Baja por el hallazgo indicado. Fuente: master original, fila 53. | I14: Pendiente | O14: =IF(I14="Pendiente","Pendiente",IF(I14="Equivalente confirmado",IF(OR(J14="",K14=""),"Falta código o nombre",IF(OR(L14="",M14=""),"Falta validación",IF(OR(NOT(ISNUMBER(N14)),N14<=0),"Falta fecha","Homologado"))),IF(I14="Sin equivalente en AVAIN",IF(OR(J14<>"",K14<>""),"Quitar código y nombre",IF(OR(L14="",M14=""),"Falta validación",IF(OR(NOT(ISNUMBER(N14)),N14<=0),"Falta fecha","Sin equivalente confirmado"))),"Revisar decisión"))) -> Pendiente
A15: D-132 | B15: Descartables | C15: Guía microgotero | D15: 278 | E15: GUIAMACROGOTEROV13/14 | F15: Variante distinta | G15: Baja | H15: El master pide microgotero. El código 278 dice macrogotero. Buscar el código de microgotero. Confianza histórica: Alta; ajustada a Baja por el hallazgo indicado. Fuente: master original, fila 57. | I15: Pendiente | O15: =IF(I15="Pendiente","Pendiente",IF(I15="Equivalente confirmado",IF(OR(J15="",K15=""),"Falta código o nombre",IF(OR(L15="",M15=""),"Falta validación",IF(OR(NOT(ISNUMBER(N15)),N15<=0),"Falta fecha","Homologado"))),IF(I15="Sin equivalente en AVAIN",IF(OR(J15<>"",K15<>""),"Quitar código y nombre",IF(OR(L15="",M15=""),"Falta validación",IF(OR(NOT(ISNUMBER(N15)),N15<=0),"Falta fecha","Sin equivalente confirmado"))),"Revisar decisión"))) -> Pendiente
A16: D-141 | B16: Descartables | C16: Gasas estériles 10x10 | D16: 404 | E16: GUANTESESTERILES | F16: Producto distinto | G16: Baja | H16: El master pide gasas estériles 10x10. El código 404 dice guantes estériles. Buscar el código de gasas. Confianza histórica: Media; ajustada a Baja por el hallazgo indicado. Fuente: master original, fila 58. | I16: Pendiente | O16: =IF(I16="Pendiente","Pendiente",IF(I16="Equivalente confirmado",IF(OR(J16="",K16=""),"Falta código o nombre",IF(OR(L16="",M16=""),"Falta validación",IF(OR(NOT(ISNUMBER(N16)),N16<=0),"Falta fecha","Homologado"))),IF(I16="Sin equivalente en AVAIN",IF(OR(J16<>"",K16<>""),"Quitar código y nombre",IF(OR(L16="",M16=""),"Falta validación",IF(OR(NOT(ISNUMBER(N16)),N16<=0),"Falta fecha","Sin equivalente confirmado"))),"Revisar decisión"))) -> Pendiente
A17: E-184 | B17: Equipamiento | C17: Aspirador de secreciones (eléctrico) | D17: 405 | E17: ASPIRADORMANUAL | F17: Equipo distinto | G17: Baja | H17: El master pide aspirador eléctrico. El código 405 dice aspirador manual. Buscar el equipo eléctrico. Fuente: master original, fila 187. | I17: Pendiente | O17: =IF(I17="Pendiente","Pendiente",IF(I17="Equivalente confirmado",IF(OR(J17="",K17=""),"Falta código o nombre",IF(OR(L17="",M17=""),"Falta validación",IF(OR(NOT(ISNUMBER(N17)),N17<=0),"Falta fecha","Homologado"))),IF(I17="Sin equivalente en AVAIN",IF(OR(J17<>"",K17<>""),"Quitar código y nombre",IF(OR(L17="",M17=""),"Falta validación",IF(OR(NOT(ISNUMBER(N17)),N17<=0),"Falta fecha","Sin equivalente confirmado"))),"Revisar decisión"))) -> Pendiente
A18: K-282 | B18: Componentes de kit | C18: Tarjetas de trauma (triage) | D18: 424 | E18: TIJERA MULTIUSO | F18: Producto distinto | G18: Baja | H18: El master pide tarjetas de triage. El código 424 dice tijera multiuso. Buscar tarjetas de triage. Confianza histórica: Sin coincidencia; ajustada a Baja por el hallazgo indicado. Fuente: master original, fila 280. | I18: Pendiente | O18: =IF(I18="Pendiente","Pendiente",IF(I18="Equivalente confirmado",IF(OR(J18="",K18=""),"Falta código o nombre",IF(OR(L18="",M18=""),"Falta validación",IF(OR(NOT(ISNUMBER(N18)),N18<=0),"Falta fecha","Homologado"))),IF(I18="Sin equivalente en AVAIN",IF(OR(J18<>"",K18<>""),"Quitar código y nombre",IF(OR(L18="",M18=""),"Falta validación",IF(OR(NOT(ISNUMBER(N18)),N18<=0),"Falta fecha","Sin equivalente confirmado"))),"Revisar decisión"))) -> Pendiente
A19: M01-006 | B19: Medicación | C19: Ketorolac 10 mg SL | D19: 147 | E19: KETOROLAC | F19: Código compartido: revisar | G19: Media | H19: El código también aparece en M01-007. Confirmar si son el mismo producto o variantes distintas. No agrupar dosis, tamaños o equipos diferentes. Fuente: master original, fila 168. | I19: Pendiente | O19: =IF(I19="Pendiente","Pendiente",IF(I19="Equivalente confirmado",IF(OR(J19="",K19=""),"Falta código o nombre",IF(OR(L19="",M19=""),"Falta validación",IF(OR(NOT(ISNUMBER(N19)),N19<=0),"Falta fecha","Homologado"))),IF(I19="Sin equivalente en AVAIN",IF(OR(J19<>"",K19<>""),"Quitar código y nombre",IF(OR(L19="",M19=""),"Falta validación",IF(OR(NOT(ISNUMBER(N19)),N19<=0),"Falta fecha","Sin equivalente confirmado"))),"Revisar decisión"))) -> Pendiente
... A291: K-288 | B291: Componentes de kit | C291: Campos estériles | D291: 358 | E291: CAMPOESTERIL | F291: Coincidencia por validar | G291: Alta | H291: El relevamiento indica una coincidencia probable. Confirmar las características del producto y la existencia del código en esta base. Fuente: master original, fila 165. | I291: Pendiente | O291: =IF(I291="Pendiente","Pendiente",IF(I291="Equivalente confirmado",IF(OR(J291="",K291=""),"Falta código o nombre",IF(OR(L291="",M291=""),"Falta validación",IF(OR(NOT(ISNUMBER(N291)),N291<=0),"Falta fecha","Homologado"))),IF(I291="Sin equivalente en AVAIN",IF(OR(J291<>"",K291<>""),"Quitar código y nombre",IF(OR(L291="",M291=""),"Falta validación",IF(OR(NOT(ISNUMBER(N291)),N291<=0),"Falta fecha","Sin equivalente confirmado"))),"Revisar decisión"))) -> Pendiente

Sheet San Juan
A2: Revisión de San Juan
A3: 284 ítems del master. Esta hoja registra únicamente las decisiones de San Juan.
A4: 1. Comparar C con D/E. 2. Leer clasificación, confianza y observaciones en F:H. 3. Completar el amarillo I:N.
A5: Confianza del relevamiento original, ajustada cuando se detectó un conflicto. La confianza histórica íntegra está en Datos originales.
A6: Comparación con el master · propuestas pendientes de validación | I6: Completar por la base | O6: Estado actual
A7: ID común | B7: Tipo de ítem | C7: Ítem que pide el master | D7: Códigos Base San Juan | E7: Nomenclatura Base San Juan | F7: Clasificación del cruce | G7: Nivel de confianza | H7: Observaciones y qué revisar | I7: Decisión de la base | J7: Código AVAIN confirmado | K7: Nombre AVAIN confirmado | L7: Validó el producto (nombre) | M7: Validó el código AVAIN (nombre) | N7: Fecha de validación | O7: Estado de esta base
A8: M01-008 | B8: Medicación | C8: Paracetamol 500 mg | D8: MED150 | E8: Paracetamol Comp x 1 gr | F8: Revisar presentación | G8: Baja | H8: Master paracetamol 500 mg; San Juan registra 1 g. Misma sustancia, dosis distinta. Buscar 500 mg; no homologar por posibilidad de fraccionamiento. Fuente: master original, fila 12. | I8: Pendiente | O8: =IF(I8="Pendiente","Pendiente",IF(I8="Equivalente confirmado",IF(OR(J8="",K8=""),"Falta código o nombre",IF(OR(L8="",M8=""),"Falta validación",IF(OR(NOT(ISNUMBER(N8)),N8<=0),"Falta fecha","Homologado"))),IF(I8="Sin equivalente en AVAIN",IF(OR(J8<>"",K8<>""),"Quitar código y nombre",IF(OR(L8="",M8=""),"Falta validación",IF(OR(NOT(ISNUMBER(N8)),N8<=0),"Falta fecha","Sin equivalente confirmado"))),"Revisar decisión"))) -> Pendiente
A9: M01-011 | B9: Medicación | C9: Tramadol 100 mg/2 ml amp. | D9: MED181 | E9: Tramadol 50mg/2ml amp | F9: Revisar presentación | G9: Baja | H9: Mismo principio activo, dosis distinta: master tramadol 100 mg/2 ml; MED181, 50 mg/2 ml. Confirmar la descripción y buscar la dosis requerida. Confianza histórica: Alta; ajustada a Baja por el hallazgo indicado. Fuente: master original, fila 15. | I9: Pendiente | O9: =IF(I9="Pendiente","Pendiente",IF(I9="Equivalente confirmado",IF(OR(J9="",K9=""),"Falta código o nombre",IF(OR(L9="",M9=""),"Falta validación",IF(OR(NOT(ISNUMBER(N9)),N9<=0),"Falta fecha","Homologado"))),IF(I9="Sin equivalente en AVAIN",IF(OR(J9<>"",K9<>""),"Quitar código y nombre",IF(OR(L9="",M9=""),"Falta validación",IF(OR(NOT(ISNUMBER(N9)),N9<=0),"Falta fecha","Sin equivalente confirmado"))),"Revisar decisión"))) -> Pendiente
A10: M01-017 | B10: Medicación | C10: Caramelos con antibiótico | D10: MED30 | E10: Caramelos antigripales con benzocaina 20.7mg | F10: Producto distinto | G10: Baja | H10: Master caramelos con antibiótico; San Juan registra benzocaína. La descripción no acredita el antibiótico solicitado. Fuente: master original, fila 21. | I10: Pendiente | O10: =IF(I10="Pendiente","Pendiente",IF(I10="Equivalente confirmado",IF(OR(J10="",K10=""),"Falta código o nombre",IF(OR(L10="",M10=""),"Falta validación",IF(OR(NOT(ISNUMBER(N10)),N10<=0),"Falta fecha","Homologado"))),IF(I10="Sin equivalente en AVAIN",IF(OR(J10<>"",K10<>""),"Quitar código y nombre",IF(OR(L10="",M10=""),"Falta validación",IF(OR(NOT(ISNUMBER(N10)),N10<=0),"Falta fecha","Sin equivalente confirmado"))),"Revisar decisión"))) -> Pendiente
A11: M06-004 | B11: Medicación | C11: Betametasona retard amp. | D11: DES044 | E11: Dexametasona 1 amp=2ml | F11: Producto distinto | G11: Baja | H11: Master betametasona retard; San Juan registra dexametasona. Son principios activos distintos; la clase terapéutica no los hace equivalentes. Fuente: master original, fila 9. | I11: Pendiente | O11: =IF(I11="Pendiente","Pendiente",IF(I11="Equivalente confirmado",IF(OR(J11="",K11=""),"Falta código o nombre",IF(OR(L11="",M11=""),"Falta validación",IF(OR(NOT(ISNUMBER(N11)),N11<=0),"Falta fecha","Homologado"))),IF(I11="Sin equivalente en AVAIN",IF(OR(J11<>"",K11<>""),"Quitar código y nombre",IF(OR(L11="",M11=""),"Falta validación",IF(OR(NOT(ISNUMBER(N11)),N11<=0),"Falta fecha","Sin equivalente confirmado"))),"Revisar decisión"))) -> Pendiente
A12: M08-004 | B12: Medicación | C12: Butilbromuro de hioscina 10 mg comp. | D12: MED100 | E12: Hioscina x 20 mg Amp x 1 ml | F12: Revisar presentación | G12: Baja | H12: Master hioscina 10 mg comprimidos; San Juan registra 20 mg en ampolla. Forma y dosis distintas. Fuente: master original, fila 194. | I12: Pendiente | O12: =IF(I12="Pendiente","Pendiente",IF(I12="Equivalente confirmado",IF(OR(J12="",K12=""),"Falta código o nombre",IF(OR(L12="",M12=""),"Falta validación",IF(OR(NOT(ISNUMBER(N12)),N12<=0),"Falta fecha","Homologado"))),IF(I12="Sin equivalente en AVAIN",IF(OR(J12<>"",K12<>""),"Quitar código y nombre",IF(OR(L12="",M12=""),"Falta validación",IF(OR(NOT(ISNUMBER(N12)),N12<=0),"Falta fecha","Sin equivalente confirmado"))),"Revisar decisión"))) -> Pendiente
A13: M12-003 | B13: Medicación | C13: Hidroclorotiazida 25 mg | D13: MED95 | E13: Hidroclorotiazida Comp x 50 mg | F13: Revisar presentación | G13: Baja | H13: Master hidroclorotiazida 25 mg; San Juan registra 50 mg. Misma sustancia, dosis distinta. Fuente: master original, fila 105. | I13: Pendiente | O13: =IF(I13="Pendiente","Pendiente",IF(I13="Equivalente confirmado",IF(OR(J13="",K13=""),"Falta código o nombre",IF(OR(L13="",M13=""),"Falta validación",IF(OR(NOT(ISNUMBER(N13)),N13<=0),"Falta fecha","Homologado"))),IF(I13="Sin equivalente en AVAIN",IF(OR(J13<>"",K13<>""),"Quitar código y nombre",IF(OR(L13="",M13=""),"Falta validación",IF(OR(NOT(ISNUMBER(N13)),N13<=0),"Falta fecha","Sin equivalente confirmado"))),"Revisar decisión"))) -> Pendiente
A14: M13-004 | B14: Medicación | C14: Dextrosa 25% 500 ml | D14: MED58 | E14: Dextrosa al 5% x 500 ml sachet | F14: Revisar presentación | G14: Baja | H14: El master pide dextrosa 25% de 500 ml. MED58 dice dextrosa 5% de 500 ml. Misma sustancia, concentración distinta. Buscar la concentración correcta. Fuente: master original, fila 42. | I14: Pendiente | O14: =IF(I14="Pendiente","Pendiente",IF(I14="Equivalente confirmado",IF(OR(J14="",K14=""),"Falta código o nombre",IF(OR(L14="",M14=""),"Falta validación",IF(OR(NOT(ISNUMBER(N14)),N14<=0),"Falta fecha","Homologado"))),IF(I14="Sin equivalente en AVAIN",IF(OR(J14<>"",K14<>""),"Quitar código y nombre",IF(OR(L14="",M14=""),"Falta validación",IF(OR(NOT(ISNUMBER(N14)),N14<=0),"Falta fecha","Sin equivalente confirmado"))),"Revisar decisión"))) -> Pendiente
A15: D-132 | B15: Descartables | C15: Guía microgotero | D15: DESC73 | E15: Guia Macrogotero | F15: Variante distinta | G15: Baja | H15: El master pide microgotero. DESC73 dice macrogotero. Buscar el código de microgotero. Confianza histórica: Alta; ajustada a Baja por el hallazgo indicado. Fuente: master original, fila 57. | I15: Pendiente | O15: =IF(I15="Pendiente","Pendiente",IF(I15="Equivalente confirmado",IF(OR(J15="",K15=""),"Falta código o nombre",IF(OR(L15="",M15=""),"Falta validación",IF(OR(NOT(ISNUMBER(N15)),N15<=0),"Falta fecha","Homologado"))),IF(I15="Sin equivalente en AVAIN",IF(OR(J15<>"",K15<>""),"Quitar código y nombre",IF(OR(L15="",M15=""),"Falta validación",IF(OR(NOT(ISNUMBER(N15)),N15<=0),"Falta fecha","Sin equivalente confirmado"))),"Revisar decisión"))) -> Pendiente
A16: D-175 | B16: Descartables | C16: Iodopovidona 10% 1 L | D16: MED200 | E16: iodopovidona 100 ml sol/topica | F16: Revisar presentación | G16: Baja | H16: Master iodopovidona 10% de 1 litro; San Juan registra 100 ml y omite concentración. Volumen distinto; confirmar además 10%. Fuente: master original, fila 244. | I16: Pendiente | O16: =IF(I16="Pendiente","Pendiente",IF(I16="Equivalente confirmado",IF(OR(J16="",K16=""),"Falta código o nombre",IF(OR(L16="",M16=""),"Falta validación",IF(OR(NOT(ISNUMBER(N16)),N16<=0),"Falta fecha","Homologado"))),IF(I16="Sin equivalente en AVAIN",IF(OR(J16<>"",K16<>""),"Quitar código y nombre",IF(OR(L16="",M16=""),"Falta validación",IF(OR(NOT(ISNUMBER(N16)),N16<=0),"Falta fecha","Sin equivalente confirmado"))),"Revisar decisión"))) -> Pendiente
A17: D-176 | B17: Descartables | C17: Agua oxigenada 1000 ml | D17: DESC9 | E17: Agua oxigenada x 100ml | F17: Revisar presentación | G17: Baja | H17: Master agua oxigenada 1000 ml; San Juan registra 100 ml. Volumen distinto. Fuente: master original, fila 245. | I17: Pendiente | O17: =IF(I17="Pendiente","Pendiente",IF(I17="Equivalente confirmado",IF(OR(J17="",K17=""),"Falta código o nombre",IF(OR(L17="",M17=""),"Falta validación",IF(OR(NOT(ISNUMBER(N17)),N17<=0),"Falta fecha","Homologado"))),IF(I17="Sin equivalente en AVAIN",IF(OR(J17<>"",K17<>""),"Quitar código y nombre",IF(OR(L17="",M17=""),"Falta validación",IF(OR(NOT(ISNUMBER(N17)),N17<=0),"Falta fecha","Sin equivalente confirmado"))),"Revisar decisión"))) -> Pendiente
A18: M08-003 | B18: Medicación | C18: Butilbromuro de hioscina 20 mg amp. | D18: MED100 | E18: Hioscina x 20 mg Amp x 1 ml | F18: Código compartido: revisar | G18: Media | H18: El código también aparece en M08-004, M08-005. Confirmar si son el mismo producto o variantes distintas. No agrupar dosis, tamaños o equipos diferentes. Confianza histórica: Alta; ajustada a Media por el hallazgo indicado. Fuente: master original, fila 70. | I18: Pendiente | O18: =IF(I18="Pendiente","Pendiente",IF(I18="Equivalente confirmado",IF(OR(J18="",K18=""),"Falta código o nombre",IF(OR(L18="",M18=""),"Falta validación",IF(OR(NOT(ISNUMBER(N18)),N18<=0),"Falta fecha","Homologado"))),IF(I18="Sin equivalente en AVAIN",IF(OR(J18<>"",K18<>""),"Quitar código y nombre",IF(OR(L18="",M18=""),"Falta validación",IF(OR(NOT(ISNUMBER(N18)),N18<=0),"Falta fecha","Sin equivalente confirmado"))),"Revisar decisión"))) -> Pendiente
A19: M08-005 | B19: Medicación | C19: Hioscina + Dipirona amp. | D19: MED100 | E19: Hioscina x 20 mg Amp x 1 ml | F19: Código compartido: revisar | G19: Media | H19: El código también aparece en M08-003, M08-004. Confirmar si son el mismo producto o variantes distintas. No agrupar dosis, tamaños o equipos diferentes. Fuente: master original, fila 72. | I19: Pendiente | O19: =IF(I19="Pendiente","Pendiente",IF(I19="Equivalente confirmado",IF(OR(J19="",K19=""),"Falta código o nombre",IF(OR(L19="",M19=""),"Falta validación",IF(OR(NOT(ISNUMBER(N19)),N19<=0),"Falta fecha","Homologado"))),IF(I19="Sin equivalente en AVAIN",IF(OR(J19<>"",K19<>""),"Quitar código y nombre",IF(OR(L19="",M19=""),"Falta validación",IF(OR(NOT(ISNUMBER(N19)),N19<=0),"Falta fecha","Sin equivalente confirmado"))),"Revisar decisión"))) -> Pendiente
... A64: K-289 | B64: Componentes de kit | C64: Gasas | D64: DESC64 | E64: Gasas 10 x 10 cm | F64: Código compartido: revisar | G64: Media | H64: El código también aparece en D-141, K-243. Confirmar si son el mismo producto o variantes distintas. No agrupar dosis, tamaños o equipos diferentes. Fuente: master original, fila 286. | I64: Pendiente | O64: =IF(I64="Pendiente","Pendiente",IF(I64="Equivalente confirmado",IF(OR(J64="",K64=""),"Falta código o nombre",IF(OR(L64="",M64=""),"Falta validación",IF(OR(NOT(ISNUMBER(N64)),N64<=0),"Falta fecha","Homologado"))),IF(I64="Sin equivalente en AVAIN",IF(OR(J64<>"",K64<>""),"Quitar código y nombre",IF(OR(L64="",M64=""),"Falta validación",IF(OR(NOT(ISNUMBER(N64)),N64<=0),"Falta fecha","Sin equivalente confirmado"))),"Revisar decisión"))) -> Pendiente
A65: M01-009 | B65: Medicación | C65: Dipirona 500 mg comp. | F65: Sin código encontrado | G65: Sin coincidencia | H65: Buscar este ítem en el catálogo de la base. Si existe, registrar código y nombre confirmados. Si no existe, registrar Sin equivalente en AVAIN. Fuente: master original, fila 173. | I65: Pendiente | O65: =IF(I65="Pendiente","Pendiente",IF(I65="Equivalente confirmado",IF(OR(J65="",K65=""),"Falta código o nombre",IF(OR(L65="",M65=""),"Falta validación",IF(OR(NOT(ISNUMBER(N65)),N65<=0),"Falta fecha","Homologado"))),IF(I65="Sin equivalente en AVAIN",IF(OR(J65<>"",K65<>""),"Quitar código y nombre",IF(OR(L65="",M65=""),"Falta validación",IF(OR(NOT(ISNUMBER(N65)),N65<=0),"Falta fecha","Sin equivalente confirmado"))),"Revisar decisión"))) -> Pendiente
A66: M01-010 | B66: Medicación | C66: Dipirona 1 g/2 ml amp. | F66: Sin código encontrado | G66: Sin coincidencia | H66: Buscar este ítem en el catálogo de la base. Si existe, registrar código y nombre confirmados. Si no existe, registrar Sin equivalente en AVAIN. Fuente: master original, fila 14. | I66: Pendiente | O66: =IF(I66="Pendiente","Pendiente",IF(I66="Equivalente confirmado",IF(OR(J66="",K66=""),"Falta código o nombre",IF(OR(L66="",M66=""),"Falta validación",IF(OR(NOT(ISNUMBER(N66)),N66<=0),"Falta fecha","Homologado"))),IF(I66="Sin equivalente en AVAIN",IF(OR(J66<>"",K66<>""),"Quitar código y nombre",IF(OR(L66="",M66=""),"Falta validación",IF(OR(NOT(ISNUMBER(N66)),N66<=0),"Falta fecha","Sin equivalente confirmado"))),"Revisar decisión"))) -> Pendiente
A67: M01-012 | B67: Medicación | C67: Tramadol + Paracetamol comp. | F67: Sin código encontrado | G67: Sin coincidencia | H67: Buscar este ítem en el catálogo de la base. Si existe, registrar código y nombre confirmados. Si no existe, registrar Sin equivalente en AVAIN. Fuente: master original, fila 175. | I67: Pendiente | O67: =IF(I67="Pendiente","Pendiente",IF(I67="Equivalente confirmado",IF(OR(J67="",K67=""),"Falta código o nombre",IF(OR(L67="",M67=""),"Falta validación",IF(OR(NOT(ISNUMBER(N67)),N67<=0),"Falta fecha","Homologado"))),IF(I67="Sin equivalente en AVAIN",IF(OR(J67<>"",K67<>""),"Quitar código y nombre",IF(OR(L67="",M67=""),"Falta validación",IF(OR(NOT(ISNUMBER(N67)),N67<=0),"Falta fecha","Sin equivalente confirmado"))),"Revisar decisión"))) -> Pendiente
A68: M01-013 | B68: Medicación | C68: Meloxicam 15 mg | F68: Sin código encontrado | G68: Sin coincidencia | H68: Buscar este ítem en el catálogo de la base. Si existe, registrar código y nombre confirmados. Si no existe, registrar Sin equivalente en AVAIN. Fuente: master original, fila 178. | I68: Pendiente | O68: =IF(I68="Pendiente","Pendiente",IF(I68="Equivalente confirmado",IF(OR(J68="",K68=""),"Falta código o nombre",IF(OR(L68="",M68=""),"Falta validación",IF(OR(NOT(ISNUMBER(N68)),N68<=0),"Falta fecha","Homologado"))),IF(I68="Sin equivalente en AVAIN",IF(OR(J68<>"",K68<>""),"Quitar código y nombre",IF(OR(L68="",M68=""),"Falta validación",IF(OR(NOT(ISNUMBER(N68)),N68<=0),"Falta fecha","Sin equivalente confirmado"))),"Revisar decisión"))) -> Pendiente
A69: M01-014 | B69: Medicación | C69: Colchicina 1 mg | F69: Sin código encontrado | G69: Sin coincidencia | H69: Buscar este ítem en el catálogo de la base. Si existe, registrar código y nombre confirmados. Si no existe, registrar Sin equivalente en AVAIN. Fuente: master original, fila 18. | I69: Pendiente | O69: =IF(I69="Pendiente","Pendiente",IF(I69="Equivalente confirmado",IF(OR(J69="",K69=""),"Falta código o nombre",IF(OR(L69="",M69=""),"Falta validación",IF(OR(NOT(ISNUMBER(N69)),N69<=0),"Falta fecha","Homologado"))),IF(I69="Sin equivalente en AVAIN",IF(OR(J69<>"",K69<>""),"Quitar código y nombre",IF(OR(L69="",M69=""),"Falta validación",IF(OR(NOT(ISNUMBER(N69)),N69<=0),"Falta fecha","Sin equivalente confirmado"))),"Revisar decisión"))) -> Pendiente
A70: M01-015 | B70: Medicación | C70: Ergotamina (antimigrañoso) | F70: Sin código encontrado | G70: Sin coincidencia | H70: Buscar este ítem en el catálogo de la base. Si existe, registrar código y nombre confirmados. Si no existe, registrar Sin equivalente en AVAIN. Fuente: master original, fila 19. | I70: Pendiente | O70: =IF(I70="Pendiente","Pendiente",IF(I70="Equivalente confirmado",IF(OR(J70="",K70=""),"Falta código o nombre",IF(OR(L70="",M70=""),"Falta validación",IF(OR(NOT(ISNUMBER(N70)),N70<=0),"Falta fecha","Homologado"))),IF(I70="Sin equivalente en AVAIN",IF(OR(J70<>"",K70<>""),"Quitar código y nombre",IF(OR(L70="",M70=""),"Falta validación",IF(OR(NOT(ISNUMBER(N70)),N70<=0),"Falta fecha","Sin equivalente confirmado"))),"Revisar decisión"))) -> Pendiente
A71: M01-016 | B71: Medicación | C71: Bencidamina comp. desleíble | F71: Sin código encontrado | G71: Sin coincidencia | H71: Buscar este ítem en el catálogo de la base. Si existe, registrar código y nombre confirmados. Si no existe, registrar Sin equivalente en AVAIN. Fuente: master original, fila 20. | I71: Pendiente | O71: =IF(I71="Pendiente","Pendiente",IF(I71="Equivalente confirmado",IF(OR(J71="",K71=""),"Falta código o nombre",IF(OR(L71="",M71=""),"Falta validación",IF(OR(NOT(ISNUMBER(N71)),N71<=0),"Falta fecha","Homologado"))),IF(I71="Sin equivalente en AVAIN",IF(OR(J71<>"",K71<>""),"Quitar código y nombre",IF(OR(L71="",M71=""),"Falta validación",IF(OR(NOT(ISNUMBER(N71)),N71<=0),"Falta fecha","Sin equivalente confirmado"))),"Revisar decisión"))) -> Pendiente
A72: M02-002 | B72: Medicación | C72: Fentanilo 250 µg/5 ml | F72: Sin código encontrado | G72: Sin coincidencia | H72: Buscar este ítem en el catálogo de la base. Si existe, registrar código y nombre confirmados. Si no existe, registrar Sin equivalente en AVAIN. Fuente: master original, fila 23. | I72: Pendiente | O72: =IF(I72="Pendiente","Pendiente",IF(I72="Equivalente confirmado",IF(OR(J72="",K72=""),"Falta código o nombre",IF(OR(L72="",M72=""),"Falta validación",IF(OR(NOT(ISNUMBER(N72)),N72<=0),"Falta fecha","Homologado"))),IF(I72="Sin equivalente en AVAIN",IF(OR(J72<>"",K72<>""),"Quitar código y nombre",IF(OR(L72="",M72=""),"Falta validación",IF(OR(NOT(ISNUMBER(N72)),N72<=0),"Falta fecha","Sin equivalente confirmado"))),"Revisar decisión"))) -> Pendiente
A73: M02-003 | B73: Medicación | C73: Morfina 10 mg/1 ml | F73: Sin código encontrado | G73: Sin coincidencia | H73: Buscar este ítem en el catálogo de la base. Si existe, registrar código y nombre confirmados. Si no existe, registrar Sin equivalente en AVAIN. Fuente: master original, fila 24. | I73: Pendiente | O73: =IF(I73="Pendiente","Pendiente",IF(I73="Equivalente confirmado",IF(OR(J73="",K73=""),"Falta código o nombre",IF(OR(L73="",M73=""),"Falta validación",IF(OR(NOT(ISNUMBER(N73)),N73<=0),"Falta fecha","Homologado"))),IF(I73="Sin equivalente en AVAIN",IF(OR(J73<>"",K73<>""),"Quitar código y nombre",IF(OR(L73="",M73=""),"Falta validación",IF(OR(NOT(ISNUMBER(N73)),N73<=0),"Falta fecha","Sin equivalente confirmado"))),"Revisar decisión"))) -> Pendiente
A74: M02-004 | B74: Medicación | C74: Nalbufina 10 mg/1 ml | F74: Sin código encontrado | G74: Sin coincidencia | H74: Buscar este ítem en el catálogo de la base. Si existe, registrar código y nombre confirmados. Si no existe, registrar Sin equivalente en AVAIN. Fuente: master original, fila 25. | I74: Pendiente | O74: =IF(I74="Pendiente","Pendiente",IF(I74="Equivalente confirmado",IF(OR(J74="",K74=""),"Falta código o nombre",IF(OR(L74="",M74=""),"Falta validación",IF(OR(NOT(ISNUMBER(N74)),N74<=0),"Falta fecha","Homologado"))),IF(I74="Sin equivalente en AVAIN",IF(OR(J74<>"",K74<>""),"Quitar código y nombre",IF(OR(L74="",M74=""),"Falta validación",IF(OR(NOT(ISNUMBER(N74)),N74<=0),"Falta fecha","Sin equivalente confirmado"))),"Revisar decisión"))) -> Pendiente
A75: M02-005 | B75: Medicación | C75: Etomidato 20 mg/10 ml | F75: Sin código encontrado | G75: Sin coincidencia | H75: Buscar este ítem en el catálogo de la base. Si existe, registrar código y nombre confirmados. Si no existe, registrar Sin equivalente en AVAIN. Fuente: master original, fila 26. | I75: Pendiente | O75: =IF(I75="Pendiente","Pendiente",IF(I75="Equivalente confirmado",IF(OR(J75="",K75=""),"Falta código o nombre",IF(OR(L75="",M75=""),"Falta validación",IF(OR(NOT(ISNUMBER(N75)),N75<=0),"Falta fecha","Homologado"))),IF(I75="Sin equivalente en AVAIN",IF(OR(J75<>"",K75<>""),"Quitar código y nombre",IF(OR(L75="",M75=""),"Falta validación",IF(OR(NOT(ISNUMBER(N75)),N75<=0),"Falta fecha","Sin equivalente confirmado"))),"Revisar decisión"))) -> Pendiente
A76: M02-006 | B76: Medicación | C76: Propofol 200 mg/20 ml | F76: Sin código encontrado | G76: Sin coincidencia | H76: Buscar este ítem en el catálogo de la base. Si existe, registrar código y nombre confirmados. Si no existe, registrar Sin equivalente en AVAIN. Fuente: master original, fila 27. | I76: Pendiente | O76: =IF(I76="Pendiente","Pendiente",IF(I76="Equivalente confirmado",IF(OR(J76="",K76=""),"Falta código o nombre",IF(OR(L76="",M76=""),"Falta validación",IF(OR(NOT(ISNUMBER(N76)),N76<=0),"Falta fecha","Homologado"))),IF(I76="Sin equivalente en AVAIN",IF(OR(J76<>"",K76<>""),"Quitar código y nombre",IF(OR(L76="",M76=""),"Falta validación",IF(OR(NOT(ISNUMBER(N76)),N76<=0),"Falta fecha","Sin equivalente confirmado"))),"Revisar decisión"))) -> Pendiente
A77: M02-007 | B77: Medicación | C77: Succinilcolina 100 mg | F77: Sin código encontrado | G77: Sin coincidencia | H77: Buscar este ítem en el catálogo de la base. Si existe, registrar código y nombre confirmados. Si no existe, registrar Sin equivalente en AVAIN. Fuente: master original, fila 179. | I77: Pendiente | O77: =IF(I77="Pendiente","Pendiente",IF(I77="Equivalente confirmado",IF(OR(J77="",K77=""),"Falta código o nombre",IF(OR(L77="",M77=""),"Falta validación",IF(OR(NOT(ISNUMBER(N77)),N77<=0),"Falta fecha","Homologado"))),IF(I77="Sin equivalente en AVAIN",IF(OR(J77<>"",K77<>""),"Quitar código y nombre",IF(OR(L77="",M77=""),"Falta validación",IF(OR(NOT(ISNUMBER(N77)),N77<=0),"Falta fecha","Sin equivalente confirmado"))),"Revisar decisión"))) -> Pendiente
A78: M03-005 | B78: Medicación | C78: Bicarbonato de sodio 8,4% | D78: DES058 | E78: Bicarbonato de sodio 1 fco =100ml | F78: Equivalencia a revisar | G78: Media | H78: Comparar producto, concentración, forma, presentación o tamaño. La descripción relevada no alcanza para confirmar la equivalencia. Fuente: master original, fila 180. | I78: Pendiente | O78: =IF(I78="Pendiente","Pendiente",IF(I78="Equivalente confirmado",IF(OR(J78="",K78=""),"Falta código o nombre",IF(OR(L78="",M78=""),"Falta validación",IF(OR(NOT(ISNUMBER(N78)),N78<=0),"Falta fecha","Homologado"))),IF(I78="Sin equivalente en AVAIN",IF(OR(J78<>"",K78<>""),"Quitar código y nombre",IF(OR(L78="",M78=""),"Falta validación",IF(OR(NOT(ISNUMBER(N78)),N78<=0),"Falta fecha","Sin equivalente confirmado"))),"Revisar decisión"))) -> Pendiente
A79: M03-006 | B79: Medicación | C79: Gluconato de calcio 10% | F79: Sin código encontrado | G79: Sin coincidencia | H79: Buscar este ítem en el catálogo de la base. Si existe, registrar código y nombre confirmados. Si no existe, registrar Sin equivalente en AVAIN. Fuente: master original, fila 34. | I79: Pendiente | O79: =IF(I79="Pendiente","Pendiente",IF(I79="Equivalente confirmado",IF(OR(J79="",K79=""),"Falta código o nombre",IF(OR(L79="",M79=""),"Falta validación",IF(OR(NOT(ISNUMBER(N79)),N79<=0),"Falta fecha","Homologado"))),IF(I79="Sin equivalente en AVAIN",IF(OR(J79<>"",K79<>""),"Quitar código y nombre",IF(OR(L79="",M79=""),"Falta validación",IF(OR(NOT(ISNUMBER(N79)),N79<=0),"Falta fecha","Sin equivalente confirmado"))),"Revisar decisión"))) -> Pendiente
A80: M03-007 | B80: Medicación | C80: Dopamina 200 mg/5 ml | F80: Sin código encontrado | G80: Sin coincidencia | H80: Buscar este ítem en el catálogo de la base. Si existe, registrar código y nombre confirmados. Si no existe, registrar Sin equivalente en AVAIN. Fuente: master original, fila 35. | I80: Pendiente | O80: =IF(I80="Pendiente","Pendiente",IF(I80="Equivalente confirmado",IF(OR(J80="",K80=""),"Falta código o nombre",IF(OR(L80="",M80=""),"Falta validación",IF(OR(NOT(ISNUMBER(N80)),N80<=0),"Falta fecha","Homologado"))),IF(I80="Sin equivalente en AVAIN",IF(OR(J80<>"",K80<>""),"Quitar código y nombre",IF(OR(L80="",M80=""),"Falta validación",IF(OR(NOT(ISNUMBER(N80)),N80<=0),"Falta fecha","Sin equivalente confirmado"))),"Revisar decisión"))) -> Pendiente
A81: M03-008 | B81: Medicación | C81: Noradrenalina 4 mg/4 ml | F81: Sin código encontrado | G81: Sin coincidencia | H81: Buscar este ítem en el catálogo de la base. Si existe, registrar código y nombre confirmados. Si no existe, registrar Sin equivalente en AVAIN. Fuente: master original, fila 36. | I81: Pendiente | O81: =IF(I81="Pendiente","Pendiente",IF(I81="Equivalente confirmado",IF(OR(J81="",K81=""),"Falta código o nombre",IF(OR(L81="",M81=""),"Falta validación",IF(OR(NOT(ISNUMBER(N81)),N81<=0),"Falta fecha","Homologado"))),IF(I81="Sin equivalente en AVAIN",IF(OR(J81<>"",K81<>""),"Quitar código y nombre",IF(OR(L81="",M81=""),"Falta validación",IF(OR(NOT(ISNUMBER(N81)),N81<=0),"Falta fecha","Sin equivalente confirmado"))),"Revisar decisión"))) -> Pendiente
A82: M03-009 | B82: Medicación | C82: Dobutamina 250 mg/20 ml | F82: Sin código encontrado | G82: Sin coincidencia | H82: Buscar este ítem en el catálogo de la base. Si existe, registrar código y nombre confirmados. Si no existe, registrar Sin equivalente en AVAIN. Fuente: master original, fila 37. | I82: Pendiente | O82: =IF(I82="Pendiente","Pendiente",IF(I82="Equivalente confirmado",IF(OR(J82="",K82=""),"Falta código o nombre",IF(OR(L82="",M82=""),"Falta validación",IF(OR(NOT(ISNUMBER(N82)),N82<=0),"Falta fecha","Homologado"))),IF(I82="Sin equivalente en AVAIN",IF(OR(J82<>"",K82<>""),"Quitar código y nombre",IF(OR(L82="",M82=""),"Falta validación",IF(OR(NOT(ISNUMBER(N82)),N82<=0),"Falta fecha","Sin equivalente confirmado"))),"Revisar decisión"))) -> Pendiente
A83: M03-010 | B83: Medicación | C83: Cloruro de potasio amp. | F83: Sin código encontrado | G83: Sin coincidencia | H83: Buscar este ítem en el catálogo de la base. Si existe, registrar código y nombre confirmados. Si no existe, registrar Sin equivalente en AVAIN. Fuente: master original, fila 38. | I83: Pendiente | O83: =IF(I83="Pendiente","Pendiente",IF(I83="Equivalente confirmado",IF(OR(J83="",K83=""),"Falta código o nombre",IF(OR(L83="",M83=""),"Falta validación",IF(OR(NOT(ISNUMBER(N83)),N83<=0),"Falta fecha","Homologado"))),IF(I83="Sin equivalente en AVAIN",IF(OR(J83<>"",K83<>""),"Quitar código y nombre",IF(OR(L83="",M83=""),"Falta validación",IF(OR(NOT(ISNUMBER(N83)),N83<=0),"Falta fecha","Sin equivalente confirmado"))),"Revisar decisión"))) -> Pendiente
A84: M04-001 | B84: Medicación | C84: Clopidogrel 75 mg | F84: Sin código encontrado | G84: Sin coincidencia | H84: Buscar este ítem en el catálogo de la base. Si existe, registrar código y nombre confirmados. Si no existe, registrar Sin equivalente en AVAIN. Fuente: master original, fila 39. | I84: Pendiente | O84: =IF(I84="Pendiente","Pendiente",IF(I84="Equivalente confirmado",IF(OR(J84="",K84=""),"Falta código o nombre",IF(OR(L84="",M84=""),"Falta validación",IF(OR(NOT(ISNUMBER(N84)),N84<=0),"Falta fecha","Homologado"))),IF(I84="Sin equivalente en AVAIN",IF(OR(J84<>"",K84<>""),"Quitar código y nombre",IF(OR(L84="",M84=""),"Falta validación",IF(OR(NOT(ISNUMBER(N84)),N84<=0),"Falta fecha","Sin equivalente confirmado"))),"Revisar decisión"))) -> Pendiente
A85: M04-006 | B85: Medicación | C85: Isosorbide dinitrato 5 mg SL | F85: Sin código encontrado | G85: Sin coincidencia | H85: Buscar este ítem en el catálogo de la base. Si existe, registrar código y nombre confirmados. Si no existe, registrar Sin equivalente en AVAIN. Fuente: master original, fila 44. | I85: Pendiente | O85: =IF(I85="Pendiente","Pendiente",IF(I85="Equivalente confirmado",IF(OR(J85="",K85=""),"Falta código o nombre",IF(OR(L85="",M85=""),"Falta validación",IF(OR(NOT(ISNUMBER(N85)),N85<=0),"Falta fecha","Homologado"))),IF(I85="Sin equivalente en AVAIN",IF(OR(J85<>"",K85<>""),"Quitar código y nombre",IF(OR(L85="",M85=""),"Falta validación",IF(OR(NOT(ISNUMBER(N85)),N85<=0),"Falta fecha","Sin equivalente confirmado"))),"Revisar decisión"))) -> Pendiente
A86: M04-007 | B86: Medicación | C86: Nitroglicerina 25-50 mg amp. | D86: DES042 | E86: Nitroglicerina 1 amp=3ml | F86: Equivalencia a revisar | G86: Media | H86: Comparar producto, concentración, forma, presentación o tamaño. La descripción relevada no alcanza para confirmar la equivalencia. Fuente: master original, fila 45. | I86: Pendiente | O86: =IF(I86="Pendiente","Pendiente",IF(I86="Equivalente confirmado",IF(OR(J86="",K86=""),"Falta código o nombre",IF(OR(L86="",M86=""),"Falta validación",IF(OR(NOT(ISNUMBER(N86)),N86<=0),"Falta fecha","Homologado"))),IF(I86="Sin equivalente en AVAIN",IF(OR(J86<>"",K86<>""),"Quitar código y nombre",IF(OR(L86="",M86=""),"Falta validación",IF(OR(NOT(ISNUMBER(N86)),N86<=0),"Falta fecha","Sin equivalente confirmado"))),"Revisar decisión"))) -> Pendiente
A87: M04-008 | B87: Medicación | C87: Digoxina 0,25 mg/1 ml | F87: Sin código encontrado | G87: Sin coincidencia | H87: Buscar este ítem en el catálogo de la base. Si existe, registrar código y nombre confirmados. Si no existe, registrar Sin equivalente en AVAIN. Fuente: master original, fila 46. | I87: Pendiente | O87: =IF(I87="Pendiente","Pendiente",IF(I87="Equivalente confirmado",IF(OR(J87="",K87=""),"Falta código o nombre",IF(OR(L87="",M87=""),"Falta validación",IF(OR(NOT(ISNUMBER(N87)),N87<=0),"Falta fecha","Homologado"))),IF(I87="Sin equivalente en AVAIN",IF(OR(J87<>"",K87<>""),"Quitar código y nombre",IF(OR(L87="",M87=""),"Falta validación",IF(OR(NOT(ISNUMBER(N87)),N87<=0),"Falta fecha","Sin equivalente confirmado"))),"Revisar decisión"))) -> Pendiente
A88: M04-009 | B88: Medicación | C88: Labetalol 20 mg/4 ml | F88: Sin código encontrado | G88: Sin coincidencia | H88: Buscar este ítem en el catálogo de la base. Si existe, registrar código y nombre confirmados. Si no existe, registrar Sin equivalente en AVAIN. Fuente: master original, fila 47. | I88: Pendiente | O88: =IF(I88="Pendiente","Pendiente",IF(I88="Equivalente confirmado",IF(OR(J88="",K88=""),"Falta código o nombre",IF(OR(L88="",M88=""),"Falta validación",IF(OR(NOT(ISNUMBER(N88)),N88<=0),"Falta fecha","Homologado"))),IF(I88="Sin equivalente en AVAIN",IF(OR(J88<>"",K88<>""),"Quitar código y nombre",IF(OR(L88="",M88=""),"Falta validación",IF(OR(NOT(ISNUMBER(N88)),N88<=0),"Falta fecha","Sin equivalente confirmado"))),"Revisar decisión"))) -> Pendiente
A89: M04-010 | B89: Medicación | C89: Nitroprusiato de sodio 50 mg | F89: Sin código encontrado | G89: Sin coincidencia | H89: Buscar este ítem en el catálogo de la base. Si existe, registrar código y nombre confirmados. Si no existe, registrar Sin equivalente en AVAIN. Fuente: master original, fila 48. | I89: Pendiente | O89: =IF(I89="Pendiente","Pendiente",IF(I89="Equivalente confirmado",IF(OR(J89="",K89=""),"Falta código o nombre",IF(OR(L89="",M89=""),"Falta validación",IF(OR(NOT(ISNUMBER(N89)),N89<=0),"Falta fecha","Homologado"))),IF(I89="Sin equivalente en AVAIN",IF(OR(J89<>"",K89<>""),"Quitar código y nombre",IF(OR(L89="",M89=""),"Falta validación",IF(OR(NOT(ISNUMBER(N89)),N89<=0),"Falta fecha","Sin equivalente confirmado"))),"Revisar decisión"))) -> Pendiente
A90: M04-011 | B90: Medicación | C90: Atorvastatina 20 mg | F90: Sin código encontrado | G90: Sin coincidencia | H90: Buscar este ítem en el catálogo de la base. Si existe, registrar código y nombre confirmados. Si no existe, registrar Sin equivalente en AVAIN. Fuente: master original, fila 49. | I90: Pendiente | O90: =IF(I90="Pendiente","Pendiente",IF(I90="Equivalente confirmado",IF(OR(J90="",K90=""),"Falta código o nombre",IF(OR(L90="",M90=""),"Falta validación",IF(OR(NOT(ISNUMBER(N90)),N90<=0),"Falta fecha","Homologado"))),IF(I90="Sin equivalente en AVAIN",IF(OR(J90<>"",K90<>""),"Quitar código y nombre",IF(OR(L90="",M90=""),"Falta validación",IF(OR(NOT(ISNUMBER(N90)),N90<=0),"Falta fecha","Sin equivalente confirmado"))),"Revisar decisión"))) -> Pendiente
A91: M04-012 | B91: Medicación | C91: Bisoprolol 2,5 mg | F91: Sin código encontrado | G91: Sin coincidencia | H91: Buscar este ítem en el catálogo de la base. Si existe, registrar código y nombre confirmados. Si no existe, registrar Sin equivalente en AVAIN. Fuente: master original, fila 50. | I91: Pendiente | O91: =IF(I91="Pendiente","Pendiente",IF(I91="Equivalente confirmado",IF(OR(J91="",K91=""),"Falta código o nombre",IF(OR(L91="",M91=""),"Falta validación",IF(OR(NOT(ISNUMBER(N91)),N91<=0),"Falta fecha","Homologado"))),IF(I91="Sin equivalente en AVAIN",IF(OR(J91<>"",K91<>""),"Quitar código y nombre",IF(OR(L91="",M91=""),"Falta validación",IF(OR(NOT(ISNUMBER(N91)),N91<=0),"Falta fecha","Sin equivalente confirmado"))),"Revisar decisión"))) -> Pendiente
A92: M04-013 | B92: Medicación | C92: Nifedipina 30 mg | F92: Sin código encontrado | G92: Sin coincidencia | H92: Buscar este ítem en el catálogo de la base. Si existe, registrar código y nombre confirmados. Si no existe, registrar Sin equivalente en AVAIN. Fuente: master original, fila 51. | I92: Pendiente | O92: =IF(I92="Pendiente","Pendiente",IF(I92="Equivalente confirmado",IF(OR(J92="",K92=""),"Falta código o nombre",IF(OR(L92="",M92=""),"Falta validación",IF(OR(NOT(ISNUMBER(N92)),N92<=0),"Falta fecha","Homologado"))),IF(I92="Sin equivalente en AVAIN",IF(OR(J92<>"",K92<>""),"Quitar código y nombre",IF(OR(L92="",M92=""),"Falta validación",IF(OR(NOT(ISNUMBER(N92)),N92<=0),"Falta fecha","Sin equivalente confirmado"))),"Revisar decisión"))) -> Pendiente
A93: M04-014 | B93: Medicación | C93: Ácido tranexámico 500 mg/5 ml | F93: Sin código encontrado | G93: Sin coincidencia | H93: Buscar este ítem en el catálogo de la base. Si existe, registrar código y nombre confirmados. Si no existe, registrar Sin equivalente en AVAIN. Fuente: master original, fila 52. | I93: Pendiente | O93: =IF(I93="Pendiente","Pendiente",IF(I93="Equivalente confirmado",IF(OR(J93="",K93=""),"Falta código o nombre",IF(OR(L93="",M93=""),"Falta validación",IF(OR(NOT(ISNUMBER(N93)),N93<=0),"Falta fecha","Homologado"))),IF(I93="Sin equivalente en AVAIN",IF(OR(J93<>"",K93<>""),"Quitar código y nombre",IF(OR(L93="",M93=""),"Falta validación",IF(OR(NOT(ISNUMBER(N93)),N93<=0),"Falta fecha","Sin equivalente confirmado"))),"Revisar decisión"))) -> Pendiente
A94: M04-015 | B94: Medicación | C94: Sulfato de magnesio 25% | F94: Sin código encontrado | G94: Sin coincidencia | H94: Buscar este ítem en el catálogo de la base. Si existe, registrar código y nombre confirmados. Si no existe, registrar Sin equivalente en AVAIN. Fuente: master original, fila 184. | I94: Pendiente | O94: =IF(I94="Pendiente","Pendiente",IF(I94="Equivalente confirmado",IF(OR(J94="",K94=""),"Falta código o nombre",IF(OR(L94="",M94=""),"Falta validación",IF(OR(NOT(ISNUMBER(N94)),N94<=0),"Falta fecha","Homologado"))),IF(I94="Sin equivalente en AVAIN",IF(OR(J94<>"",K94<>""),"Quitar código y nombre",IF(OR(L94="",M94=""),"Falta validación",IF(OR(NOT(ISNUMBER(N94)),N94<=0),"Falta fecha","Sin equivalente confirmado"))),"Revisar decisión"))) -> Pendiente
A95: M04-016 | B95: Medicación | C95: Alteplasa 50 mg | F95: Sin código encontrado | G95: Sin coincidencia | H95: Buscar este ítem en el catálogo de la base. Si existe, registrar código y nombre confirmados. Si no existe, registrar Sin equivalente en AVAIN. Fuente: master original, fila 54. | I95: Pendiente | O95: =IF(I95="Pendiente","Pendiente",IF(I95="Equivalente confirmado",IF(OR(J95="",K95=""),"Falta código o nombre",IF(OR(L95="",M95=""),"Falta validación",IF(OR(NOT(ISNUMBER(N95)),N95<=0),"Falta fecha","Homologado"))),IF(I95="Sin equivalente en AVAIN",IF(OR(J95<>"",K95<>""),"Quitar código y nombre",IF(OR(L95="",M95=""),"Falta validación",IF(OR(NOT(ISNUMBER(N95)),N95<=0),"Falta fecha","Sin equivalente confirmado"))),"Revisar decisión"))) -> Pendiente
A96: M05-003 | B96: Medicación | C96: Ipratropio bromuro p/neb. | F96: Sin código encontrado | G96: Sin coincidencia | H96: Buscar este ítem en el catálogo de la base. Si existe, registrar código y nombre confirmados. Si no existe, registrar Sin equivalente en AVAIN. Fuente: master original, fila 186. | I96: Pendiente | O96: =IF(I96="Pendiente","Pendiente",IF(I96="Equivalente confirmado",IF(OR(J96="",K96=""),"Falta código o nombre",IF(OR(L96="",M96=""),"Falta validación",IF(OR(NOT(ISNUMBER(N96)),N96<=0),"Falta fecha","Homologado"))),IF(I96="Sin equivalente en AVAIN",IF(OR(J96<>"",K96<>""),"Quitar código y nombre",IF(OR(L96="",M96=""),"Falta validación",IF(OR(NOT(ISNUMBER(N96)),N96<=0),"Falta fecha","Sin equivalente confirmado"))),"Revisar decisión"))) -> Pendiente
A97: M05-004 | B97: Medicación | C97: Budesonide aerosol | F97: Sin código encontrado | G97: Sin coincidencia | H97: Buscar este ítem en el catálogo de la base. Si existe, registrar código y nombre confirmados. Si no existe, registrar Sin equivalente en AVAIN. Fuente: master original, fila 188. | I97: Pendiente | O97: =IF(I97="Pendiente","Pendiente",IF(I97="Equivalente confirmado",IF(OR(J97="",K97=""),"Falta código o nombre",IF(OR(L97="",M97=""),"Falta validación",IF(OR(NOT(ISNUMBER(N97)),N97<=0),"Falta fecha","Homologado"))),IF(I97="Sin equivalente en AVAIN",IF(OR(J97<>"",K97<>""),"Quitar código y nombre",IF(OR(L97="",M97=""),"Falta validación",IF(OR(NOT(ISNUMBER(N97)),N97<=0),"Falta fecha","Sin equivalente confirmado"))),"Revisar decisión"))) -> Pendiente
A98: M05-005 | B98: Medicación | C98: Solución hipertónica nasal (Hypersol) | F98: Sin código encontrado | G98: Sin coincidencia | H98: Buscar este ítem en el catálogo de la base. Si existe, registrar código y nombre confirmados. Si no existe, registrar Sin equivalente en AVAIN. Fuente: master original, fila 6. | I98: Pendiente | O98: =IF(I98="Pendiente","Pendiente",IF(I98="Equivalente confirmado",IF(OR(J98="",K98=""),"Falta código o nombre",IF(OR(L98="",M98=""),"Falta validación",IF(OR(NOT(ISNUMBER(N98)),N98<=0),"Falta fecha","Homologado"))),IF(I98="Sin equivalente en AVAIN",IF(OR(J98<>"",K98<>""),"Quitar código y nombre",IF(OR(L98="",M98=""),"Falta validación",IF(OR(NOT(ISNUMBER(N98)),N98<=0),"Falta fecha","Sin equivalente confirmado"))),"Revisar decisión"))) -> Pendiente
... A194: K-227 | B194: Componentes de kit | C194: Lubricante hidrosoluble | F194: Sin código encontrado | G194: Sin coincidencia | H194: Buscar este ítem en el catálogo de la base. Si existe, registrar código y nombre confirmados. Si no existe, registrar Sin equivalente en AVAIN. Fuente: master original, fila 229. | I194: Pendiente | O194: =IF(I194="Pendiente","Pendiente",IF(I194="Equivalente confirmado",IF(OR(J194="",K194=""),"Falta código o nombre",IF(OR(L194="",M194=""),"Falta validación",IF(OR(NOT(ISNUMBER(N194)),N194<=0),"Falta fecha","Homologado"))),IF(I194="Sin equivalente en AVAIN",IF(OR(J194<>"",K194<>""),"Quitar código y nombre",IF(OR(L194="",M194=""),"Falta validación",IF(OR(NOT(ISNUMBER(N194)),N194<=0),"Falta fecha","Sin equivalente confirmado"))),"Revisar decisión"))) -> Pendiente
A195: K-229 | B195: Componentes de kit | C195: Filtro MHEF | D195: DESC61 | E195: Filtro para ventilación artificial | F195: Equivalencia a revisar | G195: Media | H195: Comparar producto, concentración, forma, presentación o tamaño. La descripción relevada no alcanza para confirmar la equivalencia. Fuente: master original, fila 231. | I195: Pendiente | O195: =IF(I195="Pendiente","Pendiente",IF(I195="Equivalente confirmado",IF(OR(J195="",K195=""),"Falta código o nombre",IF(OR(L195="",M195=""),"Falta validación",IF(OR(NOT(ISNUMBER(N195)),N195<=0),"Falta fecha","Homologado"))),IF(I195="Sin equivalente en AVAIN",IF(OR(J195<>"",K195<>""),"Quitar código y nombre",IF(OR(L195="",M195=""),"Falta validación",IF(OR(NOT(ISNUMBER(N195)),N195<=0),"Falta fecha","Sin equivalente confirmado"))),"Revisar decisión"))) -> Pendiente
A196: K-232 | B196: Componentes de kit | C196: Collar cervical adulto regulable | F196: Sin código encontrado | G196: Sin coincidencia | H196: Buscar este ítem en el catálogo de la base. Si existe, registrar código y nombre confirmados. Si no existe, registrar Sin equivalente en AVAIN. Fuente: master original, fila 119. | I196: Pendiente | O196: =IF(I196="Pendiente","Pendiente",IF(I196="Equivalente confirmado",IF(OR(J196="",K196=""),"Falta código o nombre",IF(OR(L196="",M196=""),"Falta validación",IF(OR(NOT(ISNUMBER(N196)),N196<=0),"Falta fecha","Homologado"))),IF(I196="Sin equivalente en AVAIN",IF(OR(J196<>"",K196<>""),"Quitar código y nombre",IF(OR(L196="",M196=""),"Falta validación",IF(OR(NOT(ISNUMBER(N196)),N196<=0),"Falta fecha","Sin equivalente confirmado"))),"Revisar decisión"))) -> Pendiente
A197: K-233 | B197: Componentes de kit | C197: Guantes estériles 7,5 y 8 | F197: Sin código encontrado | G197: Sin coincidencia | H197: Buscar este ítem en el catálogo de la base. Si existe, registrar código y nombre confirmados. Si no existe, registrar Sin equivalente en AVAIN. Fuente: master original, fila 269. | I197: Pendiente | O197: =IF(I197="Pendiente","Pendiente",IF(I197="Equivalente confirmado",IF(OR(J197="",K197=""),"Falta código o nombre",IF(OR(L197="",M197=""),"Falta validación",IF(OR(NOT(ISNUMBER(N197)),N197<=0),"Falta fecha","Homologado"))),IF(I197="Sin equivalente en AVAIN",IF(OR(J197<>"",K197<>""),"Quitar código y nombre",IF(OR(L197="",M197=""),"Falta validación",IF(OR(NOT(ISNUMBER(N197)),N197<=0),"Falta fecha","Sin equivalente confirmado"))),"Revisar decisión"))) -> Pendiente
A198: K-235 | B198: Componentes de kit | C198: Antiparras | F198: Sin código encontrado | G198: Sin coincidencia | H198: Buscar este ítem en el catálogo de la base. Si existe, registrar código y nombre confirmados. Si no existe, registrar Sin equivalente en AVAIN. Fuente: master original, fila 236. | I198: Pendiente | O198: =IF(I198="Pendiente","Pendiente",IF(I198="Equivalente confirmado",IF(OR(J198="",K198=""),"Falta código o nombre",IF(OR(L198="",M198=""),"Falta validación",IF(OR(NOT(ISNUMBER(N198)),N198<=0),"Falta fecha","Homologado"))),IF(I198="Sin equivalente en AVAIN",IF(OR(J198<>"",K198<>""),"Quitar código y nombre",IF(OR(L198="",M198=""),"Falta validación",IF(OR(NOT(ISNUMBER(N198)),N198<=0),"Falta fecha","Sin equivalente confirmado"))),"Revisar decisión"))) -> Pendiente
A199: K-237 | B199: Componentes de kit | C199: Cánula orofaríngea (varios) | F199: Sin código encontrado | G199: Sin coincidencia | H199: Buscar este ítem en el catálogo de la base. Si existe, registrar código y nombre confirmados. Si no existe, registrar Sin equivalente en AVAIN. Fuente: master original, fila 238. | I199: Pendiente | O199: =IF(I199="Pendiente","Pendiente",IF(I199="Equivalente confirmado",IF(OR(J199="",K199=""),"Falta código o nombre",IF(OR(L199="",M199=""),"Falta validación",IF(OR(NOT(ISNUMBER(N199)),N199<=0),"Falta fecha","Homologado"))),IF(I199="Sin equivalente en AVAIN",IF(OR(J199<>"",K199<>""),"Quitar código y nombre",IF(OR(L199="",M199=""),"Falta validación",IF(OR(NOT(ISNUMBER(N199)),N199<=0),"Falta fecha","Sin equivalente confirmado"))),"Revisar decisión"))) -> Pendiente
A200: K-238 | B200: Componentes de kit | C200: Tijera de trauma | F200: Sin código encontrado | G200: Sin coincidencia | H200: Buscar este ítem en el catálogo de la base. Si existe, registrar código y nombre confirmados. Si no existe, registrar Sin equivalente en AVAIN. Fuente: master original, fila 134. | I200: Pendiente | O200: =IF(I200="Pendiente","Pendiente",IF(I200="Equivalente confirmado",IF(OR(J200="",K200=""),"Falta código o nombre",IF(OR(L200="",M200=""),"Falta validación",IF(OR(NOT(ISNUMBER(N200)),N200<=0),"Falta fecha","Homologado"))),IF(I200="Sin equivalente en AVAIN",IF(OR(J200<>"",K200<>""),"Quitar código y nombre",IF(OR(L200="",M200=""),"Falta validación",IF(OR(NOT(ISNUMBER(N200)),N200<=0),"Falta fecha","Sin equivalente confirmado"))),"Revisar decisión"))) -> Pendiente
A201: K-239 | B201: Componentes de kit | C201: Hoja de bisturí | F201: Sin código encontrado | G201: Sin coincidencia | H201: Buscar este ítem en el catálogo de la base. Si existe, registrar código y nombre confirmados. Si no existe, registrar Sin equivalente en AVAIN. Fuente: master original, fila 270. | I201: Pendiente | O201: =IF(I201="Pendiente","Pendiente",IF(I201="Equivalente confirmado",IF(OR(J201="",K201=""),"Falta código o nombre",IF(OR(L201="",M201=""),"Falta validación",IF(OR(NOT(ISNUMBER(N201)),N201<=0),"Falta fecha","Homologado"))),IF(I201="Sin equivalente en AVAIN",IF(OR(J201<>"",K201<>""),"Quitar código y nombre",IF(OR(L201="",M201=""),"Falta validación",IF(OR(NOT(ISNUMBER(N201)),N201<=0),"Falta fecha","Sin equivalente confirmado"))),"Revisar decisión"))) -> Pendiente
A202: K-242 | B202: Componentes de kit | C202: Set de férulas (MMSS-MMII) | F202: Sin código encontrado | G202: Sin coincidencia | H202: Buscar este ítem en el catálogo de la base. Si existe, registrar código y nombre confirmados. Si no existe, registrar Sin equivalente en AVAIN. Fuente: master original, fila 243. | I202: Pendiente | O202: =IF(I202="Pendiente","Pendiente",IF(I202="Equivalente confirmado",IF(OR(J202="",K202=""),"Falta código o nombre",IF(OR(L202="",M202=""),"Falta validación",IF(OR(NOT(ISNUMBER(N202)),N202<=0),"Falta fecha","Homologado"))),IF(I202="Sin equivalente en AVAIN",IF(OR(J202<>"",K202<>""),"Quitar código y nombre",IF(OR(L202="",M202=""),"Falta validación",IF(OR(NOT(ISNUMBER(N202)),N202<=0),"Falta fecha","Sin equivalente confirmado"))),"Revisar decisión"))) -> Pendiente
A203: K-245 | B203: Componentes de kit | C203: Mantas térmicas | F203: Sin código encontrado | G203: Sin coincidencia | H203: Buscar este ítem en el catálogo de la base. Si existe, registrar código y nombre confirmados. Si no existe, registrar Sin equivalente en AVAIN. Fuente: master original, fila 246. | I203: Pendiente | O203: =IF(I203="Pendiente","Pendiente",IF(I203="Equivalente confirmado",IF(OR(J203="",K203=""),"Falta código o nombre",IF(OR(L203="",M203=""),"Falta validación",IF(OR(NOT(ISNUMBER(N203)),N203<=0),"Falta fecha","Homologado"))),IF(I203="Sin equivalente en AVAIN",IF(OR(J203<>"",K203<>""),"Quitar código y nombre",IF(OR(L203="",M203=""),"Falta validación",IF(OR(NOT(ISNUMBER(N203)),N203<=0),"Falta fecha","Sin equivalente confirmado"))),"Revisar decisión"))) -> Pendiente
A204: K-246 | B204: Componentes de kit | C204: Parches oculares | F204: Sin código encontrado | G204: Sin coincidencia | H204: Buscar este ítem en el catálogo de la base. Si existe, registrar código y nombre confirmados. Si no existe, registrar Sin equivalente en AVAIN. Fuente: master original, fila 271. | I204: Pendiente | O204: =IF(I204="Pendiente","Pendiente",IF(I204="Equivalente confirmado",IF(OR(J204="",K204=""),"Falta código o nombre",IF(OR(L204="",M204=""),"Falta validación",IF(OR(NOT(ISNUMBER(N204)),N204<=0),"Falta fecha","Homologado"))),IF(I204="Sin equivalente en AVAIN",IF(OR(J204<>"",K204<>""),"Quitar código y nombre",IF(OR(L204="",M204=""),"Falta validación",IF(OR(NOT(ISNUMBER(N204)),N204<=0),"Falta fecha","Sin equivalente confirmado"))),"Revisar decisión"))) -> Pendiente
A205: K-247 | B205: Componentes de kit | C205: Torniquete táctico | F205: Sin código encontrado | G205: Sin coincidencia | H205: Buscar este ítem en el catálogo de la base. Si existe, registrar código y nombre confirmados. Si no existe, registrar Sin equivalente en AVAIN. Fuente: master original, fila 140. | I205: Pendiente | O205: =IF(I205="Pendiente","Pendiente",IF(I205="Equivalente confirmado",IF(OR(J205="",K205=""),"Falta código o nombre",IF(OR(L205="",M205=""),"Falta validación",IF(OR(NOT(ISNUMBER(N205)),N205<=0),"Falta fecha","Homologado"))),IF(I205="Sin equivalente en AVAIN",IF(OR(J205<>"",K205<>""),"Quitar código y nombre",IF(OR(L205="",M205=""),"Falta validación",IF(OR(NOT(ISNUMBER(N205)),N205<=0),"Falta fecha","Sin equivalente confirmado"))),"Revisar decisión"))) -> Pendiente
A206: K-248 | B206: Componentes de kit | C206: Linterna | F206: Sin código encontrado | G206: Sin coincidencia | H206: Buscar este ítem en el catálogo de la base. Si existe, registrar código y nombre confirmados. Si no existe, registrar Sin equivalente en AVAIN. Fuente: master original, fila 249. | I206: Pendiente | O206: =IF(I206="Pendiente","Pendiente",IF(I206="Equivalente confirmado",IF(OR(J206="",K206=""),"Falta código o nombre",IF(OR(L206="",M206=""),"Falta validación",IF(OR(NOT(ISNUMBER(N206)),N206<=0),"Falta fecha","Homologado"))),IF(I206="Sin equivalente en AVAIN",IF(OR(J206<>"",K206<>""),"Quitar código y nombre",IF(OR(L206="",M206=""),"Falta validación",IF(OR(NOT(ISNUMBER(N206)),N206<=0),"Falta fecha","Sin equivalente confirmado"))),"Revisar decisión"))) -> Pendiente
A207: K-250 | B207: Componentes de kit | C207: Set de férulas pediátricas | F207: Sin código encontrado | G207: Sin coincidencia | H207: Buscar este ítem en el catálogo de la base. Si existe, registrar código y nombre confirmados. Si no existe, registrar Sin equivalente en AVAIN. Fuente: master original, fila 250. | I207: Pendiente | O207: =IF(I207="Pendiente","Pendiente",IF(I207="Equivalente confirmado",IF(OR(J207="",K207=""),"Falta código o nombre",IF(OR(L207="",M207=""),"Falta validación",IF(OR(NOT(ISNUMBER(N207)),N207<=0),"Falta fecha","Homologado"))),IF(I207="Sin equivalente en AVAIN",IF(OR(J207<>"",K207<>""),"Quitar código y nombre",IF(OR(L207="",M207=""),"Falta validación",IF(OR(NOT(ISNUMBER(N207)),N207<=0),"Falta fecha","Sin equivalente confirmado"))),"Revisar decisión"))) -> Pendiente
... A229: K-290 | B229: Componentes de kit | C229: Antiparras | F229: Sin código encontrado | G229: Sin coincidencia | H229: Buscar este ítem en el catálogo de la base. Si existe, registrar código y nombre confirmados. Si no existe, registrar Sin equivalente en AVAIN. Fuente: master original, fila 287. | I229: Pendiente | O229: =IF(I229="Pendiente","Pendiente",IF(I229="Equivalente confirmado",IF(OR(J229="",K229=""),"Falta código o nombre",IF(OR(L229="",M229=""),"Falta validación",IF(OR(NOT(ISNUMBER(N229)),N229<=0),"Falta fecha","Homologado"))),IF(I229="Sin equivalente en AVAIN",IF(OR(J229<>"",K229<>""),"Quitar código y nombre",IF(OR(L229="",M229=""),"Falta validación",IF(OR(NOT(ISNUMBER(N229)),N229<=0),"Falta fecha","Sin equivalente confirmado"))),"Revisar decisión"))) -> Pendiente
A230: M01-001 | B230: Medicación | C230: Ácido acetilsalicílico 100 mg | D230: MED4 | E230: Acido Acetil Salicílico Comp x 100 mg | F230: Coincidencia por validar | G230: Alta | H230: El relevamiento indica una coincidencia probable. Confirmar las características del producto y la existencia del código en esta base. Fuente: master original, fila 166. | I230: Pendiente | O230: =IF(I230="Pendiente","Pendiente",IF(I230="Equivalente confirmado",IF(OR(J230="",K230=""),"Falta código o nombre",IF(OR(L230="",M230=""),"Falta validación",IF(OR(NOT(ISNUMBER(N230)),N230<=0),"Falta fecha","Homologado"))),IF(I230="Sin equivalente en AVAIN",IF(OR(J230<>"",K230<>""),"Quitar código y nombre",IF(OR(L230="",M230=""),"Falta validación",IF(OR(NOT(ISNUMBER(N230)),N230<=0),"Falta fecha","Sin equivalente confirmado"))),"Revisar decisión"))) -> Pendiente
A231: M01-002 | B231: Medicación | C231: Diclofenac 75 mg comp. | D231: DES001 | E231: Diclofenac Comp x 75mg | F231: Coincidencia por validar | G231: Alta | H231: El relevamiento indica una coincidencia probable. Confirmar las características del producto y la existencia del código en esta base. Fuente: master original, fila 4. | I231: Pendiente | O231: =IF(I231="Pendiente","Pendiente",IF(I231="Equivalente confirmado",IF(OR(J231="",K231=""),"Falta código o nombre",IF(OR(L231="",M231=""),"Falta validación",IF(OR(NOT(ISNUMBER(N231)),N231<=0),"Falta fecha","Homologado"))),IF(I231="Sin equivalente en AVAIN",IF(OR(J231<>"",K231<>""),"Quitar código y nombre",IF(OR(L231="",M231=""),"Falta validación",IF(OR(NOT(ISNUMBER(N231)),N231<=0),"Falta fecha","Sin equivalente confirmado"))),"Revisar decisión"))) -> Pendiente
A232: M01-003 | B232: Medicación | C232: Diclofenac 75 mg/3 ml amp. | D232: MED62 | E232: Diclofenac 75mg Amp x 3ml | F232: Coincidencia por validar | G232: Alta | H232: El relevamiento indica una coincidencia probable. Confirmar las características del producto y la existencia del código en esta base. Fuente: master original, fila 5. | I232: Pendiente | O232: =IF(I232="Pendiente","Pendiente",IF(I232="Equivalente confirmado",IF(OR(J232="",K232=""),"Falta código o nombre",IF(OR(L232="",M232=""),"Falta validación",IF(OR(NOT(ISNUMBER(N232)),N232<=0),"Falta fecha","Homologado"))),IF(I232="Sin equivalente en AVAIN",IF(OR(J232<>"",K232<>""),"Quitar código y nombre",IF(OR(L232="",M232=""),"Falta validación",IF(OR(NOT(ISNUMBER(N232)),N232<=0),"Falta fecha","Sin equivalente confirmado"))),"Revisar decisión"))) -> Pendiente
A233: M01-004 | B233: Medicación | C233: Diclofenac + Pridinol comp. | D233: MED61 | E233: Diclofenac + Pridinol Comp x 50/4 mg | F233: Coincidencia por validar | G233: Alta | H233: El relevamiento indica una coincidencia probable. Confirmar las características del producto y la existencia del código en esta base. Fuente: master original, fila 167. | I233: Pendiente | O233: =IF(I233="Pendiente","Pendiente",IF(I233="Equivalente confirmado",IF(OR(J233="",K233=""),"Falta código o nombre",IF(OR(L233="",M233=""),"Falta validación",IF(OR(NOT(ISNUMBER(N233)),N233<=0),"Falta fecha","Homologado"))),IF(I233="Sin equivalente en AVAIN",IF(OR(J233<>"",K233<>""),"Quitar código y nombre",IF(OR(L233="",M233=""),"Falta validación",IF(OR(NOT(ISNUMBER(N233)),N233<=0),"Falta fecha","Sin equivalente confirmado"))),"Revisar decisión"))) -> Pendiente
A234: M01-005 | B234: Medicación | C234: Ibuprofeno 600 mg | D234: MED102 | E234: Ibuprofeno Comp x 600 mg | F234: Coincidencia por validar | G234: Alta | H234: El relevamiento indica una coincidencia probable. Confirmar las características del producto y la existencia del código en esta base. Este ID estaba duplicado; aquí aparece una sola vez. Fuente: master original, fila 7. | I234: Pendiente | O234: =IF(I234="Pendiente","Pendiente",IF(I234="Equivalente confirmado",IF(OR(J234="",K234=""),"Falta código o nombre",IF(OR(L234="",M234=""),"Falta validación",IF(OR(NOT(ISNUMBER(N234)),N234<=0),"Falta fecha","Homologado"))),IF(I234="Sin equivalente en AVAIN",IF(OR(J234<>"",K234<>""),"Quitar código y nombre",IF(OR(L234="",M234=""),"Falta validación",IF(OR(NOT(ISNUMBER(N234)),N234<=0),"Falta fecha","Sin equivalente confirmado"))),"Revisar decisión"))) -> Pendiente
A235: M01-006 | B235: Medicación | C235: Ketorolac 10 mg SL | D235: MED110 | E235: Ketorolac Comp SL X 10 mg | F235: Coincidencia por validar | G235: Alta | H235: El relevamiento indica una coincidencia probable. Confirmar las características del producto y la existencia del código en esta base. Fuente: master original, fila 168. | I235: Pendiente | O235: =IF(I235="Pendiente","Pendiente",IF(I235="Equivalente confirmado",IF(OR(J235="",K235=""),"Falta código o nombre",IF(OR(L235="",M235=""),"Falta validación",IF(OR(NOT(ISNUMBER(N235)),N235<=0),"Falta fecha","Homologado"))),IF(I235="Sin equivalente en AVAIN",IF(OR(J235<>"",K235<>""),"Quitar código y nombre",IF(OR(L235="",M235=""),"Falta validación",IF(OR(NOT(ISNUMBER(N235)),N235<=0),"Falta fecha","Sin equivalente confirmado"))),"Revisar decisión"))) -> Pendiente
A236: M01-007 | B236: Medicación | C236: Ketorolac 30 mg/1 ml amp. | D236: MED109 | E236: Ketorolac 30mg Amp x 1 ml | F236: Coincidencia por validar | G236: Alta | H236: El relevamiento indica una coincidencia probable. Confirmar las características del producto y la existencia del código en esta base. Fuente: master original, fila 171. | I236: Pendiente | O236: =IF(I236="Pendiente","Pendiente",IF(I236="Equivalente confirmado",IF(OR(J236="",K236=""),"Falta código o nombre",IF(OR(L236="",M236=""),"Falta validación",IF(OR(NOT(ISNUMBER(N236)),N236<=0),"Falta fecha","Homologado"))),IF(I236="Sin equivalente en AVAIN",IF(OR(J236<>"",K236<>""),"Quitar código y nombre",IF(OR(L236="",M236=""),"Falta validación",IF(OR(NOT(ISNUMBER(N236)),N236<=0),"Falta fecha","Sin equivalente confirmado"))),"Revisar decisión"))) -> Pendiente
A237: M01-018 | B237: Medicación | C237: Ketorolac 20 mg comp. | D237: MED111 | E237: Ketorolac Comp x 20 mg | F237: Coincidencia por validar | G237: Alta | H237: El relevamiento indica una coincidencia probable. Confirmar las características del producto y la existencia del código en esta base. Fuente: master original, fila 169. | I237: Pendiente | O237: =IF(I237="Pendiente","Pendiente",IF(I237="Equivalente confirmado",IF(OR(J237="",K237=""),"Falta código o nombre",IF(OR(L237="",M237=""),"Falta validación",IF(OR(NOT(ISNUMBER(N237)),N237<=0),"Falta fecha","Homologado"))),IF(I237="Sin equivalente en AVAIN",IF(OR(J237<>"",K237<>""),"Quitar código y nombre",IF(OR(L237="",M237=""),"Falta validación",IF(OR(NOT(ISNUMBER(N237)),N237<=0),"Falta fecha","Sin equivalente confirmado"))),"Revisar decisión"))) -> Pendiente
A238: M02-001 | B238: Medicación | C238: Midazolam 15 mg/3 ml | D238: MED134 | E238: Midazolan 5mg/ml Amp x 3 ml | F238: Coincidencia por validar | G238: Alta | H238: El relevamiento indica una coincidencia probable. Confirmar las características del producto y la existencia del código en esta base. Fuente: master original, fila 22. | I238: Pendiente | O238: =IF(I238="Pendiente","Pendiente",IF(I238="Equivalente confirmado",IF(OR(J238="",K238=""),"Falta código o nombre",IF(OR(L238="",M238=""),"Falta validación",IF(OR(NOT(ISNUMBER(N238)),N238<=0),"Falta fecha","Homologado"))),IF(I238="Sin equivalente en AVAIN",IF(OR(J238<>"",K238<>""),"Quitar código y nombre",IF(OR(L238="",M238=""),"Falta validación",IF(OR(NOT(ISNUMBER(N238)),N238<=0),"Falta fecha","Sin equivalente confirmado"))),"Revisar decisión"))) -> Pendiente
A239: M03-001 | B239: Medicación | C239: Adrenalina 1 mg/1 ml | D239: MED9 | E239: Adrenalina amp 1 ml | F239: Coincidencia por validar | G239: Alta | H239: El relevamiento indica una coincidencia probable. Confirmar las características del producto y la existencia del código en esta base. Fuente: master original, fila 29. | I239: Pendiente | O239: =IF(I239="Pendiente","Pendiente",IF(I239="Equivalente confirmado",IF(OR(J239="",K239=""),"Falta código o nombre",IF(OR(L239="",M239=""),"Falta validación",IF(OR(NOT(ISNUMBER(N239)),N239<=0),"Falta fecha","Homologado"))),IF(I239="Sin equivalente en AVAIN",IF(OR(J239<>"",K239<>""),"Quitar código y nombre",IF(OR(L239="",M239=""),"Falta validación",IF(OR(NOT(ISNUMBER(N239)),N239<=0),"Falta fecha","Sin equivalente confirmado"))),"Revisar decisión"))) -> Pendiente
A240: M03-002 | B240: Medicación | C240: Atropina 1 mg/1 ml | D240: MED174 | E240: Sulfato de Atropina 1mg Amp x 1 ml | F240: Coincidencia por validar | G240: Alta | H240: El relevamiento indica una coincidencia probable. Confirmar las características del producto y la existencia del código en esta base. Fuente: master original, fila 30. | I240: Pendiente | O240: =IF(I240="Pendiente","Pendiente",IF(I240="Equivalente confirmado",IF(OR(J240="",K240=""),"Falta código o nombre",IF(OR(L240="",M240=""),"Falta validación",IF(OR(NOT(ISNUMBER(N240)),N240<=0),"Falta fecha","Homologado"))),IF(I240="Sin equivalente en AVAIN",IF(OR(J240<>"",K240<>""),"Quitar código y nombre",IF(OR(L240="",M240=""),"Falta validación",IF(OR(NOT(ISNUMBER(N240)),N240<=0),"Falta fecha","Sin equivalente confirmado"))),"Revisar decisión"))) -> Pendiente
A241: M03-003 | B241: Medicación | C241: Amiodarona 150 mg/3 ml | D241: MED11 | E241: Amiodarona 150 mg Amp x 3 ml | F241: Coincidencia por validar | G241: Alta | H241: El relevamiento indica una coincidencia probable. Confirmar las características del producto y la existencia del código en esta base. Fuente: master original, fila 31. | I241: Pendiente | O241: =IF(I241="Pendiente","Pendiente",IF(I241="Equivalente confirmado",IF(OR(J241="",K241=""),"Falta código o nombre",IF(OR(L241="",M241=""),"Falta validación",IF(OR(NOT(ISNUMBER(N241)),N241<=0),"Falta fecha","Homologado"))),IF(I241="Sin equivalente en AVAIN",IF(OR(J241<>"",K241<>""),"Quitar código y nombre",IF(OR(L241="",M241=""),"Falta validación",IF(OR(NOT(ISNUMBER(N241)),N241<=0),"Falta fecha","Sin equivalente confirmado"))),"Revisar decisión"))) -> Pendiente
... A291: K-260 | B291: Componentes de kit | C291: Sonda NG pediátrica K30/K33 | D291: DESC117 | E291: Sonda nasogástrica K 30 | F291: Coincidencia por validar | G291: Alta | H291: El relevamiento indica una coincidencia probable. Confirmar las características del producto y la existencia del código en esta base. Fuente: master original, fila 144. | I291: Pendiente | O291: =IF(I291="Pendiente","Pendiente",IF(I291="Equivalente confirmado",IF(OR(J291="",K291=""),"Falta código o nombre",IF(OR(L291="",M291=""),"Falta validación",IF(OR(NOT(ISNUMBER(N291)),N291<=0),"Falta fecha","Homologado"))),IF(I291="Sin equivalente en AVAIN",IF(OR(J291<>"",K291<>""),"Quitar código y nombre",IF(OR(L291="",M291=""),"Falta validación",IF(OR(NOT(ISNUMBER(N291)),N291<=0),"Falta fecha","Sin equivalente confirmado"))),"Revisar decisión"))) -> Pendiente

Sheet Salta
A2: Revisión de Salta
A3: 284 ítems del master. Esta hoja registra únicamente las decisiones de Salta.
A4: 1. Comparar C con D/E. 2. Leer clasificación, confianza y observaciones en F:H. 3. Completar el amarillo I:N.
A5: Cruce del inventario recibido: 24/09/2026. D/E contienen candidatos; sólo una validación completa permite homologarlos.
A6: Comparación con el master · propuestas pendientes de validación | I6: Completar por la base | O6: Estado actual
A7: ID común | B7: Tipo de ítem | C7: Ítem que pide el master | D7: Códigos Base Salta | E7: Nomenclatura Base Salta | F7: Clasificación del cruce | G7: Nivel de confianza | H7: Observaciones y qué revisar | I7: Decisión de la base | J7: Código AVAIN confirmado | K7: Nombre AVAIN confirmado | L7: Validó el producto (nombre) | M7: Validó el código AVAIN (nombre) | N7: Fecha de validación | O7: Estado de esta base
A8: M01-018 | B8: Medicación | C8: Ketorolac 20 mg comp. | D8: 162 | E8: Ketorolac S/L Comprimidos x 10mg sl | F8: Revisar presentación | G8: Baja | H8: Mismo principio activo, presentación distinta: master 20 mg comprimidos; Salta 10 mg sublingual. No corresponde confirmar este código para 20 mg sin resolver la diferencia. Fuente: Inventario Salta, fila(s) 166. | I8: Pendiente | O8: =IF(I8="Pendiente","Pendiente",IF(I8="Equivalente confirmado",IF(OR(J8="",K8=""),"Falta código o nombre",IF(OR(L8="",M8=""),"Falta validación",IF(OR(NOT(ISNUMBER(N8)),N8<=0),"Falta fecha","Homologado"))),IF(I8="Sin equivalente en AVAIN",IF(OR(J8<>"",K8<>""),"Quitar código y nombre",IF(OR(L8="",M8=""),"Falta validación",IF(OR(NOT(ISNUMBER(N8)),N8<=0),"Falta fecha","Sin equivalente confirmado"))),"Revisar decisión"))) -> Pendiente
A9: M03-006 | B9: Medicación | C9: Gluconato de calcio 10% | D9: 393 | E9: Gluconato de calcio amp 40mg/10ml | F9: Revisar presentación | G9: Baja | H9: Mismo principio activo, concentración declarada distinta: master 10%; Salta 40 mg/10 ml. Revisar el rótulo y corregir el dato si corresponde; no asumir equivalencia. Fuente: Inventario Salta, fila(s) 136. | I9: Pendiente | O9: =IF(I9="Pendiente","Pendiente",IF(I9="Equivalente confirmado",IF(OR(J9="",K9=""),"Falta código o nombre",IF(OR(L9="",M9=""),"Falta validación",IF(OR(NOT(ISNUMBER(N9)),N9<=0),"Falta fecha","Homologado"))),IF(I9="Sin equivalente en AVAIN",IF(OR(J9<>"",K9<>""),"Quitar código y nombre",IF(OR(L9="",M9=""),"Falta validación",IF(OR(NOT(ISNUMBER(N9)),N9<=0),"Falta fecha","Sin equivalente confirmado"))),"Revisar decisión"))) -> Pendiente
A10: M04-002 | B10: Medicación | C10: Atenolol 50 mg | D10: 291 | E10: Atenolol 25mg Comp | F10: Revisar presentación | G10: Baja | H10: Mismo principio activo, dosis distinta: master atenolol 50 mg; Salta 25 mg. Buscar 50 mg o resolver la diferencia con el responsable. Fuente: Inventario Salta, fila(s) 48. | I10: Pendiente | O10: =IF(I10="Pendiente","Pendiente",IF(I10="Equivalente confirmado",IF(OR(J10="",K10=""),"Falta código o nombre",IF(OR(L10="",M10=""),"Falta validación",IF(OR(NOT(ISNUMBER(N10)),N10<=0),"Falta fecha","Homologado"))),IF(I10="Sin equivalente en AVAIN",IF(OR(J10<>"",K10<>""),"Quitar código y nombre",IF(OR(L10="",M10=""),"Falta validación",IF(OR(NOT(ISNUMBER(N10)),N10<=0),"Falta fecha","Sin equivalente confirmado"))),"Revisar decisión"))) -> Pendiente
A11: M12-003 | B11: Medicación | C11: Hidroclorotiazida 25 mg | D11: 142 | E11: Hidroclorotiazida Comprimidosx 50mg | F11: Revisar presentación | G11: Baja | H11: Mismo principio activo, dosis distinta: master hidroclorotiazida 25 mg; Salta 50 mg. Revisar presentación antes de asociar el código. Fuente: Inventario Salta, fila(s) 149. | I11: Pendiente | O11: =IF(I11="Pendiente","Pendiente",IF(I11="Equivalente confirmado",IF(OR(J11="",K11=""),"Falta código o nombre",IF(OR(L11="",M11=""),"Falta validación",IF(OR(NOT(ISNUMBER(N11)),N11<=0),"Falta fecha","Homologado"))),IF(I11="Sin equivalente en AVAIN",IF(OR(J11<>"",K11<>""),"Quitar código y nombre",IF(OR(L11="",M11=""),"Falta validación",IF(OR(NOT(ISNUMBER(N11)),N11<=0),"Falta fecha","Sin equivalente confirmado"))),"Revisar decisión"))) -> Pendiente
A12: M13-004 | B12: Medicación | C12: Dextrosa 25% 500 ml | D12: 132 | E12: Glucosado hipertónico al 25% 1 amp=10ml 250mg/1ml | F12: Revisar presentación | G12: Media | H12: Coincide glucosa/dextrosa al 25%, pero cambia el volumen: master 500 ml; Salta ampolla de 10 ml. Revisar presentación. El código 94 es 5% y tampoco cubre este ítem. Fuente: Inventario Salta, fila(s) 137. | I12: Pendiente | O12: =IF(I12="Pendiente","Pendiente",IF(I12="Equivalente confirmado",IF(OR(J12="",K12=""),"Falta código o nombre",IF(OR(L12="",M12=""),"Falta validación",IF(OR(NOT(ISNUMBER(N12)),N12<=0),"Falta fecha","Homologado"))),IF(I12="Sin equivalente en AVAIN",IF(OR(J12<>"",K12<>""),"Quitar código y nombre",IF(OR(L12="",M12=""),"Falta validación",IF(OR(NOT(ISNUMBER(N12)),N12<=0),"Falta fecha","Sin equivalente confirmado"))),"Revisar decisión"))) -> Pendiente
A13: M13-006 | B13: Medicación | C13: Agua destilada 5 ml amp. | D13: 17 | E13: Agua para Inyectable 1 amp=10ml | F13: Revisar presentación | G13: Media | H13: Volumen distinto: master agua destilada, ampolla de 5 ml; Salta agua para inyectable, ampolla de 10 ml. Confirmar además la especificación del agua. No asociar automáticamente. Fuente: Inventario Salta, fila(s) 21. | I13: Pendiente | O13: =IF(I13="Pendiente","Pendiente",IF(I13="Equivalente confirmado",IF(OR(J13="",K13=""),"Falta código o nombre",IF(OR(L13="",M13=""),"Falta validación",IF(OR(NOT(ISNUMBER(N13)),N13<=0),"Falta fecha","Homologado"))),IF(I13="Sin equivalente en AVAIN",IF(OR(J13<>"",K13<>""),"Quitar código y nombre",IF(OR(L13="",M13=""),"Falta validación",IF(OR(NOT(ISNUMBER(N13)),N13<=0),"Falta fecha","Sin equivalente confirmado"))),"Revisar decisión"))) -> Pendiente
A14: D-133 | B14: Descartables | C14: Mariposa (butterfly) Nº 21-23 | D14: 270 | E14: Agujas epicraneales N°27 | F14: Revisar presentación | G14: Baja | H14: Mismo tipo de aguja epicraneal, calibre distinto: master Nº 21-23; Salta sólo informa Nº 27. Revisar calibre; no confirmar como equivalente. Fuente: Inventario Salta, fila(s) 26. | I14: Pendiente | O14: =IF(I14="Pendiente","Pendiente",IF(I14="Equivalente confirmado",IF(OR(J14="",K14=""),"Falta código o nombre",IF(OR(L14="",M14=""),"Falta validación",IF(OR(NOT(ISNUMBER(N14)),N14<=0),"Falta fecha","Homologado"))),IF(I14="Sin equivalente en AVAIN",IF(OR(J14<>"",K14<>""),"Quitar código y nombre",IF(OR(L14="",M14=""),"Falta validación",IF(OR(NOT(ISNUMBER(N14)),N14<=0),"Falta fecha","Sin equivalente confirmado"))),"Revisar decisión"))) -> Pendiente
A15: K-275 | B15: Componentes de kit | C15: Cánula orofaríngea 9-10-12 mm | D15: 304 258 412 | E15: Canula de guedel 90mm Canula de Guedel 100mm Canula de Guedel 120mm | F15: Revisar presentación | G15: Baja | H15: Las medidas declaradas no coinciden: master 9-10-12 mm; Salta 90-100-120 mm. Revisar presentación y posible error de nomenclatura en el master. No corregir multiplicando por 10 sin validación. Fuente: Inventario Salta, fila(s) 65, 62, 63. | I15: Pendiente | O15: =IF(I15="Pendiente","Pendiente",IF(I15="Equivalente confirmado",IF(OR(J15="",K15=""),"Falta código o nombre",IF(OR(L15="",M15=""),"Falta validación",IF(OR(NOT(ISNUMBER(N15)),N15<=0),"Falta fecha","Homologado"))),IF(I15="Sin equivalente en AVAIN",IF(OR(J15<>"",K15<>""),"Quitar código y nombre",IF(OR(L15="",M15=""),"Falta validación",IF(OR(NOT(ISNUMBER(N15)),N15<=0),"Falta fecha","Sin equivalente confirmado"))),"Revisar decisión"))) -> Pendiente
A16: M01-015 | B16: Medicación | C16: Ergotamina (antimigrañoso) | D16: 186 | E16: Migral (ergotamina antimigrañoso) Comprimidos | F16: Revisar datos | G16: Media | H16: Salta identifica ergotamina y la marca Migral. El master no detalla composición completa ni dosis del antimigrañoso. Confirmar la formulación; la marca por sí sola no reduce la confianza. Fuente: Inventario Salta, fila(s) 194. | I16: Pendiente | O16: =IF(I16="Pendiente","Pendiente",IF(I16="Equivalente confirmado",IF(OR(J16="",K16=""),"Falta código o nombre",IF(OR(L16="",M16=""),"Falta validación",IF(OR(NOT(ISNUMBER(N16)),N16<=0),"Falta fecha","Homologado"))),IF(I16="Sin equivalente en AVAIN",IF(OR(J16<>"",K16<>""),"Quitar código y nombre",IF(OR(L16="",M16=""),"Falta validación",IF(OR(NOT(ISNUMBER(N16)),N16<=0),"Falta fecha","Sin equivalente confirmado"))),"Revisar decisión"))) -> Pendiente
A17: M03-001 | B17: Medicación | C17: Adrenalina 1 mg/1 ml | D17: 14 | E17: Adrenalina 1 amp=1ml | F17: Revisar datos | G17: Media | H17: Coinciden adrenalina y ampolla de 1 ml. Salta no informa los 1 mg requeridos. Confirmar concentración. Fuente: Inventario Salta, fila(s) 17. | I17: Pendiente | O17: =IF(I17="Pendiente","Pendiente",IF(I17="Equivalente confirmado",IF(OR(J17="",K17=""),"Falta código o nombre",IF(OR(L17="",M17=""),"Falta validación",IF(OR(NOT(ISNUMBER(N17)),N17<=0),"Falta fecha","Homologado"))),IF(I17="Sin equivalente en AVAIN",IF(OR(J17<>"",K17<>""),"Quitar código y nombre",IF(OR(L17="",M17=""),"Falta validación",IF(OR(NOT(ISNUMBER(N17)),N17<=0),"Falta fecha","Sin equivalente confirmado"))),"Revisar decisión"))) -> Pendiente
A18: M03-002 | B18: Medicación | C18: Atropina 1 mg/1 ml | D18: 230 | E18: Sulfato de Atropina (Klonatropina) 1 amp=1 ml | F18: Revisar datos | G18: Media | H18: Coinciden atropina y ampolla de 1 ml. Salta no informa los 1 mg requeridos. Klonatropina se conserva como nombre comercial; verificar dosis. Fuente: Inventario Salta, fila(s) 247. | I18: Pendiente | O18: =IF(I18="Pendiente","Pendiente",IF(I18="Equivalente confirmado",IF(OR(J18="",K18=""),"Falta código o nombre",IF(OR(L18="",M18=""),"Falta validación",IF(OR(NOT(ISNUMBER(N18)),N18<=0),"Falta fecha","Homologado"))),IF(I18="Sin equivalente en AVAIN",IF(OR(J18<>"",K18<>""),"Quitar código y nombre",IF(OR(L18="",M18=""),"Falta validación",IF(OR(NOT(ISNUMBER(N18)),N18<=0),"Falta fecha","Sin equivalente confirmado"))),"Revisar decisión"))) -> Pendiente
A19: M04-007 | B19: Medicación | C19: Nitroglicerina 25-50 mg amp. | D19: 399 | E19: Nitroglicerina | F19: Revisar datos | G19: Media | H19: Salta sólo dice Nitroglicerina. Faltan dosis, volumen y forma; el master pide 25-50 mg en ampolla. Fuente: Inventario Salta, fila(s) 199. | I19: Pendiente | O19: =IF(I19="Pendiente","Pendiente",IF(I19="Equivalente confirmado",IF(OR(J19="",K19=""),"Falta código o nombre",IF(OR(L19="",M19=""),"Falta validación",IF(OR(NOT(ISNUMBER(N19)),N19<=0),"Falta fecha","Homologado"))),IF(I19="Sin equivalente en AVAIN",IF(OR(J19<>"",K19<>""),"Quitar código y nombre",IF(OR(L19="",M19=""),"Falta validación",IF(OR(NOT(ISNUMBER(N19)),N19<=0),"Falta fecha","Sin equivalente confirmado"))),"Revisar decisión"))) -> Pendiente
... A218: K-290 | B218: Componentes de kit | C218: Antiparras | D218: 273 | E218: Antiparras transparentes | F218: Coincidencia | G218: Alta | H218: Coinciden las características que explicita el ítem del master. Fuente: Inventario Salta, fila(s) 44. | I218: Pendiente | O218: =IF(I218="Pendiente","Pendiente",IF(I218="Equivalente confirmado",IF(OR(J218="",K218=""),"Falta código o nombre",IF(OR(L218="",M218=""),"Falta validación",IF(OR(NOT(ISNUMBER(N218)),N218<=0),"Falta fecha","Homologado"))),IF(I218="Sin equivalente en AVAIN",IF(OR(J218<>"",K218<>""),"Quitar código y nombre",IF(OR(L218="",M218=""),"Falta validación",IF(OR(NOT(ISNUMBER(N218)),N218<=0),"Falta fecha","Sin equivalente confirmado"))),"Revisar decisión"))) -> Pendiente
A219: M01-013 | B219: Medicación | C219: Meloxicam 15 mg | F219: Sin coincidencia | G219: Sin coincidencia | H219: No se identificó un candidato en el inventario recibido. Buscar en el catálogo completo de Salta; esto no demuestra que el producto no exista en AVAIN. | I219: Pendiente | O219: =IF(I219="Pendiente","Pendiente",IF(I219="Equivalente confirmado",IF(OR(J219="",K219=""),"Falta código o nombre",IF(OR(L219="",M219=""),"Falta validación",IF(OR(NOT(ISNUMBER(N219)),N219<=0),"Falta fecha","Homologado"))),IF(I219="Sin equivalente en AVAIN",IF(OR(J219<>"",K219<>""),"Quitar código y nombre",IF(OR(L219="",M219=""),"Falta validación",IF(OR(NOT(ISNUMBER(N219)),N219<=0),"Falta fecha","Sin equivalente confirmado"))),"Revisar decisión"))) -> Pendiente
A220: M01-014 | B220: Medicación | C220: Colchicina 1 mg | F220: Sin coincidencia | G220: Sin coincidencia | H220: No se identificó un candidato en el inventario recibido. Buscar en el catálogo completo de Salta; esto no demuestra que el producto no exista en AVAIN. | I220: Pendiente | O220: =IF(I220="Pendiente","Pendiente",IF(I220="Equivalente confirmado",IF(OR(J220="",K220=""),"Falta código o nombre",IF(OR(L220="",M220=""),"Falta validación",IF(OR(NOT(ISNUMBER(N220)),N220<=0),"Falta fecha","Homologado"))),IF(I220="Sin equivalente en AVAIN",IF(OR(J220<>"",K220<>""),"Quitar código y nombre",IF(OR(L220="",M220=""),"Falta validación",IF(OR(NOT(ISNUMBER(N220)),N220<=0),"Falta fecha","Sin equivalente confirmado"))),"Revisar decisión"))) -> Pendiente
A221: M01-016 | B221: Medicación | C221: Bencidamina comp. desleíble | F221: Sin coincidencia | G221: Sin coincidencia | H221: No se encontró bencidamina. Los caramelos con antibiótico no documentan ese principio activo. | I221: Pendiente | O221: =IF(I221="Pendiente","Pendiente",IF(I221="Equivalente confirmado",IF(OR(J221="",K221=""),"Falta código o nombre",IF(OR(L221="",M221=""),"Falta validación",IF(OR(NOT(ISNUMBER(N221)),N221<=0),"Falta fecha","Homologado"))),IF(I221="Sin equivalente en AVAIN",IF(OR(J221<>"",K221<>""),"Quitar código y nombre",IF(OR(L221="",M221=""),"Falta validación",IF(OR(NOT(ISNUMBER(N221)),N221<=0),"Falta fecha","Sin equivalente confirmado"))),"Revisar decisión"))) -> Pendiente
A222: M02-002 | B222: Medicación | C222: Fentanilo 250 µg/5 ml | F222: Sin coincidencia | G222: Sin coincidencia | H222: No se identificó un candidato en el inventario recibido. Buscar en el catálogo completo de Salta; esto no demuestra que el producto no exista en AVAIN. | I222: Pendiente | O222: =IF(I222="Pendiente","Pendiente",IF(I222="Equivalente confirmado",IF(OR(J222="",K222=""),"Falta código o nombre",IF(OR(L222="",M222=""),"Falta validación",IF(OR(NOT(ISNUMBER(N222)),N222<=0),"Falta fecha","Homologado"))),IF(I222="Sin equivalente en AVAIN",IF(OR(J222<>"",K222<>""),"Quitar código y nombre",IF(OR(L222="",M222=""),"Falta validación",IF(OR(NOT(ISNUMBER(N222)),N222<=0),"Falta fecha","Sin equivalente confirmado"))),"Revisar decisión"))) -> Pendiente
A223: M02-003 | B223: Medicación | C223: Morfina 10 mg/1 ml | F223: Sin coincidencia | G223: Sin coincidencia | H223: No se identificó un candidato en el inventario recibido. Buscar en el catálogo completo de Salta; esto no demuestra que el producto no exista en AVAIN. | I223: Pendiente | O223: =IF(I223="Pendiente","Pendiente",IF(I223="Equivalente confirmado",IF(OR(J223="",K223=""),"Falta código o nombre",IF(OR(L223="",M223=""),"Falta validación",IF(OR(NOT(ISNUMBER(N223)),N223<=0),"Falta fecha","Homologado"))),IF(I223="Sin equivalente en AVAIN",IF(OR(J223<>"",K223<>""),"Quitar código y nombre",IF(OR(L223="",M223=""),"Falta validación",IF(OR(NOT(ISNUMBER(N223)),N223<=0),"Falta fecha","Sin equivalente confirmado"))),"Revisar decisión"))) -> Pendiente
A224: M02-005 | B224: Medicación | C224: Etomidato 20 mg/10 ml | F224: Sin coincidencia | G224: Sin coincidencia | H224: No se identificó un candidato en el inventario recibido. Buscar en el catálogo completo de Salta; esto no demuestra que el producto no exista en AVAIN. | I224: Pendiente | O224: =IF(I224="Pendiente","Pendiente",IF(I224="Equivalente confirmado",IF(OR(J224="",K224=""),"Falta código o nombre",IF(OR(L224="",M224=""),"Falta validación",IF(OR(NOT(ISNUMBER(N224)),N224<=0),"Falta fecha","Homologado"))),IF(I224="Sin equivalente en AVAIN",IF(OR(J224<>"",K224<>""),"Quitar código y nombre",IF(OR(L224="",M224=""),"Falta validación",IF(OR(NOT(ISNUMBER(N224)),N224<=0),"Falta fecha","Sin equivalente confirmado"))),"Revisar decisión"))) -> Pendiente
A225: M02-006 | B225: Medicación | C225: Propofol 200 mg/20 ml | F225: Sin coincidencia | G225: Sin coincidencia | H225: No se identificó un candidato en el inventario recibido. Buscar en el catálogo completo de Salta; esto no demuestra que el producto no exista en AVAIN. | I225: Pendiente | O225: =IF(I225="Pendiente","Pendiente",IF(I225="Equivalente confirmado",IF(OR(J225="",K225=""),"Falta código o nombre",IF(OR(L225="",M225=""),"Falta validación",IF(OR(NOT(ISNUMBER(N225)),N225<=0),"Falta fecha","Homologado"))),IF(I225="Sin equivalente en AVAIN",IF(OR(J225<>"",K225<>""),"Quitar código y nombre",IF(OR(L225="",M225=""),"Falta validación",IF(OR(NOT(ISNUMBER(N225)),N225<=0),"Falta fecha","Sin equivalente confirmado"))),"Revisar decisión"))) -> Pendiente
A226: M02-007 | B226: Medicación | C226: Succinilcolina 100 mg | F226: Sin coincidencia | G226: Sin coincidencia | H226: No se identificó un candidato en el inventario recibido. Buscar en el catálogo completo de Salta; esto no demuestra que el producto no exista en AVAIN. | I226: Pendiente | O226: =IF(I226="Pendiente","Pendiente",IF(I226="Equivalente confirmado",IF(OR(J226="",K226=""),"Falta código o nombre",IF(OR(L226="",M226=""),"Falta validación",IF(OR(NOT(ISNUMBER(N226)),N226<=0),"Falta fecha","Homologado"))),IF(I226="Sin equivalente en AVAIN",IF(OR(J226<>"",K226<>""),"Quitar código y nombre",IF(OR(L226="",M226=""),"Falta validación",IF(OR(NOT(ISNUMBER(N226)),N226<=0),"Falta fecha","Sin equivalente confirmado"))),"Revisar decisión"))) -> Pendiente
A227: M03-009 | B227: Medicación | C227: Dobutamina 250 mg/20 ml | F227: Sin coincidencia | G227: Sin coincidencia | H227: No se identificó un candidato en el inventario recibido. Buscar en el catálogo completo de Salta; esto no demuestra que el producto no exista en AVAIN. | I227: Pendiente | O227: =IF(I227="Pendiente","Pendiente",IF(I227="Equivalente confirmado",IF(OR(J227="",K227=""),"Falta código o nombre",IF(OR(L227="",M227=""),"Falta validación",IF(OR(NOT(ISNUMBER(N227)),N227<=0),"Falta fecha","Homologado"))),IF(I227="Sin equivalente en AVAIN",IF(OR(J227<>"",K227<>""),"Quitar código y nombre",IF(OR(L227="",M227=""),"Falta validación",IF(OR(NOT(ISNUMBER(N227)),N227<=0),"Falta fecha","Sin equivalente confirmado"))),"Revisar decisión"))) -> Pendiente
A228: M03-010 | B228: Medicación | C228: Cloruro de potasio amp. | F228: Sin coincidencia | G228: Sin coincidencia | H228: No se identificó un candidato en el inventario recibido. Buscar en el catálogo completo de Salta; esto no demuestra que el producto no exista en AVAIN. | I228: Pendiente | O228: =IF(I228="Pendiente","Pendiente",IF(I228="Equivalente confirmado",IF(OR(J228="",K228=""),"Falta código o nombre",IF(OR(L228="",M228=""),"Falta validación",IF(OR(NOT(ISNUMBER(N228)),N228<=0),"Falta fecha","Homologado"))),IF(I228="Sin equivalente en AVAIN",IF(OR(J228<>"",K228<>""),"Quitar código y nombre",IF(OR(L228="",M228=""),"Falta validación",IF(OR(NOT(ISNUMBER(N228)),N228<=0),"Falta fecha","Sin equivalente confirmado"))),"Revisar decisión"))) -> Pendiente
A229: M04-011 | B229: Medicación | C229: Atorvastatina 20 mg | F229: Sin coincidencia | G229: Sin coincidencia | H229: No se encontró atorvastatina 20 mg. Rosuvastatina es otro principio activo y no se propone como equivalente. | I229: Pendiente | O229: =IF(I229="Pendiente","Pendiente",IF(I229="Equivalente confirmado",IF(OR(J229="",K229=""),"Falta código o nombre",IF(OR(L229="",M229=""),"Falta validación",IF(OR(NOT(ISNUMBER(N229)),N229<=0),"Falta fecha","Homologado"))),IF(I229="Sin equivalente en AVAIN",IF(OR(J229<>"",K229<>""),"Quitar código y nombre",IF(OR(L229="",M229=""),"Falta validación",IF(OR(NOT(ISNUMBER(N229)),N229<=0),"Falta fecha","Sin equivalente confirmado"))),"Revisar decisión"))) -> Pendiente
A230: M04-012 | B230: Medicación | C230: Bisoprolol 2,5 mg | F230: Sin coincidencia | G230: Sin coincidencia | H230: No se identificó un candidato en el inventario recibido. Buscar en el catálogo completo de Salta; esto no demuestra que el producto no exista en AVAIN. | I230: Pendiente | O230: =IF(I230="Pendiente","Pendiente",IF(I230="Equivalente confirmado",IF(OR(J230="",K230=""),"Falta código o nombre",IF(OR(L230="",M230=""),"Falta validación",IF(OR(NOT(ISNUMBER(N230)),N230<=0),"Falta fecha","Homologado"))),IF(I230="Sin equivalente en AVAIN",IF(OR(J230<>"",K230<>""),"Quitar código y nombre",IF(OR(L230="",M230=""),"Falta validación",IF(OR(NOT(ISNUMBER(N230)),N230<=0),"Falta fecha","Sin equivalente confirmado"))),"Revisar decisión"))) -> Pendiente
... A291: K-286 | B291: Componentes de kit | C291: Camisolín | F291: Sin coincidencia | G291: Sin coincidencia | H291: No se identificó un candidato en el inventario recibido. Buscar en el catálogo completo de Salta; esto no demuestra que el producto no exista en AVAIN. | I291: Pendiente | O291: =IF(I291="Pendiente","Pendiente",IF(I291="Equivalente confirmado",IF(OR(J291="",K291=""),"Falta código o nombre",IF(OR(L291="",M291=""),"Falta validación",IF(OR(NOT(ISNUMBER(N291)),N291<=0),"Falta fecha","Homologado"))),IF(I291="Sin equivalente en AVAIN",IF(OR(J291<>"",K291<>""),"Quitar código y nombre",IF(OR(L291="",M291=""),"Falta validación",IF(OR(NOT(ISNUMBER(N291)),N291<=0),"Falta fecha","Sin equivalente confirmado"))),"Revisar decisión"))) -> Pendiente

Sheet Master vs SAP
A2: Master vs SAP · un único cruce para las tres bases
A3: 284 ítems del master. Códigos SAP candidatos en D/E; el ID común los vincula con Neuquén, San Juan y Salta.
A4: 1. Comparar C con D/E. 2. Leer clasificación, confianza y observaciones en F:H. 3. Completar el amarillo I:N.
A5: Cruce al 25/09/2026. Alta = atributos explícitos compatibles; no es aprobación. Cada código y nombre ocupa la misma línea.
A6: Comparación con el master · propuestas pendientes de validación | I6: Completar por responsables SAP | O6: Estado actual
A7: ID común | B7: Tipo de ítem | C7: Ítem que pide el master | D7: Códigos SAP | E7: Nomenclatura SAP | F7: Clasificación del cruce | G7: Nivel de confianza | H7: Observaciones y qué revisar | I7: Decisión sobre SAP | J7: Código SAP confirmado | K7: Nombre SAP confirmado | L7: Validó el producto (nombre) | M7: Validó el código SAP (nombre) | N7: Fecha de validación | O7: Estado del cruce SAP
A8: M01-008 | B8: Medicación | C8: Paracetamol 500 mg | D8: 1000470 | E8: PARACETAMOL COMP 1 GRAMO | F8: Revisar presentación | G8: Baja | H8: Mismo principio activo, dosis distinta: master paracetamol 500 mg; SAP 1 gramo. No se identificó 500 mg puro. No homologar por fraccionamiento de comprimidos. Fuente: hoja SAP, primera fila por código (mismo orden): 4. | I8: Pendiente | O8: =IF(I8="Pendiente","Pendiente",IF(I8="Equivalente confirmado",IF(OR(J8="",K8=""),"Falta código o nombre",IF(OR(L8="",M8=""),"Falta validación",IF(OR(NOT(ISNUMBER(N8)),N8<=0),"Falta fecha","Homologado"))),IF(I8="Sin equivalente en SAP",IF(OR(J8<>"",K8<>""),"Quitar código y nombre",IF(OR(L8="",M8=""),"Falta validación",IF(OR(NOT(ISNUMBER(N8)),N8<=0),"Falta fecha","Sin equivalente confirmado"))),"Revisar decisión"))) -> Pendiente
A9: M01-011 | B9: Medicación | C9: Tramadol 100 mg/2 ml amp. | D9: 1000635 | E9: TRAMADOL 50MG AMPOLLA | F9: Revisar presentación | G9: Baja | H9: Mismo principio activo, dosis distinta: master tramadol 100 mg/2 ml; SAP 50 mg por ampolla, sin volumen. Buscar 100 mg/2 ml y confirmar la descripción. Fuente: hoja SAP, primera fila por código (mismo orden): 825. | I9: Pendiente | O9: =IF(I9="Pendiente","Pendiente",IF(I9="Equivalente confirmado",IF(OR(J9="",K9=""),"Falta código o nombre",IF(OR(L9="",M9=""),"Falta validación",IF(OR(NOT(ISNUMBER(N9)),N9<=0),"Falta fecha","Homologado"))),IF(I9="Sin equivalente en SAP",IF(OR(J9<>"",K9<>""),"Quitar código y nombre",IF(OR(L9="",M9=""),"Falta validación",IF(OR(NOT(ISNUMBER(N9)),N9<=0),"Falta fecha","Sin equivalente confirmado"))),"Revisar decisión"))) -> Pendiente
A10: M03-008 | B10: Medicación | C10: Noradrenalina 4 mg/4 ml | D10: 1000295 | E10: NORADRENALINA 1MG AMPOLLA DE 1 ML INYEC | F10: Revisar presentación | G10: Media | H10: Concentración equivalente (1 mg/ml), presentación distinta: master 4 mg/4 ml; SAP 1 mg en ampolla de 1 ml. Revisar cantidad total y envase; no sumar ampollas para homologar. Fuente: hoja SAP, primera fila por código (mismo orden): 696. | I10: Pendiente | O10: =IF(I10="Pendiente","Pendiente",IF(I10="Equivalente confirmado",IF(OR(J10="",K10=""),"Falta código o nombre",IF(OR(L10="",M10=""),"Falta validación",IF(OR(NOT(ISNUMBER(N10)),N10<=0),"Falta fecha","Homologado"))),IF(I10="Sin equivalente en SAP",IF(OR(J10<>"",K10<>""),"Quitar código y nombre",IF(OR(L10="",M10=""),"Falta validación",IF(OR(NOT(ISNUMBER(N10)),N10<=0),"Falta fecha","Sin equivalente confirmado"))),"Revisar decisión"))) -> Pendiente
A11: M04-012 | B11: Medicación | C11: Bisoprolol 2,5 mg | D11: 1005292 1000833 | E11: BISOPROLOL 5MG X 10COMP BISOPROLOL 5MG 30u COMPRIMIDOS | F11: Revisar presentación | G11: Baja | H11: Mismo principio activo, dosis distinta: master bisoprolol 2,5 mg; ambos materiales SAP son 5 mg (envases de 10 y 30). No equivalen a 2,5 mg por el solo hecho de poder fraccionarse. Fuente: hoja SAP, primera fila por código (mismo orden): 266, 901. | I11: Pendiente | O11: =IF(I11="Pendiente","Pendiente",IF(I11="Equivalente confirmado",IF(OR(J11="",K11=""),"Falta código o nombre",IF(OR(L11="",M11=""),"Falta validación",IF(OR(NOT(ISNUMBER(N11)),N11<=0),"Falta fecha","Homologado"))),IF(I11="Sin equivalente en SAP",IF(OR(J11<>"",K11<>""),"Quitar código y nombre",IF(OR(L11="",M11=""),"Falta validación",IF(OR(NOT(ISNUMBER(N11)),N11<=0),"Falta fecha","Sin equivalente confirmado"))),"Revisar decisión"))) -> Pendiente
A12: M16-003 | B12: Medicación | C12: Vitamina K 10 mg | D12: 1000310 | E12: VITAMINA K 1 ML AMP 1mg/0,5ml | F12: Revisar presentación | G12: Baja | H12: Misma vitamina, dosis declarada distinta: master 10 mg; SAP 1 mg/0,5 ml en ampolla de 1 ml (=2 mg por ampolla). Verificar descripción y presentación; no tratarla como 10 mg. Fuente: hoja SAP, primera fila por código (mismo orden): 704. | I12: Pendiente | O12: =IF(I12="Pendiente","Pendiente",IF(I12="Equivalente confirmado",IF(OR(J12="",K12=""),"Falta código o nombre",IF(OR(L12="",M12=""),"Falta validación",IF(OR(NOT(ISNUMBER(N12)),N12<=0),"Falta fecha","Homologado"))),IF(I12="Sin equivalente en SAP",IF(OR(J12<>"",K12<>""),"Quitar código y nombre",IF(OR(L12="",M12=""),"Falta validación",IF(OR(NOT(ISNUMBER(N12)),N12<=0),"Falta fecha","Sin equivalente confirmado"))),"Revisar decisión"))) -> Pendiente
A13: D-175 | B13: Descartables | C13: Iodopovidona 10% 1 L | D13: 1000497 1000590 | E13: IODOPOVIDONA SOLUC 10% X 60 ML IODOPOVIDONA SOLUCION 10% X 100ML | F13: Revisar presentación | G13: Media | H13: Coincide iodopovidona 10%, pero el master pide 1 litro y SAP registra 60/100 ml. Revisar volumen. No se encontró 1 litro explícito. Fuente: hoja SAP, primera fila por código (mismo orden): 235, 815. | I13: Pendiente | O13: =IF(I13="Pendiente","Pendiente",IF(I13="Equivalente confirmado",IF(OR(J13="",K13=""),"Falta código o nombre",IF(OR(L13="",M13=""),"Falta validación",IF(OR(NOT(ISNUMBER(N13)),N13<=0),"Falta fecha","Homologado"))),IF(I13="Sin equivalente en SAP",IF(OR(J13<>"",K13<>""),"Quitar código y nombre",IF(OR(L13="",M13=""),"Falta validación",IF(OR(NOT(ISNUMBER(N13)),N13<=0),"Falta fecha","Sin equivalente confirmado"))),"Revisar decisión"))) -> Pendiente
A14: E-188 | B14: Equipamiento | C14: Tubo O2 portátil 2 m³ c/manómetro | D14: 5001822 | E14: CILINDRO ULTRALIVIANO 0,5 M3 ALUMINIO | F14: Revisar presentación | G14: Baja | H14: Capacidad distinta: master tubo portátil de 2 m³ con manómetro; SAP cilindro ultraliviano de 0,5 m³, sin manómetro ni gas explícitos. No es equivalencia confirmada. Verificar equipo completo de 2 m³. Fuente: hoja SAP, primera fila por código (mismo orden): 386. | I14: Pendiente | O14: =IF(I14="Pendiente","Pendiente",IF(I14="Equivalente confirmado",IF(OR(J14="",K14=""),"Falta código o nombre",IF(OR(L14="",M14=""),"Falta validación",IF(OR(NOT(ISNUMBER(N14)),N14<=0),"Falta fecha","Homologado"))),IF(I14="Sin equivalente en SAP",IF(OR(J14<>"",K14<>""),"Quitar código y nombre",IF(OR(L14="",M14=""),"Falta validación",IF(OR(NOT(ISNUMBER(N14)),N14<=0),"Falta fecha","Sin equivalente confirmado"))),"Revisar decisión"))) -> Pendiente
A15: E-189 | B15: Equipamiento | C15: Tubo O2 fijo 7 m³ c/manómetro | D15: 5004118 | E15: CILINDRO DE OXIGENO MED 10.6M3 7.5 ACERO | F15: Revisar presentación | G15: Baja | H15: Capacidad declarada distinta: master 7 m³ con manómetro; SAP dice 10.6M3 7.5 ACERO, sin manómetro. Aclarar qué representa 7.5 y buscar la capacidad requerida; no interpretar ese número como 7 m³. Fuente: hoja SAP, primera fila por código (mismo orden): 388. | I15: Pendiente | O15: =IF(I15="Pendiente","Pendiente",IF(I15="Equivalente confirmado",IF(OR(J15="",K15=""),"Falta código o nombre",IF(OR(L15="",M15=""),"Falta validación",IF(OR(NOT(ISNUMBER(N15)),N15<=0),"Falta fecha","Homologado"))),IF(I15="Sin equivalente en SAP",IF(OR(J15<>"",K15<>""),"Quitar código y nombre",IF(OR(L15="",M15=""),"Falta validación",IF(OR(NOT(ISNUMBER(N15)),N15<=0),"Falta fecha","Sin equivalente confirmado"))),"Revisar decisión"))) -> Pendiente
A16: K-275 | B16: Componentes de kit | C16: Cánula orofaríngea 9-10-12 mm | D16: 2000403 2000404 2001254 | E16: CANULA DE GUEDEL 90CM N2 AMARILLO CANULA DE GUEDEL 10CM N4 ROJO CANULA DE GUEDEL 12CM N5 NARANJA | F16: Revisar presentación | G16: Baja | H16: Medidas declaradas distintas: master 9-10-12 mm; SAP 90CM, 10CM y 12CM. Hay posibles errores de unidad/numeración; no corregir por intuición. Validar ambas descripciones antes de asociar. Fuente: hoja SAP, primera fila por código (mismo orden): 452, 1358, 1750. | I16: Pendiente | O16: =IF(I16="Pendiente","Pendiente",IF(I16="Equivalente confirmado",IF(OR(J16="",K16=""),"Falta código o nombre",IF(OR(L16="",M16=""),"Falta validación",IF(OR(NOT(ISNUMBER(N16)),N16<=0),"Falta fecha","Homologado"))),IF(I16="Sin equivalente en SAP",IF(OR(J16<>"",K16<>""),"Quitar código y nombre",IF(OR(L16="",M16=""),"Falta validación",IF(OR(NOT(ISNUMBER(N16)),N16<=0),"Falta fecha","Sin equivalente confirmado"))),"Revisar decisión"))) -> Pendiente
A17: M01-015 | B17: Medicación | C17: Ergotamina (antimigrañoso) | D17: 1000193 | E17: MIGRAL COMPRIMIDO | F17: Revisar datos | G17: Media | H17: Candidato por marca Migral, cuya familia contiene ergotamina en combinaciones. El master no define composición ni dosis y SAP no indica la variante. Confirmar la formulación completa. La marca sola no acredita qué combinación es. R2. Fuente: hoja SAP, primera fila por código (mismo orden): 672. | I17: Pendiente | O17: =IF(I17="Pendiente","Pendiente",IF(I17="Equivalente confirmado",IF(OR(J17="",K17=""),"Falta código o nombre",IF(OR(L17="",M17=""),"Falta validación",IF(OR(NOT(ISNUMBER(N17)),N17<=0),"Falta fecha","Homologado"))),IF(I17="Sin equivalente en SAP",IF(OR(J17<>"",K17<>""),"Quitar código y nombre",IF(OR(L17="",M17=""),"Falta validación",IF(OR(NOT(ISNUMBER(N17)),N17<=0),"Falta fecha","Sin equivalente confirmado"))),"Revisar decisión"))) -> Pendiente
A18: M01-016 | B18: Medicación | C18: Bencidamina comp. desleíble | D18: 1000748 | E18: BENCIDAMINA COMP | F18: Revisar datos | G18: Media | H18: Coinciden bencidamina y comprimidos. SAP no aclara si son desleíbles; confirmar la forma solicitada. Fuente: hoja SAP, primera fila por código (mismo orden): 394. | I18: Pendiente | O18: =IF(I18="Pendiente","Pendiente",IF(I18="Equivalente confirmado",IF(OR(J18="",K18=""),"Falta código o nombre",IF(OR(L18="",M18=""),"Falta validación",IF(OR(NOT(ISNUMBER(N18)),N18<=0),"Falta fecha","Homologado"))),IF(I18="Sin equivalente en SAP",IF(OR(J18<>"",K18<>""),"Quitar código y nombre",IF(OR(L18="",M18=""),"Falta validación",IF(OR(NOT(ISNUMBER(N18)),N18<=0),"Falta fecha","Sin equivalente confirmado"))),"Revisar decisión"))) -> Pendiente
A19: M02-005 | B19: Medicación | C19: Etomidato 20 mg/10 ml | D19: 1005141 | E19: ETOMIDATO 20MG AMP | F19: Revisar datos | G19: Media | H19: Coinciden etomidato 20 mg y ampolla; SAP no indica los 10 ml del master. Confirmar volumen. Fuente: hoja SAP, primera fila por código (mismo orden): 306. | I19: Pendiente | O19: =IF(I19="Pendiente","Pendiente",IF(I19="Equivalente confirmado",IF(OR(J19="",K19=""),"Falta código o nombre",IF(OR(L19="",M19=""),"Falta validación",IF(OR(NOT(ISNUMBER(N19)),N19<=0),"Falta fecha","Homologado"))),IF(I19="Sin equivalente en SAP",IF(OR(J19<>"",K19<>""),"Quitar código y nombre",IF(OR(L19="",M19=""),"Falta validación",IF(OR(NOT(ISNUMBER(N19)),N19<=0),"Falta fecha","Sin equivalente confirmado"))),"Revisar decisión"))) -> Pendiente
... A274: K-290 | B274: Componentes de kit | C274: Antiparras | D274: 2000010 | E274: ANTIPARRA DE PLASTICO | F274: Coincidencia | G274: Alta | H274: Coinciden los atributos que explicita el ítem del master. Fuente: hoja SAP, primera fila por código (mismo orden): 1018. | I274: Pendiente | O274: =IF(I274="Pendiente","Pendiente",IF(I274="Equivalente confirmado",IF(OR(J274="",K274=""),"Falta código o nombre",IF(OR(L274="",M274=""),"Falta validación",IF(OR(NOT(ISNUMBER(N274)),N274<=0),"Falta fecha","Homologado"))),IF(I274="Sin equivalente en SAP",IF(OR(J274<>"",K274<>""),"Quitar código y nombre",IF(OR(L274="",M274=""),"Falta validación",IF(OR(NOT(ISNUMBER(N274)),N274<=0),"Falta fecha","Sin equivalente confirmado"))),"Revisar decisión"))) -> Pendiente
A275: M02-002 | B275: Medicación | C275: Fentanilo 250 µg/5 ml | F275: Sin coincidencia | G275: Sin coincidencia | H275: No se identificó un candidato respaldado en la hoja SAP recibida. Confirmar con el catálogo completo o solicitar el alta; la ausencia en este archivo no demuestra ausencia en el sistema. | I275: Pendiente | O275: =IF(I275="Pendiente","Pendiente",IF(I275="Equivalente confirmado",IF(OR(J275="",K275=""),"Falta código o nombre",IF(OR(L275="",M275=""),"Falta validación",IF(OR(NOT(ISNUMBER(N275)),N275<=0),"Falta fecha","Homologado"))),IF(I275="Sin equivalente en SAP",IF(OR(J275<>"",K275<>""),"Quitar código y nombre",IF(OR(L275="",M275=""),"Falta validación",IF(OR(NOT(ISNUMBER(N275)),N275<=0),"Falta fecha","Sin equivalente confirmado"))),"Revisar decisión"))) -> Pendiente
A276: M02-003 | B276: Medicación | C276: Morfina 10 mg/1 ml | F276: Sin coincidencia | G276: Sin coincidencia | H276: No se identificó un candidato respaldado en la hoja SAP recibida. Confirmar con el catálogo completo o solicitar el alta; la ausencia en este archivo no demuestra ausencia en el sistema. | I276: Pendiente | O276: =IF(I276="Pendiente","Pendiente",IF(I276="Equivalente confirmado",IF(OR(J276="",K276=""),"Falta código o nombre",IF(OR(L276="",M276=""),"Falta validación",IF(OR(NOT(ISNUMBER(N276)),N276<=0),"Falta fecha","Homologado"))),IF(I276="Sin equivalente en SAP",IF(OR(J276<>"",K276<>""),"Quitar código y nombre",IF(OR(L276="",M276=""),"Falta validación",IF(OR(NOT(ISNUMBER(N276)),N276<=0),"Falta fecha","Sin equivalente confirmado"))),"Revisar decisión"))) -> Pendiente
A277: M02-006 | B277: Medicación | C277: Propofol 200 mg/20 ml | F277: Sin coincidencia | G277: Sin coincidencia | H277: No se identificó un candidato respaldado en la hoja SAP recibida. Confirmar con el catálogo completo o solicitar el alta; la ausencia en este archivo no demuestra ausencia en el sistema. | I277: Pendiente | O277: =IF(I277="Pendiente","Pendiente",IF(I277="Equivalente confirmado",IF(OR(J277="",K277=""),"Falta código o nombre",IF(OR(L277="",M277=""),"Falta validación",IF(OR(NOT(ISNUMBER(N277)),N277<=0),"Falta fecha","Homologado"))),IF(I277="Sin equivalente en SAP",IF(OR(J277<>"",K277<>""),"Quitar código y nombre",IF(OR(L277="",M277=""),"Falta validación",IF(OR(NOT(ISNUMBER(N277)),N277<=0),"Falta fecha","Sin equivalente confirmado"))),"Revisar decisión"))) -> Pendiente
A278: M03-009 | B278: Medicación | C278: Dobutamina 250 mg/20 ml | F278: Sin coincidencia | G278: Sin coincidencia | H278: No se identificó un candidato respaldado en la hoja SAP recibida. Confirmar con el catálogo completo o solicitar el alta; la ausencia en este archivo no demuestra ausencia en el sistema. | I278: Pendiente | O278: =IF(I278="Pendiente","Pendiente",IF(I278="Equivalente confirmado",IF(OR(J278="",K278=""),"Falta código o nombre",IF(OR(L278="",M278=""),"Falta validación",IF(OR(NOT(ISNUMBER(N278)),N278<=0),"Falta fecha","Homologado"))),IF(I278="Sin equivalente en SAP",IF(OR(J278<>"",K278<>""),"Quitar código y nombre",IF(OR(L278="",M278=""),"Falta validación",IF(OR(NOT(ISNUMBER(N278)),N278<=0),"Falta fecha","Sin equivalente confirmado"))),"Revisar decisión"))) -> Pendiente
A279: M04-016 | B279: Medicación | C279: Alteplasa 50 mg | F279: Sin coincidencia | G279: Sin coincidencia | H279: No se encontró alteplasa explícita. Metalyse no se asigna por similitud de uso o por ser un trombolítico; debe confirmarse el principio activo solicitado. | I279: Pendiente | O279: =IF(I279="Pendiente","Pendiente",IF(I279="Equivalente confirmado",IF(OR(J279="",K279=""),"Falta código o nombre",IF(OR(L279="",M279=""),"Falta validación",IF(OR(NOT(ISNUMBER(N279)),N279<=0),"Falta fecha","Homologado"))),IF(I279="Sin equivalente en SAP",IF(OR(J279<>"",K279<>""),"Quitar código y nombre",IF(OR(L279="",M279=""),"Falta validación",IF(OR(NOT(ISNUMBER(N279)),N279<=0),"Falta fecha","Sin equivalente confirmado"))),"Revisar decisión"))) -> Pendiente
A280: M10-002 | B280: Medicación | C280: Flumazenil 0,5 mg/5 ml | F280: Sin coincidencia | G280: Sin coincidencia | H280: No se identificó un candidato respaldado en la hoja SAP recibida. Confirmar con el catálogo completo o solicitar el alta; la ausencia en este archivo no demuestra ausencia en el sistema. | I280: Pendiente | O280: =IF(I280="Pendiente","Pendiente",IF(I280="Equivalente confirmado",IF(OR(J280="",K280=""),"Falta código o nombre",IF(OR(L280="",M280=""),"Falta validación",IF(OR(NOT(ISNUMBER(N280)),N280<=0),"Falta fecha","Homologado"))),IF(I280="Sin equivalente en SAP",IF(OR(J280<>"",K280<>""),"Quitar código y nombre",IF(OR(L280="",M280=""),"Falta validación",IF(OR(NOT(ISNUMBER(N280)),N280<=0),"Falta fecha","Sin equivalente confirmado"))),"Revisar decisión"))) -> Pendiente
A281: M10-003 | B281: Medicación | C281: Carbón activado | F281: Sin coincidencia | G281: Sin coincidencia | H281: No se identificó un candidato respaldado en la hoja SAP recibida. Confirmar con el catálogo completo o solicitar el alta; la ausencia en este archivo no demuestra ausencia en el sistema. | I281: Pendiente | O281: =IF(I281="Pendiente","Pendiente",IF(I281="Equivalente confirmado",IF(OR(J281="",K281=""),"Falta código o nombre",IF(OR(L281="",M281=""),"Falta validación",IF(OR(NOT(ISNUMBER(N281)),N281<=0),"Falta fecha","Homologado"))),IF(I281="Sin equivalente en SAP",IF(OR(J281<>"",K281<>""),"Quitar código y nombre",IF(OR(L281="",M281=""),"Falta validación",IF(OR(NOT(ISNUMBER(N281)),N281<=0),"Falta fecha","Sin equivalente confirmado"))),"Revisar decisión"))) -> Pendiente
A282: M12-003 | B282: Medicación | C282: Hidroclorotiazida 25 mg | F282: Sin coincidencia | G282: Sin coincidencia | H282: No se identificó un candidato respaldado en la hoja SAP recibida. Confirmar con el catálogo completo o solicitar el alta; la ausencia en este archivo no demuestra ausencia en el sistema. | I282: Pendiente | O282: =IF(I282="Pendiente","Pendiente",IF(I282="Equivalente confirmado",IF(OR(J282="",K282=""),"Falta código o nombre",IF(OR(L282="",M282=""),"Falta validación",IF(OR(NOT(ISNUMBER(N282)),N282<=0),"Falta fecha","Homologado"))),IF(I282="Sin equivalente en SAP",IF(OR(J282<>"",K282<>""),"Quitar código y nombre",IF(OR(L282="",M282=""),"Falta validación",IF(OR(NOT(ISNUMBER(N282)),N282<=0),"Falta fecha","Sin equivalente confirmado"))),"Revisar decisión"))) -> Pendiente
A283: M13-007 | B283: Medicación | C283: Insulina corriente humana | F283: Sin coincidencia | G283: Sin coincidencia | H283: No se identificó insulina corriente/regular humana. El material de insulina aspártica no corresponde al mismo tipo de insulina. | I283: Pendiente | O283: =IF(I283="Pendiente","Pendiente",IF(I283="Equivalente confirmado",IF(OR(J283="",K283=""),"Falta código o nombre",IF(OR(L283="",M283=""),"Falta validación",IF(OR(NOT(ISNUMBER(N283)),N283<=0),"Falta fecha","Homologado"))),IF(I283="Sin equivalente en SAP",IF(OR(J283<>"",K283<>""),"Quitar código y nombre",IF(OR(L283="",M283=""),"Falta validación",IF(OR(NOT(ISNUMBER(N283)),N283<=0),"Falta fecha","Sin equivalente confirmado"))),"Revisar decisión"))) -> Pendiente
A284: M14-002 | B284: Medicación | C284: Proparacaína 0,5% gotas | F284: Sin coincidencia | G284: Sin coincidencia | H284: No se identificó un candidato respaldado en la hoja SAP recibida. Confirmar con el catálogo completo o solicitar el alta; la ausencia en este archivo no demuestra ausencia en el sistema. | I284: Pendiente | O284: =IF(I284="Pendiente","Pendiente",IF(I284="Equivalente confirmado",IF(OR(J284="",K284=""),"Falta código o nombre",IF(OR(L284="",M284=""),"Falta validación",IF(OR(NOT(ISNUMBER(N284)),N284<=0),"Falta fecha","Homologado"))),IF(I284="Sin equivalente en SAP",IF(OR(J284<>"",K284<>""),"Quitar código y nombre",IF(OR(L284="",M284=""),"Falta validación",IF(OR(NOT(ISNUMBER(N284)),N284<=0),"Falta fecha","Sin equivalente confirmado"))),"Revisar decisión"))) -> Pendiente
A285: M16-001 | B285: Medicación | C285: Vacuna antitetánica | F285: Sin coincidencia | G285: Sin coincidencia | H285: No se identificó un candidato respaldado en la hoja SAP recibida. Confirmar con el catálogo completo o solicitar el alta; la ausencia en este archivo no demuestra ausencia en el sistema. | I285: Pendiente | O285: =IF(I285="Pendiente","Pendiente",IF(I285="Equivalente confirmado",IF(OR(J285="",K285=""),"Falta código o nombre",IF(OR(L285="",M285=""),"Falta validación",IF(OR(NOT(ISNUMBER(N285)),N285<=0),"Falta fecha","Homologado"))),IF(I285="Sin equivalente en SAP",IF(OR(J285<>"",K285<>""),"Quitar código y nombre",IF(OR(L285="",M285=""),"Falta validación",IF(OR(NOT(ISNUMBER(N285)),N285<=0),"Falta fecha","Sin equivalente confirmado"))),"Revisar decisión"))) -> Pendiente
A286: M16-002 | B286: Medicación | C286: Enoxaparina 40 mg | F286: Sin coincidencia | G286: Sin coincidencia | H286: No se identificó un candidato respaldado en la hoja SAP recibida. Confirmar con el catálogo completo o solicitar el alta; la ausencia en este archivo no demuestra ausencia en el sistema. | I286: Pendiente | O286: =IF(I286="Pendiente","Pendiente",IF(I286="Equivalente confirmado",IF(OR(J286="",K286=""),"Falta código o nombre",IF(OR(L286="",M286=""),"Falta validación",IF(OR(NOT(ISNUMBER(N286)),N286<=0),"Falta fecha","Homologado"))),IF(I286="Sin equivalente en SAP",IF(OR(J286<>"",K286<>""),"Quitar código y nombre",IF(OR(L286="",M286=""),"Falta validación",IF(OR(NOT(ISNUMBER(N286)),N286<=0),"Falta fecha","Sin equivalente confirmado"))),"Revisar decisión"))) -> Pendiente
... A291: K-282 | B291: Componentes de kit | C291: Tarjetas de trauma (triage) | F291: Sin coincidencia | G291: Sin coincidencia | H291: No se identificaron tarjetas de triage/trauma. Los formularios asistenciales genéricos no se proponen como sustitutos. | I291: Pendiente | O291: =IF(I291="Pendiente","Pendiente",IF(I291="Equivalente confirmado",IF(OR(J291="",K291=""),"Falta código o nombre",IF(OR(L291="",M291=""),"Falta validación",IF(OR(NOT(ISNUMBER(N291)),N291<=0),"Falta fecha","Homologado"))),IF(I291="Sin equivalente en SAP",IF(OR(J291<>"",K291<>""),"Quitar código y nombre",IF(OR(L291="",M291=""),"Falta validación",IF(OR(NOT(ISNUMBER(N291)),N291<=0),"Falta fecha","Sin equivalente confirmado"))),"Revisar decisión"))) -> Pendiente

Sheet Datos originales
A2: Datos originales del relevamiento
A3: Fuente: Vademecum_Homologado_AVAIN__NQN-SJN.xlsx, hoja Homologación AVAIN. Se conservan las 285 filas originales.
A4: La confianza Alta/Media/Baja es histórica. No equivale a la aprobación de la base. Los campos de costo quedan fuera de este trabajo.
A5: Nomenclatura Original proviene de la homologación histórica a costos; la propuesta común usa Ítem Original.
A6: Fila en archivo original | B6: Tipo de Master | C6: ID Original | D6: Ítem Original | E6: Nomenclatura Original | F6: Código AVAIN Nqn | G6: Codigo AVAIN SJN | H6: Nomenclatura AVAIN Nqn | I6: Nomenclatura AVAIN SJN | J6: Nivel de Confianza NQN | K6: Nivel de Confianza SJN | L6: Observaciones NQN | M6: Observaciones SJN | N6: Categoría | O6: Principio Activo | P6: Concentración | Q6: Forma | R6: Vía
A7: 3 | B7: MEDICAMENTO | C7: M05-001 | D7: Salbutamol aerosol (puff) | E7: SALBUTAMOL CON AEROCAMARA | F7: 204 | G7: MED160 | H7: SALBUTAMOL | I7: Salbutamol 100 mcg inhal Aer x 200 dosis | J7: Media | K7: Alta | L7: Coincidencia razonable de principio activo/nombre, pero con diferencias menores (forma, dosis o presentación) no confirmadas del todo: revisar antes de usar. Alternativa igualmente plausible: «VENTOLIN» (cód. 235). | M7: Coincidencia de nombre, principio activo y presentación con alta similitud textual. | N7: RESPIRATORIO · BRONCODILATADORES | O7: Salbutamol | P7: 100 µg/dosis | Q7: Inhalador | R7: Inhalatoria
A8: 4 | B8: MEDICAMENTO | C8: M01-002 | D8: Diclofenac 75 mg comp. | E8: DICLOFENAC 75 COMP | F8: 83 | G8: DES001 | H8: DICLOFENAC75COMP | I8: Diclofenac Comp x 75mg | J8: Alta | K8: Alta | L8: Se corrigió a "DICLOFENAC 75 COMP" (forma comprimido); el algoritmo había preferido por error la presentación en ampolla. | M8: Coincidencia de nombre, principio activo y presentación con alta similitud textual. | N8: ANALGÉSICOS Y ANTIINFLAMATORIOS | O8: Diclofenac sódico | P8: 75 mg | Q8: Comprimido | R8: Oral
A9: 5 | B9: MEDICAMENTO | C9: M01-003 | D9: Diclofenac 75 mg/3 ml amp. | E9: DICLOFENAC SODICO 75 MG AMPOLLA | F9: 89 | G9: MED62 | H9: DICLOFENACSODICO75MGAMPOLLA | I9: Diclofenac 75mg Amp x 3ml | J9: Media | K9: Alta | L9: Coincidencia razonable de principio activo/nombre, pero con diferencias menores (forma, dosis o presentación) no confirmadas del todo: revisar antes de usar. | M9: Coincidencia de nombre, principio activo y presentación con alta similitud textual. | N9: ANALGÉSICOS Y ANTIINFLAMATORIOS | O9: Diclofenac sódico | P9: 75 mg / 3 ml | Q9: Ampolla | R9: IM/EV
A10: 6 | B10: MEDICAMENTO | C10: M05-005 | D10: Solución hipertónica nasal (Hypersol) | E10: GLUCOSADO HIPERTONICO AMP | F10: 123 | H10: GLUCOSADO HIPERTONICO AMP | J10: Sin coincidencia | K10: Sin coincidencia | L10: No hay en AVAIN una solución hipertónica nasal ni glucosado hipertónico equivalente a "Hypersol"; el candidato más cercano por texto (Ringer Lactato) es una solución distinta. Se prefiere dejar sin homologar. | M10: No se encontró un equivalente confiable en AVAIN San Juan (catálogo SJN es más acotado que el de Neuquén: 125 códigos vs. 462). | N10: RESPIRATORIO · BRONCODILATADORES | O10: NaCl hipertónica | P10: - | Q10: Spray nasal | R10: Nasal
A11: 7 | B11: MEDICAMENTO | C11: M01-005 | D11: Ibuprofeno 600 mg | E11: IBUPROFENO 600 MG CAPSULA BLANDA | F11: 396 | G11: MED102 | H11: IBUPROFENO600MGCOMPRECUBIERTOS | I11: Ibuprofeno Comp x 600 mg | J11: Media | K11: Alta | L11: Coincidencia razonable de principio activo/nombre, pero con diferencias menores (forma, dosis o presentación) no confirmadas del todo: revisar antes de usar. Alternativa igualmente plausible: «IBUPROFENO600MGCAPSULABLANDA» (cód. 136). | M11: Coincidencia de nombre, principio activo y presentación con alta similitud textual. | N11: ANALGÉSICOS Y ANTIINFLAMATORIOS | O11: Ibuprofeno | P11: 600 mg | Q11: Comprimido | R11: Oral
A12: 8 | B12: MEDICAMENTO | C12: M01-005 | D12: Ibuprofeno 600 mg | E12: IBUPROFENO 600 MG CAPSULA BLANDA | F12: 396 | G12: MED102 | H12: IBUPROFENO600MGCOMPRECUBIERTOS | I12: Ibuprofeno Comp x 600 mg | J12: Media | K12: Alta | L12: Coincidencia razonable de principio activo/nombre, pero con diferencias menores (forma, dosis o presentación) no confirmadas del todo: revisar antes de usar. Alternativa igualmente plausible: «IBUPROFENO600MGCAPSULABLANDA» (cód. 136). | M12: Coincidencia de nombre, principio activo y presentación con alta similitud textual. | N12: ANALGÉSICOS Y ANTIINFLAMATORIOS | O12: Ibuprofeno | P12: 600 mg | Q12: Comprimido | R12: Oral
A13: 9 | B13: MEDICAMENTO | C13: M06-004 | D13: Betametasona retard amp. | E13: CORTEROID BETAMETASONA | F13: 61 | G13: DES044 | H13: CORTEROIDBETAMETASONA | I13: Dexametasona 1 amp=2ml | J13: Media | K13: Baja | L13: Se prefirió "CORTEROIDBETAMETASONA" (betametasona pura) sobre las combinaciones con diclofenac; AVAIN no especifica si es formulación retard. | M13: AVAIN SJN no tiene betametasona; el corticoide disponible más cercano es dexametasona (amp x 2 ml), principio activo distinto. | N13: CORTICOIDES | O13: Betametasona | P13: 2 ml | Q13: Fco. ampolla | R13: IM
A14: 10 | B14: MEDICAMENTO | C14: M07-004 | D14: Caladryl crema/spray | E14: DIFENHIDRAMINA 10 MG X 1 ML AMP | F14: 503 | H14: Difenhidramina+Calamina | J14: Alta | K14: Sin coincidencia | L14: Coincidencia de nombre, principio activo y presentación con alta similitud textual. | M14: No se encontró un equivalente confiable en AVAIN San Juan (catálogo SJN es más acotado que el de Neuquén: 125 códigos vs. 462). | N14: ANTIHISTAMÍNICOS / ANTIALÉRGICOS | O14: Difenhidramina+Calamina | P14: - | Q14: Crema/Spray | R14: Tópica
A15: 11 | B15: MEDICAMENTO | C15: M08-006 | D15: Omeprazol 40 mg fco. amp. | E15: OMEPRAZOL 20 MG COMP | F15: 170 | G15: MED147 | H15: OMEPRAZOL 20 MG COMP | I15: Omeprazol 40 mg Fco amp polvo p/ rest | J15: Sin coincidencia | K15: Alta | L15: AVAIN solo registra Omeprazol en comprimidos de 20 mg (uso oral); el ítem pide frasco-ampolla EV de 40 mg. Ni la forma farmacéutica ni la dosis coinciden: se prefiere dejar sin homologar. | M15: Coincidencia de nombre, principio activo y presentación con alta similitud textual. | N15: DIGESTIVO | O15: Omeprazol | P15: 40 mg | Q15: Fco. ampolla | R15: EV
A16: 12 | B16: MEDICAMENTO | C16: M01-008 | D16: Paracetamol 500 mg | E16: PARACETAMOL 500 MG | F16: 179 | G16: MED150 | H16: PARACETAMOL500MG | I16: Paracetamol Comp x 1 gr | J16: Alta | K16: Baja | L16: Coincidencia de nombre, principio activo y presentación con alta similitud textual. | M16: Mismo principio activo; AVAIN SJN solo tiene la presentación de 1 g, no 500 mg. Dosis no coincide: verificar antes de usar (podría fraccionarse el comprimido). | N16: ANALGÉSICOS Y ANTIINFLAMATORIOS | O16: Paracetamol | P16: 500 mg | Q16: Comprimido | R16: Oral
A17: 13 | B17: MEDICAMENTO | C17: M11-001 | D17: Amoxicilina + Ác. clavulánico 1 g | E17: AMOXICILINA + AC. CLAVULANICO | F17: 16 | G17: MED14 | H17: AMOXICILINA+AC.CLAVULANICO | I17: Amoxicilina + Clavulanato Comp x 1 mg | J17: Alta | K17: Alta | L17: Coincidencia de nombre, principio activo y presentación con alta similitud textual. | M17: Coincidencia de nombre, principio activo y presentación con alta similitud textual. | N17: ANTIBIÓTICOS / ANTIVIRALES | O17: Amox+Clav | P17: 1 g | Q17: Comprimido | R17: Oral
A18: 14 | B18: MEDICAMENTO | C18: M01-010 | D18: Dipirona 1 g/2 ml amp. | E18: DIPIRONA AMP | F18: 93 | H18: DIPIRONAAMP | J18: Media | K18: Sin coincidencia | L18: Coincidencia razonable de principio activo/nombre, pero con diferencias menores (forma, dosis o presentación) no confirmadas del todo: revisar antes de usar. | M18: No se encontró un equivalente confiable en AVAIN San Juan (catálogo SJN es más acotado que el de Neuquén: 125 códigos vs. 462). | N18: ANALGÉSICOS Y ANTIINFLAMATORIOS | O18: Dipirona | P18: 1 g / 2 ml | Q18: Ampolla | R18: IM/EV
A19: 15 | B19: MEDICAMENTO | C19: M01-011 | D19: Tramadol 100 mg/2 ml amp. | E19: TRAMADOL 100 MG AMP | F19: 327 | G19: MED181 | H19: TRAMADOL100MGAMP | I19: Tramadol 50mg/2ml amp | J19: Alta | K19: Alta | L19: Coincidencia de nombre, principio activo y presentación con alta similitud textual. | M19: Coincidencia de nombre, principio activo y presentación con alta similitud textual. | N19: ANALGÉSICOS Y ANTIINFLAMATORIOS | O19: Tramadol | P19: 100 mg / 2 ml | Q19: Ampolla | R19: IM/EV/SC
A20: 16 | B20: MEDICAMENTO | C20: M11-002 | D20: Cefalexina 500 mg | E20: CEFALEXINA | F20: 50 | H20: CEFALEXINA | J20: Alta | K20: Sin coincidencia | L20: Coincidencia de nombre, principio activo y presentación con alta similitud textual. | M20: No se encontró un equivalente confiable en AVAIN San Juan (catálogo SJN es más acotado que el de Neuquén: 125 códigos vs. 462). | N20: ANTIBIÓTICOS / ANTIVIRALES | O20: Cefalexina | P20: 500 mg | Q20: Comprimido | R20: Oral
A21: 17 | B21: MEDICAMENTO | C21: M11-003 | D21: Azitromicina 500 mg | E21: AZITROMICINA | F21: 28 | H21: AZITROMICINA | J21: Alta | K21: Sin coincidencia | L21: Coincidencia de nombre, principio activo y presentación con alta similitud textual. | M21: No se encontró un equivalente confiable en AVAIN San Juan (catálogo SJN es más acotado que el de Neuquén: 125 códigos vs. 462). | N21: ANTIBIÓTICOS / ANTIVIRALES | O21: Azitromicina | P21: 500 mg | Q21: Comprimido | R21: Oral
A22: 18 | B22: MEDICAMENTO | C22: M01-014 | D22: Colchicina 1 mg | F22: 485 | H22: Colchicina | J22: Alta | K22: Sin coincidencia | L22: Coincidencia de nombre, principio activo y presentación con alta similitud textual. | M22: No se encontró un artículo equivalente confiable en AVAIN San Juan con la evidencia disponible. | N22: ANALGÉSICOS Y ANTIINFLAMATORIOS | O22: Colchicina | P22: 1 mg | Q22: Comprimido | R22: Oral
A23: 19 | B23: MEDICAMENTO | C23: M01-015 | D23: Ergotamina (antimigrañoso) | F23: 486 | H23: Ergotamina | J23: Media | K23: Sin coincidencia | L23: Coincidencia razonable de principio activo/nombre, pero con diferencias menores (forma, dosis o presentación) no confirmadas del todo: revisar antes de usar. | M23: No se encontró un artículo equivalente confiable en AVAIN San Juan con la evidencia disponible. | N23: ANALGÉSICOS Y ANTIINFLAMATORIOS | O23: Ergotamina | P23: 1 mg | Q23: Comprimido | R23: Oral
A24: 20 | B24: MEDICAMENTO | C24: M01-016 | D24: Bencidamina comp. desleíble | F24: 487 | H24: Bencidamina | J24: Media | K24: Sin coincidencia | L24: Coincidencia razonable de principio activo/nombre, pero con diferencias menores (forma, dosis o presentación) no confirmadas del todo: revisar antes de usar. | M24: No se encontró un artículo equivalente confiable en AVAIN San Juan con la evidencia disponible. | N24: ANALGÉSICOS Y ANTIINFLAMATORIOS | O24: Bencidamina | P24: 3 mg | Q24: Comp. desleíble | R24: Oral
A25: 21 | B25: MEDICAMENTO | C25: M01-017 | D25: Caramelos con antibiótico | E25: CARAMELOS CON ANTIBIOTICO | F25: 438 | G25: MED30 | H25: CARAMELOS CON ANTIBIOTICO | I25: Caramelos antigripales con benzocaina 20.7mg | J25: Sin coincidencia | K25: Baja | L25: "Caramelos con antibiótico" (pastillas para garganta) no tiene equivalente identificable en AVAIN. | M25: AVAIN SJN no tiene caramelos "con antibiótico"; el único producto de la categoría es "Caramelos antigripales con benzocaína", con un principio activo distinto (anestésico local, no antibiótico). | N25: ANALGÉSICOS Y ANTIINFLAMATORIOS | O25: - | P25: - | Q25: Pastilla | R25: Oral
A26: 22 | B26: MEDICAMENTO | C26: M02-001 | D26: Midazolam 15 mg/3 ml | E26: MIDAZOLAM 5MG AMP | F26: 330 | G26: MED134 | H26: MIDAZOLAM5MGAMP | I26: Midazolan 5mg/ml Amp x 3 ml | J26: Media | K26: Alta | L26: Único registro de midazolam en AVAIN es de 5 mg por ampolla; el ítem pide 15 mg/3 ml (equivalente a 5 mg/ml en concentración, pero distinta presentación total). Revisar si corresponde usar varias ampollas de 5 mg o si existe otra presentación no cargada. | M26: Coincidencia de nombre, principio activo y presentación con alta similitud textual. | N26: SEDACIÓN · ANALGESIA · RSI | O26: Midazolam | P26: 15 mg / 3 ml | Q26: Ampolla | R26: EV/IM
A27: 23 | B27: MEDICAMENTO | C27: M02-002 | D27: Fentanilo 250 µg/5 ml | E27: FENTANILO AMP | F27: 309 | H27: FENTANILOAMP | J27: Media | K27: Sin coincidencia | L27: Coincidencia razonable de principio activo/nombre, pero con diferencias menores (forma, dosis o presentación) no confirmadas del todo: revisar antes de usar. | M27: No se encontró un artículo equivalente confiable en AVAIN San Juan con la evidencia disponible. | N27: SEDACIÓN · ANALGESIA · RSI | O27: Fentanilo | P27: 250 µg / 5 ml | Q27: Ampolla | R27: EV
A28: 24 | B28: MEDICAMENTO | C28: M02-003 | D28: Morfina 10 mg/1 ml | E28: MORFINA 10MG AMP | F28: 331 | H28: MORFINA10MGAMP | J28: Media | K28: Sin coincidencia | L28: Coincidencia razonable de principio activo/nombre, pero con diferencias menores (forma, dosis o presentación) no confirmadas del todo: revisar antes de usar. | M28: No se encontró un artículo equivalente confiable en AVAIN San Juan con la evidencia disponible. | N28: SEDACIÓN · ANALGESIA · RSI | O28: Morfina | P28: 10 mg / 1 ml | Q28: Ampolla | R28: EV/IM/SC
A29: 25 | B29: MEDICAMENTO | C29: M02-004 | D29: Nalbufina 10 mg/1 ml | E29: NALBUFINA AMP | F29: 272 | H29: NALBUFINAAMP | J29: Media | K29: Sin coincidencia | L29: Coincidencia razonable de principio activo/nombre, pero con diferencias menores (forma, dosis o presentación) no confirmadas del todo: revisar antes de usar. | M29: No se encontró un equivalente confiable en AVAIN San Juan (catálogo SJN es más acotado que el de Neuquén: 125 códigos vs. 462). | N29: SEDACIÓN · ANALGESIA · RSI | O29: Nalbufina | P29: 10 mg / 1 ml | Q29: Ampolla | R29: EV/IM/SC
A30: 26 | B30: MEDICAMENTO | C30: M02-005 | D30: Etomidato 20 mg/10 ml | F30: 488 | H30: Etomidato | J30: Media | K30: Sin coincidencia | L30: Coincidencia razonable de principio activo/nombre, pero con diferencias menores (forma, dosis o presentación) no confirmadas del todo: revisar antes de usar. | M30: No se encontró un equivalente confiable en AVAIN San Juan (catálogo SJN es más acotado que el de Neuquén: 125 códigos vs. 462). | N30: SEDACIÓN · ANALGESIA · RSI | O30: Etomidato | P30: 2 mg / ml | Q30: Ampolla | R30: EV
A31: 27 | B31: MEDICAMENTO | C31: M02-006 | D31: Propofol 200 mg/20 ml | F31: 489 | H31: Propofol | J31: Media | K31: Sin coincidencia | L31: Coincidencia razonable de principio activo/nombre, pero con diferencias menores (forma, dosis o presentación) no confirmadas del todo: revisar antes de usar. | M31: No se encontró un artículo equivalente confiable en AVAIN San Juan con la evidencia disponible. | N31: SEDACIÓN · ANALGESIA · RSI | O31: Propofol | P31: 10 mg / ml | Q31: Ampolla | R31: EV
A32: 28 | B32: MEDICAMENTO | C32: M11-004 | D32: Ciprofloxacina 500 mg | E32: CIPROFLOXACINA | F32: 55 | G32: MED37 | H32: CIPROFLOXACINA | I32: Ciprofloxacina Comp x 500 mg | J32: Media | K32: Alta | L32: Coincidencia razonable de principio activo/nombre, pero con diferencias menores (forma, dosis o presentación) no confirmadas del todo: revisar antes de usar. Alternativa igualmente plausible: «CIPROFLOXACINA» (cód. 56). | M32: Coincidencia de nombre, principio activo y presentación con alta similitud textual. | N32: ANTIBIÓTICOS / ANTIVIRALES | O32: Ciprofloxacina | P32: 500 mg | Q32: Comprimido | R32: Oral
A33: 29 | B33: MEDICAMENTO | C33: M03-001 | D33: Adrenalina 1 mg/1 ml | E33: ADRENALINA INY | F33: 2 | G33: MED9 | H33: ADRENALINAINY | I33: Adrenalina amp 1 ml | J33: Media | K33: Alta | L33: Coincidencia razonable de principio activo/nombre, pero con diferencias menores (forma, dosis o presentación) no confirmadas del todo: revisar antes de usar. Alternativa igualmente plausible: «ADRENALINAINY» (cód. 3). | M33: Coincidencia de nombre, principio activo y presentación con alta similitud textual. | N33: DROGAS RCP / PARO | O33: Adrenalina | P33: 1 mg / 1 ml | Q33: Ampolla | R33: EV/IM
A34: 30 | B34: MEDICAMENTO | C34: M03-002 | D34: Atropina 1 mg/1 ml | E34: ATROPINA AMP | F34: 26 | G34: MED174 | H34: ATROPINAAMP | I34: Sulfato de Atropina 1mg Amp x 1 ml | J34: Media | K34: Alta | L34: Coincidencia razonable de principio activo/nombre, pero con diferencias menores (forma, dosis o presentación) no confirmadas del todo: revisar antes de usar. | M34: Coincidencia de nombre, principio activo y presentación con alta similitud textual. | N34: DROGAS RCP / PARO | O34: Atropina | P34: 1 mg / 1 ml | Q34: Ampolla | R34: EV
A35: 31 | B35: MEDICAMENTO | C35: M03-003 | D35: Amiodarona 150 mg/3 ml | E35: AMIODARONA AMP | F35: 342 | G35: MED11 | H35: AMIODARONAAMP | I35: Amiodarona 150 mg Amp x 3 ml | J35: Media | K35: Alta | L35: Coincidencia razonable de principio activo/nombre, pero con diferencias menores (forma, dosis o presentación) no confirmadas del todo: revisar antes de usar. | M35: Coincidencia de nombre, principio activo y presentación con alta similitud textual. | N35: DROGAS RCP / PARO | O35: Amiodarona | P35: 150 mg / 3 ml | Q35: Ampolla | R35: EV
A36: 32 | B36: MEDICAMENTO | C36: M03-004 | D36: Adenosina 6 mg/2 ml | E36: ADENOSINA AMP | F36: 311 | G36: MED8 | H36: ADENOSINAAMP | I36: Adenosina Amp x 2 ml | J36: Media | K36: Alta | L36: Coincidencia razonable de principio activo/nombre, pero con diferencias menores (forma, dosis o presentación) no confirmadas del todo: revisar antes de usar. | M36: Coincidencia de nombre, principio activo y presentación con alta similitud textual. | N36: DROGAS RCP / PARO | O36: Adenosina | P36: 6 mg / 2 ml | Q36: Ampolla | R36: EV
A37: 33 | B37: MEDICAMENTO | C37: M11-013 | D37: Aciclovir 400 mg | E37: ACICLOVIR 5% | F37: 1 | H37: ACICLOVIR 5% | J37: Sin coincidencia | K37: Sin coincidencia | L37: AVAIN solo registra Aciclovir en presentación tópica (ACICLOVIR 5% crema, cód. 1); no existe la forma oral 400 mg solicitada. Se prefiere dejar sin homologar antes que asignar un código de forma farmacéutica distinta. | M37: No se encontró un artículo equivalente confiable en AVAIN San Juan con la evidencia disponible. | N37: ANTIBIÓTICOS / ANTIVIRALES | O37: Aciclovir | P37: 400 mg | Q37: Comprimido | R37: Oral
A38: 34 | B38: MEDICAMENTO | C38: M03-006 | D38: Gluconato de calcio 10% | E38: GLUCONATO DE CALCIO AMP | F38: 122 | H38: GLUCONATODECALCIOAMP | J38: Media | K38: Sin coincidencia | L38: Coincidencia razonable de principio activo/nombre, pero con diferencias menores (forma, dosis o presentación) no confirmadas del todo: revisar antes de usar. | M38: No se encontró un artículo equivalente confiable en AVAIN San Juan con la evidencia disponible. | N38: DROGAS RCP / PARO | O38: Gluconato Ca | P38: 10% | Q38: Ampolla | R38: EV
A39: 35 | B39: MEDICAMENTO | C39: M03-007 | D39: Dopamina 200 mg/5 ml | F39: 490 | H39: Dopamina | J39: Media | K39: Sin coincidencia | L39: Coincidencia razonable de principio activo/nombre, pero con diferencias menores (forma, dosis o presentación) no confirmadas del todo: revisar antes de usar. | M39: No se encontró un artículo equivalente confiable en AVAIN San Juan con la evidencia disponible. | N39: DROGAS RCP / PARO | O39: Dopamina | P39: 200 mg / 5 ml | Q39: Ampolla | R39: EV
A40: 36 | B40: MEDICAMENTO | C40: M03-008 | D40: Noradrenalina 4 mg/4 ml | F40: 480 | H40: NORADRENALINA | J40: Alta | K40: Sin coincidencia | L40: Coincidencia de nombre, principio activo y presentación con alta similitud textual. | M40: No se encontró un equivalente confiable en AVAIN San Juan (catálogo SJN es más acotado que el de Neuquén: 125 códigos vs. 462). | N40: DROGAS RCP / PARO | O40: Noradrenalina | P40: 4 mg / 4 ml | Q40: Ampolla | R40: EV
A41: 37 | B41: MEDICAMENTO | C41: M03-009 | D41: Dobutamina 250 mg/20 ml | F41: 491 | H41: Dobutamina | J41: Media | K41: Sin coincidencia | L41: Coincidencia razonable de principio activo/nombre, pero con diferencias menores (forma, dosis o presentación) no confirmadas del todo: revisar antes de usar. | M41: No se encontró un equivalente confiable en AVAIN San Juan (catálogo SJN es más acotado que el de Neuquén: 125 códigos vs. 462). | N41: DROGAS RCP / PARO | O41: Dobutamina | P41: 250 mg / 20 ml | Q41: Ampolla | R41: EV
A42: 38 | B42: MEDICAMENTO | C42: M03-010 | D42: Cloruro de potasio amp. | E42: CLORURO DE POTASIO | F42: 529 | H42: CLORURO DE POTASIO | J42: Sin coincidencia | K42: Sin coincidencia | L42: No se encontró cloruro de potasio en AVAIN. El candidato con mayor similitud de texto ("cloruro de sodio hipertónico") es un electrolito distinto: no corresponde homologar por el riesgo de confusión entre ambos. | M42: No se encontró un equivalente confiable en AVAIN San Juan (catálogo SJN es más acotado que el de Neuquén: 125 códigos vs. 462). | N42: DROGAS RCP / PARO | O42: KCl | P42: - | Q42: Ampolla | R42: EV (diluido)
A43: 39 | B43: MEDICAMENTO | C43: M04-001 | D43: Clopidogrel 75 mg | F43: 492 | H43: Clopidogrel | J43: Alta | K43: Sin coincidencia | L43: Coincidencia de nombre, principio activo y presentación con alta similitud textual. | M43: No se encontró un artículo equivalente confiable en AVAIN San Juan con la evidencia disponible. | N43: CARDIOVASCULAR | O43: Clopidogrel | P43: 75 mg | Q43: Comprimido | R43: Oral
A44: 40 | B44: MEDICAMENTO | C44: M04-002 | D44: Atenolol 50 mg | E44: ATENOLOL 50 MG COMP | F44: 313 | G44: DES036 | H44: ATENOLOL50MGCOMP | I44: Atenolol Comp x 50 mg | J44: Media | K44: Alta | L44: Coincidencia razonable de principio activo/nombre, pero con diferencias menores (forma, dosis o presentación) no confirmadas del todo: revisar antes de usar. Alternativa igualmente plausible: «ATENOLOL50MGCOMP» (cód. 314). | M44: Coincidencia de nombre, principio activo y presentación con alta similitud textual. | N44: CARDIOVASCULAR | O44: Atenolol | P44: 50 mg | Q44: Comprimido | R44: Oral
A45: 41 | B45: MEDICAMENTO | C45: M04-003 | D45: Enalapril 10 mg | E45: ENALAPRIL COMP | F45: 101 | G45: MED72 | H45: ENALAPRILCOMP | I45: Enalapril Comp x 10 mg | J45: Alta | K45: Alta | L45: Se corrigió a "ENALAPRIL COMP" (forma oral); el ítem pide comprimido, no la forma inyectable (enalaprilato). | M45: Coincidencia de nombre, principio activo y presentación con alta similitud textual. | N45: CARDIOVASCULAR | O45: Enalapril | P45: 10 mg | Q45: Comprimido | R45: Oral
A46: 42 | B46: MEDICAMENTO | C46: M13-004 | D46: Dextrosa 25% 500 ml | E46: GLUCOSADO HIPERTONICO AMP | F46: 516 | G46: MED58 | H46: Dextrosa25%Amp. | I46: Dextrosa al 5% x 500 ml sachet | J46: Alta | K46: Baja | L46: Coincidencia de nombre, principio activo y presentación con alta similitud textual. | M46: AVAIN SJN solo registra Dextrosa al 5% (no 25%); volumen de 500 ml coincide (presentación en sachet). Concentración no coincide: verificar antes de usar. | N46: SOLUCIONES PARENTERALES | O46: Dextrosa 25% | P46: 500 ml | Q46: Baxter | R46: EV
A47: 43 | B47: MEDICAMENTO | C47: M04-005 | D47: Losartán 50 mg | F47: 493 | G47: DES041 | H47: Losartan | I47: Losartán Comp x 50mg | J47: Media | K47: Alta | L47: Coincidencia razonable de principio activo/nombre, pero con diferencias menores (forma, dosis o presentación) no confirmadas del todo: revisar antes de usar. | M47: Coincidencia de nombre, principio activo y presentación con alta similitud textual. | N47: CARDIOVASCULAR | O47: Losartán | P47: 50 mg | Q47: Comprimido | R47: Oral
A48: 44 | B48: MEDICAMENTO | C48: M04-006 | D48: Isosorbide dinitrato 5 mg SL | E48: DINITRATO DE ISOSORBIDE | F48: 92 | H48: DINITRATODEISOSORBIDE | J48: Media | K48: Sin coincidencia | L48: Coincidencia razonable de principio activo/nombre, pero con diferencias menores (forma, dosis o presentación) no confirmadas del todo: revisar antes de usar. | M48: No se encontró un artículo equivalente confiable en AVAIN San Juan con la evidencia disponible. | N48: CARDIOVASCULAR | O48: Isosorbide DN | P48: 5 mg | Q48: Comprimido SL | R48: Sublingual
A49: 45 | B49: MEDICAMENTO | C49: M04-007 | D49: Nitroglicerina 25-50 mg amp. | F49: 479 | G49: DES042 | H49: NITROGLICERINA25MG | I49: Nitroglicerina 1 amp=3ml | J49: Alta | K49: Media | L49: Coincidencia de nombre, principio activo y presentación con alta similitud textual. | M49: Mismo principio activo y formato de ampolla (3 ml); AVAIN SJN no especifica la dosis por ampolla. | N49: CARDIOVASCULAR | O49: Nitroglicerina | P49: 25–50 mg | Q49: Ampolla | R49: EV
A50: 46 | B50: MEDICAMENTO | C50: M04-008 | D50: Digoxina 0,25 mg/1 ml | E50: DIGOXINA | F50: 308 | H50: DIGOXINA | J50: Media | K50: Sin coincidencia | L50: Coincidencia razonable de principio activo/nombre, pero con diferencias menores (forma, dosis o presentación) no confirmadas del todo: revisar antes de usar. | M50: No se encontró un artículo equivalente confiable en AVAIN San Juan con la evidencia disponible. | N50: CARDIOVASCULAR | O50: Digoxina | P50: 0,25 mg / 1 ml | Q50: Ampolla | R50: EV
A51: 47 | B51: MEDICAMENTO | C51: M04-009 | D51: Labetalol 20 mg/4 ml | F51: 494 | H51: Labetalol | J51: Media | K51: Sin coincidencia | L51: Coincidencia razonable de principio activo/nombre, pero con diferencias menores (forma, dosis o presentación) no confirmadas del todo: revisar antes de usar. | M51: No se encontró un artículo equivalente confiable en AVAIN San Juan con la evidencia disponible. | N51: CARDIOVASCULAR | O51: Labetalol | P51: 20 mg / 4 ml | Q51: Ampolla | R51: EV
A52: 48 | B52: MEDICAMENTO | C52: M04-010 | D52: Nitroprusiato de sodio 50 mg | F52: 495 | H52: Nitroprusiato Na | J52: Sin coincidencia | K52: Sin coincidencia | L52: No se encontró nitroprusiato de sodio en AVAIN. | M52: No se encontró un artículo equivalente confiable en AVAIN San Juan con la evidencia disponible. | N52: CARDIOVASCULAR | O52: Nitroprusiato Na | P52: 50 mg | Q52: Fco. ampolla | R52: EV
A53: 49 | B53: MEDICAMENTO | C53: M04-011 | D53: Atorvastatina 20 mg | F53: 496 | H53: Atorvastatina | J53: Alta | K53: Sin coincidencia | L53: Coincidencia de nombre, principio activo y presentación con alta similitud textual. | M53: No se encontró un equivalente confiable en AVAIN San Juan (catálogo SJN es más acotado que el de Neuquén: 125 códigos vs. 462). | N53: CARDIOVASCULAR | O53: Atorvastatina | P53: 20 mg | Q53: Comprimido | R53: Oral
A54: 50 | B54: MEDICAMENTO | C54: M04-012 | D54: Bisoprolol 2,5 mg | F54: 497 | H54: Bisoprolol | J54: Alta | K54: Sin coincidencia | L54: Coincidencia de nombre, principio activo y presentación con alta similitud textual. | M54: No se encontró un artículo equivalente confiable en AVAIN San Juan con la evidencia disponible. | N54: CARDIOVASCULAR | O54: Bisoprolol | P54: 2,5 mg | Q54: Comprimido | R54: Oral
A55: 51 | B55: MEDICAMENTO | C55: M04-013 | D55: Nifedipina 30 mg | F55: 498 | H55: Nifedipina | J55: Alta | K55: Sin coincidencia | L55: Coincidencia de nombre, principio activo y presentación con alta similitud textual. | M55: No se encontró un artículo equivalente confiable en AVAIN San Juan con la evidencia disponible. | N55: CARDIOVASCULAR | O55: Nifedipina | P55: 30 mg | Q55: Comprimido | R55: Oral
A56: 52 | B56: MEDICAMENTO | C56: M04-014 | D56: Ácido tranexámico 500 mg/5 ml | F56: 499 | H56: Ac.tranexamico | J56: Media | K56: Sin coincidencia | L56: Coincidencia razonable de principio activo/nombre, pero con diferencias menores (forma, dosis o presentación) no confirmadas del todo: revisar antes de usar. | M56: No se encontró un artículo equivalente confiable en AVAIN San Juan con la evidencia disponible. | N56: CARDIOVASCULAR | O56: Ác. tranexámico | P56: 500 mg / 5 ml | Q56: Fco. ampolla | R56: EV
A57: 53 | B57: MEDICAMENTO | C57: M13-007 | D57: Insulina corriente humana | E57: INSULINA HUMALOG MIX 25 100 U/ML X 3ML | F57: 389 | H57: INSULINA HUMALOG MIX 25 100 U/ML X 3ML | J57: Sin coincidencia | K57: Sin coincidencia | L57: AVAIN no registra insulina corriente/regular; solo aparecen presentaciones de insulina de acción distinta (mix) o insumos de aplicación. No corresponde asignar un código de otro tipo de insulina. | M57: No se encontró un artículo equivalente confiable en AVAIN San Juan con la evidencia disponible. | N57: SOLUCIONES PARENTERALES | O57: Insulina regular | P57: 100 UI/ml | Q57: Fco. ampolla | R57: SC/EV
A58: 54 | B58: MEDICAMENTO | C58: M04-016 | D58: Alteplasa 50 mg | F58: 501 | H58: Alteplasa | J58: Alta | K58: Sin coincidencia | L58: Coincidencia de nombre, principio activo y presentación con alta similitud textual. | M58: No se encontró un equivalente confiable en AVAIN San Juan (catálogo SJN es más acotado que el de Neuquén: 125 códigos vs. 462). | N58: CARDIOVASCULAR | O58: Alteplasa | P58: 50 mg | Q58: Fco. ampolla | R58: EV
A59: 55 | B59: MEDICAMENTO | C59: M14-003 | D59: Lágrimas artificiales | E59: IRIX LAGRIMAS | F59: 477 | G59: DES094 | H59: IRIX LAGRIMAS | I59: Lagrimas naturales Gotas oftálmicas | J59: Sin coincidencia | K59: Alta | L59: No se encontraron lágrimas artificiales en AVAIN. | M59: Coincidencia de nombre y categoría (lágrimas/lubricante oftálmico). | N59: OFTÁLMICOS | O59: - | P59: - | Q59: Gotas oftálmicas | R59: Oftálmica
A60: 56 | B60: MEDICAMENTO | C60: M15-005 | D60: Ác. fusídico + Betametasona crema | E60: CORTEROID BETAMETASONA | F60: 518 | H60: Ac.fusidico+Beta | J60: Media | K60: Sin coincidencia | L60: Coincidencia de principio activo (ácido fusídico + betametasona); AVAIN no especifica forma farmacéutica (crema) en la nomenclatura. | M60: No se encontró un artículo equivalente confiable en AVAIN San Juan con la evidencia disponible. | N60: ANESTÉSICOS LOCALES / TÓPICOS | O60: Ác. fusídico+Beta | P60: 15–50 g | Q60: Crema | R60: Tópica
A61: 57 | B61: DESCARTABLE | C61: D-132 | D61: Guía microgotero | E61: GUIA MACROGOTERO V13/14 | F61: 278 | G61: DESC73 | H61: GUIAMACROGOTEROV13/14 | I61: Guia Macrogotero | J61: Alta | K61: Alta | L61: Coincidencia de nombre, principio activo y presentación con alta similitud textual. | M61: Coincidencia de nombre, principio activo y presentación con alta similitud textual. | N61: ACCESOS VASCULARES
A62: 58 | B62: DESCARTABLE | C62: D-141 | D62: Gasas estériles 10x10 | E62: Gasas 10x10cm | F62: 404 | G62: DESC64 | H62: GUANTESESTERILES | I62: Gasas 10 x 10 cm | J62: Media | K62: Alta | L62: Coincidencia razonable de principio activo/nombre, pero con diferencias menores (forma, dosis o presentación) no confirmadas del todo: revisar antes de usar. | M62: Se corrigió a "Gasas 10 x 10 cm" (coincidencia exacta de tamaño); el algoritmo había preferido por error "Apósitos estériles", un producto distinto. | N62: CURACIÓN
A63: 59 | B63: DESCARTABLE | C63: D-142 | D63: Apósitos estériles 10x20 | E63: Apositos esteril | F63: 256 | G63: DESC21 | H63: Apositosesteril | I63: Apositos estériles | J63: Alta | K63: Alta | L63: Coincidencia de nombre, principio activo y presentación con alta similitud textual. | M63: Coincidencia de nombre, principio activo y presentación con alta similitud textual. | N63: CURACIÓN
A64: 60 | B64: MEDICAMENTO | C64: M06-001 | D64: Dexametasona 8 mg/2 ml | E64: DEXAMETASONA AMP | F64: 65 | G64: MED55 | H64: DECADRON | I64: Dexametasona 8mg Amp x 2 ml | J64: Media | K64: Alta | L64: Coincidencia razonable de principio activo/nombre, pero con diferencias menores (forma, dosis o presentación) no confirmadas del todo: revisar antes de usar. Alternativa igualmente plausible: «DECADRONA.L.DEXAMETASONA» (cód. 66). | M64: Coincidencia de nombre, principio activo y presentación con alta similitud textual. | N64: CORTICOIDES | O64: Dexametasona | P64: 8 mg / 2 ml | Q64: Ampolla | R64: EV/IM
A65: 61 | B65: DESCARTABLE | C65: D-143 | D65: Vendas Cambric 5 cm | E65: VENDA CAMBRIC 5CM | F65: 334 | G65: DESC171 | H65: VENDACAMBRIC5CM | I65: Vendas de 7 cm. | J65: Alta | K65: Baja | L65: Coincidencia de nombre, principio activo y presentación con alta similitud textual. | M65: AVAIN SJN solo tiene vendas de 7 cm de ancho; no hay presentación de 5 cm. | N65: CURACIÓN
A66: 62 | B66: MEDICAMENTO | C66: M06-003 | D66: Hidrocortisona 500 mg | E66: HIDROCORTISONA 500 MG AMP | F66: 130 | G66: MED96 | H66: HIDROCORTISONA500MGAMP | I66: Hidrocortisona Fco amp polvo p/rest 500 mg | J66: Alta | K66: Alta | L66: Coincidencia de nombre, principio activo y presentación con alta similitud textual. | M66: Coincidencia de nombre, principio activo y presentación con alta similitud textual. | N66: CORTICOIDES | O66: Hidrocortisona | P66: 500 mg | Q66: Fco. ampolla | R66: EV
A67: 63 | B67: DESCARTABLE | C67: D-144 | D67: Vendas Cambric 10 cm | E67: VENDA CAMBRIC 5CM | F67: 335 | G67: DESC171 | H67: VENDACAMBRIC10CM | I67: Vendas de 7 cm. | J67: Alta | K67: Baja | L67: Coincidencia de nombre, principio activo y presentación con alta similitud textual. | M67: AVAIN SJN solo tiene vendas de 7 cm de ancho; no hay presentación de 10 cm. | N67: CURACIÓN
A68: 64 | B68: MEDICAMENTO | C68: M07-001 | D68: Difenhidramina 10 mg/1 ml | E68: DIFENHIDRAMINA 10 MG X 1 ML AMP | F68: 244 | G68: MED65 | H68: DIFENHIDRAMINA10MGX1MLAMP | I68: Difenhidramina 10mg Amp x 1 ml | J68: Alta | K68: Alta | L68: Coincidencia de nombre, principio activo y presentación con alta similitud textual. | M68: Coincidencia de nombre, principio activo y presentación con alta similitud textual. | N68: ANTIHISTAMÍNICOS / ANTIALÉRGICOS | O68: Difenhidramina | P68: 10 mg / 1 ml | Q68: Ampolla | R68: EV/IM
A69: 65 | B69: MEDICAMENTO | C69: M07-002 | D69: Loratadina 10 mg | E69: LORATADINA COMP | F69: 154 | H69: LORATADINAX10U | J69: Alta | K69: Sin coincidencia | L69: Coincidencia de nombre, principio activo y presentación con alta similitud textual. | M69: No se encontró un artículo equivalente confiable en AVAIN San Juan con la evidencia disponible. | N69: ANTIHISTAMÍNICOS / ANTIALÉRGICOS | O69: Loratadina | P69: 10 mg | Q69: Comprimido | R69: Oral
A70: 66 | B70: DESCARTABLE | C70: D-145 | D70: Tela adhesiva hipoalergénica 5 cm | E70: Cinta adhesiva traspore | F70: 483 | G70: DESC135 | H70: CINTAADHESIVA5CM | I70: Tela Hipoalergénica 5cm | J70: Media | K70: Alta | L70: Coincidencia razonable de principio activo/nombre, pero con diferencias menores (forma, dosis o presentación) no confirmadas del todo: revisar antes de usar. | M70: Coincidencia exacta de nombre y medida (5 cm). | N70: CURACIÓN
A71: 67 | B71: DESCARTABLE | C71: D-149 | D71: Algodón (paquete) | E71: ALGODÓN | F71: 12 | G71: DESC19 | H71: ALGODÓN | I71: Algodón (paquete) | J71: Media | K71: Alta | L71: Coincidencia razonable de principio activo/nombre, pero con diferencias menores (forma, dosis o presentación) no confirmadas del todo: revisar antes de usar. | M71: Coincidencia de nombre, principio activo y presentación con alta similitud textual. | N71: CURACIÓN
A72: 68 | B72: MEDICAMENTO | C72: M08-001 | D72: Metoclopramida 10 mg/2 ml | E72: METOCLOPRAMIDA AMP | F72: 161 | G72: MED130 | H72: METROCLOPRAMIDA10MG | I72: Metoclopramida 10 mg Amp x 2 ml | J72: Media | K72: Alta | L72: Coincidencia razonable de principio activo/nombre, pero con diferencias menores (forma, dosis o presentación) no confirmadas del todo: revisar antes de usar. Alternativa igualmente plausible: «RELIVERAN» (cód. 196). | M72: Coincidencia de nombre, principio activo y presentación con alta similitud textual. | N72: DIGESTIVO | O72: Metoclopramida | P72: 10 mg / 2 ml | Q72: Ampolla | R72: EV/IM
A73: 69 | B73: DESCARTABLE | C73: D-152 | D73: Guantes de examen (caja) | E73: TEST DE DROGA SALIVA (CAJA X 25 UNIDADES) | F73: 402 | G73: 32 | H73: guanteslatexs | I73: GUANTES DE EXAMINACIÓN TALLE S | J73: Baja | K73: Media | L73: AVAIN registra "guantes látex S" como posible equivalente genérico de guantes de examen; no se especifica si son estériles o no ni la cantidad por caja. | M73: Coincidencia razonable de principio activo/nombre, pero con diferencias menores (forma, dosis o presentación) no confirmadas del todo: revisar antes de usar. Alternativa igualmente plausible: «Guantes de examinacion G c/u» (cód. DESC67). | N73: BIOSEGURIDAD
A74: 70 | B74: MEDICAMENTO | C74: M08-003 | D74: Butilbromuro de hioscina 20 mg amp. | E74: HIOSCINA SIMPLE AMP | F74: 37 | G74: MED100 | H74: BUSCAPINA | I74: Hioscina x 20 mg Amp x 1 ml | J74: Media | K74: Alta | L74: Coincidencia razonable de principio activo/nombre, pero con diferencias menores (forma, dosis o presentación) no confirmadas del todo: revisar antes de usar. Alternativa igualmente plausible: «BUSCAPINA» (cód. 36). | M74: Coincidencia de nombre, principio activo y presentación con alta similitud textual. | N74: DIGESTIVO | O74: Hioscina | P74: 20 mg / ml | Q74: Ampolla | R74: EV/IM
A75: 71 | B75: DESCARTABLE | C75: D-158 | D75: Bolsa roja patógenos | E75: BOLSA COLECTORA ORINA | F75: 304 | H75: BOLSASROJAS | J75: Media | K75: Sin coincidencia | L75: Coincidencia razonable de principio activo/nombre, pero con diferencias menores (forma, dosis o presentación) no confirmadas del todo: revisar antes de usar. | M75: No se encontró un equivalente confiable en AVAIN San Juan (catálogo SJN es más acotado que el de Neuquén: 125 códigos vs. 462). | N75: BIOSEGURIDAD
A76: 72 | B76: MEDICAMENTO | C76: M08-005 | D76: Hioscina + Dipirona amp. | E76: HIOSCINA SIMPLE AMP | F76: 504 | G76: MED100 | H76: Hioscina+Dipirona | I76: Hioscina x 20 mg Amp x 1 ml | J76: Alta | K76: Media | L76: Coincidencia de nombre, principio activo y presentación con alta similitud textual. | M76: Coincidencia razonable de principio activo/nombre, pero con diferencias menores (forma, dosis o presentación) no confirmadas del todo: revisar antes de usar. | N76: DIGESTIVO | O76: Hioscina+Dipirona | P76: 20 mg / 2,5 g / 5 ml | Q76: Ampolla | R76: EV/IM
A77: 73 | B77: DESCARTABLE | C77: D-172 | D77: Test troponina | E77: TEST DE DROGA SALIVA (CAJA X 25 UNIDADES) | F77: 1001 | H77: TEST TROPONINA | J77: Sin coincidencia | K77: Sin coincidencia | L77: No se encontró test de troponina en AVAIN. | M77: No se encontró un equivalente confiable en AVAIN San Juan (catálogo SJN es más acotado que el de Neuquén: 125 códigos vs. 462). | N77: MONITOREO / DIAGNÓSTICO
A78: 74 | B78: MEDICAMENTO | C78: M08-007 | D78: Omeprazol 20 mg comp. | E78: OMEPRAZOL 20 MG COMP | F78: 170 | G78: MED148 | H78: OMEPRAZOL20MGCOMP | I78: Omeprazol Comp x 20 mg | J78: Alta | K78: Alta | L78: Coincidencia de nombre, principio activo y presentación con alta similitud textual. | M78: Coincidencia de nombre, principio activo y presentación con alta similitud textual. | N78: DIGESTIVO | O78: Omeprazol | P78: 20 mg | Q78: Comprimido | R78: Oral
A79: 75 | B79: MEDICAMENTO | C79: M08-008 | D79: Famotidina 20 mg | F79: 505 | G79: MED78 | H79: Famotidina | I79: Famotidina Comp x 20 mg | J79: Alta | K79: Alta | L79: Coincidencia de nombre, principio activo y presentación con alta similitud textual. | M79: Coincidencia de nombre, principio activo y presentación con alta similitud textual. | N79: DIGESTIVO | O79: Famotidina | P79: 20 mg | Q79: Comprimido | R79: Oral
A80: 76 | B80: MEDICAMENTO | C80: M08-009 | D80: Hidróxido Al + Mg masticable | F80: 506 | H80: Al/Mghidroxido | J80: Alta | K80: Sin coincidencia | L80: Coincidencia de nombre, principio activo y presentación con alta similitud textual. | M80: No se encontró un artículo equivalente confiable en AVAIN San Juan con la evidencia disponible. | N80: DIGESTIVO | O80: Al/Mg hidróxido | P80: - | Q80: Comp. masticable | R80: Oral
A81: 77 | B81: EQUIPAMIENTO | C81: E-189 | D81: Tubo O2 fijo 7 m³ c/manómetro | E81: TUBO ENDOTRAQUEALES 8.5 | F81: 561 | H81: TUBO O2 | J81: Sin coincidencia | K81: Sin coincidencia | L81: AVAIN solo tiene un tubo de oxígeno portátil de 0,500 m³ (cód. 290); no hay un tubo fijo de 7 m³. Diferencia de capacidad y tipo de instalación demasiado grande para homologar con confianza. | M81: No se encontró un equivalente confiable en AVAIN San Juan (catálogo SJN es más acotado que el de Neuquén: 125 códigos vs. 462). | N81: ELECTROMEDICINA
A82: 78 | B82: MEDICAMENTO | C82: M08-011 | D82: Trimebutina + Simeticona | F82: 507 | G82: DESC150 | H82: Trimebutina+Simeticona | I82: Trimebutina / Simeticona comp | J82: Alta | K82: Alta | L82: Coincidencia de nombre, principio activo y presentación con alta similitud textual. | M82: Coincidencia de nombre, principio activo y presentación con alta similitud textual. | N82: DIGESTIVO | O82: Trimebutina+Simeticona | P82: 200/120 mg | Q82: Comprimido | R82: Oral
A83: 79 | B83: MEDICAMENTO | C83: M08-012 | D83: Sales de rehidratación oral | F83: 401 | H83: SALESDEREHIDRATACIONORALX28GS | J83: Alta | K83: Sin coincidencia | L83: Coincidencia de nombre, principio activo y presentación con alta similitud textual. | M83: No se encontró un equivalente confiable en AVAIN San Juan (catálogo SJN es más acotado que el de Neuquén: 125 códigos vs. 462). | N83: DIGESTIVO | O83: SRO | P83: - | Q83: Polvo (sobre) | R83: Oral
A84: 80 | B84: MEDICAMENTO | C84: M09-001 | D84: Diazepam 10 mg/2 ml | E84: DIAZEPAM AMP | F84: 234 | G84: MED60 | H84: VALIUM10MGDIASEPAM | I84: Diazepam 10 mg (Ps) Amp x 2 ml | J84: Media | K84: Alta | L84: Coincidencia razonable de principio activo/nombre, pero con diferencias menores (forma, dosis o presentación) no confirmadas del todo: revisar antes de usar. Alternativa igualmente plausible: «DIAZEPAMAMP» (cód. 77). | M84: Coincidencia de nombre, principio activo y presentación con alta similitud textual. | N84: ANTICONVULSIVANTES / NEURO | O84: Diazepam | P84: 10 mg / 2 ml | Q84: Ampolla | R84: EV/IM
A85: 81 | B85: MEDICAMENTO | C85: M09-002 | D85: Fenitoína 100 mg/2 ml | E85: FENITOINA AMP | F85: 249 | H85: FENITOINAAMP | J85: Media | K85: Sin coincidencia | L85: Coincidencia razonable de principio activo/nombre, pero con diferencias menores (forma, dosis o presentación) no confirmadas del todo: revisar antes de usar. | M85: No se encontró un artículo equivalente confiable en AVAIN San Juan con la evidencia disponible. | N85: ANTICONVULSIVANTES / NEURO | O85: Fenitoína | P85: 100 mg / 2 ml | Q85: Fco. ampolla | R85: EV
A86: 82 | B86: EQUIPAMIENTO | C86: E-190 | D86: Tabla larga rígida (7 velcros) | E86: TABLA RIGIDA c/INMOVILIZADOR CERVICAL | F86: 422 | H86: TABLARIGIDAc/INMOVILIZADORCERVICAL | J86: Alta | K86: Sin coincidencia | L86: Coincidencia directa: "tabla rígida con inmovilizador cervical" corresponde a la tabla larga rígida solicitada. | M86: No se encontró un artículo equivalente confiable en AVAIN San Juan con la evidencia disponible. | N86: INMOVILIZACIÓN / TRAUMA
A87: 83 | B87: EQUIPAMIENTO | C87: E-191 | D87: Chaleco de extricación (KED) | E87: CHALECO ESTIRCACION (KENDRICH) | F87: 408 | H87: CHALECOESTIRCACION(KENDRICH) | J87: Alta | K87: Sin coincidencia | L87: Coincidencia de nombre, principio activo y presentación con alta similitud textual. | M87: No se encontró un equivalente confiable en AVAIN San Juan (catálogo SJN es más acotado que el de Neuquén: 125 códigos vs. 462). | N87: INMOVILIZACIÓN / TRAUMA
A88: 84 | B88: MEDICAMENTO | C88: M09-005 | D88: Haloperidol 5 mg/1 ml | E88: HALOPERIDOL AMP | F88: 325 | H88: HALOPERIDOLAMP | J88: Media | K88: Sin coincidencia | L88: Coincidencia razonable de principio activo/nombre, pero con diferencias menores (forma, dosis o presentación) no confirmadas del todo: revisar antes de usar. | M88: No se encontró un artículo equivalente confiable en AVAIN San Juan con la evidencia disponible. | N88: ANTICONVULSIVANTES / NEURO | O88: Haloperidol | P88: 5 mg / 1 ml | Q88: Ampolla | R88: IM/EV
A89: 85 | B89: EQUIPAMIENTO | C89: E-192 | D89: Inmovilizador cervical (head blocks) | E89: TABLA RIGIDA c/INMOVILIZADOR CERVICAL | F89: 422 | H89: TABLARIGIDAc/INMOVILIZADORCERVICAL | J89: Media | K89: Sin coincidencia | L89: Coincidencia razonable de principio activo/nombre, pero con diferencias menores (forma, dosis o presentación) no confirmadas del todo: revisar antes de usar. | M89: No se encontró un artículo equivalente confiable en AVAIN San Juan con la evidencia disponible. | N89: INMOVILIZACIÓN / TRAUMA
A90: 86 | B90: MEDICAMENTO | C90: M10-001 | D90: Naloxona 0,4 mg/1 ml | E90: NALOXONA AMP | F90: 306 | G90: MED141 | H90: NALOXONAAMP | I90: Naloxona 0,4mg Amp x 1 ml | J90: Media | K90: Alta | L90: Coincidencia razonable de principio activo/nombre, pero con diferencias menores (forma, dosis o presentación) no confirmadas del todo: revisar antes de usar. Alternativa igualmente plausible: «NALOXONAAMP» (cód. 166). | M90: Coincidencia de nombre, principio activo y presentación con alta similitud textual. | N90: ANTÍDOTOS | O90: Naloxona | P90: 0,4 mg / ml | Q90: Fco. ampolla | R90: EV/IM
A91: 87 | B91: MEDICAMENTO | C91: M10-002 | D91: Flumazenil 0,5 mg/5 ml | E91: FLUMAZENIL AMP | F91: 321 | H91: FLUMAZENILAMP | J91: Media | K91: Sin coincidencia | L91: Coincidencia razonable de principio activo/nombre, pero con diferencias menores (forma, dosis o presentación) no confirmadas del todo: revisar antes de usar. | M91: No se encontró un equivalente confiable en AVAIN San Juan (catálogo SJN es más acotado que el de Neuquén: 125 códigos vs. 462). | N91: ANTÍDOTOS | O91: Flumazenil | P91: 0,5 mg / 5 ml | Q91: Fco. ampolla | R91: EV
