Workbook

Sheet Resumen
A1: Inventario físico vs SAP · tablero
A2: Todos los indicadores son FÓRMULAS sobre la hoja «Casos»: si se corrige un dato allí, acá se actualiza solo.
A4: Generado | B4: 30/10/2026, 05:04:24
A5: Revisor | B5: (sin identificar)
A7: UNIVERSO ANALIZADO
A8: Casos totales | B8: =COUNTA(Casos!B5:B100000)
A9: Ítems de los inventarios físicos | B9: =COUNTIF(Casos!C:C,"Inventario físico")
A10: Unidades físicas contadas | B10: =SUMIF(Casos!C:C,"Inventario físico",Casos!O:O)
A12: CLASIFICACIÓN | B12: Casos | C12: Unidades físicas | D12: Stock SAP
A13: A · Identificado en SAP | B13: =COUNTIF(Casos!D:D,"A · Identificado en SAP") | C13: =SUMIF(Casos!D:D,"A · Identificado en SAP",Casos!O:O) | D13: =SUMIF(Casos!D:D,"A · Identificado en SAP",Casos!P:P)
A14: B · Candidato a alta | B14: =COUNTIF(Casos!D:D,"B · Candidato a alta") | C14: =SUMIF(Casos!D:D,"B · Candidato a alta",Casos!O:O) | D14: =SUMIF(Casos!D:D,"B · Candidato a alta",Casos!P:P)
A15: C · Candidato a baja | B15: =COUNTIF(Casos!D:D,"C · Candidato a baja") | C15: =SUMIF(Casos!D:D,"C · Candidato a baja",Casos!O:O) | D15: =SUMIF(Casos!D:D,"C · Candidato a baja",Casos!P:P)
A16: D · Requiere revisión | B16: =COUNTIF(Casos!D:D,"D · Requiere revisión") | C16: =SUMIF(Casos!D:D,"D · Requiere revisión",Casos!O:O) | D16: =SUMIF(Casos!D:D,"D · Requiere revisión",Casos!P:P)
A17: E · Fuera del alcance | B17: =COUNTIF(Casos!D:D,"E · Fuera del alcance") | C17: =SUMIF(Casos!D:D,"E · Fuera del alcance",Casos!O:O) | D17: =SUMIF(Casos!D:D,"E · Fuera del alcance",Casos!P:P)
A19: POR BASE | B19: A | C19: B | D19: C | E19: D | F19: E | G19: Ítems físicos | H19: Unidades físicas
A20: San Juan | B20: =COUNTIFS(Casos!G:G,"San Juan",Casos!D:D,"A · Identificado en SAP") | C20: =COUNTIFS(Casos!G:G,"San Juan",Casos!D:D,"B · Candidato a alta") | D20: =COUNTIFS(Casos!G:G,"San Juan",Casos!D:D,"C · Candidato a baja") | E20: =COUNTIFS(Casos!G:G,"San Juan",Casos!D:D,"D · Requiere revisión") | F20: =COUNTIFS(Casos!G:G,"San Juan",Casos!D:D,"E · Fuera del alcance") | G20: =COUNTIFS(Casos!G:G,"San Juan",Casos!C:C,"Inventario físico") | H20: =SUMIFS(Casos!O:O,Casos!G:G,"San Juan",Casos!C:C,"Inventario físico")
A21: Neuquén | B21: =COUNTIFS(Casos!G:G,"Neuquén",Casos!D:D,"A · Identificado en SAP") | C21: =COUNTIFS(Casos!G:G,"Neuquén",Casos!D:D,"B · Candidato a alta") | D21: =COUNTIFS(Casos!G:G,"Neuquén",Casos!D:D,"C · Candidato a baja") | E21: =COUNTIFS(Casos!G:G,"Neuquén",Casos!D:D,"D · Requiere revisión") | F21: =COUNTIFS(Casos!G:G,"Neuquén",Casos!D:D,"E · Fuera del alcance") | G21: =COUNTIFS(Casos!G:G,"Neuquén",Casos!C:C,"Inventario físico") | H21: =SUMIFS(Casos!O:O,Casos!G:G,"Neuquén",Casos!C:C,"Inventario físico")
A22: Salta | B22: =COUNTIFS(Casos!G:G,"Salta",Casos!D:D,"A · Identificado en SAP") | C22: =COUNTIFS(Casos!G:G,"Salta",Casos!D:D,"B · Candidato a alta") | D22: =COUNTIFS(Casos!G:G,"Salta",Casos!D:D,"C · Candidato a baja") | E22: =COUNTIFS(Casos!G:G,"Salta",Casos!D:D,"D · Requiere revisión") | F22: =COUNTIFS(Casos!G:G,"Salta",Casos!D:D,"E · Fuera del alcance") | G22: =COUNTIFS(Casos!G:G,"Salta",Casos!C:C,"Inventario físico") | H22: =SUMIFS(Casos!O:O,Casos!G:G,"Salta",Casos!C:C,"Inventario físico")
A24: POR TIPO DE MATERIAL | B24: A | C24: B | D24: C | E24: D | F24: E
A25: Descartable | B25: =COUNTIFS(Casos!K:K,"Descartable",Casos!D:D,"A · Identificado en SAP") | C25: =COUNTIFS(Casos!K:K,"Descartable",Casos!D:D,"B · Candidato a alta") | D25: =COUNTIFS(Casos!K:K,"Descartable",Casos!D:D,"C · Candidato a baja") | E25: =COUNTIFS(Casos!K:K,"Descartable",Casos!D:D,"D · Requiere revisión") | F25: =COUNTIFS(Casos!K:K,"Descartable",Casos!D:D,"E · Fuera del alcance")
A26: Equipamiento | B26: =COUNTIFS(Casos!K:K,"Equipamiento",Casos!D:D,"A · Identificado en SAP") | C26: =COUNTIFS(Casos!K:K,"Equipamiento",Casos!D:D,"B · Candidato a alta") | D26: =COUNTIFS(Casos!K:K,"Equipamiento",Casos!D:D,"C · Candidato a baja") | E26: =COUNTIFS(Casos!K:K,"Equipamiento",Casos!D:D,"D · Requiere revisión") | F26: =COUNTIFS(Casos!K:K,"Equipamiento",Casos!D:D,"E · Fuera del alcance")
A27: Indumentaria | B27: =COUNTIFS(Casos!K:K,"Indumentaria",Casos!D:D,"A · Identificado en SAP") | C27: =COUNTIFS(Casos!K:K,"Indumentaria",Casos!D:D,"B · Candidato a alta") | D27: =COUNTIFS(Casos!K:K,"Indumentaria",Casos!D:D,"C · Candidato a baja") | E27: =COUNTIFS(Casos!K:K,"Indumentaria",Casos!D:D,"D · Requiere revisión") | F27: =COUNTIFS(Casos!K:K,"Indumentaria",Casos!D:D,"E · Fuera del alcance")
A28: Medicamento | B28: =COUNTIFS(Casos!K:K,"Medicamento",Casos!D:D,"A · Identificado en SAP") | C28: =COUNTIFS(Casos!K:K,"Medicamento",Casos!D:D,"B · Candidato a alta") | D28: =COUNTIFS(Casos!K:K,"Medicamento",Casos!D:D,"C · Candidato a baja") | E28: =COUNTIFS(Casos!K:K,"Medicamento",Casos!D:D,"D · Requiere revisión") | F28: =COUNTIFS(Casos!K:K,"Medicamento",Casos!D:D,"E · Fuera del alcance")
A29: Repuesto / seguridad | B29: =COUNTIFS(Casos!K:K,"Repuesto / seguridad",Casos!D:D,"A · Identificado en SAP") | C29: =COUNTIFS(Casos!K:K,"Repuesto / seguridad",Casos!D:D,"B · Candidato a alta") | D29: =COUNTIFS(Casos!K:K,"Repuesto / seguridad",Casos!D:D,"C · Candidato a baja") | E29: =COUNTIFS(Casos!K:K,"Repuesto / seguridad",Casos!D:D,"D · Requiere revisión") | F29: =COUNTIFS(Casos!K:K,"Repuesto / seguridad",Casos!D:D,"E · Fuera del alcance")
A31: ESTADO DE LA GESTIÓN
A32: Pendientes de decidir | B32: =COUNTIF(Casos!AH:AH,"Sin decidir")
A33: Correspondencias confirmadas | B33: =COUNTIF(Casos!AH:AH,"Correspondencia confirmada")
A34: Propuestas aprobadas | B34: =COUNTIF(Casos!AH:AH,"Aprobado")
A35: Propuestas rechazadas | B35: =COUNTIF(Casos!AH:AH,"Rechazado")
A36: Marcados como revisados | B36: =COUNTIF(Casos!AG:AG,"Revisado")
A37: Pendientes de validación | B37: =COUNTIF(Casos!AG:AG,"Pendiente de validación")
A38: Casos con observación | B38: =COUNTIF(Casos!AK:AK,"?*")
A39: Códigos corregidos a mano | B39: =COUNTIF(Casos!U:U,"Sí")
A41: VALORIZACIÓN POR PRECIO DE ÚLTIMA COMPRA
A42: Materiales valorizados | B42: =COUNTIF(Casos!Z:Z,"Valorizado por última compra")
A43: Pendientes de valorización | B43: =COUNTIF(Casos!Z:Z,"Pendiente de valorización")
A44: Valorización total por última compra | B44: =SUMIF(Casos!Z:Z,"Valorizado por última compra",Casos!AD:AD)
A45: El precio de última compra no está en los archivos recibidos, así que el total de arriba es 0 y todos los casos figuran como pendientes. Ver la hoja «Metodología».
A47: REFERENCIA DE SAP · NO es precio de última compra
A48: Valor de stock de SAP de los casos, por clasificación. Es el valor contable dividido por las unidades. Se informa aparte y nunca se suma a la valorización por última compra.
A49: A · Identificado en SAP | B49: =SUMIF(Casos!D:D,"A · Identificado en SAP",Casos!AF:AF)
A50: B · Candidato a alta | B50: =SUMIF(Casos!D:D,"B · Candidato a alta",Casos!AF:AF)
A51: C · Candidato a baja | B51: =SUMIF(Casos!D:D,"C · Candidato a baja",Casos!AF:AF)
A52: D · Requiere revisión | B52: =SUMIF(Casos!D:D,"D · Requiere revisión",Casos!AF:AF)
A53: E · Fuera del alcance | B53: =SUMIF(Casos!D:D,"E · Fuera del alcance",Casos!AF:AF)

Sheet Casos
A1: Conciliación de inventarios físicos contra SAP · detalle completo
A2: Una fila por caso. Los ítems de los inventarios físicos más los materiales de SAP que ningún inventario identificó. Las columnas Q, AD y AF son fórmulas. Exportado el 30/10/2026, 05:04:24.
A4: Nº | B4: ID del caso | C4: Origen del registro | D4: Clasificación | E4: Curso de acción sugerido | F4: Motivo de revisión | G4: Base | H4: Centro | I4: Sistema de origen | J4: Informe de origen | K4: Tipo | L4: Código en inventario físico | M4: Nomenclatura del inventario físico | N4: Presentación detectada | O4: Cantidad física · UNIDADES | P4: Stock SAP en la base · UNIDADES | Q4: Cantidad a valorizar · UNIDADES | R4: Nº de lotes | S4: Código SAP · análisis | T4: Código SAP · vigente | U4: ¿Código corregido a mano? | V4: Descripción en SAP | W4: Atributos verificados | X4: Confianza del cruce | Y4: Justificación de la correspondencia | Z4: Estado de valorización | AA4: Precio de última compra · $ | AB4: Fecha de la última compra | AC4: Fuente del precio | AD4: Valorización · $ | AE4: VU de referencia SAP · $ | AF4: Valor de referencia SAP · $ | AG4: Estado de revisión | AH4: Decisión registrada | AI4: Revisor | AJ4: Fecha de la decisión | AK4: Observaciones
A5: 1 | B5: 1120-DESC1 | C5: Inventario físico | D5: A · Identificado en SAP | E5: Registrar existencia en SAP en esta base | G5: San Juan | H5: 1120 | I5: AVAIN | J5: Stock en Almacén · BASE SAN JUAN | K5: Descartable | L5: DESC1 | M5: Abbocath Nº 14 | N5: calibre 14 | O5: 8 | P5: 0 | Q5: =IF(C5="Inventario físico",O5,P5) | R5: 1 | S5: 2000002 | T5: 2000002 | U5: No | V5: CATETER INTRAVENOSO 14G T/ABBOCATH | W5: calibre | X5: Media | Y5: Candidato 2000002 «CATETER INTRAVENOSO 14G T/ABBOCATH». Denominación: 100% del nombre del inventario explicado por el texto de SAP y 32% a la inversa. Atributos verificados: calibre. Sin contradicción en ningún atributo. | Z5: Pendiente de valorización | AC5: No disponible en los archivos recibidos | AD5: =IF(AA5="","Pendiente",AA5*Q5) | AE5: 254.79867 | AF5: =IF(AE5="","",AE5*Q5) | AG5: Pendiente | AH5: Sin decidir
A6: 2 | B6: 1120-DESC2 | C6: Inventario físico | D6: A · Identificado en SAP | E6: Mantener identificación | G6: San Juan | H6: 1120 | I6: AVAIN | J6: Stock en Almacén · BASE SAN JUAN | K6: Descartable | L6: DESC2 | M6: Abbocath Nº 16 | N6: calibre 16 | O6: 202 | P6: 60 | Q6: =IF(C6="Inventario físico",O6,P6) | R6: 2 | S6: 2000003 | T6: 2000003 | U6: No | V6: CATETER INTRAVENOSO 16G T/ABBOCATH | W6: calibre | X6: Media | Y6: Candidato 2000003 «CATETER INTRAVENOSO 16G T/ABBOCATH». Denominación: 100% del nombre del inventario explicado por el texto de SAP y 32% a la inversa. Atributos verificados: calibre. Sin contradicción en ningún atributo. | Z6: Pendiente de valorización | AC6: No disponible en los archivos recibidos | AD6: =IF(AA6="","Pendiente",AA6*Q6) | AE6: 214.29833 | AF6: =IF(AE6="","",AE6*Q6) | AG6: Pendiente | AH6: Sin decidir
A7: 3 | B7: 1120-DESC4 | C7: Inventario físico | D7: A · Identificado en SAP | E7: Mantener identificación | G7: San Juan | H7: 1120 | I7: AVAIN | J7: Stock en Almacén · BASE SAN JUAN | K7: Descartable | L7: DESC4 | M7: Abbocath Nº 20 | N7: calibre 20 | O7: 272 | P7: 870 | Q7: =IF(C7="Inventario físico",O7,P7) | R7: 3 | S7: 2000005 | T7: 2000005 | U7: No | V7: CATETER INTRAVENOSO 20G T/ABBOCATH | W7: calibre | X7: Media | Y7: Candidato 2000005 «CATETER INTRAVENOSO 20G T/ABBOCATH». Denominación: 100% del nombre del inventario explicado por el texto de SAP y 32% a la inversa. Atributos verificados: calibre. Sin contradicción en ningún atributo. | Z7: Pendiente de valorización | AC7: No disponible en los archivos recibidos | AD7: =IF(AA7="","Pendiente",AA7*Q7) | AE7: 176.58761 | AF7: =IF(AE7="","",AE7*Q7) | AG7: Pendiente | AH7: Sin decidir
A8: 4 | B8: 1120-DESC5 | C8: Inventario físico | D8: A · Identificado en SAP | E8: Mantener identificación | G8: San Juan | H8: 1120 | I8: AVAIN | J8: Stock en Almacén · BASE SAN JUAN | K8: Descartable | L8: DESC5 | M8: Abbocath Nº 22 | N8: calibre 22 | O8: 217 | P8: 500 | Q8: =IF(C8="Inventario físico",O8,P8) | R8: 2 | S8: 2000006 | T8: 2000006 | U8: No | V8: CATETER INTRAVENOSO 22G T/ABBOCATH | W8: calibre | X8: Media | Y8: Candidato 2000006 «CATETER INTRAVENOSO 22G T/ABBOCATH». Denominación: 100% del nombre del inventario explicado por el texto de SAP y 32% a la inversa. Atributos verificados: calibre. Sin contradicción en ningún atributo. | Z8: Pendiente de valorización | AC8: No disponible en los archivos recibidos | AD8: =IF(AA8="","Pendiente",AA8*Q8) | AE8: 170.50266 | AF8: =IF(AE8="","",AE8*Q8) | AG8: Pendiente | AH8: Sin decidir
A9: 5 | B9: 1120-MED4 | C9: Inventario físico | D9: D · Requiere revisión | E9: Revisar y decidir | F9: Coincidencia parcial de denominación | G9: San Juan | H9: 1120 | I9: AVAIN | J9: Stock en Almacén · BASE SAN JUAN | K9: Medicamento | L9: MED4 | M9: Acido Acetil Salicílico Comp x 100 mg | N9: concentración 100 mg · forma comprimido | O9: 100 | P9: 0 | Q9: =IF(C9="Inventario físico",O9,P9) | R9: 1 | U9: No | V9: ACIDO ACETILSALICILICO 100MG | W9: concentración | Y9: Candidato 1001237 «ACIDO ACETILSALICILICO 100MG». Denominación: 62% del nombre del inventario explicado por el texto de SAP y 94% a la inversa. Atributos verificados: concentración. La coincidencia de denominación no alcanza para dar la identificación por confirmada. | Z9: Pendiente de valorización | AC9: No disponible en los archivos recibidos | AD9: =IF(AA9="","Pendiente",AA9*Q9) | AF9: =IF(AE9="","",AE9*Q9) | AG9: Pendiente | AH9: Sin decidir
A10: 6 | B10: 1120-MED8 | C10: Inventario físico | D10: A · Identificado en SAP | E10: Mantener identificación | G10: San Juan | H10: 1120 | I10: AVAIN | J10: Stock en Almacén · BASE SAN JUAN | K10: Medicamento | L10: MED8 | M10: Adenosina Amp x 2 ml | N10: forma ampolla · volumen 2 ml | O10: 5 | P10: 7 | Q10: =IF(C10="Inventario físico",O10,P10) | R10: 1 | S10: 1000304 | T10: 1000304 | U10: No | V10: ADENOSINA 2 ML AMP 3 MG/1 ML | W10: forma farmacéutica, volumen / presentación | X10: Alta | Y10: Candidato 1000304 «ADENOSINA 2 ML AMP 3 MG/1 ML». Denominación: 100% del nombre del inventario explicado por el texto de SAP y 100% a la inversa. Atributos verificados: forma farmacéutica, volumen / presentación. Sin contradicción en ningún atributo. | Z10: Pendiente de valorización | AC10: No disponible en los archivos recibidos | AD10: =IF(AA10="","Pendiente",AA10*Q10) | AE10: 879.89714 | AF10: =IF(AE10="","",AE10*Q10) | AG10: Pendiente | AH10: Sin decidir
A11: 7 | B11: 1120-MED9 | C11: Inventario físico | D11: A · Identificado en SAP | E11: Mantener identificación | G11: San Juan | H11: 1120 | I11: AVAIN | J11: Stock en Almacén · BASE SAN JUAN | K11: Medicamento | L11: MED9 | M11: Adrenalina amp 1 ml | N11: forma ampolla · volumen 1 ml | O11: 41 | P11: 104 | Q11: =IF(C11="Inventario físico",O11,P11) | R11: 1 | S11: 1000002 | T11: 1000002 | U11: No | V11: ADRENALINA 1MG AMPOLLA DE 1 ML INYEC | W11: forma farmacéutica, volumen / presentación | X11: Alta | Y11: Candidato 1000002 «ADRENALINA 1MG AMPOLLA DE 1 ML INYEC». Denominación: 100% del nombre del inventario explicado por el texto de SAP y 100% a la inversa. Atributos verificados: forma farmacéutica, volumen / presentación. Sin contradicción en ningún atributo. | Z11: Pendiente de valorización | AC11: No disponible en los archivos recibidos | AD11: =IF(AA11="","Pendiente",AA11*Q11) | AE11: 310.67721 | AF11: =IF(AE11="","",AE11*Q11) | AG11: Pendiente | AH11: Sin decidir
A12: 8 | B12: 1120-DESC291 | C12: Inventario físico | D12: A · Identificado en SAP | E12: Registrar existencia en SAP en esta base | G12: San Juan | H12: 1120 | I12: AVAIN | J12: Stock en Almacén · BASE SAN JUAN | K12: Medicamento | L12: DESC291 | M12: Agua Oxigenada 10 Vol x 500 ml | N12: volumen 500 ml · cantidad sin unidad 10 | O12: 3 | P12: 0 | Q12: =IF(C12="Inventario físico",O12,P12) | R12: 2 | S12: 1000052 | T12: 1000052 | U12: No | V12: AGUA OXIGENADA 10 VOL. X 500ML | W12: volumen / presentación, cantidad o dosis sin unidad | X12: Alta | Y12: Candidato 1000052 «AGUA OXIGENADA 10 VOL. X 500ML». Denominación: 100% del nombre del inventario explicado por el texto de SAP y 100% a la inversa. Atributos verificados: volumen / presentación, cantidad o dosis sin unidad. Sin contradicción en ningún atributo. | Z12: Pendiente de valorización | AC12: No disponible en los archivos recibidos | AD12: =IF(AA12="","Pendiente",AA12*Q12) | AE12: 542.5805 | AF12: =IF(AE12="","",AE12*Q12) | AG12: Pendiente | AH12: Sin decidir
A13: 9 | B13: 1120-DESC9 | C13: Inventario físico | D13: A · Identificado en SAP | E13: Mantener identificación | G13: San Juan | H13: 1120 | I13: AVAIN | J13: Stock en Almacén · BASE SAN JUAN | K13: Medicamento | L13: DESC9 | M13: Agua oxigenada x 100ml | N13: volumen 100 ml | O13: 11 | P13: 15 | Q13: =IF(C13="Inventario físico",O13,P13) | R13: 1 | S13: 1000004 | T13: 1000004 | U13: No | V13: AGUA OXIGENADA 10 VOL. X 100ML | W13: volumen / presentación | X13: Alta | Y13: Candidato 1000004 «AGUA OXIGENADA 10 VOL. X 100ML». Denominación: 100% del nombre del inventario explicado por el texto de SAP y 64% a la inversa. Atributos verificados: volumen / presentación. Sin contradicción en ningún atributo. | Z13: Pendiente de valorización | AC13: No disponible en los archivos recibidos | AD13: =IF(AA13="","Pendiente",AA13*Q13) | AE13: 335.13333 | AF13: =IF(AE13="","",AE13*Q13) | AG13: Pendiente | AH13: Sin decidir
A14: 10 | B14: 1120-DESC10 | C14: Inventario físico | D14: A · Identificado en SAP | E14: Mantener identificación | G14: San Juan | H14: 1120 | I14: AVAIN | J14: Stock en Almacén · BASE SAN JUAN | K14: Medicamento | L14: DESC10 | M14: Aguja 40/12 | N14: calibre 40/12 | O14: 20 | P14: 95 | Q14: =IF(C14="Inventario físico",O14,P14) | R14: 1 | S14: 1000772 | T14: 1000772 | U14: No | V14: AGUJA 40/12 | W14: calibre | X14: Alta | Y14: Candidato 1000772 «AGUJA 40/12». Denominación: 100% del nombre del inventario explicado por el texto de SAP y 100% a la inversa. Atributos verificados: calibre. Sin contradicción en ningún atributo. | Z14: Pendiente de valorización | AC14: No disponible en los archivos recibidos | AD14: =IF(AA14="","Pendiente",AA14*Q14) | AE14: 174.82526 | AF14: =IF(AE14="","",AE14*Q14) | AG14: Pendiente | AH14: Sin decidir
A15: 11 | B15: 1120-DESC11 | C15: Inventario físico | D15: A · Identificado en SAP | E15: Mantener identificación | G15: San Juan | H15: 1120 | I15: AVAIN | J15: Stock en Almacén · BASE SAN JUAN | K15: Descartable | L15: DESC11 | M15: Agujas 16/5 | N15: calibre 16/5 | O15: 300 | P15: 1020 | Q15: =IF(C15="Inventario físico",O15,P15) | R15: 1 | S15: 2000007 | T15: 2000007 | U15: No | V15: AGUJA HIPODERMICA 25G x ⅝ - 16/5 | W15: calibre | X15: Media | Y15: Candidato 2000007 «AGUJA HIPODERMICA 25G x ⅝ - 16/5». Denominación: 90% del nombre del inventario explicado por el texto de SAP y 41% a la inversa. Atributos verificados: calibre. Sin contradicción en ningún atributo. | Z15: Pendiente de valorización | AC15: No disponible en los archivos recibidos | AD15: =IF(AA15="","Pendiente",AA15*Q15) | AE15: 27.725941 | AF15: =IF(AE15="","",AE15*Q15) | AG15: Pendiente | AH15: Sin decidir
A16: 12 | B16: 1120-DESC12 | C16: Inventario físico | D16: A · Identificado en SAP | E16: Mantener identificación | G16: San Juan | H16: 1120 | I16: AVAIN | J16: Stock en Almacén · BASE SAN JUAN | K16: Descartable | L16: DESC12 | M16: Agujas 25/8 | N16: calibre 25/8 | O16: 975 | P16: 1548 | Q16: =IF(C16="Inventario físico",O16,P16) | R16: 1 | S16: 2000008 | T16: 2000008 | U16: No | V16: AGUJA HIPODERMICA 21G x 1 - 25/8 | W16: calibre | X16: Media | Y16: Candidato 2000008 «AGUJA HIPODERMICA 21G x 1 - 25/8». Denominación: 90% del nombre del inventario explicado por el texto de SAP y 41% a la inversa. Atributos verificados: calibre. Sin contradicción en ningún atributo. | Z16: Pendiente de valorización | AC16: No disponible en los archivos recibidos | AD16: =IF(AA16="","Pendiente",AA16*Q16) | AE16: 24.974767 | AF16: =IF(AE16="","",AE16*Q16) | AG16: Pendiente | AH16: Sin decidir
A17: 13 | B17: 1120-DESC13 | C17: Inventario físico | D17: A · Identificado en SAP | E17: Mantener identificación | G17: San Juan | H17: 1120 | I17: AVAIN | J17: Stock en Almacén · BASE SAN JUAN | K17: Descartable | L17: DESC13 | M17: Agujas 40/8 | N17: calibre 40/8 | O17: 100 | P17: 1229 | Q17: =IF(C17="Inventario físico",O17,P17) | R17: 1 | S17: 2000009 | T17: 2000009 | U17: No | V17: AGUJA HIPODERMICA 21G x 1 ½ - 40/8 | W17: calibre | X17: Media | Y17: Candidato 2000009 «AGUJA HIPODERMICA 21G x 1 ½ - 40/8». Denominación: 90% del nombre del inventario explicado por el texto de SAP y 41% a la inversa. Atributos verificados: calibre. Sin contradicción en ningún atributo. | Z17: Pendiente de valorización | AC17: No disponible en los archivos recibidos | AD17: =IF(AA17="","Pendiente",AA17*Q17) | AE17: 55.786672 | AF17: =IF(AE17="","",AE17*Q17) | AG17: Pendiente | AH17: Sin decidir
A18: 14 | B18: 1120-DESC14 | C18: Inventario físico | D18: A · Identificado en SAP | E18: Mantener identificación | G18: San Juan | H18: 1120 | I18: AVAIN | J18: Stock en Almacén · BASE SAN JUAN | K18: Medicamento | L18: DESC14 | M18: Alcohol 70% x 1000 ml | N18: concentración 70% · volumen 1000 ml | O18: 9 | P18: 91 | Q18: =IF(C18="Inventario físico",O18,P18) | R18: 1 | S18: 1000017 | T18: 1000017 | U18: No | V18: ALCOHOL AL 70% X 1000ML | W18: concentración, volumen / presentación | X18: Alta | Y18: Candidato 1000017 «ALCOHOL AL 70% X 1000ML». Denominación: 100% del nombre del inventario explicado por el texto de SAP y 100% a la inversa. Atributos verificados: concentración, volumen / presentación. Sin contradicción en ningún atributo. | Z18: Pendiente de valorización | AC18: No disponible en los archivos recibidos | AD18: =IF(AA18="","Pendiente",AA18*Q18) | AE18: 2977.7323 | AF18: =IF(AE18="","",AE18*Q18) | AG18: Pendiente | AH18: Sin decidir
A19: 15 | B19: 1120-DESC15 | C19: Inventario físico | D19: A · Identificado en SAP | E19: Mantener identificación | G19: San Juan | H19: 1120 | I19: AVAIN | J19: Stock en Almacén · BASE SAN JUAN | K19: Medicamento | L19: DESC15 | M19: Alcohol 96% x 1000ml | N19: concentración 96% · volumen 1000 ml | O19: 3 | P19: 51 | Q19: =IF(C19="Inventario físico",O19,P19) | R19: 1 | S19: 1000053 | T19: 1000053 | U19: No | V19: ALCOHOL AL 96% X 1000ML | W19: concentración, volumen / presentación | X19: Alta | Y19: Candidato 1000053 «ALCOHOL AL 96% X 1000ML». Denominación: 100% del nombre del inventario explicado por el texto de SAP y 100% a la inversa. Atributos verificados: concentración, volumen / presentación. Sin contradicción en ningún atributo. | Z19: Pendiente de valorización | AC19: No disponible en los archivos recibidos | AD19: =IF(AA19="","Pendiente",AA19*Q19) | AE19: 2606.5129 | AF19: =IF(AE19="","",AE19*Q19) | AG19: Pendiente | AH19: Sin decidir
A20: 16 | B20: 1120-DESC16 | C20: Inventario físico | D20: A · Identificado en SAP | E20: Registrar existencia en SAP en esta base | G20: San Juan | H20: 1120 | I20: AVAIN | J20: Stock en Almacén · BASE SAN JUAN | K20: Medicamento | L20: DESC16 | M20: Alcohol 96% x 500ml | N20: concentración 96% · volumen 500 ml | O20: 2 | P20: 0 | Q20: =IF(C20="Inventario físico",O20,P20) | R20: 1 | S20: 1000054 | T20: 1000054 | U20: No | V20: ALCOHOL AL 96% X 500ML | W20: concentración, volumen / presentación | X20: Alta | Y20: Candidato 1000054 «ALCOHOL AL 96% X 500ML». Denominación: 100% del nombre del inventario explicado por el texto de SAP y 100% a la inversa. Atributos verificados: concentración, volumen / presentación. Sin contradicción en ningún atributo. | Z20: Pendiente de valorización | AC20: No disponible en los archivos recibidos | AD20: =IF(AA20="","Pendiente",AA20*Q20) | AE20: 449.91858 | AF20: =IF(AE20="","",AE20*Q20) | AG20: Pendiente | AH20: Sin decidir
A21: 17 | B21: 1120-DESC18 | C21: Inventario físico | D21: A · Identificado en SAP | E21: Mantener identificación | G21: San Juan | H21: 1120 | I21: AVAIN | J21: Stock en Almacén · BASE SAN JUAN | K21: Medicamento | L21: DESC18 | M21: Alcohol en gel x 500 ml | N21: forma crema · volumen 500 ml | O21: 16 | P21: 48 | Q21: =IF(C21="Inventario físico",O21,P21) | R21: 1 | S21: 1000058 | T21: 1000058 | U21: No | V21: ALCOHOL EN GEL X 500ML | W21: forma farmacéutica, volumen / presentación | X21: Alta | Y21: Candidato 1000058 «ALCOHOL EN GEL X 500ML». Denominación: 100% del nombre del inventario explicado por el texto de SAP y 100% a la inversa. Atributos verificados: forma farmacéutica, volumen / presentación. Sin contradicción en ningún atributo. | Z21: Pendiente de valorización | AC21: No disponible en los archivos recibidos | AD21: =IF(AA21="","Pendiente",AA21*Q21) | AE21: 1052.1065 | AF21: =IF(AE21="","",AE21*Q21) | AG21: Pendiente | AH21: Sin decidir
... A23: 19 | B23: 1120-MED11 | C23: Inventario físico | D23: A · Identificado en SAP | E23: Mantener identificación | G23: San Juan | H23: 1120 | I23: AVAIN | J23: Stock en Almacén · BASE SAN JUAN | K23: Medicamento | L23: MED11 | M23: Amiodarona 150 mg Amp x 3 ml | N23: concentración 150 mg · forma ampolla · volumen 3 ml | O23: 75 | P23: 55 | Q23: =IF(C23="Inventario físico",O23,P23) | R23: 1 | S23: 1000005 | T23: 1000005 | U23: No | V23: AMIODARONA 150MG AMPOLLA DE 3 ML INYEC | W23: concentración, forma farmacéutica, volumen / presentación | X23: Alta | Y23: Candidato 1000005 «AMIODARONA 150MG AMPOLLA DE 3 ML INYEC». Denominación: 100% del nombre del inventario explicado por el texto de SAP y 100% a la inversa. Atributos verificados: concentración, forma farmacéutica, volumen / presentación. Sin contradicción en ningún atributo. | Z23: Pendiente de valorización | AC23: No disponible en los archivos recibidos | AD23: =IF(AA23="","Pendiente",AA23*Q23) | AE23: 1983.4744 | AF23: =IF(AE23="","",AE23*Q23) | AG23: Pendiente | AH23: Sin decidir
A24: 20 | B24: 1120-MED186 | C24: Inventario físico | D24: D · Requiere revisión | E24: Revisar y decidir | F24: Conflicto de presentación | G24: San Juan | H24: 1120 | I24: AVAIN | J24: Stock en Almacén · BASE SAN JUAN | K24: Medicamento | L24: MED186 | M24: amiodarona 200mg comp | N24: concentración 200 mg · forma comprimido | O24: 20 | P24: 0 | Q24: =IF(C24="Inventario físico",O24,P24) | R24: 1 | U24: No | Y24: El candidato más parecido es 1000005 «AMIODARONA 150MG AMPOLLA DE 3 ML INYEC», pero difiere en concentración, forma farmacéutica. No se asigna el código: una diferencia de presentación significa que no es el mismo material. | Z24: Pendiente de valorización | AC24: No disponible en los archivos recibidos | AD24: =IF(AA24="","Pendiente",AA24*Q24) | AF24: =IF(AE24="","",AE24*Q24) | AG24: Pendiente | AH24: Sin decidir
A25: 21 | B25: 1120-MED14 | C25: Inventario físico | D25: D · Requiere revisión | E25: Revisar y decidir | F25: Conflicto de presentación | G25: San Juan | H25: 1120 | I25: AVAIN | J25: Stock en Almacén · BASE SAN JUAN | K25: Medicamento | L25: MED14 | M25: Amoxicilina + Clavulanato Comp x 1 mg | N25: concentración 1 mg · forma comprimido | O25: 371 | P25: 0 | Q25: =IF(C25="Inventario físico",O25,P25) | R25: 1 | U25: No | Y25: El candidato más parecido es 1005299 «AMOXICILINA +AC. CLAVULONICO 1GR COMP», pero difiere en concentración. No se asigna el código: una diferencia de presentación significa que no es el mismo material. | Z25: Pendiente de valorización | AC25: No disponible en los archivos recibidos | AD25: =IF(AA25="","Pendiente",AA25*Q25) | AF25: =IF(AE25="","",AE25*Q25) | AG25: Pendiente | AH25: Sin decidir
A26: 22 | B26: 1120-MED156 | C26: Inventario físico | D26: D · Requiere revisión | E26: Revisar y decidir | F26: Varios códigos SAP posibles | G26: San Juan | H26: 1120 | I26: AVAIN | J26: Stock en Almacén · BASE SAN JUAN | K26: Medicamento | L26: MED156 | M26: Antigripal comp | N26: forma comprimido | O26: 60 | P26: 0 | Q26: =IF(C26="Inventario físico",O26,P26) | R26: 1 | U26: No | W26: forma farmacéutica | Y26: Candidato 1001216 «TAVINEX ANTIGRIPAL COMP.». Denominación: 100% del nombre del inventario explicado por el texto de SAP y 48% a la inversa. Atributos verificados: forma farmacéutica. Pero 1001297 «PULMONIX ANTIGRIP 20 COMP» es igual de plausible. Hay que elegir cuál corresponde. | Z26: Pendiente de valorización | AC26: No disponible en los archivos recibidos | AD26: =IF(AA26="","Pendiente",AA26*Q26) | AF26: =IF(AE26="","",AE26*Q26) | AG26: Pendiente | AH26: Sin decidir
A27: 23 | B27: 1120-DESC21 | C27: Inventario físico | D27: D · Requiere revisión | E27: Revisar y decidir | F27: Falta un atributo para confirmar la presentación | G27: San Juan | H27: 1120 | I27: AVAIN | J27: Stock en Almacén · BASE SAN JUAN | K27: Descartable | L27: DESC21 | M27: Apositos estériles | O27: 160 | P27: 0 | Q27: =IF(C27="Inventario físico",O27,P27) | R27: 1 | U27: No | V27: APOSITO NO ESTERIL (G+A) 10X20CM | Y27: Candidato 2000095 «APOSITO NO ESTERIL (G+A) 10X20CM». Denominación: 52% del nombre del inventario explicado por el texto de SAP y 42% a la inversa. Sap declara la presentación y el inventario físico no, así que la equivalencia no puede confirmarse con la información disponible. | Z27: Pendiente de valorización | AC27: No disponible en los archivos recibidos | AD27: =IF(AA27="","Pendiente",AA27*Q27) | AF27: =IF(AE27="","",AE27*Q27) | AG27: Pendiente | AH27: Sin decidir
A28: 24 | B28: 1120-MED16 | C28: Inventario físico | D28: A · Identificado en SAP | E28: Mantener identificación | G28: San Juan | H28: 1120 | I28: AVAIN | J28: Stock en Almacén · BASE SAN JUAN | K28: Medicamento | L28: MED16 | M28: Atenolol Comp x 50 mg | N28: concentración 50 mg · forma comprimido | O28: 25 | P28: 29 | Q28: =IF(C28="Inventario físico",O28,P28) | R28: 2 | S28: 1005233 | T28: 1005233 | U28: No | V28: ATENOLOL 50MG X 10COMP | W28: concentración, forma farmacéutica | X28: Alta | Y28: Candidato 1005233 «ATENOLOL 50MG X 10COMP». Denominación: 100% del nombre del inventario explicado por el texto de SAP y 49% a la inversa. Atributos verificados: concentración, forma farmacéutica. Sin contradicción en ningún atributo. | Z28: Pendiente de valorización | AC28: No disponible en los archivos recibidos | AD28: =IF(AA28="","Pendiente",AA28*Q28) | AE28: 800.31586 | AF28: =IF(AE28="","",AE28*Q28) | AG28: Pendiente | AH28: Sin decidir
A29: 25 | B29: 1120-MED18 | C29: Inventario físico | D29: A · Identificado en SAP | E29: Mantener identificación | G29: San Juan | H29: 1120 | I29: AVAIN | J29: Stock en Almacén · BASE SAN JUAN | K29: Medicamento | L29: MED18 | M29: Azitromicina Comp x 500 mg | N29: concentración 500 mg · forma comprimido | O29: 6 | P29: 164 | Q29: =IF(C29="Inventario físico",O29,P29) | R29: 1 | S29: 1000486 | T29: 1000486 | U29: No | V29: AZITROMICINA 500 MG COMP | W29: concentración, forma farmacéutica | X29: Alta | Y29: Candidato 1000486 «AZITROMICINA 500 MG COMP». Denominación: 100% del nombre del inventario explicado por el texto de SAP y 100% a la inversa. Atributos verificados: concentración, forma farmacéutica. Sin contradicción en ningún atributo. | Z29: Pendiente de valorización | AC29: No disponible en los archivos recibidos | AD29: =IF(AA29="","Pendiente",AA29*Q29) | AE29: 441.36567 | AF29: =IF(AE29="","",AE29*Q29) | AG29: Pendiente | AH29: Sin decidir
A30: 26 | B30: 1120-DESC22 | C30: Inventario físico | D30: D · Requiere revisión | E30: Revisar y decidir | F30: Coincidencia parcial de denominación | G30: San Juan | H30: 1120 | I30: AVAIN | J30: Stock en Almacén · BASE SAN JUAN | K30: Descartable | L30: DESC22 | M30: Bajalenguas x 1 ud | O30: 1800 | P30: 0 | Q30: =IF(C30="Inventario físico",O30,P30) | R30: 1 | U30: No | V30: BAJALENGUAS DE MADERA | Y30: Candidato 2000011 «BAJALENGUAS DE MADERA». Denominación: 100% del nombre del inventario explicado por el texto de SAP y 48% a la inversa. La coincidencia de denominación no alcanza para dar la identificación por confirmada. | Z30: Pendiente de valorización | AC30: No disponible en los archivos recibidos | AD30: =IF(AA30="","Pendiente",AA30*Q30) | AF30: =IF(AE30="","",AE30*Q30) | AG30: Pendiente | AH30: Sin decidir
A31: 27 | B31: 1120-DESC24 | C31: Inventario físico | D31: D · Requiere revisión | E31: Revisar y decidir | F31: Coincidencia parcial de denominación | G31: San Juan | H31: 1120 | I31: AVAIN | J31: Stock en Almacén · BASE SAN JUAN | K31: Descartable | L31: DESC24 | M31: Barbijos N95 c/válvula | O31: 10 | P31: 0 | Q31: =IF(C31="Inventario físico",O31,P31) | R31: 1 | U31: No | V31: VALVULA ESPIRATORIA | Y31: Candidato 2001024 «VALVULA ESPIRATORIA». Denominación: 33% del nombre del inventario explicado por el texto de SAP y 48% a la inversa. La coincidencia de denominación no alcanza para dar la identificación por confirmada. | Z31: Pendiente de valorización | AC31: No disponible en los archivos recibidos | AD31: =IF(AA31="","Pendiente",AA31*Q31) | AF31: =IF(AE31="","",AE31*Q31) | AG31: Pendiente | AH31: Sin decidir
A32: 28 | B32: 1120-DESC25 | C32: Inventario físico | D32: D · Requiere revisión | E32: Revisar y decidir | F32: Coincidencia parcial de denominación | G32: San Juan | H32: 1120 | I32: AVAIN | J32: Stock en Almacén · BASE SAN JUAN | K32: Descartable | L32: DESC25 | M32: Barbijos quirúrgicos x 1 ud | O32: 350 | P32: 0 | Q32: =IF(C32="Inventario físico",O32,P32) | R32: 1 | U32: No | V32: TIJERA QUIRURGICA | Y32: Candidato 2001378 «TIJERA QUIRURGICA». Denominación: 46% del nombre del inventario explicado por el texto de SAP y 47% a la inversa. La coincidencia de denominación no alcanza para dar la identificación por confirmada. | Z32: Pendiente de valorización | AC32: No disponible en los archivos recibidos | AD32: =IF(AA32="","Pendiente",AA32*Q32) | AF32: =IF(AE32="","",AE32*Q32) | AG32: Pendiente | AH32: Sin decidir
A33: 29 | B33: 1120-DESC26 | C33: Inventario físico | D33: D · Requiere revisión | E33: Revisar y decidir | F33: Falta un atributo para confirmar la presentación | G33: San Juan | H33: 1120 | I33: AVAIN | J33: Stock en Almacén · BASE SAN JUAN | K33: Descartable | L33: DESC26 | M33: Bolsa Colectora de orina T/K-207 | N33: modelo K207 | O33: 3 | P33: 0 | Q33: =IF(C33="Inventario físico",O33,P33) | R33: 1 | U33: No | V33: BOLSA COLECTORA DE ORINA X 2000 ML | Y33: Candidato 2000100 «BOLSA COLECTORA DE ORINA X 2000 ML». Denominación: 100% del nombre del inventario explicado por el texto de SAP y 100% a la inversa. El inventario físico declara la presentación y SAP no, así que la equivalencia no puede confirmarse con la información disponible. | Z33: Pendiente de valorización | AC33: No disponible en los archivos recibidos | AD33: =IF(AA33="","Pendiente",AA33*Q33) | AF33: =IF(AE33="","",AE33*Q33) | AG33: Pendiente | AH33: Sin decidir
A34: 30 | B34: 1120-DESC27 | C34: Inventario físico | D34: D · Requiere revisión | E34: Revisar y decidir | F34: Coincidencia parcial de denominación | G34: San Juan | H34: 1120 | I34: AVAIN | J34: Stock en Almacén · BASE SAN JUAN | K34: Descartable | L34: DESC27 | M34: Bolsa de Resucitación manual (tipo Ambú) con reservorio adulto | N34: población adulto | O34: 6 | P34: 0 | Q34: =IF(C34="Inventario físico",O34,P34) | R34: 1 | U34: No | V34: MASCARA PARA O2 ADULTO CON RESERVORIO | W34: población | Y34: Candidato 2000363 «MASCARA PARA O2 ADULTO CON RESERVORIO». Denominación: 39% del nombre del inventario explicado por el texto de SAP y 68% a la inversa. Atributos verificados: población. La coincidencia de denominación no alcanza para dar la identificación por confirmada. | Z34: Pendiente de valorización | AC34: No disponible en los archivos recibidos | AD34: =IF(AA34="","Pendiente",AA34*Q34) | AF34: =IF(AE34="","",AE34*Q34) | AG34: Pendiente | AH34: Sin decidir
A35: 31 | B35: 1120-DESC285 | C35: Inventario físico | D35: D · Requiere revisión | E35: Revisar y decidir | F35: Falta un atributo para confirmar la presentación | G35: San Juan | H35: 1120 | I35: AVAIN | J35: Stock en Almacén · BASE SAN JUAN | K35: Descartable | L35: DESC285 | M35: Brazalete para Tensiómetro | O35: 2 | P35: 0 | Q35: =IF(C35="Inventario físico",O35,P35) | R35: 1 | U35: No | V35: BRAZALETE ADULTO | Y35: Candidato 2001483 «BRAZALETE ADULTO». Denominación: 54% del nombre del inventario explicado por el texto de SAP y 59% a la inversa. Sap declara la presentación y el inventario físico no, así que la equivalencia no puede confirmarse con la información disponible. | Z35: Pendiente de valorización | AC35: No disponible en los archivos recibidos | AD35: =IF(AA35="","Pendiente",AA35*Q35) | AF35: =IF(AE35="","",AE35*Q35) | AG35: Pendiente | AH35: Sin decidir
A36: 32 | B36: 1120-MED25 | C36: Inventario físico | D36: A · Identificado en SAP | E36: Mantener identificación | G36: San Juan | H36: 1120 | I36: AVAIN | J36: Stock en Almacén · BASE SAN JUAN | K36: Medicamento | L36: MED25 | M36: Budesonide (gotas para NBZ) x 20ml | N36: forma gotas · volumen 20 ml | O36: 2 | P36: 20 | Q36: =IF(C36="Inventario físico",O36,P36) | R36: 1 | S36: 1000381 | T36: 1000381 | U36: No | V36: BUDESONIDA DENVER SOL 20ML | W36: volumen / presentación | X36: Media | Y36: Candidato 1000381 «BUDESONIDA DENVER SOL 20ML». Denominación: 90% del nombre del inventario explicado por el texto de SAP y 32% a la inversa. Atributos verificados: volumen / presentación. Sin contradicción en ningún atributo. | Z36: Pendiente de valorización | AC36: No disponible en los archivos recibidos | AD36: =IF(AA36="","Pendiente",AA36*Q36) | AE36: 8615.0595 | AF36: =IF(AE36="","",AE36*Q36) | AG36: Pendiente | AH36: Sin decidir
A37: 33 | B37: 1120-DESC35 | C37: Inventario físico | D37: B · Candidato a alta | E37: Proponer alta de material nuevo | G37: San Juan | H37: 1120 | I37: AVAIN | J37: Stock en Almacén · BASE SAN JUAN | K37: Descartable | L37: DESC35 | M37: Canula de Yankauer T/K 67 | N37: modelo K67 | O37: 6 | P37: 0 | Q37: =IF(C37="Inventario físico",O37,P37) | R37: 2 | U37: No | Y37: No se encontró en SAP ningún material cuya denominación y presentación se correspondan con este ítem. | Z37: Pendiente de valorización | AC37: No disponible en los archivos recibidos | AD37: =IF(AA37="","Pendiente",AA37*Q37) | AF37: =IF(AE37="","",AE37*Q37) | AG37: Pendiente | AH37: Sin decidir
A38: 34 | B38: 1120-DESC36 | C38: Inventario físico | D38: D · Requiere revisión | E38: Revisar y decidir | F38: Falta un atributo para confirmar la presentación | G38: San Juan | H38: 1120 | I38: AVAIN | J38: Stock en Almacén · BASE SAN JUAN | K38: Descartable | L38: DESC36 | M38: Canula nasal | O38: 1316 | P38: 0 | Q38: =IF(C38="Inventario físico",O38,P38) | R38: 2 | U38: No | V38: CANULA NASAL O2T SIL 100% COD 230-09 PED | Y38: Candidato 2000103 «CANULA NASAL O2T SIL 100% COD 230-09 PED». Denominación: 100% del nombre del inventario explicado por el texto de SAP y 30% a la inversa. Sap declara la presentación y el inventario físico no, así que la equivalencia no puede confirmarse con la información disponible. | Z38: Pendiente de valorización | AC38: No disponible en los archivos recibidos | AD38: =IF(AA38="","Pendiente",AA38*Q38) | AF38: =IF(AE38="","",AE38*Q38) | AG38: Pendiente | AH38: Sin decidir
A39: 35 | B39: 1120-DESC280 | C39: Inventario físico | D39: D · Requiere revisión | E39: Revisar y decidir | F39: Falta un atributo para confirmar la presentación | G39: San Juan | H39: 1120 | I39: AVAIN | J39: Stock en Almacén · BASE SAN JUAN | K39: Descartable | L39: DESC280 | M39: Canula Orofaringea N° 8 | N39: calibre N° 8 | O39: 3 | P39: 0 | Q39: =IF(C39="Inventario físico",O39,P39) | R39: 1 | U39: No | V39: KIT CANULAS OROFARINGEAS (TUBOS DE MAYO) | Y39: Candidato 2000659 «KIT CANULAS OROFARINGEAS (TUBOS DE MAYO)». Denominación: 90% del nombre del inventario explicado por el texto de SAP y 63% a la inversa. El inventario físico declara la presentación y SAP no, así que la equivalencia no puede confirmarse con la información disponible. | Z39: Pendiente de valorización | AC39: No disponible en los archivos recibidos | AD39: =IF(AA39="","Pendiente",AA39*Q39) | AF39: =IF(AE39="","",AE39*Q39) | AG39: Pendiente | AH39: Sin decidir
A40: 36 | B40: 1120-MED30 | C40: Inventario físico | D40: D · Requiere revisión | E40: Revisar y decidir | F40: Falta un atributo para confirmar la presentación | G40: San Juan | H40: 1120 | I40: AVAIN | J40: Stock en Almacén · BASE SAN JUAN | K40: Medicamento | L40: MED30 | M40: Caramelos antigripales con benzocaina 20.7mg | N40: concentración 20,7 mg | O40: 351 | P40: 0 | Q40: =IF(C40="Inventario físico",O40,P40) | R40: 1 | U40: No | V40: PULMONIX ANTIGRIP 20 COMP | Y40: Candidato 1001297 «PULMONIX ANTIGRIP 20 COMP». Denominación: 31% del nombre del inventario explicado por el texto de SAP y 45% a la inversa. El inventario físico declara la presentación y SAP no, así que la equivalencia no puede confirmarse con la información disponible. | Z40: Pendiente de valorización | AC40: No disponible en los archivos recibidos | AD40: =IF(AA40="","Pendiente",AA40*Q40) | AF40: =IF(AE40="","",AE40*Q40) | AG40: Pendiente | AH40: Sin decidir
A41: 37 | B41: 1120-DESC281 | C41: Inventario físico | D41: D · Requiere revisión | E41: Revisar y decidir | F41: Coincidencia parcial de denominación | G41: San Juan | H41: 1120 | I41: AVAIN | J41: Stock en Almacén · BASE SAN JUAN | K41: Descartable | L41: DESC281 | M41: Chata Plástica | O41: 5 | P41: 0 | Q41: =IF(C41="Inventario físico",O41,P41) | R41: 1 | U41: No | V41: ANTIPARRA DE PLASTICO | Y41: Candidato 2000010 «ANTIPARRA DE PLASTICO». Denominación: 45% del nombre del inventario explicado por el texto de SAP y 45% a la inversa. La coincidencia de denominación no alcanza para dar la identificación por confirmada. | Z41: Pendiente de valorización | AC41: No disponible en los archivos recibidos | AD41: =IF(AA41="","Pendiente",AA41*Q41) | AF41: =IF(AE41="","",AE41*Q41) | AG41: Pendiente | AH41: Sin decidir
A42: 38 | B42: 1120-DESC43 | C42: Inventario físico | D42: B · Candidato a alta | E42: Proponer alta de material nuevo | G42: San Juan | H42: 1120 | I42: AVAIN | J42: Stock en Almacén · BASE SAN JUAN | K42: Descartable | L42: DESC43 | M42: Cintas de aproximacion tipo SteriStrip (3 mm x 7,5 cm) | N42: longitud 0,3 cm, 7,5 cm | O42: 2 | P42: 0 | Q42: =IF(C42="Inventario físico",O42,P42) | R42: 1 | U42: No | Y42: No se encontró en SAP ningún material cuya denominación y presentación se correspondan con este ítem. | Z42: Pendiente de valorización | AC42: No disponible en los archivos recibidos | AD42: =IF(AA42="","Pendiente",AA42*Q42) | AF42: =IF(AE42="","",AE42*Q42) | AG42: Pendiente | AH42: Sin decidir
A43: 39 | B43: 1120-DESC44 | C43: Inventario físico | D43: B · Candidato a alta | E43: Proponer alta de material nuevo | G43: San Juan | H43: 1120 | I43: AVAIN | J43: Stock en Almacén · BASE SAN JUAN | K43: Descartable | L43: DESC44 | M43: Cintas de aproximacion tipo SteriStrip (6 mm x 10 cm) | N43: longitud 0,6 cm, 10 cm | O43: 12 | P43: 0 | Q43: =IF(C43="Inventario físico",O43,P43) | R43: 1 | U43: No | Y43: No se encontró en SAP ningún material cuya denominación y presentación se correspondan con este ítem. | Z43: Pendiente de valorización | AC43: No disponible en los archivos recibidos | AD43: =IF(AA43="","Pendiente",AA43*Q43) | AF43: =IF(AE43="","",AE43*Q43) | AG43: Pendiente | AH43: Sin decidir
A44: 40 | B44: 1120-MED35 | C44: Inventario físico | D44: D · Requiere revisión | E44: Revisar y decidir | F44: Coincidencia parcial de denominación | G44: San Juan | H44: 1120 | I44: AVAIN | J44: Stock en Almacén · BASE SAN JUAN | K44: Medicamento | L44: MED35 | M44: Ciprofloxacina + Dexametasona 0,1% / 0,03 % Gotas oftal x 5ml | N44: concentración 0,03%, 0,1% · forma gotas · volumen 5 ml | O44: 3 | P44: 0 | Q44: =IF(C44="Inventario físico",O44,P44) | R44: 1 | U44: No | V44: DEXAMETASONA 8MG/2ML AMP(DESCONTINUADO) | W44: forma farmacéutica | Y44: Candidato 1000478 «DEXAMETASONA 8MG/2ML AMP(DESCONTINUADO)». Denominación: 27% del nombre del inventario explicado por el texto de SAP y 100% a la inversa. Atributos verificados: forma farmacéutica. La coincidencia de denominación no alcanza para dar la identificación por confirmada. | Z44: Pendiente de valorización | AC44: No disponible en los archivos recibidos | AD44: =IF(AA44="","Pendiente",AA44*Q44) | AF44: =IF(AE44="","",AE44*Q44) | AG44: Pendiente | AH44: Sin decidir
A45: 41 | B45: 1120-MED37 | C45: Inventario físico | D45: A · Identificado en SAP | E45: Mantener identificación | G45: San Juan | H45: 1120 | I45: AVAIN | J45: Stock en Almacén · BASE SAN JUAN | K45: Medicamento | L45: MED37 | M45: Ciprofloxacina Comp x 500 mg | N45: concentración 500 mg · forma comprimido | O45: 40 | P45: 250 | Q45: =IF(C45="Inventario físico",O45,P45) | R45: 1 | S45: 1000485 | T45: 1000485 | U45: No | V45: CIPROFLOXACINA 500MG COMP | W45: concentración, forma farmacéutica | X45: Alta | Y45: Candidato 1000485 «CIPROFLOXACINA 500MG COMP». Denominación: 100% del nombre del inventario explicado por el texto de SAP y 100% a la inversa. Atributos verificados: concentración, forma farmacéutica. Sin contradicción en ningún atributo. | Z45: Pendiente de valorización | AC45: No disponible en los archivos recibidos | AD45: =IF(AA45="","Pendiente",AA45*Q45) | AE45: 430.32692 | AF45: =IF(AE45="","",AE45*Q45) | AG45: Pendiente | AH45: Sin decidir
A46: 42 | B46: 1120-MED40 | C46: Inventario físico | D46: D · Requiere revisión | E46: Revisar y decidir | F46: Conflicto de presentación | G46: San Juan | H46: 1120 | I46: AVAIN | J46: Stock en Almacén · BASE SAN JUAN | K46: Medicamento | L46: MED40 | M46: Clindamicina 300 mg (FM) comp | N46: concentración 300 mg · forma comprimido | O46: 4 | P46: 0 | Q46: =IF(C46="Inventario físico",O46,P46) | R46: 1 | U46: No | Y46: El candidato más parecido es 1000567 «CLINDAMICINA 100MG», pero difiere en concentración. No se asigna el código: una diferencia de presentación significa que no es el mismo material. | Z46: Pendiente de valorización | AC46: No disponible en los archivos recibidos | AD46: =IF(AA46="","Pendiente",AA46*Q46) | AF46: =IF(AE46="","",AE46*Q46) | AG46: Pendiente | AH46: Sin decidir
A47: 43 | B47: 1120-DESC50 | C47: Inventario físico | D47: D · Requiere revisión | E47: Revisar y decidir | F47: Coincidencia parcial de denominación | G47: San Juan | H47: 1120 | I47: AVAIN | J47: Stock en Almacén · BASE SAN JUAN | K47: Descartable | L47: DESC50 | M47: Collar regulable | O47: 1 | P47: 0 | Q47: =IF(C47="Inventario físico",O47,P47) | R47: 1 | U47: No | V47: REGULADOR DE FLUJO | Y47: Candidato 2001234 «REGULADOR DE FLUJO». Denominación: 50% del nombre del inventario explicado por el texto de SAP y 42% a la inversa. La coincidencia de denominación no alcanza para dar la identificación por confirmada. | Z47: Pendiente de valorización | AC47: No disponible en los archivos recibidos | AD47: =IF(AA47="","Pendiente",AA47*Q47) | AF47: =IF(AE47="","",AE47*Q47) | AG47: Pendiente | AH47: Sin decidir
A48: 44 | B48: 1120-DESC52 | C48: Inventario físico | D48: D · Requiere revisión | E48: Revisar y decidir | F48: Coincidencia parcial de denominación | G48: San Juan | H48: 1120 | I48: AVAIN | J48: Stock en Almacén · BASE SAN JUAN | K48: Descartable | L48: DESC52 | M48: Curitas x 1 ud | O48: 192 | P48: 0 | Q48: =IF(C48="Inventario físico",O48,P48) | R48: 1 | U48: No | V48: CURITAS TELA ELASTICA | Y48: Candidato 2000532 «CURITAS TELA ELASTICA». Denominación: 100% del nombre del inventario explicado por el texto de SAP y 36% a la inversa. La coincidencia de denominación no alcanza para dar la identificación por confirmada. | Z48: Pendiente de valorización | AC48: No disponible en los archivos recibidos | AD48: =IF(AA48="","Pendiente",AA48*Q48) | AF48: =IF(AE48="","",AE48*Q48) | AG48: Pendiente | AH48: Sin decidir
A49: 45 | B49: 1120-DESC54 | C49: Inventario físico | D49: D · Requiere revisión | E49: Revisar y decidir | F49: Coincidencia parcial de denominación | G49: San Juan | H49: 1120 | I49: AVAIN | J49: Stock en Almacén · BASE SAN JUAN | K49: Descartable | L49: DESC54 | M49: Descartador Grande | O49: 4 | P49: 0 | Q49: =IF(C49="Inventario físico",O49,P49) | R49: 1 | U49: No | V49: DESCARTADOR GRANDE MODELO E7 | Y49: Candidato 2001114 «DESCARTADOR GRANDE MODELO E7». Denominación: 100% del nombre del inventario explicado por el texto de SAP y 63% a la inversa. La coincidencia de denominación no alcanza para dar la identificación por confirmada. | Z49: Pendiente de valorización | AC49: No disponible en los archivos recibidos | AD49: =IF(AA49="","Pendiente",AA49*Q49) | AF49: =IF(AE49="","",AE49*Q49) | AG49: Pendiente | AH49: Sin decidir
A50: 46 | B50: 1120-MED55 | C50: Inventario físico | D50: D · Requiere revisión | E50: Revisar y decidir | F50: Varios códigos SAP posibles | G50: San Juan | H50: 1120 | I50: AVAIN | J50: Stock en Almacén · BASE SAN JUAN | K50: Medicamento | L50: MED55 | M50: Dexametasona 8mg Amp x 2 ml | N50: concentración 8 mg · forma ampolla · volumen 2 ml | O50: 100 | P50: 0 | Q50: =IF(C50="Inventario físico",O50,P50) | R50: 1 | U50: No | W50: forma farmacéutica | Y50: Candidato 1000478 «DEXAMETASONA 8MG/2ML AMP(DESCONTINUADO)». Denominación: 100% del nombre del inventario explicado por el texto de SAP y 100% a la inversa. Atributos verificados: forma farmacéutica. Pero 1000094 «DEXAMETASONA INY 4MG/ML AMPOLLA» es igual de plausible. Hay que elegir cuál corresponde. | Z50: Pendiente de valorización | AC50: No disponible en los archivos recibidos | AD50: =IF(AA50="","Pendiente",AA50*Q50) | AF50: =IF(AE50="","",AE50*Q50) | AG50: Pendiente | AH50: Sin decidir
A51: 47 | B51: 1120-MED58 | C51: Inventario físico | D51: D · Requiere revisión | E51: Revisar y decidir | F51: Varios códigos SAP posibles | G51: San Juan | H51: 1120 | I51: AVAIN | J51: Stock en Almacén · BASE SAN JUAN | K51: Medicamento | L51: MED58 | M51: Dextrosa al 5% x 500 ml sachet | N51: concentración 5% · forma sobre · volumen 500 ml | O51: 36 | P51: 0 | Q51: =IF(C51="Inventario físico",O51,P51) | R51: 1 | U51: No | W51: concentración, forma farmacéutica, volumen / presentación | Y51: Candidato 1005357 «SOLUCIÓN DEXTROSA AL 5% DE 500 CC». Denominación: 100% del nombre del inventario explicado por el texto de SAP y 100% a la inversa. Atributos verificados: concentración, forma farmacéutica, volumen / presentación. Pero 1000033 «SOLUCIÓN DEXTROSA AL 5% DE 500 CC» es igual de plausible. Hay que elegir cuál corresponde. | Z51: Pendiente de valorización | AC51: No disponible en los archivos recibidos | AD51: =IF(AA51="","Pendiente",AA51*Q51) | AF51: =IF(AE51="","",AE51*Q51) | AG51: Pendiente | AH51: Sin decidir
A52: 48 | B52: 1120-MED60 | C52: Inventario físico | D52: A · Identificado en SAP | E52: Mantener identificación | G52: San Juan | H52: 1120 | I52: AVAIN | J52: Stock en Almacén · BASE SAN JUAN | K52: Medicamento | L52: MED60 | M52: Diazepam 10 mg (Ps) Amp x 2 ml | N52: concentración 10 mg · forma ampolla · volumen 2 ml | O52: 35 | P52: 130 | Q52: =IF(C52="Inventario físico",O52,P52) | R52: 1 | S52: 1000021 | T52: 1000021 | U52: No | V52: DIAZEPAM 10MG AMPOLLA DE 2ML INYECTABLE | W52: concentración, forma farmacéutica, volumen / presentación | X52: Alta | Y52: Candidato 1000021 «DIAZEPAM 10MG AMPOLLA DE 2ML INYECTABLE». Denominación: 100% del nombre del inventario explicado por el texto de SAP y 100% a la inversa. Atributos verificados: concentración, forma farmacéutica, volumen / presentación. Sin contradicción en ningún atributo. | Z52: Pendiente de valorización | AC52: No disponible en los archivos recibidos | AD52: =IF(AA52="","Pendiente",AA52*Q52) | AE52: 449.07469 | AF52: =IF(AE52="","",AE52*Q52) | AG52: Pendiente | AH52: Sin decidir
A53: 49 | B53: 1120-MED61 | C53: Inventario físico | D53: D · Requiere revisión | E53: Revisar y decidir | F53: Varios códigos SAP posibles | G53: San Juan | H53: 1120 | I53: AVAIN | J53: Stock en Almacén · BASE SAN JUAN | K53: Medicamento | L53: MED61 | M53: Diclofenac + Pridinol Comp x 50/4 mg | N53: concentración 4 mg · forma comprimido | O53: 5 | P53: 0 | Q53: =IF(C53="Inventario físico",O53,P53) | R53: 1 | U53: No | W53: concentración | Y53: Candidato 1000520 «DICLOFENAC 50MG + PRIDINOL 4MG». Denominación: 100% del nombre del inventario explicado por el texto de SAP y 100% a la inversa. Atributos verificados: concentración. Pero 1000889 «DICLOFENAC+PRIDINOL COMPRIMIDOS» es igual de plausible. Hay que elegir cuál corresponde. | Z53: Pendiente de valorización | AC53: No disponible en los archivos recibidos | AD53: =IF(AA53="","Pendiente",AA53*Q53) | AF53: =IF(AE53="","",AE53*Q53) | AG53: Pendiente | AH53: Sin decidir
A54: 50 | B54: 1120-MED62 | C54: Inventario físico | D54: A · Identificado en SAP | E54: Mantener identificación | G54: San Juan | H54: 1120 | I54: AVAIN | J54: Stock en Almacén · BASE SAN JUAN | K54: Medicamento | L54: MED62 | M54: Diclofenac 75mg Amp x 3ml | N54: concentración 75 mg · forma ampolla · volumen 3 ml | O54: 400 | P54: 1959 | Q54: =IF(C54="Inventario físico",O54,P54) | R54: 2 | S54: 1000045 | T54: 1000045 | U54: No | V54: DICLOFENAC 75MG AMPOLLA 3ML | W54: concentración, forma farmacéutica, volumen / presentación | X54: Alta | Y54: Candidato 1000045 «DICLOFENAC 75MG AMPOLLA 3ML». Denominación: 100% del nombre del inventario explicado por el texto de SAP y 100% a la inversa. Atributos verificados: concentración, forma farmacéutica, volumen / presentación. Sin contradicción en ningún atributo. | Z54: Pendiente de valorización | AC54: No disponible en los archivos recibidos | AD54: =IF(AA54="","Pendiente",AA54*Q54) | AE54: 527.88995 | AF54: =IF(AE54="","",AE54*Q54) | AG54: Pendiente | AH54: Sin decidir
A55: 51 | B55: 1120-MED64 | C55: Inventario físico | D55: D · Requiere revisión | E55: Revisar y decidir | F55: Varios códigos SAP posibles | G55: San Juan | H55: 1120 | I55: AVAIN | J55: Stock en Almacén · BASE SAN JUAN | K55: Medicamento | L55: MED64 | M55: Diclofenac Comp x 75 mg | N55: concentración 75 mg · forma comprimido | O55: 945 | P55: 0 | Q55: =IF(C55="Inventario físico",O55,P55) | R55: 1 | U55: No | W55: concentración, forma farmacéutica | Y55: Candidato 1000885 «DICLOFENAC 75MG 30 COMPRIMIDOS». Denominación: 100% del nombre del inventario explicado por el texto de SAP y 100% a la inversa. Atributos verificados: concentración, forma farmacéutica. Pero 1000125 «DICLOFENAC 75 MG COMPRIMIDOS» es igual de plausible. Hay que elegir cuál corresponde. | Z55: Pendiente de valorización | AC55: No disponible en los archivos recibidos | AD55: =IF(AA55="","Pendiente",AA55*Q55) | AF55: =IF(AE55="","",AE55*Q55) | AG55: Pendiente | AH55: Sin decidir
A56: 52 | B56: 1120-MED65 | C56: Inventario físico | D56: D · Requiere revisión | E56: Revisar y decidir | F56: Varios códigos SAP posibles | G56: San Juan | H56: 1120 | I56: AVAIN | J56: Stock en Almacén · BASE SAN JUAN | K56: Medicamento | L56: MED65 | M56: Difenhidramina 10mg Amp x 1 ml | N56: concentración 10 mg · forma ampolla · volumen 1 ml | O56: 11 | P56: 0 | Q56: =IF(C56="Inventario físico",O56,P56) | R56: 2 | U56: No | W56: concentración, forma farmacéutica, volumen / presentación | Y56: Candidato 1000008 «DIFENHIDRAMINA 10MG AMPOLLA DE 1ML». Denominación: 100% del nombre del inventario explicado por el texto de SAP y 100% a la inversa. Atributos verificados: concentración, forma farmacéutica, volumen / presentación. Pero 1001233 «DIFENHIDRAMINA 10 MG X 1 ML AMP» es igual de plausible. Hay que elegir cuál corresponde. | Z56: Pendiente de valorización | AC56: No disponible en los archivos recibidos | AD56: =IF(AA56="","Pendiente",AA56*Q56) | AF56: =IF(AE56="","",AE56*Q56) | AG56: Pendiente | AH56: Sin decidir
A57: 53 | B57: 1120-MED66 | C57: Inventario físico | D57: A · Identificado en SAP | E57: Mantener identificación | G57: San Juan | H57: 1120 | I57: AVAIN | J57: Stock en Almacén · BASE SAN JUAN | K57: Medicamento | L57: MED66 | M57: Difenhidramina 50mg Comp | N57: concentración 50 mg · forma comprimido | O57: 50 | P57: 263 | Q57: =IF(C57="Inventario físico",O57,P57) | R57: 2 | S57: 1000530 | T57: 1000530 | U57: No | V57: DIFENHIDRAMINA 50 MG COMPRIMIDOS | W57: concentración, forma farmacéutica | X57: Alta | Y57: Candidato 1000530 «DIFENHIDRAMINA 50 MG COMPRIMIDOS». Denominación: 100% del nombre del inventario explicado por el texto de SAP y 100% a la inversa. Atributos verificados: concentración, forma farmacéutica. Sin contradicción en ningún atributo. | Z57: Pendiente de valorización | AC57: No disponible en los archivos recibidos | AD57: =IF(AA57="","Pendiente",AA57*Q57) | AE57: 197.05369 | AF57: =IF(AE57="","",AE57*Q57) | AG57: Pendiente | AH57: Sin decidir
A58: 54 | B58: 1120-MED67 | C58: Inventario físico | D58: A · Identificado en SAP | E58: Mantener identificación | G58: San Juan | H58: 1120 | I58: AVAIN | J58: Stock en Almacén · BASE SAN JUAN | K58: Medicamento | L58: MED67 | M58: Digoxina 0,25mg Amp x 1 ml | N58: concentración 0,25 mg · forma ampolla · volumen 1 ml | O58: 2 | P58: 40 | Q58: =IF(C58="Inventario físico",O58,P58) | R58: 1 | S58: 1000063 | T58: 1000063 | U58: No | V58: DIGOXINA 0,25 MG/ML AMPOLLA DE 1ML | W58: forma farmacéutica, volumen / presentación | X58: Alta | Y58: Candidato 1000063 «DIGOXINA 0,25 MG/ML AMPOLLA DE 1ML». Denominación: 100% del nombre del inventario explicado por el texto de SAP y 100% a la inversa. Atributos verificados: forma farmacéutica, volumen / presentación. Sin contradicción en ningún atributo. | Z58: Pendiente de valorización | AC58: No disponible en los archivos recibidos | AD58: =IF(AA58="","Pendiente",AA58*Q58) | AE58: 162 | AF58: =IF(AE58="","",AE58*Q58) | AG58: Pendiente | AH58: Sin decidir
A59: 55 | B59: 1120-MED69 | C59: Inventario físico | D59: A · Identificado en SAP | E59: Mantener identificación | G59: San Juan | H59: 1120 | I59: AVAIN | J59: Stock en Almacén · BASE SAN JUAN | K59: Medicamento | L59: MED69 | M59: Dipirona 1gr Amp x 2 ml | N59: concentración 1 g · forma ampolla · volumen 2 ml | O59: 93 | P59: 670 | Q59: =IF(C59="Inventario físico",O59,P59) | R59: 2 | S59: 1000022 | T59: 1000022 | U59: No | V59: DIPIRONA 1G AMPOLLA DE 2ML INYECTABLE | W59: concentración, forma farmacéutica, volumen / presentación | X59: Alta | Y59: Candidato 1000022 «DIPIRONA 1G AMPOLLA DE 2ML INYECTABLE». Denominación: 100% del nombre del inventario explicado por el texto de SAP y 100% a la inversa. Atributos verificados: concentración, forma farmacéutica, volumen / presentación. Sin contradicción en ningún atributo. | Z59: Pendiente de valorización | AC59: No disponible en los archivos recibidos | AD59: =IF(AA59="","Pendiente",AA59*Q59) | AE59: 590.29619 | AF59: =IF(AE59="","",AE59*Q59) | AG59: Pendiente | AH59: Sin decidir
A60: 56 | B60: 1120-DESC55 | C60: Inventario físico | D60: D · Requiere revisión | E60: Revisar y decidir | F60: Falta un atributo para confirmar la presentación | G60: San Juan | H60: 1120 | I60: AVAIN | J60: Stock en Almacén · BASE SAN JUAN | K60: Descartable | L60: DESC55 | M60: Electrodos | O60: 50 | P60: 0 | Q60: =IF(C60="Inventario físico",O60,P60) | R60: 2 | U60: No | V60: ELECTRODOS ADULTO | Y60: Candidato CR-13A «ELECTRODOS ADULTO». Denominación: 100% del nombre del inventario explicado por el texto de SAP y 56% a la inversa. Sap declara la presentación y el inventario físico no, así que la equivalencia no puede confirmarse con la información disponible. | Z60: Pendiente de valorización | AC60: No disponible en los archivos recibidos | AD60: =IF(AA60="","Pendiente",AA60*Q60) | AF60: =IF(AE60="","",AE60*Q60) | AG60: Pendiente | AH60: Sin decidir
A61: 57 | B61: 1120-MED72 | C61: Inventario físico | D61: D · Requiere revisión | E61: Revisar y decidir | F61: Varios códigos SAP posibles | G61: San Juan | H61: 1120 | I61: AVAIN | J61: Stock en Almacén · BASE SAN JUAN | K61: Medicamento | L61: MED72 | M61: Enalapril Comp x 10 mg | N61: concentración 10 mg · forma comprimido | O61: 86 | P61: 0 | Q61: =IF(C61="Inventario físico",O61,P61) | R61: 2 | U61: No | W61: concentración, forma farmacéutica | Y61: Candidato 1005140 «ENALAPRIL 10MG X 10COMP». Denominación: 100% del nombre del inventario explicado por el texto de SAP y 49% a la inversa. Atributos verificados: concentración, forma farmacéutica. Pero 1000066 «ENALAPRIL MALEATO 10MG COMPRIMIDO» es igual de plausible. Hay que elegir cuál corresponde. | Z61: Pendiente de valorización | AC61: No disponible en los archivos recibidos | AD61: =IF(AA61="","Pendiente",AA61*Q61) | AF61: =IF(AE61="","",AE61*Q61) | AG61: Pendiente | AH61: Sin decidir
A62: 58 | B62: 1120-DESC175 | C62: Inventario físico | D62: D · Requiere revisión | E62: Revisar y decidir | F62: Falta un atributo para confirmar la presentación | G62: San Juan | H62: 1120 | I62: AVAIN | J62: Stock en Almacén · BASE SAN JUAN | K62: Descartable | L62: DESC175 | M62: Estetoscopio | O62: 2 | P62: 0 | Q62: =IF(C62="Inventario físico",O62,P62) | R62: 1 | U62: No | V62: ESTETOSCOPIO ADULTO | Y62: Candidato 2000016 «ESTETOSCOPIO ADULTO». Denominación: 100% del nombre del inventario explicado por el texto de SAP y 55% a la inversa. Sap declara la presentación y el inventario físico no, así que la equivalencia no puede confirmarse con la información disponible. | Z62: Pendiente de valorización | AC62: No disponible en los archivos recibidos | AD62: =IF(AA62="","Pendiente",AA62*Q62) | AF62: =IF(AE62="","",AE62*Q62) | AG62: Pendiente | AH62: Sin decidir
A63: 59 | B63: 1120-DESC286 | C63: Inventario físico | D63: D · Requiere revisión | E63: Revisar y decidir | F63: Falta un atributo para confirmar la presentación | G63: San Juan | H63: 1120 | I63: AVAIN | J63: Stock en Almacén · BASE SAN JUAN | K63: Descartable | L63: DESC286 | M63: Estetoscopio LITTMANN | O63: 1 | P63: 0 | Q63: =IF(C63="Inventario físico",O63,P63) | R63: 1 | U63: No | V63: ESTETOSCOPIO ADULTO | Y63: Candidato 2000016 «ESTETOSCOPIO ADULTO». Denominación: 45% del nombre del inventario explicado por el texto de SAP y 55% a la inversa. Sap declara la presentación y el inventario físico no, así que la equivalencia no puede confirmarse con la información disponible. | Z63: Pendiente de valorización | AC63: No disponible en los archivos recibidos | AD63: =IF(AA63="","Pendiente",AA63*Q63) | AF63: =IF(AE63="","",AE63*Q63) | AG63: Pendiente | AH63: Sin decidir
A64: 60 | B64: 1120-MED78 | C64: Inventario físico | D64: B · Candidato a alta | E64: Proponer alta de material nuevo | G64: San Juan | H64: 1120 | I64: AVAIN | J64: Stock en Almacén · BASE SAN JUAN | K64: Medicamento | L64: MED78 | M64: Famotidina Comp x 20 mg | N64: concentración 20 mg · forma comprimido | O64: 70 | P64: 0 | Q64: =IF(C64="Inventario físico",O64,P64) | R64: 2 | U64: No | Y64: No se encontró en SAP ningún material cuya denominación y presentación se correspondan con este ítem. | Z64: Pendiente de valorización | AC64: No disponible en los archivos recibidos | AD64: =IF(AA64="","Pendiente",AA64*Q64) | AF64: =IF(AE64="","",AE64*Q64) | AG64: Pendiente | AH64: Sin decidir
A65: 61 | B65: 1120-DESC58 | C65: Inventario físico | D65: D · Requiere revisión | E65: Revisar y decidir | F65: Coincidencia parcial de denominación | G65: San Juan | H65: 1120 | I65: AVAIN | J65: Stock en Almacén · BASE SAN JUAN | K65: Descartable | L65: DESC58 | M65: Ferula soft Chica | O65: 1 | P65: 0 | Q65: =IF(C65="Inventario físico",O65,P65) | R65: 1 | U65: No | V65: CAJA CURACIONES CHICA | Y65: Candidato 2000485 «CAJA CURACIONES CHICA». Denominación: 35% del nombre del inventario explicado por el texto de SAP y 49% a la inversa. La coincidencia de denominación no alcanza para dar la identificación por confirmada. | Z65: Pendiente de valorización | AC65: No disponible en los archivos recibidos | AD65: =IF(AA65="","Pendiente",AA65*Q65) | AF65: =IF(AE65="","",AE65*Q65) | AG65: Pendiente | AH65: Sin decidir
A66: 62 | B66: 1120-DESC59 | C66: Inventario físico | D66: D · Requiere revisión | E66: Revisar y decidir | F66: Coincidencia parcial de denominación | G66: San Juan | H66: 1120 | I66: AVAIN | J66: Stock en Almacén · BASE SAN JUAN | K66: Descartable | L66: DESC59 | M66: Ferula soft Grande | O66: 1 | P66: 0 | Q66: =IF(C66="Inventario físico",O66,P66) | R66: 1 | U66: No | V66: PILA GRANDE | Y66: Candidato 2000474 «PILA GRANDE». Denominación: 31% del nombre del inventario explicado por el texto de SAP y 47% a la inversa. La coincidencia de denominación no alcanza para dar la identificación por confirmada. | Z66: Pendiente de valorización | AC66: No disponible en los archivos recibidos | AD66: =IF(AA66="","Pendiente",AA66*Q66) | AF66: =IF(AE66="","",AE66*Q66) | AG66: Pendiente | AH66: Sin decidir
A67: 63 | B67: 1120-DESC61 | C67: Inventario físico | D67: B · Candidato a alta | E67: Proponer alta de material nuevo | G67: San Juan | H67: 1120 | I67: AVAIN | J67: Stock en Almacén · BASE SAN JUAN | K67: Descartable | L67: DESC61 | M67: Filtro para ventilación artificial | O67: 2 | P67: 0 | Q67: =IF(C67="Inventario físico",O67,P67) | R67: 1 | U67: No | Y67: No se encontró en SAP ningún material cuya denominación y presentación se correspondan con este ítem. | Z67: Pendiente de valorización | AC67: No disponible en los archivos recibidos | AD67: =IF(AA67="","Pendiente",AA67*Q67) | AF67: =IF(AE67="","",AE67*Q67) | AG67: Pendiente | AH67: Sin decidir
A68: 64 | B68: 1120-MED81 | C68: Inventario físico | D68: A · Identificado en SAP | E68: Mantener identificación | G68: San Juan | H68: 1120 | I68: AVAIN | J68: Stock en Almacén · BASE SAN JUAN | K68: Medicamento | L68: MED81 | M68: Fluconazol 150 mg(FM) comp | N68: concentración 150 mg · forma comprimido | O68: 18 | P68: 80 | Q68: =IF(C68="Inventario físico",O68,P68) | R68: 1 | S68: 1001270 | T68: 1001270 | U68: No | V68: FLUCONAZOL 150MG COMP | W68: concentración, forma farmacéutica | X68: Alta | Y68: Candidato 1001270 «FLUCONAZOL 150MG COMP». Denominación: 100% del nombre del inventario explicado por el texto de SAP y 100% a la inversa. Atributos verificados: concentración, forma farmacéutica. Sin contradicción en ningún atributo. | Z68: Pendiente de valorización | AC68: No disponible en los archivos recibidos | AD68: =IF(AA68="","Pendiente",AA68*Q68) | AE68: 188.532 | AF68: =IF(AE68="","",AE68*Q68) | AG68: Pendiente | AH68: Sin decidir
A69: 65 | B69: 1120-MED85 | C69: Inventario físico | D69: B · Candidato a alta | E69: Proponer alta de material nuevo | G69: San Juan | H69: 1120 | I69: AVAIN | J69: Stock en Almacén · BASE SAN JUAN | K69: Medicamento | L69: MED85 | M69: Fluticasona 250 mcg/dosis Aerosol | N69: concentración 0,25 mg/1 dosis · forma aerosol | O69: 1 | P69: 0 | Q69: =IF(C69="Inventario físico",O69,P69) | R69: 1 | U69: No | Y69: No se encontró en SAP ningún material cuya denominación y presentación se correspondan con este ítem. | Z69: Pendiente de valorización | AC69: No disponible en los archivos recibidos | AD69: =IF(AA69="","Pendiente",AA69*Q69) | AF69: =IF(AE69="","",AE69*Q69) | AG69: Pendiente | AH69: Sin decidir
A70: 66 | B70: 1120-MED84 | C70: Inventario físico | D70: B · Candidato a alta | E70: Proponer alta de material nuevo | G70: San Juan | H70: 1120 | I70: AVAIN | J70: Stock en Almacén · BASE SAN JUAN | K70: Medicamento | L70: MED84 | M70: Fluticasona Spray | N70: forma aerosol | O70: 31 | P70: 0 | Q70: =IF(C70="Inventario físico",O70,P70) | R70: 1 | U70: No | Y70: No se encontró en SAP ningún material cuya denominación y presentación se correspondan con este ítem. | Z70: Pendiente de valorización | AC70: No disponible en los archivos recibidos | AD70: =IF(AA70="","Pendiente",AA70*Q70) | AF70: =IF(AE70="","",AE70*Q70) | AG70: Pendiente | AH70: Sin decidir
A71: 67 | B71: 1120-DESC283 | C71: Inventario físico | D71: B · Candidato a alta | E71: Proponer alta de material nuevo | G71: San Juan | H71: 1120 | I71: AVAIN | J71: Stock en Almacén · BASE SAN JUAN | K71: Descartable | L71: DESC283 | M71: Frasco de Drenaje Pleural | N71: forma frasco | O71: 5 | P71: 0 | Q71: =IF(C71="Inventario físico",O71,P71) | R71: 1 | U71: No | Y71: No se encontró en SAP ningún material cuya denominación y presentación se correspondan con este ítem. | Z71: Pendiente de valorización | AC71: No disponible en los archivos recibidos | AD71: =IF(AA71="","Pendiente",AA71*Q71) | AF71: =IF(AE71="","",AE71*Q71) | AG71: Pendiente | AH71: Sin decidir
A72: 68 | B72: 1120-MED89 | C72: Inventario físico | D72: D · Requiere revisión | E72: Revisar y decidir | F72: Falta un atributo para confirmar la presentación | G72: San Juan | H72: 1120 | I72: AVAIN | J72: Stock en Almacén · BASE SAN JUAN | K72: Medicamento | L72: MED89 | M72: Fusimed B 2% x 50gr Emulsion | N72: concentración 2%, 50 g | O72: 2 | P72: 0 | Q72: =IF(C72="Inventario físico",O72,P72) | R72: 2 | U72: No | V72: FUSIMED B EMULSION | Y72: Candidato 1000731 «FUSIMED B EMULSION». Denominación: 100% del nombre del inventario explicado por el texto de SAP y 100% a la inversa. El inventario físico declara la presentación y SAP no, así que la equivalencia no puede confirmarse con la información disponible. | Z72: Pendiente de valorización | AC72: No disponible en los archivos recibidos | AD72: =IF(AA72="","Pendiente",AA72*Q72) | AF72: =IF(AE72="","",AE72*Q72) | AG72: Pendiente | AH72: Sin decidir
A73: 69 | B73: 1120-MED90 | C73: Inventario físico | D73: D · Requiere revisión | E73: Revisar y decidir | F73: Falta un atributo para confirmar la presentación | G73: San Juan | H73: 1120 | I73: AVAIN | J73: Stock en Almacén · BASE SAN JUAN | K73: Medicamento | L73: MED90 | M73: Fusimed B Otonasal x 15 gr | N73: concentración 15 g | O73: 2 | P73: 0 | Q73: =IF(C73="Inventario físico",O73,P73) | R73: 1 | U73: No | V73: FUSIMED B OTONASAL 15grs | Y73: Candidato 1001001 «FUSIMED B OTONASAL 15grs». Denominación: 100% del nombre del inventario explicado por el texto de SAP y 66% a la inversa. El inventario físico declara la presentación y SAP no, así que la equivalencia no puede confirmarse con la información disponible. | Z73: Pendiente de valorización | AC73: No disponible en los archivos recibidos | AD73: =IF(AA73="","Pendiente",AA73*Q73) | AF73: =IF(AE73="","",AE73*Q73) | AG73: Pendiente | AH73: Sin decidir
A74: 70 | B74: 1120-DESC64 | C74: Inventario físico | D74: B · Candidato a alta | E74: Proponer alta de material nuevo | G74: San Juan | H74: 1120 | I74: AVAIN | J74: Stock en Almacén · BASE SAN JUAN | K74: Descartable | L74: DESC64 | M74: Gasas 10 x 10 cm | N74: medidas 10 × 10 | O74: 281 | P74: 0 | Q74: =IF(C74="Inventario físico",O74,P74) | R74: 2 | U74: No | Y74: No se encontró en SAP ningún material cuya denominación y presentación se correspondan con este ítem. | Z74: Pendiente de valorización | AC74: No disponible en los archivos recibidos | AD74: =IF(AA74="","Pendiente",AA74*Q74) | AF74: =IF(AE74="","",AE74*Q74) | AG74: Pendiente | AH74: Sin decidir
A75: 71 | B75: 1120-DESC66 | C75: Inventario físico | D75: D · Requiere revisión | E75: Revisar y decidir | F75: Varios códigos SAP posibles | G75: San Juan | H75: 1120 | I75: AVAIN | J75: Stock en Almacén · BASE SAN JUAN | K75: Descartable | L75: DESC66 | M75: Guantes de examinacion Ch c/u | O75: 1000 | P75: 0 | Q75: =IF(C75="Inventario físico",O75,P75) | R75: 1 | U75: No | Y75: Candidato 2000270 «GUANTES DE EXAMINACION TALLE S». Denominación: 100% del nombre del inventario explicado por el texto de SAP y 71% a la inversa. Pero 2000158 «GUANTES DE EXAMINACIÓN TALLE M» es igual de plausible. Hay que elegir cuál corresponde. | Z75: Pendiente de valorización | AC75: No disponible en los archivos recibidos | AD75: =IF(AA75="","Pendiente",AA75*Q75) | AF75: =IF(AE75="","",AE75*Q75) | AG75: Pendiente | AH75: Sin decidir
A76: 72 | B76: 1120-DESC67 | C76: Inventario físico | D76: D · Requiere revisión | E76: Revisar y decidir | F76: Varios códigos SAP posibles | G76: San Juan | H76: 1120 | I76: AVAIN | J76: Stock en Almacén · BASE SAN JUAN | K76: Descartable | L76: DESC67 | M76: Guantes de examinacion G c/u | O76: 1800 | P76: 0 | Q76: =IF(C76="Inventario físico",O76,P76) | R76: 1 | U76: No | Y76: Candidato 2000270 «GUANTES DE EXAMINACION TALLE S». Denominación: 100% del nombre del inventario explicado por el texto de SAP y 71% a la inversa. Pero 2000158 «GUANTES DE EXAMINACIÓN TALLE M» es igual de plausible. Hay que elegir cuál corresponde. | Z76: Pendiente de valorización | AC76: No disponible en los archivos recibidos | AD76: =IF(AA76="","Pendiente",AA76*Q76) | AF76: =IF(AE76="","",AE76*Q76) | AG76: Pendiente | AH76: Sin decidir
A77: 73 | B77: 1120-DESC68 | C77: Inventario físico | D77: D · Requiere revisión | E77: Revisar y decidir | F77: Varios códigos SAP posibles | G77: San Juan | H77: 1120 | I77: AVAIN | J77: Stock en Almacén · BASE SAN JUAN | K77: Descartable | L77: DESC68 | M77: Guantes de examinacion M c/u | O77: 2000 | P77: 0 | Q77: =IF(C77="Inventario físico",O77,P77) | R77: 1 | U77: No | Y77: Candidato 2000270 «GUANTES DE EXAMINACION TALLE S». Denominación: 100% del nombre del inventario explicado por el texto de SAP y 71% a la inversa. Pero 2000158 «GUANTES DE EXAMINACIÓN TALLE M» es igual de plausible. Hay que elegir cuál corresponde. | Z77: Pendiente de valorización | AC77: No disponible en los archivos recibidos | AD77: =IF(AA77="","Pendiente",AA77*Q77) | AF77: =IF(AE77="","",AE77*Q77) | AG77: Pendiente | AH77: Sin decidir
A78: 74 | B78: 1120-32 | C78: Inventario físico | D78: A · Identificado en SAP | E78: Mantener identificación | G78: San Juan | H78: 1120 | I78: AVAIN | J78: Stock en Almacén · BASE SAN JUAN | K78: Descartable | L78: 32 | M78: GUANTES DE EXAMINACIÓN TALLE S | N78: talle S | O78: 10 | P78: 2547 | Q78: =IF(C78="Inventario físico",O78,P78) | R78: 1 | S78: 2000270 | T78: 2000270 | U78: No | V78: GUANTES DE EXAMINACION TALLE S | W78: talle | X78: Alta | Y78: Candidato 2000270 «GUANTES DE EXAMINACION TALLE S». Denominación: 100% del nombre del inventario explicado por el texto de SAP y 100% a la inversa. Atributos verificados: talle. Sin contradicción en ningún atributo. | Z78: Pendiente de valorización | AC78: No disponible en los archivos recibidos | AD78: =IF(AA78="","Pendiente",AA78*Q78) | AE78: 108.66174 | AF78: =IF(AE78="","",AE78*Q78) | AG78: Pendiente | AH78: Sin decidir
A79: 75 | B79: 1120-DESC69 | C79: Inventario físico | D79: D · Requiere revisión | E79: Revisar y decidir | F79: Falta un atributo para confirmar la presentación | G79: San Juan | H79: 1120 | I79: AVAIN | J79: Stock en Almacén · BASE SAN JUAN | K79: Descartable | L79: DESC69 | M79: Guantes esteriles 6.5 | O79: 40 | P79: 0 | Q79: =IF(C79="Inventario físico",O79,P79) | R79: 1 | U79: No | V79: GUANTES ESTERILES Nº 7 POR PAR | Y79: Candidato 2000156 «GUANTES ESTERILES Nº 7 POR PAR». Denominación: 100% del nombre del inventario explicado por el texto de SAP y 62% a la inversa. Sap declara la presentación y el inventario físico no, así que la equivalencia no puede confirmarse con la información disponible. | Z79: Pendiente de valorización | AC79: No disponible en los archivos recibidos | AD79: =IF(AA79="","Pendiente",AA79*Q79) | AF79: =IF(AE79="","",AE79*Q79) | AG79: Pendiente | AH79: Sin decidir
A80: 76 | B80: 1120-DESC71 | C80: Inventario físico | D80: D · Requiere revisión | E80: Revisar y decidir | F80: Falta un atributo para confirmar la presentación | G80: San Juan | H80: 1120 | I80: AVAIN | J80: Stock en Almacén · BASE SAN JUAN | K80: Descartable | L80: DESC71 | M80: Guantes Estériles 7.5 | O80: 38 | P80: 0 | Q80: =IF(C80="Inventario físico",O80,P80) | R80: 1 | U80: No | V80: GUANTES ESTERILES Nº 7 POR PAR | Y80: Candidato 2000156 «GUANTES ESTERILES Nº 7 POR PAR». Denominación: 100% del nombre del inventario explicado por el texto de SAP y 62% a la inversa. Sap declara la presentación y el inventario físico no, así que la equivalencia no puede confirmarse con la información disponible. | Z80: Pendiente de valorización | AC80: No disponible en los archivos recibidos | AD80: =IF(AA80="","Pendiente",AA80*Q80) | AF80: =IF(AE80="","",AE80*Q80) | AG80: Pendiente | AH80: Sin decidir
A81: 77 | B81: 1120-DESC72 | C81: Inventario físico | D81: D · Requiere revisión | E81: Revisar y decidir | F81: Falta un atributo para confirmar la presentación | G81: San Juan | H81: 1120 | I81: AVAIN | J81: Stock en Almacén · BASE SAN JUAN | K81: Descartable | L81: DESC72 | M81: Guantes Estériles 8 | N81: cantidad sin unidad 8 | O81: 38 | P81: 0 | Q81: =IF(C81="Inventario físico",O81,P81) | R81: 1 | U81: No | V81: GUANTES ESTERILES Nº 7 POR PAR | Y81: Candidato 2000156 «GUANTES ESTERILES Nº 7 POR PAR». Denominación: 100% del nombre del inventario explicado por el texto de SAP y 62% a la inversa. El inventario físico declara la presentación y SAP no, así que la equivalencia no puede confirmarse con la información disponible. | Z81: Pendiente de valorización | AC81: No disponible en los archivos recibidos | AD81: =IF(AA81="","Pendiente",AA81*Q81) | AF81: =IF(AE81="","",AE81*Q81) | AG81: Pendiente | AH81: Sin decidir
A82: 78 | B82: 1120-DESC73 | C82: Inventario físico | D82: D · Requiere revisión | E82: Revisar y decidir | F82: Falta un atributo para confirmar la presentación | G82: San Juan | H82: 1120 | I82: AVAIN | J82: Stock en Almacén · BASE SAN JUAN | K82: Descartable | L82: DESC73 | M82: Guia Macrogotero | O82: 1090 | P82: 0 | Q82: =IF(C82="Inventario físico",O82,P82) | R82: 2 | U82: No | V82: GUIA MACROGOTERO Nª14 | Y82: Candidato 2000023 «GUIA MACROGOTERO Nª14». Denominación: 100% del nombre del inventario explicado por el texto de SAP y 100% a la inversa. Sap declara la presentación y el inventario físico no, así que la equivalencia no puede confirmarse con la información disponible. | Z82: Pendiente de valorización | AC82: No disponible en los archivos recibidos | AD82: =IF(AA82="","Pendiente",AA82*Q82) | AF82: =IF(AE82="","",AE82*Q82) | AG82: Pendiente | AH82: Sin decidir
A83: 79 | B83: 1120-MED95 | C83: Inventario físico | D83: A · Identificado en SAP | E83: Registrar existencia en SAP en esta base | G83: San Juan | H83: 1120 | I83: AVAIN | J83: Stock en Almacén · BASE SAN JUAN | K83: Medicamento | L83: MED95 | M83: Hidroclorotiazida Comp x 50 mg | N83: concentración 50 mg · forma comprimido | O83: 10 | P83: 0 | Q83: =IF(C83="Inventario físico",O83,P83) | R83: 1 | S83: 1000651 | T83: 1000651 | U83: No | V83: HIDROCLOROTIAZIDA COMP | W83: forma farmacéutica | X83: Alta | Y83: Candidato 1000651 «HIDROCLOROTIAZIDA COMP». Denominación: 100% del nombre del inventario explicado por el texto de SAP y 100% a la inversa. Atributos verificados: forma farmacéutica. Sin contradicción en ningún atributo. | Z83: Pendiente de valorización | AC83: No disponible en los archivos recibidos | AD83: =IF(AA83="","Pendiente",AA83*Q83) | AE83: 34.53 | AF83: =IF(AE83="","",AE83*Q83) | AG83: Pendiente | AH83: Sin decidir
A84: 80 | B84: 1120-MED96 | C84: Inventario físico | D84: D · Requiere revisión | E84: Revisar y decidir | F84: Coincidencia parcial de denominación | G84: San Juan | H84: 1120 | I84: AVAIN | J84: Stock en Almacén · BASE SAN JUAN | K84: Medicamento | L84: MED96 | M84: Hidrocortisona Fco amp polvo p/rest 500 mg | N84: concentración 500 mg · forma ampolla, frasco, sobre | O84: 4 | P84: 0 | Q84: =IF(C84="Inventario físico",O84,P84) | R84: 2 | U84: No | V84: HIDROCORTISONA 500MG AMPOLLA | W84: concentración, forma farmacéutica | Y84: Candidato 1000010 «HIDROCORTISONA 500MG AMPOLLA». Denominación: 47% del nombre del inventario explicado por el texto de SAP y 100% a la inversa. Atributos verificados: concentración, forma farmacéutica. La coincidencia de denominación no alcanza para dar la identificación por confirmada. | Z84: Pendiente de valorización | AC84: No disponible en los archivos recibidos | AD84: =IF(AA84="","Pendiente",AA84*Q84) | AF84: =IF(AE84="","",AE84*Q84) | AG84: Pendiente | AH84: Sin decidir
A85: 81 | B85: 1120-MED100 | C85: Inventario físico | D85: D · Requiere revisión | E85: Revisar y decidir | F85: Varios códigos SAP posibles | G85: San Juan | H85: 1120 | I85: AVAIN | J85: Stock en Almacén · BASE SAN JUAN | K85: Medicamento | L85: MED100 | M85: Hioscina x 20 mg Amp x 1 ml | N85: concentración 20 mg · forma ampolla · volumen 1 ml | O85: 117 | P85: 0 | Q85: =IF(C85="Inventario físico",O85,P85) | R85: 2 | U85: No | W85: concentración, forma farmacéutica | Y85: Candidato 1001231 «HIOSCINA 20 MG AMP cjax100». Denominación: 100% del nombre del inventario explicado por el texto de SAP y 43% a la inversa. Atributos verificados: concentración, forma farmacéutica. Pero 1000059 «BUTIL BROMURO DE HIOSCINA 20MG AMPOLLA» es igual de plausible. Hay que elegir cuál corresponde. | Z85: Pendiente de valorización | AC85: No disponible en los archivos recibidos | AD85: =IF(AA85="","Pendiente",AA85*Q85) | AF85: =IF(AE85="","",AE85*Q85) | AG85: Pendiente | AH85: Sin decidir
A86: 82 | B86: 1120-MED102 | C86: Inventario físico | D86: A · Identificado en SAP | E86: Mantener identificación | G86: San Juan | H86: 1120 | I86: AVAIN | J86: Stock en Almacén · BASE SAN JUAN | K86: Medicamento | L86: MED102 | M86: Ibuprofeno Comp x 600 mg | N86: concentración 600 mg · forma comprimido | O86: 222 | P86: 5940 | Q86: =IF(C86="Inventario físico",O86,P86) | R86: 1 | S86: 1000124 | T86: 1000124 | U86: No | V86: IBUPROFENO COMP 600MG | W86: concentración, forma farmacéutica | X86: Alta | Y86: Candidato 1000124 «IBUPROFENO COMP 600MG». Denominación: 100% del nombre del inventario explicado por el texto de SAP y 100% a la inversa. Atributos verificados: concentración, forma farmacéutica. Sin contradicción en ningún atributo. | Z86: Pendiente de valorización | AC86: No disponible en los archivos recibidos | AD86: =IF(AA86="","Pendiente",AA86*Q86) | AE86: 62.891318 | AF86: =IF(AE86="","",AE86*Q86) | AG86: Pendiente | AH86: Sin decidir
A87: 83 | B87: 1120-MED200 | C87: Inventario físico | D87: D · Requiere revisión | E87: Revisar y decidir | F87: Coincidencia parcial de denominación | G87: San Juan | H87: 1120 | I87: AVAIN | J87: Stock en Almacén · BASE SAN JUAN | K87: Medicamento | L87: MED200 | M87: iodopovidona 100 ml sol/topica | N87: volumen 100 ml | O87: 6 | P87: 0 | Q87: =IF(C87="Inventario físico",O87,P87) | R87: 1 | U87: No | V87: IODOPOVIDONA SOLUCION 10% X 100ML | W87: volumen / presentación | Y87: Candidato 1000590 «IODOPOVIDONA SOLUCION 10% X 100ML». Denominación: 31% del nombre del inventario explicado por el texto de SAP y 100% a la inversa. Atributos verificados: volumen / presentación. La coincidencia de denominación no alcanza para dar la identificación por confirmada. | Z87: Pendiente de valorización | AC87: No disponible en los archivos recibidos | AD87: =IF(AA87="","Pendiente",AA87*Q87) | AF87: =IF(AE87="","",AE87*Q87) | AG87: Pendiente | AH87: Sin decidir
A88: 84 | B88: 1120-MED108 | C88: Inventario físico | D88: B · Candidato a alta | E88: Proponer alta de material nuevo | G88: San Juan | H88: 1120 | I88: AVAIN | J88: Stock en Almacén · BASE SAN JUAN | K88: Medicamento | L88: MED108 | M88: Jarabe (Ambroxol - Clorhidrato) 120 ml | N88: forma jarabe · volumen 120 ml | O88: 34 | P88: 0 | Q88: =IF(C88="Inventario físico",O88,P88) | R88: 1 | U88: No | Y88: No se encontró en SAP ningún material cuya denominación y presentación se correspondan con este ítem. | Z88: Pendiente de valorización | AC88: No disponible en los archivos recibidos | AD88: =IF(AA88="","Pendiente",AA88*Q88) | AF88: =IF(AE88="","",AE88*Q88) | AG88: Pendiente | AH88: Sin decidir
A89: 85 | B89: 1120-DESC77 | C89: Inventario físico | D89: D · Requiere revisión | E89: Revisar y decidir | F89: Varios códigos SAP posibles | G89: San Juan | H89: 1120 | I89: AVAIN | J89: Stock en Almacén · BASE SAN JUAN | K89: Descartable | L89: DESC77 | M89: Jeringas 1 cc | N89: volumen 1 ml | O89: 22 | P89: 0 | Q89: =IF(C89="Inventario físico",O89,P89) | R89: 1 | U89: No | W89: volumen / presentación | Y89: Candidato 2000451 «JERINGA DE 1ML C AGUJA 25G». Denominación: 90% del nombre del inventario explicado por el texto de SAP y 47% a la inversa. Atributos verificados: volumen / presentación. Pero 2000412 «JERINGA INSULINA x 1cc» es igual de plausible. Hay que elegir cuál corresponde. | Z89: Pendiente de valorización | AC89: No disponible en los archivos recibidos | AD89: =IF(AA89="","Pendiente",AA89*Q89) | AF89: =IF(AE89="","",AE89*Q89) | AG89: Pendiente | AH89: Sin decidir
A90: 86 | B90: 1120-DESC78 | C90: Inventario físico | D90: A · Identificado en SAP | E90: Mantener identificación | G90: San Juan | H90: 1120 | I90: AVAIN | J90: Stock en Almacén · BASE SAN JUAN | K90: Descartable | L90: DESC78 | M90: Jeringas 10 cc | N90: volumen 10 ml | O90: 918 | P90: 2367 | Q90: =IF(C90="Inventario físico",O90,P90) | R90: 3 | S90: 2000028 | T90: 2000028 | U90: No | V90: JERINGA 10 ML | W90: volumen / presentación | X90: Alta | Y90: Candidato 2000028 «JERINGA 10 ML». Denominación: 90% del nombre del inventario explicado por el texto de SAP y 90% a la inversa. Atributos verificados: volumen / presentación. Sin contradicción en ningún atributo. | Z90: Pendiente de valorización | AC90: No disponible en los archivos recibidos | AD90: =IF(AA90="","Pendiente",AA90*Q90) | AE90: 94.901888 | AF90: =IF(AE90="","",AE90*Q90) | AG90: Pendiente | AH90: Sin decidir
A91: 87 | B91: 1120-DESC79 | C91: Inventario físico | D91: A · Identificado en SAP | E91: Mantener identificación | G91: San Juan | H91: 1120 | I91: AVAIN | J91: Stock en Almacén · BASE SAN JUAN | K91: Descartable | L91: DESC79 | M91: Jeringas 20 cc | N91: volumen 20 ml | O91: 26 | P91: 4 | Q91: =IF(C91="Inventario físico",O91,P91) | R91: 1 | S91: 2000029 | T91: 2000029 | U91: No | V91: JERINGA 20 ML | W91: volumen / presentación | X91: Alta | Y91: Candidato 2000029 «JERINGA 20 ML». Denominación: 90% del nombre del inventario explicado por el texto de SAP y 90% a la inversa. Atributos verificados: volumen / presentación. Sin contradicción en ningún atributo. | Z91: Pendiente de valorización | AC91: No disponible en los archivos recibidos | AD91: =IF(AA91="","Pendiente",AA91*Q91) | AE91: 6134.2475 | AF91: =IF(AE91="","",AE91*Q91) | AG91: Pendiente | AH91: Sin decidir
A92: 88 | B92: 1120-DESC80 | C92: Inventario físico | D92: A · Identificado en SAP | E92: Mantener identificación | G92: San Juan | H92: 1120 | I92: AVAIN | J92: Stock en Almacén · BASE SAN JUAN | K92: Descartable | L92: DESC80 | M92: Jeringas 5 cc | N92: volumen 5 ml | O92: 105 | P92: 758 | Q92: =IF(C92="Inventario físico",O92,P92) | R92: 1 | S92: 2000027 | T92: 2000027 | U92: No | V92: JERINGA DE 5 ML | W92: volumen / presentación | X92: Alta | Y92: Candidato 2000027 «JERINGA DE 5 ML». Denominación: 90% del nombre del inventario explicado por el texto de SAP y 90% a la inversa. Atributos verificados: volumen / presentación. Sin contradicción en ningún atributo. | Z92: Pendiente de valorización | AC92: No disponible en los archivos recibidos | AD92: =IF(AA92="","Pendiente",AA92*Q92) | AE92: 150.34199 | AF92: =IF(AE92="","",AE92*Q92) | AG92: Pendiente | AH92: Sin decidir
A93: 89 | B93: 1120-MED109 | C93: Inventario físico | D93: D · Requiere revisión | E93: Revisar y decidir | F93: Varios códigos SAP posibles | G93: San Juan | H93: 1120 | I93: AVAIN | J93: Stock en Almacén · BASE SAN JUAN | K93: Medicamento | L93: MED109 | M93: Ketorolac 30mg Amp x 1 ml | N93: concentración 30 mg · forma ampolla · volumen 1 ml | O93: 83 | P93: 0 | Q93: =IF(C93="Inventario físico",O93,P93) | R93: 1 | U93: No | W93: forma farmacéutica | Y93: Candidato 1001291 «KETOROLAC 30 MG/2ML AMP». Denominación: 100% del nombre del inventario explicado por el texto de SAP y 100% a la inversa. Atributos verificados: forma farmacéutica. Pero 1000196 «KETOROLAC 30 MG/1ML AMP» es igual de plausible. Hay que elegir cuál corresponde. | Z93: Pendiente de valorización | AC93: No disponible en los archivos recibidos | AD93: =IF(AA93="","Pendiente",AA93*Q93) | AF93: =IF(AE93="","",AE93*Q93) | AG93: Pendiente | AH93: Sin decidir
A94: 90 | B94: 1120-MED110 | C94: Inventario físico | D94: A · Identificado en SAP | E94: Mantener identificación | G94: San Juan | H94: 1120 | I94: AVAIN | J94: Stock en Almacén · BASE SAN JUAN | K94: Medicamento | L94: MED110 | M94: Ketorolac Comp SL X 10 mg | N94: concentración 10 mg · forma comprimido | O94: 920 | P94: 1693 | Q94: =IF(C94="Inventario físico",O94,P94) | R94: 1 | S94: 1000129 | T94: 1000129 | U94: No | V94: KETOROLAC 10MG SUBLINGUAL | W94: concentración | X94: Media | Y94: Candidato 1000129 «KETOROLAC 10MG SUBLINGUAL». Denominación: 100% del nombre del inventario explicado por el texto de SAP y 47% a la inversa. Atributos verificados: concentración. Sin contradicción en ningún atributo. | Z94: Pendiente de valorización | AC94: No disponible en los archivos recibidos | AD94: =IF(AA94="","Pendiente",AA94*Q94) | AE94: 63.42788 | AF94: =IF(AE94="","",AE94*Q94) | AG94: Pendiente | AH94: Sin decidir
A95: 91 | B95: 1120-MED111 | C95: Inventario físico | D95: A · Identificado en SAP | E95: Mantener identificación | G95: San Juan | H95: 1120 | I95: AVAIN | J95: Stock en Almacén · BASE SAN JUAN | K95: Medicamento | L95: MED111 | M95: Ketorolac Comp x 20 mg | N95: concentración 20 mg · forma comprimido | O95: 240 | P95: 441 | Q95: =IF(C95="Inventario físico",O95,P95) | R95: 1 | S95: 1000528 | T95: 1000528 | U95: No | V95: KETOROLAC 20 MG COMPRIMIDOS | W95: concentración, forma farmacéutica | X95: Alta | Y95: Candidato 1000528 «KETOROLAC 20 MG COMPRIMIDOS». Denominación: 100% del nombre del inventario explicado por el texto de SAP y 100% a la inversa. Atributos verificados: concentración, forma farmacéutica. Sin contradicción en ningún atributo. | Z95: Pendiente de valorización | AC95: No disponible en los archivos recibidos | AD95: =IF(AA95="","Pendiente",AA95*Q95) | AE95: 195.05331 | AF95: =IF(AE95="","",AE95*Q95) | AG95: Pendiente | AH95: Sin decidir
A96: 92 | B96: 1120-MED112 | C96: Inventario físico | D96: D · Requiere revisión | E96: Revisar y decidir | F96: Varios códigos SAP posibles | G96: San Juan | H96: 1120 | I96: AVAIN | J96: Stock en Almacén · BASE SAN JUAN | K96: Medicamento | L96: MED112 | M96: Labetalol 5mg/ml Amp x 4 ml | N96: concentración 5 mg/1 ml · forma ampolla · volumen 4 ml | O96: 2 | P96: 0 | Q96: =IF(C96="Inventario físico",O96,P96) | R96: 1 | U96: No | W96: forma farmacéutica | Y96: Candidato 1000634 «LABETALOL 20MG AMPOLLA». Denominación: 100% del nombre del inventario explicado por el texto de SAP y 100% a la inversa. Atributos verificados: forma farmacéutica. Pero 1005202 «LABETALOL 5MG AMP» es igual de plausible. Hay que elegir cuál corresponde. | Z96: Pendiente de valorización | AC96: No disponible en los archivos recibidos | AD96: =IF(AA96="","Pendiente",AA96*Q96) | AF96: =IF(AE96="","",AE96*Q96) | AG96: Pendiente | AH96: Sin decidir
A97: 93 | B97: 1120-MED114 | C97: Inventario físico | D97: D · Requiere revisión | E97: Revisar y decidir | F97: Coincidencia parcial de denominación | G97: San Juan | H97: 1120 | I97: AVAIN | J97: Stock en Almacén · BASE SAN JUAN | K97: Medicamento | L97: MED114 | M97: Lagrimas naturales Gotas oftalm 15ml | N97: forma gotas · volumen 15 ml | O97: 2 | P97: 0 | Q97: =IF(C97="Inventario físico",O97,P97) | R97: 1 | U97: No | V97: PH LAGRIMAS 15ML GOTAS | W97: forma farmacéutica, volumen / presentación | Y97: Candidato 1001112 «PH LAGRIMAS 15ML GOTAS». Denominación: 31% del nombre del inventario explicado por el texto de SAP y 100% a la inversa. Atributos verificados: forma farmacéutica, volumen / presentación. La coincidencia de denominación no alcanza para dar la identificación por confirmada. | Z97: Pendiente de valorización | AC97: No disponible en los archivos recibidos | AD97: =IF(AA97="","Pendiente",AA97*Q97) | AF97: =IF(AE97="","",AE97*Q97) | AG97: Pendiente | AH97: Sin decidir
A98: 94 | B98: 1120-MED115 | C98: Inventario físico | D98: A · Identificado en SAP | E98: Mantener identificación | G98: San Juan | H98: 1120 | I98: AVAIN | J98: Stock en Almacén · BASE SAN JUAN | K98: Medicamento | L98: MED115 | M98: Levofloxacina Comp x 500 mg | N98: concentración 500 mg · forma comprimido | O98: 14 | P98: 5 | Q98: =IF(C98="Inventario físico",O98,P98) | R98: 1 | S98: 1000565 | T98: 1000565 | U98: No | V98: LEVOFLOXACINA 500MG | W98: concentración | X98: Alta | Y98: Candidato 1000565 «LEVOFLOXACINA 500MG». Denominación: 100% del nombre del inventario explicado por el texto de SAP y 100% a la inversa. Atributos verificados: concentración. Sin contradicción en ningún atributo. | Z98: Pendiente de valorización | AC98: No disponible en los archivos recibidos | AD98: =IF(AA98="","Pendiente",AA98*Q98) | AE98: 10689.728 | AF98: =IF(AE98="","",AE98*Q98) | AG98: Pendiente | AH98: Sin decidir
A99: 95 | B99: 1120-DESC83 | C99: Inventario físico | D99: D · Requiere revisión | E99: Revisar y decidir | F99: Coincidencia parcial de denominación | G99: San Juan | H99: 1120 | I99: AVAIN | J99: Stock en Almacén · BASE SAN JUAN | K99: Descartable | L99: DESC83 | M99: Linterna Chica | O99: 2 | P99: 0 | Q99: =IF(C99="Inventario físico",O99,P99) | R99: 1 | U99: No | V99: LINTERNA LAPICERA | Y99: Candidato 2000483 «LINTERNA LAPICERA». Denominación: 51% del nombre del inventario explicado por el texto de SAP y 48% a la inversa. La coincidencia de denominación no alcanza para dar la identificación por confirmada. | Z99: Pendiente de valorización | AC99: No disponible en los archivos recibidos | AD99: =IF(AA99="","Pendiente",AA99*Q99) | AF99: =IF(AE99="","",AE99*Q99) | AG99: Pendiente | AH99: Sin decidir
A100: 96 | B100: 1120-DESC84 | C100: Inventario físico | D100: A · Identificado en SAP | E100: Mantener identificación | G100: San Juan | H100: 1120 | I100: AVAIN | J100: Stock en Almacén · BASE SAN JUAN | K100: Descartable | L100: DESC84 | M100: Llave de 3 vías | N100: cantidad sin unidad 3 | O100: 10 | P100: 100 | Q100: =IF(C100="Inventario físico",O100,P100) | R100: 1 | S100: 2000060 | T100: 2000060 | U100: No | V100: LLAVE DE 3 VIAS | W100: cantidad o dosis sin unidad | X100: Alta | Y100: Candidato 2000060 «LLAVE DE 3 VIAS». Denominación: 100% del nombre del inventario explicado por el texto de SAP y 100% a la inversa. Atributos verificados: cantidad o dosis sin unidad. Sin contradicción en ningún atributo. | Z100: Pendiente de valorización | AC100: No disponible en los archivos recibidos | AD100: =IF(AA100="","Pendiente",AA100*Q100) | AE100: 208.7056 | AF100: =IF(AE100="","",AE100*Q100) | AG100: Pendiente | AH100: Sin decidir
A101: 97 | B101: 1120-MED118 | C101: Inventario físico | D101: A · Identificado en SAP | E101: Mantener identificación | G101: San Juan | H101: 1120 | I101: AVAIN | J101: Stock en Almacén · BASE SAN JUAN | K101: Medicamento | L101: MED118 | M101: Loperamida Comp x 2 mg | N101: concentración 2 mg · forma comprimido | O101: 23 | P101: 1050 | Q101: =IF(C101="Inventario físico",O101,P101) | R101: 3 | S101: 1000597 | T101: 1000597 | U101: No | V101: LOPERAMIDA 2MG COMPRIMIDO | W101: concentración, forma farmacéutica | X101: Alta | Y101: Candidato 1000597 «LOPERAMIDA 2MG COMPRIMIDO». Denominación: 100% del nombre del inventario explicado por el texto de SAP y 100% a la inversa. Atributos verificados: concentración, forma farmacéutica. Sin contradicción en ningún atributo. | Z101: Pendiente de valorización | AC101: No disponible en los archivos recibidos | AD101: =IF(AA101="","Pendiente",AA101*Q101) | AE101: 37.520695 | AF101: =IF(AE101="","",AE101*Q101) | AG101: Pendiente | AH101: Sin decidir
A102: 98 | B102: 1120-MED120 | C102: Inventario físico | D102: D · Requiere revisión | E102: Revisar y decidir | F102: Coincidencia parcial de denominación | G102: San Juan | H102: 1120 | I102: AVAIN | J102: Stock en Almacén · BASE SAN JUAN | K102: Medicamento | L102: MED120 | M102: Loratadina/betametasona 10mg/0,6 mgcomp (FM) | N102: cantidad sin unidad 10 | O102: 20 | P102: 0 | Q102: =IF(C102="Inventario físico",O102,P102) | R102: 1 | U102: No | V102: BETAMETASONA+LORATADINA X 10 COMP | W102: cantidad o dosis sin unidad | Y102: Candidato 1005261 «BETAMETASONA+LORATADINA X 10 COMP». Denominación: 61% del nombre del inventario explicado por el texto de SAP y 100% a la inversa. Atributos verificados: cantidad o dosis sin unidad. La coincidencia de denominación no alcanza para dar la identificación por confirmada. | Z102: Pendiente de valorización | AC102: No disponible en los archivos recibidos | AD102: =IF(AA102="","Pendiente",AA102*Q102) | AF102: =IF(AE102="","",AE102*Q102) | AG102: Pendiente | AH102: Sin decidir
...

Sheet A Identificados
A1: Materiales físicos identificados en SAP
A2: Existen en el inventario físico y tienen un código de SAP cuya nomenclatura y presentación se corresponden. No hay que darlos de alta.
A4: Nº | B4: Base | C4: Tipo | D4: Código SAP | E4: Descripción en SAP | F4: Código inventario físico | G4: Nomenclatura del inventario físico | H4: Presentación | I4: Cantidad física · UNIDADES | J4: Stock SAP · UNIDADES | K4: Atributos verificados | L4: Confianza | M4: Justificación | N4: Estado de valorización | O4: VU de referencia SAP · $ | P4: Valor de referencia SAP · $ | Q4: Estado de revisión | R4: Decisión registrada | S4: Revisor | T4: Observaciones
A5: 1 | B5: San Juan | C5: Descartable | D5: 2000002 | E5: CATETER INTRAVENOSO 14G T/ABBOCATH | F5: DESC1 | G5: Abbocath Nº 14 | H5: calibre 14 | I5: 8 | J5: 0 | K5: calibre | L5: Media | M5: Candidato 2000002 «CATETER INTRAVENOSO 14G T/ABBOCATH». Denominación: 100% del nombre del inventario explicado por el texto de SAP y 32% a la inversa. Atributos verificados: calibre. Sin contradicción en ningún atributo. | N5: Pendiente de valorización | O5: 254.79867 | P5: =IF(O5="","",O5*MAX(I5,J5)) | Q5: Pendiente | R5: Sin decidir
A6: 2 | B6: San Juan | C6: Descartable | D6: 2000003 | E6: CATETER INTRAVENOSO 16G T/ABBOCATH | F6: DESC2 | G6: Abbocath Nº 16 | H6: calibre 16 | I6: 202 | J6: 60 | K6: calibre | L6: Media | M6: Candidato 2000003 «CATETER INTRAVENOSO 16G T/ABBOCATH». Denominación: 100% del nombre del inventario explicado por el texto de SAP y 32% a la inversa. Atributos verificados: calibre. Sin contradicción en ningún atributo. | N6: Pendiente de valorización | O6: 214.29833 | P6: =IF(O6="","",O6*MAX(I6,J6)) | Q6: Pendiente | R6: Sin decidir
A7: 3 | B7: San Juan | C7: Descartable | D7: 2000005 | E7: CATETER INTRAVENOSO 20G T/ABBOCATH | F7: DESC4 | G7: Abbocath Nº 20 | H7: calibre 20 | I7: 272 | J7: 870 | K7: calibre | L7: Media | M7: Candidato 2000005 «CATETER INTRAVENOSO 20G T/ABBOCATH». Denominación: 100% del nombre del inventario explicado por el texto de SAP y 32% a la inversa. Atributos verificados: calibre. Sin contradicción en ningún atributo. | N7: Pendiente de valorización | O7: 176.58761 | P7: =IF(O7="","",O7*MAX(I7,J7)) | Q7: Pendiente | R7: Sin decidir
A8: 4 | B8: San Juan | C8: Descartable | D8: 2000006 | E8: CATETER INTRAVENOSO 22G T/ABBOCATH | F8: DESC5 | G8: Abbocath Nº 22 | H8: calibre 22 | I8: 217 | J8: 500 | K8: calibre | L8: Media | M8: Candidato 2000006 «CATETER INTRAVENOSO 22G T/ABBOCATH». Denominación: 100% del nombre del inventario explicado por el texto de SAP y 32% a la inversa. Atributos verificados: calibre. Sin contradicción en ningún atributo. | N8: Pendiente de valorización | O8: 170.50266 | P8: =IF(O8="","",O8*MAX(I8,J8)) | Q8: Pendiente | R8: Sin decidir
A9: 6 | B9: San Juan | C9: Medicamento | D9: 1000304 | E9: ADENOSINA 2 ML AMP 3 MG/1 ML | F9: MED8 | G9: Adenosina Amp x 2 ml | H9: forma ampolla · volumen 2 ml | I9: 5 | J9: 7 | K9: forma farmacéutica, volumen / presentación | L9: Alta | M9: Candidato 1000304 «ADENOSINA 2 ML AMP 3 MG/1 ML». Denominación: 100% del nombre del inventario explicado por el texto de SAP y 100% a la inversa. Atributos verificados: forma farmacéutica, volumen / presentación. Sin contradicción en ningún atributo. | N9: Pendiente de valorización | O9: 879.89714 | P9: =IF(O9="","",O9*MAX(I9,J9)) | Q9: Pendiente | R9: Sin decidir
A10: 7 | B10: San Juan | C10: Medicamento | D10: 1000002 | E10: ADRENALINA 1MG AMPOLLA DE 1 ML INYEC | F10: MED9 | G10: Adrenalina amp 1 ml | H10: forma ampolla · volumen 1 ml | I10: 41 | J10: 104 | K10: forma farmacéutica, volumen / presentación | L10: Alta | M10: Candidato 1000002 «ADRENALINA 1MG AMPOLLA DE 1 ML INYEC». Denominación: 100% del nombre del inventario explicado por el texto de SAP y 100% a la inversa. Atributos verificados: forma farmacéutica, volumen / presentación. Sin contradicción en ningún atributo. | N10: Pendiente de valorización | O10: 310.67721 | P10: =IF(O10="","",O10*MAX(I10,J10)) | Q10: Pendiente | R10: Sin decidir
A11: 8 | B11: San Juan | C11: Medicamento | D11: 1000052 | E11: AGUA OXIGENADA 10 VOL. X 500ML | F11: DESC291 | G11: Agua Oxigenada 10 Vol x 500 ml | H11: volumen 500 ml · cantidad sin unidad 10 | I11: 3 | J11: 0 | K11: volumen / presentación, cantidad o dosis sin unidad | L11: Alta | M11: Candidato 1000052 «AGUA OXIGENADA 10 VOL. X 500ML». Denominación: 100% del nombre del inventario explicado por el texto de SAP y 100% a la inversa. Atributos verificados: volumen / presentación, cantidad o dosis sin unidad. Sin contradicción en ningún atributo. | N11: Pendiente de valorización | O11: 542.5805 | P11: =IF(O11="","",O11*MAX(I11,J11)) | Q11: Pendiente | R11: Sin decidir
A12: 9 | B12: San Juan | C12: Medicamento | D12: 1000004 | E12: AGUA OXIGENADA 10 VOL. X 100ML | F12: DESC9 | G12: Agua oxigenada x 100ml | H12: volumen 100 ml | I12: 11 | J12: 15 | K12: volumen / presentación | L12: Alta | M12: Candidato 1000004 «AGUA OXIGENADA 10 VOL. X 100ML». Denominación: 100% del nombre del inventario explicado por el texto de SAP y 64% a la inversa. Atributos verificados: volumen / presentación. Sin contradicción en ningún atributo. | N12: Pendiente de valorización | O12: 335.13333 | P12: =IF(O12="","",O12*MAX(I12,J12)) | Q12: Pendiente | R12: Sin decidir
A13: 10 | B13: San Juan | C13: Medicamento | D13: 1000772 | E13: AGUJA 40/12 | F13: DESC10 | G13: Aguja 40/12 | H13: calibre 40/12 | I13: 20 | J13: 95 | K13: calibre | L13: Alta | M13: Candidato 1000772 «AGUJA 40/12». Denominación: 100% del nombre del inventario explicado por el texto de SAP y 100% a la inversa. Atributos verificados: calibre. Sin contradicción en ningún atributo. | N13: Pendiente de valorización | O13: 174.82526 | P13: =IF(O13="","",O13*MAX(I13,J13)) | Q13: Pendiente | R13: Sin decidir
A14: 11 | B14: San Juan | C14: Descartable | D14: 2000007 | E14: AGUJA HIPODERMICA 25G x ⅝ - 16/5 | F14: DESC11 | G14: Agujas 16/5 | H14: calibre 16/5 | I14: 300 | J14: 1020 | K14: calibre | L14: Media | M14: Candidato 2000007 «AGUJA HIPODERMICA 25G x ⅝ - 16/5». Denominación: 90% del nombre del inventario explicado por el texto de SAP y 41% a la inversa. Atributos verificados: calibre. Sin contradicción en ningún atributo. | N14: Pendiente de valorización | O14: 27.725941 | P14: =IF(O14="","",O14*MAX(I14,J14)) | Q14: Pendiente | R14: Sin decidir
A15: 12 | B15: San Juan | C15: Descartable | D15: 2000008 | E15: AGUJA HIPODERMICA 21G x 1 - 25/8 | F15: DESC12 | G15: Agujas 25/8 | H15: calibre 25/8 | I15: 975 | J15: 1548 | K15: calibre | L15: Media | M15: Candidato 2000008 «AGUJA HIPODERMICA 21G x 1 - 25/8». Denominación: 90% del nombre del inventario explicado por el texto de SAP y 41% a la inversa. Atributos verificados: calibre. Sin contradicción en ningún atributo. | N15: Pendiente de valorización | O15: 24.974767 | P15: =IF(O15="","",O15*MAX(I15,J15)) | Q15: Pendiente | R15: Sin decidir
A16: 13 | B16: San Juan | C16: Descartable | D16: 2000009 | E16: AGUJA HIPODERMICA 21G x 1 ½ - 40/8 | F16: DESC13 | G16: Agujas 40/8 | H16: calibre 40/8 | I16: 100 | J16: 1229 | K16: calibre | L16: Media | M16: Candidato 2000009 «AGUJA HIPODERMICA 21G x 1 ½ - 40/8». Denominación: 90% del nombre del inventario explicado por el texto de SAP y 41% a la inversa. Atributos verificados: calibre. Sin contradicción en ningún atributo. | N16: Pendiente de valorización | O16: 55.786672 | P16: =IF(O16="","",O16*MAX(I16,J16)) | Q16: Pendiente | R16: Sin decidir
... A49: 113 | B49: San Juan | C49: Medicamento | D49: 1000133 | E49: OMEPRAZOL DE 20MG COMPRIMIDOS | F49: MED148 | G49: Omeprazol Comp x 20 mg | H49: concentración 20 mg · forma comprimido | I49: 25 | J49: 84 | K49: concentración, forma farmacéutica | L49: Alta | M49: Candidato 1000133 «OMEPRAZOL DE 20MG COMPRIMIDOS». Denominación: 100% del nombre del inventario explicado por el texto de SAP y 100% a la inversa. Atributos verificados: concentración, forma farmacéutica. Sin contradicción en ningún atributo. | N49: Pendiente de valorización | O49: 52.137619 | P49: =IF(O49="","",O49*MAX(I49,J49)) | Q49: Pendiente | R49: Sin decidir
A50: 115 | B50: San Juan | C50: Descartable | D50: 2000470 | E50: OTOSCOPIO | F50: DESC94 | G50: Otoscopio | I50: 5 | J50: 0 | L50: Alta | M50: Candidato 2000470 «OTOSCOPIO». Denominación: 100% del nombre del inventario explicado por el texto de SAP y 100% a la inversa. Sin contradicción en ningún atributo. | N50: Pendiente de valorización | O50: 38539.108 | P50: =IF(O50="","",O50*MAX(I50,J50)) | Q50: Pendiente | R50: Sin decidir
A51: 116 | B51: San Juan | C51: Medicamento | D51: 1000470 | E51: PARACETAMOL COMP 1 GRAMO | F51: MED150 | G51: Paracetamol Comp x 1 gr | H51: concentración 1 g · forma comprimido | I51: 1048 | J51: 3831 | K51: concentración, forma farmacéutica | L51: Alta | M51: Candidato 1000470 «PARACETAMOL COMP 1 GRAMO». Denominación: 100% del nombre del inventario explicado por el texto de SAP y 45% a la inversa. Atributos verificados: concentración, forma farmacéutica. Sin contradicción en ningún atributo. | N51: Pendiente de valorización | O51: 87.157123 | P51: =IF(O51="","",O51*MAX(I51,J51)) | Q51: Pendiente | R51: Sin decidir
A52: 122 | B52: San Juan | C52: Medicamento | D52: 1000106 | E52: RIFAMICINA SPRAY 30ML | F52: DES104 | G52: Rifamicina Spray x 30ml | H52: forma aerosol · volumen 30 ml | I52: 3 | J52: 0 | K52: forma farmacéutica, volumen / presentación | L52: Alta | M52: Candidato 1000106 «RIFAMICINA SPRAY 30ML». Denominación: 100% del nombre del inventario explicado por el texto de SAP y 100% a la inversa. Atributos verificados: forma farmacéutica, volumen / presentación. Sin contradicción en ningún atributo. | N52: Pendiente de valorización | O52: 2216.5473 | P52: =IF(O52="","",O52*MAX(I52,J52)) | Q52: Pendiente | R52: Sin decidir
A53: 128 | B53: San Juan | C53: Medicamento | D53: 1001118 | E53: SALES REHIDRATANTES SOBRE POLVO | F53: MED162 | G53: Sales de Rehidratación (FM) sobre x 28gr | H53: concentración 28 g · forma sobre | I53: 2 | J53: 70 | K53: forma farmacéutica | L53: Alta | M53: Candidato 1001118 «SALES REHIDRATANTES SOBRE POLVO». Denominación: 95% del nombre del inventario explicado por el texto de SAP y 95% a la inversa. Atributos verificados: forma farmacéutica. Sin contradicción en ningún atributo. | N53: Pendiente de valorización | O53: 1601.2671 | P53: =IF(O53="","",O53*MAX(I53,J53)) | Q53: Pendiente | R53: Sin decidir
A54: 132 | B54: San Juan | C54: Medicamento | D54: 1000089 | E54: SOLUCION FISIOLOGICA DE 500CC | F54: MED168 | G54: Solucion fisiológica x 500 ml | H54: forma solucion · volumen 500 ml | I54: 249 | J54: 1271 | K54: forma farmacéutica, volumen / presentación | L54: Alta | M54: Candidato 1000089 «SOLUCION FISIOLOGICA DE 500CC». Denominación: 100% del nombre del inventario explicado por el texto de SAP y 100% a la inversa. Atributos verificados: forma farmacéutica, volumen / presentación. Sin contradicción en ningún atributo. | N54: Pendiente de valorización | O54: 1447.5172 | P54: =IF(O54="","",O54*MAX(I54,J54)) | Q54: Pendiente | R54: Sin decidir
A55: 133 | B55: San Juan | C55: Medicamento | D55: 1000035 | E55: SOLUCIÓN RINGER LACTATO 500 ML | F55: MED169 | G55: Solución ringer lactato x 500 ml | H55: forma solucion · volumen 500 ml | I55: 292 | J55: 630 | K55: forma farmacéutica, volumen / presentación | L55: Alta | M55: Candidato 1000035 «SOLUCIÓN RINGER LACTATO 500 ML». Denominación: 100% del nombre del inventario explicado por el texto de SAP y 100% a la inversa. Atributos verificados: forma farmacéutica, volumen / presentación. Sin contradicción en ningún atributo. | N55: Pendiente de valorización | O55: 2155.479 | P55: =IF(O55="","",O55*MAX(I55,J55)) | Q55: Pendiente | R55: Sin decidir
A56: 136 | B56: San Juan | C56: Descartable | D56: 2000867 | E56: SONDA NASOGASTRICA K-10 | F56: DESC116 | G56: Sonda nasogástrica K 10 | H56: modelo K10 | I56: 6 | J56: 0 | K56: modelo / referencia | L56: Alta | M56: Candidato 2000867 «SONDA NASOGASTRICA K-10». Denominación: 100% del nombre del inventario explicado por el texto de SAP y 100% a la inversa. Atributos verificados: modelo / referencia. Sin contradicción en ningún atributo. | N56: Pendiente de valorización | O56: 178.2835 | P56: =IF(O56="","",O56*MAX(I56,J56)) | Q56: Pendiente | R56: Sin decidir
A57: 137 | B57: San Juan | C57: Descartable | D57: 2000031 | E57: SONDA NASOGASTRICA K-30 KOLLER | F57: DESC117 | G57: Sonda nasogástrica K 30 | H57: modelo K30 | I57: 1 | J57: 0 | K57: modelo / referencia | L57: Alta | M57: Candidato 2000031 «SONDA NASOGASTRICA K-30 KOLLER». Denominación: 100% del nombre del inventario explicado por el texto de SAP y 62% a la inversa. Atributos verificados: modelo / referencia. Sin contradicción en ningún atributo. | N57: Pendiente de valorización | O57: 247.40631 | P57: =IF(O57="","",O57*MAX(I57,J57)) | Q57: Pendiente | R57: Sin decidir
A58: 138 | B58: San Juan | C58: Descartable | D58: 2001863 | E58: SONDA P/ ASPIRACION K29 | F58: DESC119 | G58: Sonda para aspiración K 29 | H58: modelo K29 | I58: 6 | J58: 0 | K58: modelo / referencia | L58: Alta | M58: Candidato 2001863 «SONDA P/ ASPIRACION K29». Denominación: 100% del nombre del inventario explicado por el texto de SAP y 58% a la inversa. Atributos verificados: modelo / referencia. Sin contradicción en ningún atributo. | N58: Pendiente de valorización | O58: 353.04 | P58: =IF(O58="","",O58*MAX(I58,J58)) | Q58: Pendiente | R58: Sin decidir
A59: 139 | B59: San Juan | C59: Descartable | D59: 2000093 | E59: SONDA VESICAL DE 2 VIAS Nº 16 (LÁTEX) | F59: DESC120 | G59: Sonda vesical Nº 16 | H59: calibre 16 | I59: 3 | J59: 0 | K59: calibre | L59: Alta | M59: Candidato 2000093 «SONDA VESICAL DE 2 VIAS Nº 16 (LÁTEX)». Denominación: 100% del nombre del inventario explicado por el texto de SAP y 65% a la inversa. Atributos verificados: calibre. Sin contradicción en ningún atributo. | N59: Pendiente de valorización | O59: 438.5 | P59: =IF(O59="","",O59*MAX(I59,J59)) | Q59: Pendiente | R59: Sin decidir
A60: 143 | B60: San Juan | C60: Descartable | D60: 2001052 | E60: SUTURA MONONYLON 4-0 AGUJA REDONDA | F60: DESC122 | G60: Sutura Mononylon 4-0 | H60: cantidad sin unidad 4 | I60: 7 | J60: 0 | K60: cantidad o dosis sin unidad | L60: Media | M60: Candidato 2001052 «SUTURA MONONYLON 4-0 AGUJA REDONDA». Denominación: 100% del nombre del inventario explicado por el texto de SAP y 50% a la inversa. Atributos verificados: cantidad o dosis sin unidad. Sin contradicción en ningún atributo. | N60: Pendiente de valorización | O60: 189 | P60: =IF(O60="","",O60*MAX(I60,J60)) | Q60: Pendiente | R60: Sin decidir
A61: 144 | B61: San Juan | C61: Descartable | D61: 2001053 | E61: SUTURA MONONYLON 5-0 AGUJA REDONDA | F61: DESC123 | G61: Sutura Mononylon 5-0 | H61: cantidad sin unidad 5 | I61: 1 | J61: 0 | K61: cantidad o dosis sin unidad | L61: Media | M61: Candidato 2001053 «SUTURA MONONYLON 5-0 AGUJA REDONDA». Denominación: 100% del nombre del inventario explicado por el texto de SAP y 50% a la inversa. Atributos verificados: cantidad o dosis sin unidad. Sin contradicción en ningún atributo. | N61: Pendiente de valorización | O61: 189 | P61: =IF(O61="","",O61*MAX(I61,J61)) | Q61: Pendiente | R61: Sin decidir
A62: 148 | B62: San Juan | C62: Descartable | D62: 2000034 | E62: TELA ADHESIVA 2.5CM HOSPITALARIA | F62: DESC132 | G62: Tela Adhesiva Hospitalaria 2.5 cm | H62: longitud 2,5 cm | I62: 22 | J62: 0 | K62: longitud | L62: Alta | M62: Candidato 2000034 «TELA ADHESIVA 2.5CM HOSPITALARIA». Denominación: 100% del nombre del inventario explicado por el texto de SAP y 100% a la inversa. Atributos verificados: longitud. Sin contradicción en ningún atributo. | N62: Pendiente de valorización | O62: 480.35338 | P62: =IF(O62="","",O62*MAX(I62,J62)) | Q62: Pendiente | R62: Sin decidir
A63: 152 | B63: San Juan | C63: Descartable | D63: 2000037 | E63: TERMOMETRO DIGITAL | F63: DESC138 | G63: Termómetro digital | I63: 3 | J63: 0 | L63: Alta | M63: Candidato 2000037 «TERMOMETRO DIGITAL». Denominación: 100% del nombre del inventario explicado por el texto de SAP y 100% a la inversa. Sin contradicción en ningún atributo. | N63: Pendiente de valorización | O63: 3388.4724 | P63: =IF(O63="","",O63*MAX(I63,J63)) | Q63: Pendiente | R63: Sin decidir
A64: 163 | B64: San Juan | C64: Descartable | D64: 2002475 | E64: VENDAS TIPO CAMBRIC - 7CM | F64: DESC171 | G64: Vendas de 7 cm. | H64: longitud 7 cm | I64: 8 | J64: 0 | K64: longitud | L64: Media | M64: Candidato 2002475 «VENDAS TIPO CAMBRIC - 7CM». Denominación: 100% del nombre del inventario explicado por el texto de SAP y 54% a la inversa. Atributos verificados: longitud. Sin contradicción en ningún atributo. | N64: Pendiente de valorización | O64: 319.65818 | P64: =IF(O64="","",O64*MAX(I64,J64)) | Q64: Pendiente | R64: Sin decidir
A65: 164 | B65: Neuquén | C65: Descartable | D65: 2000006 | E65: CATETER INTRAVENOSO 22G T/ABBOCATH | F65: 522 | G65: Abbocath n° 22 | H65: calibre 22 | I65: 90 | J65: 300 | K65: calibre | L65: Media | M65: Candidato 2000006 «CATETER INTRAVENOSO 22G T/ABBOCATH». Denominación: 100% del nombre del inventario explicado por el texto de SAP y 34% a la inversa. Atributos verificados: calibre. Sin contradicción en ningún atributo. | N65: Pendiente de valorización | O65: 296.9348 | P65: =IF(O65="","",O65*MAX(I65,J65)) | Q65: Pendiente | R65: Sin decidir
A66: 170 | B66: Neuquén | C66: Medicamento | D66: 1000002 | E66: ADRENALINA 1MG AMPOLLA DE 1 ML INYEC | F66: 2 | G66: ADRENALINA INY | H66: forma ampolla | I66: 279 | J66: 5588 | K66: forma farmacéutica | L66: Alta | M66: Candidato 1000002 «ADRENALINA 1MG AMPOLLA DE 1 ML INYEC». Denominación: 100% del nombre del inventario explicado por el texto de SAP y 100% a la inversa. Atributos verificados: forma farmacéutica. Sin contradicción en ningún atributo. | N66: Pendiente de valorización | O66: 287.35597 | P66: =IF(O66="","",O66*MAX(I66,J66)) | Q66: Pendiente | R66: Sin decidir
A67: 175 | B67: Neuquén | C67: Descartable | D67: 2000008 | E67: AGUJA HIPODERMICA 21G x 1 - 25/8 | F67: 273 | G67: Aguja 25/8 | H67: calibre 25/8 | I67: 3188 | J67: 12581 | K67: calibre | L67: Media | M67: Candidato 2000008 «AGUJA HIPODERMICA 21G x 1 - 25/8». Denominación: 100% del nombre del inventario explicado por el texto de SAP y 44% a la inversa. Atributos verificados: calibre. Sin contradicción en ningún atributo. | N67: Pendiente de valorización | O67: 23.068594 | P67: =IF(O67="","",O67*MAX(I67,J67)) | Q67: Pendiente | R67: Sin decidir
A68: 176 | B68: Neuquén | C68: Descartable | D68: 2000009 | E68: AGUJA HIPODERMICA 21G x 1 ½ - 40/8 | F68: 270 | G68: Aguja 40/8 | H68: calibre 40/8 | I68: 2044 | J68: 19567 | K68: calibre | L68: Media | M68: Candidato 2000009 «AGUJA HIPODERMICA 21G x 1 ½ - 40/8». Denominación: 100% del nombre del inventario explicado por el texto de SAP y 44% a la inversa. Atributos verificados: calibre. Sin contradicción en ningún atributo. | N68: Pendiente de valorización | O68: 15.742556 | P68: =IF(O68="","",O68*MAX(I68,J68)) | Q68: Pendiente | R68: Sin decidir
A69: 183 | B69: Neuquén | C69: Medicamento | D69: 1000166 | E69: AMINOFILINA 250 MG AMPOLLA | F69: 312 | G69: AMINOFILINA AMP | H69: forma ampolla | I69: 152 | J69: 828 | K69: forma farmacéutica | L69: Alta | M69: Candidato 1000166 «AMINOFILINA 250 MG AMPOLLA». Denominación: 100% del nombre del inventario explicado por el texto de SAP y 100% a la inversa. Atributos verificados: forma farmacéutica. Sin contradicción en ningún atributo. | N69: Pendiente de valorización | O69: 353.73106 | P69: =IF(O69="","",O69*MAX(I69,J69)) | Q69: Pendiente | R69: Sin decidir
A70: 184 | B70: Neuquén | C70: Medicamento | D70: 1000005 | E70: AMIODARONA 150MG AMPOLLA DE 3 ML INYEC | F70: 342 | G70: AMIODARONA AMP | H70: forma ampolla | I70: 55 | J70: 3456 | K70: forma farmacéutica | L70: Alta | M70: Candidato 1000005 «AMIODARONA 150MG AMPOLLA DE 3 ML INYEC». Denominación: 100% del nombre del inventario explicado por el texto de SAP y 100% a la inversa. Atributos verificados: forma farmacéutica. Sin contradicción en ningún atributo. | N70: Pendiente de valorización | O70: 947.2201 | P70: =IF(O70="","",O70*MAX(I70,J70)) | Q70: Pendiente | R70: Sin decidir
A71: 191 | B71: Neuquén | C71: Medicamento | D71: 1000164 | E71: ATENOLOL 100 MG COMPRIMIDO | F71: 399 | G71: ATENOLOL 100 MG COMPRIMIDOS | H71: concentración 100 mg · forma comprimido | I71: 28 | J71: 1866 | K71: concentración, forma farmacéutica | L71: Alta | M71: Candidato 1000164 «ATENOLOL 100 MG COMPRIMIDO». Denominación: 100% del nombre del inventario explicado por el texto de SAP y 100% a la inversa. Atributos verificados: concentración, forma farmacéutica. Sin contradicción en ningún atributo. | N71: Pendiente de valorización | O71: 250.32598 | P71: =IF(O71="","",O71*MAX(I71,J71)) | Q71: Pendiente | R71: Sin decidir
A72: 192 | B72: Neuquén | C72: Medicamento | D72: 1000007 | E72: ATROPINA 1MG AMPOLLA DE 1ML | F72: 26 | G72: ATROPINA AMP | H72: forma ampolla | I72: 243 | J72: 4703 | K72: forma farmacéutica | L72: Alta | M72: Candidato 1000007 «ATROPINA 1MG AMPOLLA DE 1ML». Denominación: 100% del nombre del inventario explicado por el texto de SAP y 100% a la inversa. Atributos verificados: forma farmacéutica. Sin contradicción en ningún atributo. | N72: Pendiente de valorización | O72: 196.45444 | P72: =IF(O72="","",O72*MAX(I72,J72)) | Q72: Pendiente | R72: Sin decidir
A73: 196 | B73: Neuquén | C73: Descartable | D73: 2000462 | E73: BIGOTERA DESCARTABLE | F73: 352 | G73: bigoteras | I73: 638 | J73: 520 | L73: Media | M73: Candidato 2000462 «BIGOTERA DESCARTABLE». Denominación: 90% del nombre del inventario explicado por el texto de SAP y 90% a la inversa. Sin contradicción en ningún atributo. | N73: Pendiente de valorización | O73: 663.035 | P73: =IF(O73="","",O73*MAX(I73,J73)) | Q73: Pendiente | R73: Sin decidir
A74: 200 | B74: Neuquén | C74: Medicamento | D74: 1000187 | E74: CALADRYL SOLUCION | F74: 501 | G74: CALADRYL | I74: 3 | J74: 48 | L74: Alta | M74: Candidato 1000187 «CALADRYL SOLUCION». Denominación: 100% del nombre del inventario explicado por el texto de SAP y 100% a la inversa. Sin contradicción en ningún atributo. | N74: Pendiente de valorización | O74: 3632.57 | P74: =IF(O74="","",O74*MAX(I74,J74)) | Q74: Pendiente | R74: Sin decidir
A75: 229 | B75: Neuquén | C75: Medicamento | D75: 1000021 | E75: DIAZEPAM 10MG AMPOLLA DE 2ML INYECTABLE | F75: 77 | G75: DIAZEPAM AMP | H75: forma ampolla | I75: 122 | J75: 2096 | K75: forma farmacéutica | L75: Alta | M75: Candidato 1000021 «DIAZEPAM 10MG AMPOLLA DE 2ML INYECTABLE». Denominación: 100% del nombre del inventario explicado por el texto de SAP y 100% a la inversa. Atributos verificados: forma farmacéutica. Sin contradicción en ningún atributo. | N75: Pendiente de valorización | O75: 221.2131 | P75: =IF(O75="","",O75*MAX(I75,J75)) | Q75: Pendiente | R75: Sin decidir
A76: 231 | B76: Neuquén | C76: Medicamento | D76: 1000045 | E76: DICLOFENAC 75MG AMPOLLA 3ML | F76: 80 | G76: DICLOFENAC AMP | H76: forma ampolla | I76: 33 | J76: 11285 | K76: forma farmacéutica | L76: Alta | M76: Candidato 1000045 «DICLOFENAC 75MG AMPOLLA 3ML». Denominación: 100% del nombre del inventario explicado por el texto de SAP y 100% a la inversa. Atributos verificados: forma farmacéutica. Sin contradicción en ningún atributo. | N76: Pendiente de valorización | O76: 236.1373 | P76: =IF(O76="","",O76*MAX(I76,J76)) | Q76: Pendiente | R76: Sin decidir
A77: 240 | B77: Neuquén | C77: Medicamento | D77: 1000305 | E77: FENTANILO AMP 0,25mg/5ml | F77: 309 | G77: FENTANILO AMP | H77: forma ampolla | I77: 46 | J77: 450 | K77: forma farmacéutica | L77: Alta | M77: Candidato 1000305 «FENTANILO AMP 0,25mg/5ml». Denominación: 100% del nombre del inventario explicado por el texto de SAP y 100% a la inversa. Atributos verificados: forma farmacéutica. Sin contradicción en ningún atributo. | N77: Pendiente de valorización | O77: 614.17333 | P77: =IF(O77="","",O77*MAX(I77,J77)) | Q77: Pendiente | R77: Sin decidir
A78: 243 | B78: Neuquén | C78: Medicamento | D78: 1000404 | E78: FLUMAZENIL AMP 5 ML | F78: 321 | G78: FLUMAZENIL AMP | H78: forma ampolla | I78: 189 | J78: 1326 | K78: forma farmacéutica | L78: Alta | M78: Candidato 1000404 «FLUMAZENIL AMP 5 ML». Denominación: 100% del nombre del inventario explicado por el texto de SAP y 100% a la inversa. Atributos verificados: forma farmacéutica. Sin contradicción en ningún atributo. | N78: Pendiente de valorización | O78: 944.43672 | P78: =IF(O78="","",O78*MAX(I78,J78)) | Q78: Pendiente | R78: Sin decidir
A79: 244 | B79: Neuquén | C79: Medicamento | D79: 1000100 | E79: FUROSEMIDA AMPOLLA DE 20 MG/2ML | F79: 116 | G79: FUROSEMIDA AMP | H79: forma ampolla | I79: 117 | J79: 3270 | K79: forma farmacéutica | L79: Alta | M79: Candidato 1000100 «FUROSEMIDA AMPOLLA DE 20 MG/2ML». Denominación: 100% del nombre del inventario explicado por el texto de SAP y 100% a la inversa. Atributos verificados: forma farmacéutica. Sin contradicción en ningún atributo. | N79: Pendiente de valorización | O79: 225.56696 | P79: =IF(O79="","",O79*MAX(I79,J79)) | Q79: Pendiente | R79: Sin decidir
A80: 246 | B80: Neuquén | C80: Descartable | D80: 2001670 | E80: GLUCOMETRO | F80: 383 | G80: GLUCOMETRO | I80: 19 | J80: 0 | L80: Alta | M80: Candidato 2001670 «GLUCOMETRO». Denominación: 100% del nombre del inventario explicado por el texto de SAP y 100% a la inversa. Sin contradicción en ningún atributo. | N80: Pendiente de valorización | O80: 29777 | P80: =IF(O80="","",O80*MAX(I80,J80)) | Q80: Pendiente | R80: Sin decidir
A81: 247 | B81: Neuquén | C81: Medicamento | D81: 1005248 | E81: GLUCONATO DE CALCIO 10% X 10ML AMPOLLA | F81: 122 | G81: GLUCONATO DE CALCIO AMP | H81: forma ampolla | I81: 290 | J81: 0 | K81: forma farmacéutica | L81: Alta | M81: Candidato 1005248 «GLUCONATO DE CALCIO 10% X 10ML AMPOLLA». Denominación: 100% del nombre del inventario explicado por el texto de SAP y 100% a la inversa. Atributos verificados: forma farmacéutica. Sin contradicción en ningún atributo. | N81: Pendiente de valorización | O81: 2240 | P81: =IF(O81="","",O81*MAX(I81,J81)) | Q81: Pendiente | R81: Sin decidir
A82: 249 | B82: Neuquén | C82: Descartable | D82: 2001761 | E82: GUANTES ESTERILES Nº 6.5 POR PAR | F82: 1006 | G82: Guantes Esteriles N° 6,5 | H82: calibre N° 6 | I82: 44 | J82: 100 | K82: calibre | L82: Alta | M82: Candidato 2001761 «GUANTES ESTERILES Nº 6.5 POR PAR». Denominación: 100% del nombre del inventario explicado por el texto de SAP y 61% a la inversa. Atributos verificados: calibre. Sin contradicción en ningún atributo. | N82: Pendiente de valorización | O82: 202.2452 | P82: =IF(O82="","",O82*MAX(I82,J82)) | Q82: Pendiente | R82: Sin decidir
A83: 258 | B83: Neuquén | C83: Medicamento | D83: 1000108 | E83: HALOPERIDOL 5MG/1ML AMPOLLA | F83: 325 | G83: HALOPERIDOL AMP | H83: forma ampolla | I83: 171 | J83: 973 | K83: forma farmacéutica | L83: Alta | M83: Candidato 1000108 «HALOPERIDOL 5MG/1ML AMPOLLA». Denominación: 100% del nombre del inventario explicado por el texto de SAP y 100% a la inversa. Atributos verificados: forma farmacéutica. Sin contradicción en ningún atributo. | N83: Pendiente de valorización | O83: 312.47529 | P83: =IF(O83="","",O83*MAX(I83,J83)) | Q83: Pendiente | R83: Sin decidir
A84: 260 | B84: Neuquén | C84: Medicamento | D84: 1000010 | E84: HIDROCORTISONA 500MG AMPOLLA | F84: 130 | G84: HIDROCORTISONA 500 MG AMP | H84: concentración 500 mg · forma ampolla | I84: 343 | J84: 2010 | K84: concentración, forma farmacéutica | L84: Alta | M84: Candidato 1000010 «HIDROCORTISONA 500MG AMPOLLA». Denominación: 100% del nombre del inventario explicado por el texto de SAP y 100% a la inversa. Atributos verificados: concentración, forma farmacéutica. Sin contradicción en ningún atributo. | N84: Pendiente de valorización | O84: 2174.7838 | P84: =IF(O84="","",O84*MAX(I84,J84)) | Q84: Pendiente | R84: Sin decidir
A85: 266 | B85: Neuquén | C85: Descartable | D85: 2000455 | E85: HOJA DE BISTURI Nº 24 | F85: 564 | G85: HOJA DE BISTURI Nº24 | H85: calibre N° 24 | I85: 70 | J85: 100 | K85: calibre | L85: Alta | M85: Candidato 2000455 «HOJA DE BISTURI Nº 24». Denominación: 100% del nombre del inventario explicado por el texto de SAP y 100% a la inversa. Atributos verificados: calibre. Sin contradicción en ningún atributo. | N85: Pendiente de valorización | O85: 90.91 | P85: =IF(O85="","",O85*MAX(I85,J85)) | Q85: Pendiente | R85: Sin decidir
A86: 267 | B86: Neuquén | C86: Medicamento | D86: 1000046 | E86: IBUPROFENO 400 MG COMPRIMIDOS | F86: 135 | G86: IBUPROFENO 400 MG | H86: concentración 400 mg | I86: 480 | J86: 2770 | K86: concentración | L86: Alta | M86: Candidato 1000046 «IBUPROFENO 400 MG COMPRIMIDOS». Denominación: 100% del nombre del inventario explicado por el texto de SAP y 100% a la inversa. Atributos verificados: concentración. Sin contradicción en ningún atributo. | N86: Pendiente de valorización | O86: 71.635379 | P86: =IF(O86="","",O86*MAX(I86,J86)) | Q86: Pendiente | R86: Sin decidir
A87: 269 | B87: Neuquén | C87: Descartable | D87: 2001515 | E87: INMOVILIZADOR LATERO CERVICAL | F87: 513 | G87: INMOVILIZADOR LATEROCERVICAL | I87: 8 | J87: 28 | L87: Media | M87: Candidato 2001515 «INMOVILIZADOR LATERO CERVICAL». Denominación: 95% del nombre del inventario explicado por el texto de SAP y 66% a la inversa. Sin contradicción en ningún atributo. | N87: Pendiente de valorización | O87: 50948.643 | P87: =IF(O87="","",O87*MAX(I87,J87)) | Q87: Pendiente | R87: Sin decidir
A88: 270 | B88: Neuquén | C88: Medicamento | D88: 1000041 | E88: IODOPOVIDONA SOLUCION 10% X 1000ML | F88: 137 | G88: IODOPOVIDONA 1000 ML | H88: volumen 1000 ml | I88: 41 | J88: 431 | K88: volumen / presentación | L88: Alta | M88: Candidato 1000041 «IODOPOVIDONA SOLUCION 10% X 1000ML». Denominación: 100% del nombre del inventario explicado por el texto de SAP y 100% a la inversa. Atributos verificados: volumen / presentación. Sin contradicción en ningún atributo. | N88: Pendiente de valorización | O88: 9402.6155 | P88: =IF(O88="","",O88*MAX(I88,J88)) | Q88: Pendiente | R88: Sin decidir
A89: 271 | B89: Neuquén | C89: Medicamento | D89: 1000497 | E89: IODOPOVIDONA SOLUC 10% X 60 ML | F89: 469 | G89: iodopovidona x 60 ml | H89: volumen 60 ml | I89: 30 | J89: 360 | K89: volumen / presentación | L89: Media | M89: Candidato 1000497 «IODOPOVIDONA SOLUC 10% X 60 ML». Denominación: 100% del nombre del inventario explicado por el texto de SAP y 47% a la inversa. Atributos verificados: volumen / presentación. Sin contradicción en ningún atributo. | N89: Pendiente de valorización | O89: 7619.6422 | P89: =IF(O89="","",O89*MAX(I89,J89)) | Q89: Pendiente | R89: Sin decidir
A90: 274 | B90: Neuquén | C90: Descartable | D90: 2000028 | E90: JERINGA 10 ML | F90: 246 | G90: JERINGAS 10 ML | H90: volumen 10 ml | I90: 2150 | J90: 20310 | K90: volumen / presentación | L90: Alta | M90: Candidato 2000028 «JERINGA 10 ML». Denominación: 90% del nombre del inventario explicado por el texto de SAP y 90% a la inversa. Atributos verificados: volumen / presentación. Sin contradicción en ningún atributo. | N90: Pendiente de valorización | O90: 36.74993 | P90: =IF(O90="","",O90*MAX(I90,J90)) | Q90: Pendiente | R90: Sin decidir
A91: 275 | B91: Neuquén | C91: Descartable | D91: 2000029 | E91: JERINGA 20 ML | F91: 523 | G91: JERINGAS 20 ML | H91: volumen 20 ml | I91: 58 | J91: 500 | K91: volumen / presentación | L91: Alta | M91: Candidato 2000029 «JERINGA 20 ML». Denominación: 90% del nombre del inventario explicado por el texto de SAP y 90% a la inversa. Atributos verificados: volumen / presentación. Sin contradicción en ningún atributo. | N91: Pendiente de valorización | O91: 156.00714 | P91: =IF(O91="","",O91*MAX(I91,J91)) | Q91: Pendiente | R91: Sin decidir
A92: 276 | B92: Neuquén | C92: Descartable | D92: 2000027 | E92: JERINGA DE 5 ML | F92: 254 | G92: JERINGAS 5 ML | H92: volumen 5 ml | I92: 830 | J92: 29110 | K92: volumen / presentación | L92: Alta | M92: Candidato 2000027 «JERINGA DE 5 ML». Denominación: 90% del nombre del inventario explicado por el texto de SAP y 90% a la inversa. Atributos verificados: volumen / presentación. Sin contradicción en ningún atributo. | N92: Pendiente de valorización | O92: 19.432985 | P92: =IF(O92="","",O92*MAX(I92,J92)) | Q92: Pendiente | R92: Sin decidir
A93: 279 | B93: Neuquén | C93: Descartable | D93: 2000058 | E93: LANCETA ESTERIL | F93: 527 | G93: LANCETAS | I93: 300 | J93: 20552 | L93: Media | M93: Candidato 2000058 «LANCETA ESTERIL». Denominación: 90% del nombre del inventario explicado por el texto de SAP y 90% a la inversa. Sin contradicción en ningún atributo. | N93: Pendiente de valorización | O93: 92.772723 | P93: =IF(O93="","",O93*MAX(I93,J93)) | Q93: Pendiente | R93: Sin decidir
A94: 285 | B94: Neuquén | C94: Medicamento | D94: 1000090 | E94: LORAZEPAM COMPRIMIDO SUBLINGUAL 1GR | F94: 329 | G94: LORAZEPAM SUBLINGUAL COMP | H94: forma comprimido | I94: 200 | J94: 3933 | K94: forma farmacéutica | L94: Alta | M94: Candidato 1000090 «LORAZEPAM COMPRIMIDO SUBLINGUAL 1GR». Denominación: 100% del nombre del inventario explicado por el texto de SAP y 100% a la inversa. Atributos verificados: forma farmacéutica. Sin contradicción en ningún atributo. | N94: Pendiente de valorización | O94: 98.680638 | P94: =IF(O94="","",O94*MAX(I94,J94)) | Q94: Pendiente | R94: Sin decidir
A95: 296 | B95: Neuquén | C95: Medicamento | D95: 1000105 | E95: METOCLOPRAMIDA 10MG/2ML AMPOLLA | F95: 160 | G95: METOCLOPRAMIDA AMP | H95: forma ampolla | I95: 146 | J95: 5600 | K95: forma farmacéutica | L95: Alta | M95: Candidato 1000105 «METOCLOPRAMIDA 10MG/2ML AMPOLLA». Denominación: 100% del nombre del inventario explicado por el texto de SAP y 100% a la inversa. Atributos verificados: forma farmacéutica. Sin contradicción en ningún atributo. | N95: Pendiente de valorización | O95: 260.12259 | P95: =IF(O95="","",O95*MAX(I95,J95)) | Q95: Pendiente | R95: Sin decidir
A96: 298 | B96: Neuquén | C96: Medicamento | D96: 1000779 | E96: METRONIDAZOL COMP. 500mg | F96: MED-008 | G96: Metronidazol 500mg | H96: concentración 500 mg | I96: 20 | J96: 0 | K96: concentración | L96: Alta | M96: Candidato 1000779 «METRONIDAZOL COMP. 500mg». Denominación: 100% del nombre del inventario explicado por el texto de SAP y 100% a la inversa. Atributos verificados: concentración. Sin contradicción en ningún atributo. | N96: Pendiente de valorización | O96: 109.56667 | P96: =IF(O96="","",O96*MAX(I96,J96)) | Q96: Pendiente | R96: Sin decidir
A97: 299 | B97: Neuquén | C97: Medicamento | D97: 1000098 | E97: MIDAZOLAN 15MG/3ML AMPOLLA INYECTABLE | F97: 330 | G97: MIDAZOLAM 5MG AMP | H97: concentración 5 mg · forma ampolla | I97: 96 | J97: 1060 | K97: forma farmacéutica | L97: Alta | M97: Candidato 1000098 «MIDAZOLAN 15MG/3ML AMPOLLA INYECTABLE». Denominación: 90% del nombre del inventario explicado por el texto de SAP y 90% a la inversa. Atributos verificados: forma farmacéutica. Sin contradicción en ningún atributo. | N97: Pendiente de valorización | O97: 520.01897 | P97: =IF(O97="","",O97*MAX(I97,J97)) | Q97: Pendiente | R97: Sin decidir
A98: 300 | B98: Neuquén | C98: Medicamento | D98: 1000314 | E98: MORFINA CLORHIDRATO 10MG | F98: 331 | G98: MORFINA 10MG AMP | H98: concentración 10 mg · forma ampolla | I98: 56 | J98: 800 | K98: concentración | L98: Media | M98: Candidato 1000314 «MORFINA CLORHIDRATO 10MG». Denominación: 100% del nombre del inventario explicado por el texto de SAP y 52% a la inversa. Atributos verificados: concentración. Sin contradicción en ningún atributo. | N98: Pendiente de valorización | O98: 803.1425 | P98: =IF(O98="","",O98*MAX(I98,J98)) | Q98: Pendiente | R98: Sin decidir
A99: 301 | B99: Neuquén | C99: Medicamento | D99: 1000307 | E99: NALOXONA AMPOLLA 0,4mg/1ml | F99: 166 | G99: NALOXONA AMP | H99: forma ampolla | I99: 198 | J99: 695 | K99: forma farmacéutica | L99: Alta | M99: Candidato 1000307 «NALOXONA AMPOLLA 0,4mg/1ml». Denominación: 100% del nombre del inventario explicado por el texto de SAP y 100% a la inversa. Atributos verificados: forma farmacéutica. Sin contradicción en ningún atributo. | N99: Pendiente de valorización | O99: 808.71237 | P99: =IF(O99="","",O99*MAX(I99,J99)) | Q99: Pendiente | R99: Sin decidir
A100: 303 | B100: Neuquén | C100: Medicamento | D100: 1000013 | E100: NITROGLICERINA 25 MG AMPOLLA | F100: 479 | G100: NITROGLICERINA 25 MG | H100: concentración 25 mg | I100: 70 | J100: 286 | K100: concentración | L100: Alta | M100: Candidato 1000013 «NITROGLICERINA 25 MG AMPOLLA». Denominación: 100% del nombre del inventario explicado por el texto de SAP y 100% a la inversa. Atributos verificados: concentración. Sin contradicción en ningún atributo. | N100: Pendiente de valorización | O100: 215.75899 | P100: =IF(O100="","",O100*MAX(I100,J100)) | Q100: Pendiente | R100: Sin decidir
A101: 305 | B101: Neuquén | C101: Medicamento | D101: 1000133 | E101: OMEPRAZOL DE 20MG COMPRIMIDOS | F101: 170 | G101: OMEPRAZOL 20 MG COMP | H101: concentración 20 mg · forma comprimido | I101: 135 | J101: 1562 | K101: concentración, forma farmacéutica | L101: Alta | M101: Candidato 1000133 «OMEPRAZOL DE 20MG COMPRIMIDOS». Denominación: 100% del nombre del inventario explicado por el texto de SAP y 100% a la inversa. Atributos verificados: concentración, forma farmacéutica. Sin contradicción en ningún atributo. | N101: Pendiente de valorización | O101: 24.470653 | P101: =IF(O101="","",O101*MAX(I101,J101)) | Q101: Pendiente | R101: Sin decidir
A102: 307 | B102: Neuquén | C102: Descartable | D102: 2000470 | E102: OTOSCOPIO | F102: 530 | G102: OTOSCOPIO | I102: 11 | J102: 71 | L102: Alta | M102: Candidato 2000470 «OTOSCOPIO». Denominación: 100% del nombre del inventario explicado por el texto de SAP y 100% a la inversa. Sin contradicción en ningún atributo. | N102: Pendiente de valorización | O102: 38328.942 | P102: =IF(O102="","",O102*MAX(I102,J102)) | Q102: Pendiente | R102: Sin decidir
A103: 308 | B103: Neuquén | C103: Medicamento | D103: 1000360 | E103: GOTAS OTOSPORIN | F103: 173 | G103: OTOSPORIN | I103: 27 | J103: 283 | L103: Alta | M103: Candidato 1000360 «GOTAS OTOSPORIN». Denominación: 100% del nombre del inventario explicado por el texto de SAP y 100% a la inversa. Sin contradicción en ningún atributo. | N103: Pendiente de valorización | O103: 2540.2689 | P103: =IF(O103="","",O103*MAX(I103,J103)) | Q103: Pendiente | R103: Sin decidir
A104: 310 | B104: Neuquén | C104: Medicamento | D104: 1000470 | E104: PARACETAMOL COMP 1 GRAMO | F104: 369 | G104: PARACETAMOL 1 G | H104: concentración 1 g | I104: 108 | J104: 6328 | K104: concentración | L104: Media | M104: Candidato 1000470 «PARACETAMOL COMP 1 GRAMO». Denominación: 100% del nombre del inventario explicado por el texto de SAP y 44% a la inversa. Atributos verificados: concentración. Sin contradicción en ningún atributo. | N104: Pendiente de valorización | O104: 110.08047 | P104: =IF(O104="","",O104*MAX(I104,J104)) | Q104: Pendiente | R104: Sin decidir
A105: 311 | B105: Neuquén | C105: Medicamento | D105: 1000030 | E105: PARACETAMOL COMPRIMIDOS POR 500MG | F105: 179 | G105: PARACETAMOL 500 MG | H105: concentración 500 mg | I105: 318 | J105: 12310 | K105: concentración | L105: Alta | M105: Candidato 1000030 «PARACETAMOL COMPRIMIDOS POR 500MG». Denominación: 100% del nombre del inventario explicado por el texto de SAP y 100% a la inversa. Atributos verificados: concentración. Sin contradicción en ningún atributo. | N105: Pendiente de valorización | O105: 30.384038 | P105: =IF(O105="","",O105*MAX(I105,J105)) | Q105: Pendiente | R105: Sin decidir
A106: 323 | B106: Neuquén | C106: Medicamento | D106: 1000430 | E106: POEN BIOPTAL GOTAS | F106: 188 | G106: POEN-BIOPTAL NF COLIRIO | H106: forma gotas | I106: 59 | J106: 689 | K106: forma farmacéutica | L106: Alta | M106: Candidato 1000430 «POEN BIOPTAL GOTAS». Denominación: 100% del nombre del inventario explicado por el texto de SAP y 100% a la inversa. Atributos verificados: forma farmacéutica. Sin contradicción en ningún atributo. | N106: Pendiente de valorización | O106: 4448.8275 | P106: =IF(O106="","",O106*MAX(I106,J106)) | Q106: Pendiente | R106: Sin decidir
A107: 326 | B107: Neuquén | C107: Medicamento | D107: 1000106 | E107: RIFAMICINA SPRAY 30ML | F107: 199 | G107: RIFAMICINA SV 1% X 30ML | H107: concentración 1% · volumen 30 ml | I107: 12 | J107: 325 | K107: volumen / presentación | L107: Alta | M107: Candidato 1000106 «RIFAMICINA SPRAY 30ML». Denominación: 100% del nombre del inventario explicado por el texto de SAP y 100% a la inversa. Atributos verificados: volumen / presentación. Sin contradicción en ningún atributo. | N107: Pendiente de valorización | O107: 2216.5473 | P107: =IF(O107="","",O107*MAX(I107,J107)) | Q107: Pendiente | R107: Sin decidir
A108: 330 | B108: Neuquén | C108: Medicamento | D108: 1000087 | E108: SALBUTAMOL PUFF ("AEROS" 250 DOSIS) 100M | F108: 505 | G108: SALBUTAMOL AEROSOL | H108: forma aerosol | I108: 33 | J108: 463 | K108: forma farmacéutica | L108: Media | M108: Candidato 1000087 «SALBUTAMOL PUFF ("AEROS" 250 DOSIS) 100M». Denominación: 100% del nombre del inventario explicado por el texto de SAP y 46% a la inversa. Atributos verificados: forma farmacéutica. Sin contradicción en ningún atributo. | N108: Pendiente de valorización | O108: 3630.0076 | P108: =IF(O108="","",O108*MAX(I108,J108)) | Q108: Pendiente | R108: Sin decidir
A109: 334 | B109: Neuquén | C109: Medicamento | D109: 1000035 | E109: SOLUCIÓN RINGER LACTATO 500 ML | F109: 216 | G109: SOLUCIÓN RINGER LACTATO | H109: forma solucion | I109: 228 | J109: 1813 | K109: forma farmacéutica | L109: Alta | M109: Candidato 1000035 «SOLUCIÓN RINGER LACTATO 500 ML». Denominación: 100% del nombre del inventario explicado por el texto de SAP y 100% a la inversa. Atributos verificados: forma farmacéutica. Sin contradicción en ningún atributo. | N109: Pendiente de valorización | O109: 1562.3013 | P109: =IF(O109="","",O109*MAX(I109,J109)) | Q109: Pendiente | R109: Sin decidir
A110: 337 | B110: Neuquén | C110: Descartable | D110: 2001866 | E110: SONDA P/ ASPIRACION K30 | F110: 349 | G110: sonda k30 | H110: modelo K30 | I110: 3 | J110: 35 | K110: modelo / referencia | L110: Alta | M110: Candidato 2001866 «SONDA P/ ASPIRACION K30». Denominación: 100% del nombre del inventario explicado por el texto de SAP y 66% a la inversa. Atributos verificados: modelo / referencia. Sin contradicción en ningún atributo. | N110: Pendiente de valorización | O110: 420 | P110: =IF(O110="","",O110*MAX(I110,J110)) | Q110: Pendiente | R110: Sin decidir
A111: 343 | B111: Neuquén | C111: Medicamento | D111: 1000671 | E111: SULFATO DE MAGNESIO AL 25% AMP | F111: 527 | G111: SULFATO DE MAGNESIO AMP X 5 ML | H111: forma ampolla · volumen 5 ml | I111: 125 | J111: 130 | K111: forma farmacéutica | L111: Alta | M111: Candidato 1000671 «SULFATO DE MAGNESIO AL 25% AMP». Denominación: 100% del nombre del inventario explicado por el texto de SAP y 100% a la inversa. Atributos verificados: forma farmacéutica. Sin contradicción en ningún atributo. | N111: Pendiente de valorización | O111: 979.62077 | P111: =IF(O111="","",O111*MAX(I111,J111)) | Q111: Pendiente | R111: Sin decidir
A112: 345 | B112: Neuquén | C112: Descartable | D112: 2001121 | E112: TENSIOMETRO DIGITAL | F112: 525 | G112: TENSIOMETRO DIGITAL | I112: 6 | J112: 10 | L112: Alta | M112: Candidato 2001121 «TENSIOMETRO DIGITAL». Denominación: 100% del nombre del inventario explicado por el texto de SAP y 100% a la inversa. Sin contradicción en ningún atributo. | N112: Pendiente de valorización | O112: 64800 | P112: =IF(O112="","",O112*MAX(I112,J112)) | Q112: Pendiente | R112: Sin decidir
A113: 346 | B113: Neuquén | C113: Descartable | D113: 2000037 | E113: TERMOMETRO DIGITAL | F113: 423 | G113: TERMOMETRO DIGITAL | I113: 37 | J113: 175 | L113: Alta | M113: Candidato 2000037 «TERMOMETRO DIGITAL». Denominación: 100% del nombre del inventario explicado por el texto de SAP y 100% a la inversa. Sin contradicción en ningún atributo. | N113: Pendiente de valorización | O113: 3353.6846 | P113: =IF(O113="","",O113*MAX(I113,J113)) | Q113: Pendiente | R113: Sin decidir
A114: 347 | B114: Neuquén | C114: Descartable | D114: 2001137 | E114: TERMOMETRO INFRARROJO | F114: 535 | G114: TERMOMETRO INFRARED | I114: 10 | J114: 10 | L114: Media | M114: Candidato 2001137 «TERMOMETRO INFRARROJO». Denominación: 95% del nombre del inventario explicado por el texto de SAP y 95% a la inversa. Sin contradicción en ningún atributo. | N114: Pendiente de valorización | O114: 17486.282 | P114: =IF(O114="","",O114*MAX(I114,J114)) | Q114: Pendiente | R114: Sin decidir
A115: 352 | B115: Neuquén | C115: Medicamento | D115: 1000672 | E115: TOBRAMICINA + DEXAMETASONA | F115: 478 | G115: TOBRAMICINA+DEXAMETASONA | I115: 4 | J115: 0 | L115: Alta | M115: Candidato 1000672 «TOBRAMICINA + DEXAMETASONA». Denominación: 100% del nombre del inventario explicado por el texto de SAP y 100% a la inversa. Sin contradicción en ningún atributo. | N115: Pendiente de valorización | O115: 2400 | P115: =IF(O115="","",O115*MAX(I115,J115)) | Q115: Pendiente | R115: Sin decidir
A116: 353 | B116: Neuquén | C116: Medicamento | D116: 1000600 | E116: TRAMADOL CLORHIDRATO 100MG AMP 2ML | F116: 327 | G116: TRAMADOL 100 MG AMP | H116: concentración 100 mg · forma ampolla | I116: 94 | J116: 0 | K116: concentración, forma farmacéutica | L116: Alta | M116: Candidato 1000600 «TRAMADOL CLORHIDRATO 100MG AMP 2ML». Denominación: 100% del nombre del inventario explicado por el texto de SAP y 48% a la inversa. Atributos verificados: concentración, forma farmacéutica. Sin contradicción en ningún atributo. | N116: Pendiente de valorización | O116: 1237.5 | P116: =IF(O116="","",O116*MAX(I116,J116)) | Q116: Pendiente | R116: Sin decidir
A117: 361 | B117: Neuquén | C117: Descartable | D117: 2000079 | E117: VENDA TIPO CAMBRIC X 10 CM | F117: 335 | G117: VENDA CAMBRIC 10CM | H117: longitud 10 cm | I117: 39 | J117: 2856 | K117: longitud | L117: Alta | M117: Candidato 2000079 «VENDA TIPO CAMBRIC X 10 CM». Denominación: 100% del nombre del inventario explicado por el texto de SAP y 100% a la inversa. Atributos verificados: longitud. Sin contradicción en ningún atributo. | N117: Pendiente de valorización | O117: 153.82973 | P117: =IF(O117="","",O117*MAX(I117,J117)) | Q117: Pendiente | R117: Sin decidir
A118: 362 | B118: Neuquén | C118: Descartable | D118: 2000528 | E118: VENDA TIPO CAMBRIC X 15 CM | F118: 381 | G118: VENDA CAMBRIC 15 CM | H118: longitud 15 cm | I118: 10 | J118: 788 | K118: longitud | L118: Alta | M118: Candidato 2000528 «VENDA TIPO CAMBRIC X 15 CM». Denominación: 100% del nombre del inventario explicado por el texto de SAP y 100% a la inversa. Atributos verificados: longitud. Sin contradicción en ningún atributo. | N118: Pendiente de valorización | O118: 410.94152 | P118: =IF(O118="","",O118*MAX(I118,J118)) | Q118: Pendiente | R118: Sin decidir
A119: 364 | B119: Neuquén | C119: Descartable | D119: 2002475 | E119: VENDAS TIPO CAMBRIC - 7CM | F119: 339 | G119: VENDA CAMBRIC 7CM | H119: longitud 7 cm | I119: 35 | J119: 0 | K119: longitud | L119: Alta | M119: Candidato 2002475 «VENDAS TIPO CAMBRIC - 7CM». Denominación: 95% del nombre del inventario explicado por el texto de SAP y 94% a la inversa. Atributos verificados: longitud. Sin contradicción en ningún atributo. | N119: Pendiente de valorización | O119: 319.65818 | P119: =IF(O119="","",O119*MAX(I119,J119)) | Q119: Pendiente | R119: Sin decidir
A120: 365 | B120: Neuquén | C120: Medicamento | D120: 1000304 | E120: ADENOSINA 2 ML AMP 3 MG/1 ML | F120: 311 | G120: ADENOSINA AMP | H120: forma ampolla | I120: 0 | J120: 1116 | K120: forma farmacéutica | L120: Alta | M120: Candidato 1000304 «ADENOSINA 2 ML AMP 3 MG/1 ML». Denominación: 100% del nombre del inventario explicado por el texto de SAP y 100% a la inversa. Atributos verificados: forma farmacéutica. Sin contradicción en ningún atributo. | N120: Pendiente de valorización | O120: 1497.545 | P120: =IF(O120="","",O120*MAX(I120,J120)) | Q120: Pendiente | R120: Sin decidir
A121: 366 | B121: Neuquén | C121: Medicamento | D121: 1000330 | E121: ANGINOTRAC COMPRIMIDO | F121: 271 | G121: ANGINOTRAT | I121: 0 | J121: 854 | L121: Media | M121: Candidato 1000330 «ANGINOTRAC COMPRIMIDO». Denominación: 90% del nombre del inventario explicado por el texto de SAP y 90% a la inversa. Sin contradicción en ningún atributo. | N121: Pendiente de valorización | O121: 758.19294 | P121: =IF(O121="","",O121*MAX(I121,J121)) | Q121: Pendiente | R121: Sin decidir
A122: 367 | B122: Neuquén | C122: Medicamento | D122: 1005233 | E122: ATENOLOL 50MG X 10COMP | F122: 313 | 314 | G122: ATENOLOL 50 MG COMP | H122: concentración 50 mg · forma comprimido | I122: 0 | J122: 0 | K122: concentración, forma farmacéutica | L122: Alta | M122: Candidato 1005233 «ATENOLOL 50MG X 10COMP». Denominación: 100% del nombre del inventario explicado por el texto de SAP y 48% a la inversa. Atributos verificados: concentración, forma farmacéutica. Sin contradicción en ningún atributo. | N122: Pendiente de valorización | O122: 800.31586 | P122: =IF(O122="","",O122*MAX(I122,J122)) | Q122: Pendiente | R122: Sin decidir
A123: 369 | B123: Neuquén | C123: Medicamento | D123: 1000169 | E123: BUSCAPINA COMPUESTA AMP | F123: 317 | G123: BUSCAPINA COMPUESTA | I123: 0 | J123: 92 | L123: Alta | M123: Candidato 1000169 «BUSCAPINA COMPUESTA AMP». Denominación: 100% del nombre del inventario explicado por el texto de SAP y 100% a la inversa. Sin contradicción en ningún atributo. | N123: Pendiente de valorización | O123: 6889.4986 | P123: =IF(O123="","",O123*MAX(I123,J123)) | Q123: Pendiente | R123: Sin decidir
A124: 372 | B124: Neuquén | C124: Medicamento | D124: 1005103 | E124: CLONAZEPAM 2MG COMPRIMIDO | F124: 532 | G124: CLONAZEPAM 2 MG | H124: concentración 2 mg | I124: 0 | J124: 0 | K124: concentración | L124: Alta | M124: Candidato 1005103 «CLONAZEPAM 2MG COMPRIMIDO». Denominación: 100% del nombre del inventario explicado por el texto de SAP y 100% a la inversa. Atributos verificados: concentración. Sin contradicción en ningún atributo. | N124: Pendiente de valorización | O124: 31.36 | P124: =IF(O124="","",O124*MAX(I124,J124)) | Q124: Pendiente | R124: Sin decidir
A125: 374 | B125: Neuquén | C125: Medicamento | D125: 1000444 | E125: DELTISONA 4MG COMPRIMIDOS | F125: 476 | G125: DELTISONA B 4 mg | H125: concentración 4 mg | I125: 0 | J125: 30 | K125: concentración | L125: Alta | M125: Candidato 1000444 «DELTISONA 4MG COMPRIMIDOS». Denominación: 100% del nombre del inventario explicado por el texto de SAP y 100% a la inversa. Atributos verificados: concentración. Sin contradicción en ningún atributo. | N125: Pendiente de valorización | O125: 9540 | P125: =IF(O125="","",O125*MAX(I125,J125)) | Q125: Pendiente | R125: Sin decidir
A126: 377 | B126: Neuquén | C126: Medicamento | D126: 1000234 | E126: GLUCOSADO HIPERTÓNICO 50% AMPOLLA | F126: 123 | G126: GLUCOSADO HIPERTONICO AMP | H126: forma ampolla | I126: 0 | J126: 100 | K126: forma farmacéutica | L126: Alta | M126: Candidato 1000234 «GLUCOSADO HIPERTÓNICO 50% AMPOLLA». Denominación: 100% del nombre del inventario explicado por el texto de SAP y 100% a la inversa. Atributos verificados: forma farmacéutica. Sin contradicción en ningún atributo. | N126: Pendiente de valorización | O126: 940 | P126: =IF(O126="","",O126*MAX(I126,J126)) | Q126: Pendiente | R126: Sin decidir
A127: 378 | B127: Neuquén | C127: Medicamento | D127: 1000615 | E127: GOTAS OFTALMICAS CON GLICERINA | F127: 125 | G127: GOTAS OFTÁLMICAS (TOBRA + DEXA) | H127: forma gotas | I127: 0 | J127: 100 | K127: forma farmacéutica | L127: Media | M127: Candidato 1000615 «GOTAS OFTALMICAS CON GLICERINA». Denominación: 100% del nombre del inventario explicado por el texto de SAP y 50% a la inversa. Atributos verificados: forma farmacéutica. Sin contradicción en ningún atributo. | N127: Pendiente de valorización | O127: 839.39 | P127: =IF(O127="","",O127*MAX(I127,J127)) | Q127: Pendiente | R127: Sin decidir
A128: 380 | B128: Neuquén | C128: Descartable | D128: 2000456 | E128: HOJA DE BISTURI Nº 15 | F128: 475 | G128: HOJA DE BISTURI Nº15 | H128: calibre N° 15 | I128: 0 | J128: 1 | K128: calibre | L128: Alta | M128: Candidato 2000456 «HOJA DE BISTURI Nº 15». Denominación: 100% del nombre del inventario explicado por el texto de SAP y 100% a la inversa. Atributos verificados: calibre. Sin contradicción en ningún atributo. | N128: Pendiente de valorización | O128: 64.45 | P128: =IF(O128="","",O128*MAX(I128,J128)) | Q128: Pendiente | R128: Sin decidir
A129: 383 | B129: Neuquén | C129: Medicamento | D129: 1000495 | E129: LIDOCAINA AL 2% SIN EPINEFRINA 5 ML | F129: 150 | G129: LIDOCAINA 2 % SIN EPINEFRINA X 5 ML | H129: concentración 2% · volumen 5 ml | I129: 0 | J129: 0 | K129: concentración, volumen / presentación | L129: Alta | M129: Candidato 1000495 «LIDOCAINA AL 2% SIN EPINEFRINA 5 ML». Denominación: 100% del nombre del inventario explicado por el texto de SAP y 100% a la inversa. Atributos verificados: concentración, volumen / presentación. Sin contradicción en ningún atributo. | N129: Pendiente de valorización | O129: 527.05882 | P129: =IF(O129="","",O129*MAX(I129,J129)) | Q129: Pendiente | R129: Sin decidir
A130: 387 | B130: Neuquén | C130: Descartable | D130: 2000398 | E130: MASCARA LARINGEA Nº 5 | F130: 284 | G130: Mascara laringea N° 5 | H130: calibre N° 5 | I130: 0 | J130: 77 | K130: calibre | L130: Alta | M130: Candidato 2000398 «MASCARA LARINGEA Nº 5». Denominación: 100% del nombre del inventario explicado por el texto de SAP y 100% a la inversa. Atributos verificados: calibre. Sin contradicción en ningún atributo. | N130: Pendiente de valorización | O130: 5345.2104 | P130: =IF(O130="","",O130*MAX(I130,J130)) | Q130: Pendiente | R130: Sin decidir
A131: 388 | B131: Neuquén | C131: Descartable | D131: 2000397 | E131: MASCARA LARINGEA Nº 4 | F131: 283 | G131: Mascara laringea n°4 | H131: calibre N° 4 | I131: 0 | J131: 167 | K131: calibre | L131: Alta | M131: Candidato 2000397 «MASCARA LARINGEA Nº 4». Denominación: 100% del nombre del inventario explicado por el texto de SAP y 100% a la inversa. Atributos verificados: calibre. Sin contradicción en ningún atributo. | N131: Pendiente de valorización | O131: 7833.2036 | P131: =IF(O131="","",O131*MAX(I131,J131)) | Q131: Pendiente | R131: Sin decidir
A132: 390 | B132: Neuquén | C132: Medicamento | D132: 1000104 | E132: NALBUFINA 10MG/1ML AMPOLLA | F132: 272 | G132: NALBUFINA AMP | H132: forma ampolla | I132: 0 | J132: 1375 | K132: forma farmacéutica | L132: Alta | M132: Candidato 1000104 «NALBUFINA 10MG/1ML AMPOLLA». Denominación: 100% del nombre del inventario explicado por el texto de SAP y 100% a la inversa. Atributos verificados: forma farmacéutica. Sin contradicción en ningún atributo. | N132: Pendiente de valorización | O132: 358.51948 | P132: =IF(O132="","",O132*MAX(I132,J132)) | Q132: Pendiente | R132: Sin decidir
A133: 391 | B133: Neuquén | C133: Descartable | D133: 2001219 | E133: OXIMETRO DE PULSO | F133: 393 | G133: OXIMETRO DE PULSO | I133: 0 | J133: 90 | L133: Alta | M133: Candidato 2001219 «OXIMETRO DE PULSO». Denominación: 100% del nombre del inventario explicado por el texto de SAP y 100% a la inversa. Sin contradicción en ningún atributo. | N133: Pendiente de valorización | O133: 9369.1598 | P133: =IF(O133="","",O133*MAX(I133,J133)) | Q133: Pendiente | R133: Sin decidir
...

Sheet B Propuestas de alta
A1: Materiales físicos sin correspondencia en SAP
A2: PROPUESTA de alta, sujeta a revisión y aprobación. No ejecuta nada en SAP.
A4: Nº | B4: Base | C4: Tipo | D4: Código SAP | E4: Descripción en SAP | F4: Código inventario físico | G4: Nomenclatura del inventario físico | H4: Presentación | I4: Cantidad física · UNIDADES | J4: Stock SAP · UNIDADES | K4: Atributos verificados | L4: Confianza | M4: Justificación | N4: Estado de valorización | O4: VU de referencia SAP · $ | P4: Valor de referencia SAP · $ | Q4: Estado de revisión | R4: Decisión registrada | S4: Revisor | T4: Observaciones
A5: 33 | B5: San Juan | C5: Descartable | F5: DESC35 | G5: Canula de Yankauer T/K 67 | H5: modelo K67 | I5: 6 | J5: 0 | M5: No se encontró en SAP ningún material cuya denominación y presentación se correspondan con este ítem. | N5: Pendiente de valorización | P5: =IF(O5="","",O5*MAX(I5,J5)) | Q5: Pendiente | R5: Sin decidir
A6: 38 | B6: San Juan | C6: Descartable | F6: DESC43 | G6: Cintas de aproximacion tipo SteriStrip (3 mm x 7,5 cm) | H6: longitud 0,3 cm, 7,5 cm | I6: 2 | J6: 0 | M6: No se encontró en SAP ningún material cuya denominación y presentación se correspondan con este ítem. | N6: Pendiente de valorización | P6: =IF(O6="","",O6*MAX(I6,J6)) | Q6: Pendiente | R6: Sin decidir
A7: 39 | B7: San Juan | C7: Descartable | F7: DESC44 | G7: Cintas de aproximacion tipo SteriStrip (6 mm x 10 cm) | H7: longitud 0,6 cm, 10 cm | I7: 12 | J7: 0 | M7: No se encontró en SAP ningún material cuya denominación y presentación se correspondan con este ítem. | N7: Pendiente de valorización | P7: =IF(O7="","",O7*MAX(I7,J7)) | Q7: Pendiente | R7: Sin decidir
A8: 60 | B8: San Juan | C8: Medicamento | F8: MED78 | G8: Famotidina Comp x 20 mg | H8: concentración 20 mg · forma comprimido | I8: 70 | J8: 0 | M8: No se encontró en SAP ningún material cuya denominación y presentación se correspondan con este ítem. | N8: Pendiente de valorización | P8: =IF(O8="","",O8*MAX(I8,J8)) | Q8: Pendiente | R8: Sin decidir
A9: 63 | B9: San Juan | C9: Descartable | F9: DESC61 | G9: Filtro para ventilación artificial | I9: 2 | J9: 0 | M9: No se encontró en SAP ningún material cuya denominación y presentación se correspondan con este ítem. | N9: Pendiente de valorización | P9: =IF(O9="","",O9*MAX(I9,J9)) | Q9: Pendiente | R9: Sin decidir
A10: 65 | B10: San Juan | C10: Medicamento | F10: MED85 | G10: Fluticasona 250 mcg/dosis Aerosol | H10: concentración 0,25 mg/1 dosis · forma aerosol | I10: 1 | J10: 0 | M10: No se encontró en SAP ningún material cuya denominación y presentación se correspondan con este ítem. | N10: Pendiente de valorización | P10: =IF(O10="","",O10*MAX(I10,J10)) | Q10: Pendiente | R10: Sin decidir
A11: 66 | B11: San Juan | C11: Medicamento | F11: MED84 | G11: Fluticasona Spray | H11: forma aerosol | I11: 31 | J11: 0 | M11: No se encontró en SAP ningún material cuya denominación y presentación se correspondan con este ítem. | N11: Pendiente de valorización | P11: =IF(O11="","",O11*MAX(I11,J11)) | Q11: Pendiente | R11: Sin decidir
A12: 67 | B12: San Juan | C12: Descartable | F12: DESC283 | G12: Frasco de Drenaje Pleural | H12: forma frasco | I12: 5 | J12: 0 | M12: No se encontró en SAP ningún material cuya denominación y presentación se correspondan con este ítem. | N12: Pendiente de valorización | P12: =IF(O12="","",O12*MAX(I12,J12)) | Q12: Pendiente | R12: Sin decidir
A13: 70 | B13: San Juan | C13: Descartable | F13: DESC64 | G13: Gasas 10 x 10 cm | H13: medidas 10 × 10 | I13: 281 | J13: 0 | M13: No se encontró en SAP ningún material cuya denominación y presentación se correspondan con este ítem. | N13: Pendiente de valorización | P13: =IF(O13="","",O13*MAX(I13,J13)) | Q13: Pendiente | R13: Sin decidir
A14: 84 | B14: San Juan | C14: Medicamento | F14: MED108 | G14: Jarabe (Ambroxol - Clorhidrato) 120 ml | H14: forma jarabe · volumen 120 ml | I14: 34 | J14: 0 | M14: No se encontró en SAP ningún material cuya denominación y presentación se correspondan con este ítem. | N14: Pendiente de valorización | P14: =IF(O14="","",O14*MAX(I14,J14)) | Q14: Pendiente | R14: Sin decidir
A15: 101 | B15: San Juan | C15: Descartable | F15: DESC284 | G15: Martillo para Reflejo Neurológico | I15: 3 | J15: 0 | M15: No se encontró en SAP ningún material cuya denominación y presentación se correspondan con este ítem. | N15: Pendiente de valorización | P15: =IF(O15="","",O15*MAX(I15,J15)) | Q15: Pendiente | R15: Sin decidir
A16: 117 | B16: San Juan | C16: Descartable | F16: DESC99 | G16: Pilas C2 | I16: 4 | J16: 0 | M16: No se encontró en SAP ningún material cuya denominación y presentación se correspondan con este ítem. | N16: Pendiente de valorización | P16: =IF(O16="","",O16*MAX(I16,J16)) | Q16: Pendiente | R16: Sin decidir
A17: 118 | B17: San Juan | C17: Descartable | F17: DESC287 | G17: Pilas CR2032 3V | H17: cantidad sin unidad 3 | I17: 13 | J17: 0 | M17: No se encontró en SAP ningún material cuya denominación y presentación se correspondan con este ítem. | N17: Pendiente de valorización | P17: =IF(O17="","",O17*MAX(I17,J17)) | Q17: Pendiente | R17: Sin decidir
A18: 129 | B18: San Juan | C18: Descartable | F18: DESC113 | G18: Saturómetro | I18: 4 | J18: 0 | M18: No se encontró en SAP ningún material cuya denominación y presentación se correspondan con este ítem. | N18: Pendiente de valorización | P18: =IF(O18="","",O18*MAX(I18,J18)) | Q18: Pendiente | R18: Sin decidir
A19: 145 | B19: San Juan | C19: Descartable | F19: DESC125 | G19: Sutura Prolene 4-0 | H19: cantidad sin unidad 4 | I19: 7 | J19: 0 | M19: No se encontró en SAP ningún material cuya denominación y presentación se correspondan con este ítem. | N19: Pendiente de valorización | P19: =IF(O19="","",O19*MAX(I19,J19)) | Q19: Pendiente | R19: Sin decidir
A20: 146 | B20: San Juan | C20: Descartable | F20: DESC126 | G20: Sutura Prolene 5-0 | H20: cantidad sin unidad 5 | I20: 1 | J20: 0 | M20: No se encontró en SAP ningún material cuya denominación y presentación se correspondan con este ítem. | N20: Pendiente de valorización | P20: =IF(O20="","",O20*MAX(I20,J20)) | Q20: Pendiente | R20: Sin decidir
A21: 165 | B21: Neuquén | C21: Descartable | F21: 264 | G21: Abocath n° 14 | H21: calibre 14 | I21: 94 | J21: 0 | M21: No se encontró en SAP ningún material cuya denominación y presentación se correspondan con este ítem. | N21: Pendiente de valorización | P21: =IF(O21="","",O21*MAX(I21,J21)) | Q21: Pendiente | R21: Sin decidir
A22: 166 | B22: Neuquén | C22: Descartable | F22: 268 | G22: Abocath n° 16 | H22: calibre 16 | I22: 241 | J22: 0 | M22: No se encontró en SAP ningún material cuya denominación y presentación se correspondan con este ítem. | N22: Pendiente de valorización | P22: =IF(O22="","",O22*MAX(I22,J22)) | Q22: Pendiente | R22: Sin decidir
A23: 167 | B23: Neuquén | C23: Descartable | F23: 265 | G23: Abocath n° 18 | H23: calibre 18 | I23: 141 | J23: 0 | M23: No se encontró en SAP ningún material cuya denominación y presentación se correspondan con este ítem. | N23: Pendiente de valorización | P23: =IF(O23="","",O23*MAX(I23,J23)) | Q23: Pendiente | R23: Sin decidir
A24: 168 | B24: Neuquén | C24: Descartable | F24: 266 | G24: Abocath n° 20 | H24: calibre 20 | I24: 182 | J24: 0 | M24: No se encontró en SAP ningún material cuya denominación y presentación se correspondan con este ítem. | N24: Pendiente de valorización | P24: =IF(O24="","",O24*MAX(I24,J24)) | Q24: Pendiente | R24: Sin decidir
A25: 181 | B25: Neuquén | C25: Descartable | F25: 379 | G25: AMBU | I25: 11 | J25: 0 | M25: No se encontró en SAP ningún material cuya denominación y presentación se correspondan con este ítem. | N25: Pendiente de valorización | P25: =IF(O25="","",O25*MAX(I25,J25)) | Q25: Pendiente | R25: Sin decidir
A26: 193 | B26: Neuquén | C26: Descartable | F26: 351 | G26: baja lenguas | I26: 1700 | J26: 0 | M26: No se encontró en SAP ningún material cuya denominación y presentación se correspondan con este ítem. | N26: Pendiente de valorización | P26: =IF(O26="","",O26*MAX(I26,J26)) | Q26: Pendiente | R26: Sin decidir
A27: 195 | B27: Neuquén | C27: Descartable | F27: 343 | G27: BARBIJOS N95 | I27: 220 | J27: 0 | M27: No se encontró en SAP ningún material cuya denominación y presentación se correspondan con este ítem. | N27: Pendiente de valorización | P27: =IF(O27="","",O27*MAX(I27,J27)) | Q27: Pendiente | R27: Sin decidir
A28: 212 | B28: Neuquén | C28: Descartable | F28: 289 | G28: Cinta adhesiva traspore | I28: 264 | J28: 0 | M28: No se encontró en SAP ningún material cuya denominación y presentación se correspondan con este ítem. | N28: Pendiente de valorización | P28: =IF(O28="","",O28*MAX(I28,J28)) | Q28: Pendiente | R28: Sin decidir
A29: 218 | B29: Neuquén | C29: Descartable | F29: 509 | G29: COLLAR FILADELFIA AJUSTABLE | I29: 5 | J29: 0 | M29: No se encontró en SAP ningún material cuya denominación y presentación se correspondan con este ítem. | N29: Pendiente de valorización | P29: =IF(O29="","",O29*MAX(I29,J29)) | Q29: Pendiente | R29: Sin decidir
A30: 225 | B30: Neuquén | C30: Descartable | F30: 361 | G30: DESCARTADOR CORTOPUNZANTES 4,5 LTS 4,5 LTS | H30: volumen 4500 ml | I30: 15 | J30: 0 | M30: No se encontró en SAP ningún material cuya denominación y presentación se correspondan con este ítem. | N30: Pendiente de valorización | P30: =IF(O30="","",O30*MAX(I30,J30)) | Q30: Pendiente | R30: Sin decidir
A31: 226 | B31: Neuquén | C31: Descartable | F31: 360 | G31: DESCARTADOR CORTOPUZANTES 7 LTS LTS | H31: volumen 7000 ml | I31: 1 | J31: 0 | M31: No se encontró en SAP ningún material cuya denominación y presentación se correspondan con este ítem. | N31: Pendiente de valorización | P31: =IF(O31="","",O31*MAX(I31,J31)) | Q31: Pendiente | R31: Sin decidir
A32: 287 | B32: Neuquén | C32: Descartable | F32: 531 | G32: MANGO DE BISTURI N° 3 | H32: calibre N° 3 | I32: 10 | J32: 0 | M32: No se encontró en SAP ningún material cuya denominación y presentación se correspondan con este ítem. | N32: Pendiente de valorización | P32: =IF(O32="","",O32*MAX(I32,J32)) | Q32: Pendiente | R32: Sin decidir
A33: 288 | B33: Neuquén | C33: Descartable | F33: 532 | G33: MANGO DE BISTURI N° 4 | H33: calibre N° 4 | I33: 13 | J33: 0 | M33: No se encontró en SAP ningún material cuya denominación y presentación se correspondan con este ítem. | N33: Pendiente de valorización | P33: =IF(O33="","",O33*MAX(I33,J33)) | Q33: Pendiente | R33: Sin decidir
A34: 289 | B34: Neuquén | C34: Descartable | F34: 536 | G34: MARTILLO | I34: 4 | J34: 0 | M34: No se encontró en SAP ningún material cuya denominación y presentación se correspondan con este ítem. | N34: Pendiente de valorización | P34: =IF(O34="","",O34*MAX(I34,J34)) | Q34: Pendiente | R34: Sin decidir
A35: 306 | B35: Neuquén | C35: Medicamento | F35: 368 | G35: OTOLEF HC GOTAS OTICAS | H35: forma gotas | I35: 22 | J35: 0 | M35: No se encontró en SAP ningún material cuya denominación y presentación se correspondan con este ítem. | N35: Pendiente de valorización | P35: =IF(O35="","",O35*MAX(I35,J35)) | Q35: Pendiente | R35: Sin decidir
A36: 309 | B36: Neuquén | C36: Descartable | F36: 392 | G36: PAPAGAYO | I36: 9 | J36: 0 | M36: No se encontró en SAP ningún material cuya denominación y presentación se correspondan con este ítem. | N36: Pendiente de valorización | P36: =IF(O36="","",O36*MAX(I36,J36)) | Q36: Pendiente | R36: Sin decidir
A37: 314 | B37: Neuquén | C37: Descartable | F37: 247 | G37: Pilas 2032 | H37: cantidad sin unidad 2032 | I37: 88 | J37: 0 | M37: No se encontró en SAP ningún material cuya denominación y presentación se correspondan con este ítem. | N37: Pendiente de valorización | P37: =IF(O37="","",O37*MAX(I37,J37)) | Q37: Pendiente | R37: Sin decidir
A38: 315 | B38: Neuquén | C38: Descartable | F38: 503 | G38: PILAS 9V | H38: cantidad sin unidad 9 | I38: 152 | J38: 0 | M38: No se encontró en SAP ningún material cuya denominación y presentación se correspondan con este ítem. | N38: Pendiente de valorización | P38: =IF(O38="","",O38*MAX(I38,J38)) | Q38: Pendiente | R38: Sin decidir
A39: 316 | B39: Neuquén | C39: Descartable | F39: 505 | G39: PILAS A76 | I39: 41 | J39: 0 | M39: No se encontró en SAP ningún material cuya denominación y presentación se correspondan con este ítem. | N39: Pendiente de valorización | P39: =IF(O39="","",O39*MAX(I39,J39)) | Q39: Pendiente | R39: Sin decidir
A40: 317 | B40: Neuquén | C40: Descartable | F40: 260 | G40: Pilas AA | I40: 3 | J40: 0 | M40: No se encontró en SAP ningún material cuya denominación y presentación se correspondan con este ítem. | N40: Pendiente de valorización | P40: =IF(O40="","",O40*MAX(I40,J40)) | Q40: Pendiente | R40: Sin decidir
A41: 319 | B41: Neuquén | C41: Descartable | F41: 504 | G41: PILAS LR41 | I41: 87 | J41: 0 | M41: No se encontró en SAP ningún material cuya denominación y presentación se correspondan con este ítem. | N41: Pendiente de valorización | P41: =IF(O41="","",O41*MAX(I41,J41)) | Q41: Pendiente | R41: Sin decidir
A42: 331 | B42: Neuquén | C42: Descartable | F42: 530 | G42: SATUROMETRO | I42: 9 | J42: 0 | M42: No se encontró en SAP ningún material cuya denominación y presentación se correspondan con este ítem. | N42: Pendiente de valorización | P42: =IF(O42="","",O42*MAX(I42,J42)) | Q42: Pendiente | R42: Sin decidir
A43: 360 | B43: Neuquén | C43: Descartable | F43: 344 | G43: TUBOS ENDOTRAQUEAL 8 | H43: cantidad sin unidad 8 | I43: 47 | J43: 0 | M43: No se encontró en SAP ningún material cuya denominación y presentación se correspondan con este ítem. | N43: Pendiente de valorización | P43: =IF(O43="","",O43*MAX(I43,J43)) | Q43: Pendiente | R43: Sin decidir
A44: 398 | B44: Neuquén | C44: Descartable | F44: 536 | G44: SUT.CUTANEA | I44: 0 | J44: 0 | M44: No se encontró en SAP ningún material cuya denominación y presentación se correspondan con este ítem. | N44: Pendiente de valorización | P44: =IF(O44="","",O44*MAX(I44,J44)) | Q44: Pendiente | R44: Sin decidir
A45: 437 | B45: Salta | C45: Medicamento | F45: 30 | G45: Alprazolam comprimidos 0,5 mg | H45: concentración 0,5 mg · forma comprimido | I45: 15 | J45: 0 | M45: No se encontró en SAP ningún material cuya denominación y presentación se correspondan con este ítem. | N45: Pendiente de valorización | P45: =IF(O45="","",O45*MAX(I45,J45)) | Q45: Pendiente | R45: Sin decidir
A46: 474 | B46: Salta | C46: Descartable | F46: 57 | G46: Canula Yankauer con tubo de conexion | I46: 4 | J46: 0 | M46: No se encontró en SAP ningún material cuya denominación y presentación se correspondan con este ítem. | N46: Pendiente de valorización | P46: =IF(O46="","",O46*MAX(I46,J46)) | Q46: Pendiente | R46: Sin decidir
A47: 480 | B47: Salta | C47: Descartable | F47: 67 | G47: Cinta Hipoalergénica 1,25cmx9m | I47: 9 | J47: 0 | M47: No se encontró en SAP ningún material cuya denominación y presentación se correspondan con este ítem. | N47: Pendiente de valorización | P47: =IF(O47="","",O47*MAX(I47,J47)) | Q47: Pendiente | R47: Sin decidir
A48: 481 | B48: Salta | C48: Descartable | F48: 68 | G48: Cinta Hipoalergénica 2,5cmx9m | I48: 87 | J48: 0 | M48: No se encontró en SAP ningún material cuya denominación y presentación se correspondan con este ítem. | N48: Pendiente de valorización | P48: =IF(O48="","",O48*MAX(I48,J48)) | Q48: Pendiente | R48: Sin decidir
A49: 482 | B49: Salta | C49: Descartable | F49: 69 | G49: Cinta Hipoalergénica 5cmx9m | H49: cantidad sin unidad 5 | I49: 6 | J49: 0 | M49: No se encontró en SAP ningún material cuya denominación y presentación se correspondan con este ítem. | N49: Pendiente de valorización | P49: =IF(O49="","",O49*MAX(I49,J49)) | Q49: Pendiente | R49: Sin decidir
A50: 505 | B50: Salta | C50: Medicamento | F50: 86 | G50: Crema de Bismuto susp. x90ml | H50: forma crema · volumen 90 ml | I50: 19 | J50: 0 | M50: No se encontró en SAP ningún material cuya denominación y presentación se correspondan con este ítem. | N50: Pendiente de valorización | P50: =IF(O50="","",O50*MAX(I50,J50)) | Q50: Pendiente | R50: Sin decidir
A51: 506 | B51: Salta | C51: Medicamento | F51: 87 | G51: Crema dermica Miclogen Antimicotico pomo 20gr | H51: concentración 20 g · forma crema | I51: 46 | J51: 0 | M51: No se encontró en SAP ningún material cuya denominación y presentación se correspondan con este ítem. | N51: Pendiente de valorización | P51: =IF(O51="","",O51*MAX(I51,J51)) | Q51: Pendiente | R51: Sin decidir
A52: 508 | B52: Salta | C52: Descartable | F52: 89 | G52: Descongestivo PC | I52: 7 | J52: 0 | M52: No se encontró en SAP ningún material cuya denominación y presentación se correspondan con este ítem. | N52: Pendiente de valorización | P52: =IF(O52="","",O52*MAX(I52,J52)) | Q52: Pendiente | R52: Sin decidir
A53: 531 | B53: Salta | C53: Medicamento | F53: 119 | G53: Famotidina Comprimidos x 20mg | H53: concentración 20 mg · forma comprimido | I53: 90 | J53: 0 | M53: No se encontró en SAP ningún material cuya denominación y presentación se correspondan con este ítem. | N53: Pendiente de valorización | P53: =IF(O53="","",O53*MAX(I53,J53)) | Q53: Pendiente | R53: Sin decidir
A54: 535 | B54: Salta | C54: Medicamento | F54: 124 | G54: Fluticasona Azelastina spray nasal 12ml/12,36g 120 dosis | H54: concentración 12,36 g · forma aerosol · volumen 12 ml · calibre 36G · cantidad sin unidad 120 | I54: 21 | J54: 0 | M54: No se encontró en SAP ningún material cuya denominación y presentación se correspondan con este ítem. | N54: Pendiente de valorización | P54: =IF(O54="","",O54*MAX(I54,J54)) | Q54: Pendiente | R54: Sin decidir
A55: 538 | B55: Salta | C55: Descartable | F55: 274 | G55: Gafas transparentes | I55: 2 | J55: 0 | M55: No se encontró en SAP ningún material cuya denominación y presentación se correspondan con este ítem. | N55: Pendiente de valorización | P55: =IF(O55="","",O55*MAX(I55,J55)) | Q55: Pendiente | R55: Sin decidir
A56: 540 | B56: Salta | C56: Descartable | F56: 129 | G56: Gasas 10 x 10 | H56: medidas 10 × 10 | I56: 832 | J56: 0 | M56: No se encontró en SAP ningún material cuya denominación y presentación se correspondan con este ítem. | N56: Pendiente de valorización | P56: =IF(O56="","",O56*MAX(I56,J56)) | Q56: Pendiente | R56: Sin decidir
A57: 591 | B57: Salta | C57: Descartable | F57: 179 | G57: Manometro para tubo ultraliviano | I57: 5 | J57: 0 | M57: No se encontró en SAP ningún material cuya denominación y presentación se correspondan con este ítem. | N57: Pendiente de valorización | P57: =IF(O57="","",O57*MAX(I57,J57)) | Q57: Pendiente | R57: Sin decidir
A58: 622 | B58: Salta | C58: Descartable | F58: 201 | G58: Pervinox 1 lt | H58: volumen 1000 ml | I58: 8 | J58: 0 | M58: No se encontró en SAP ningún material cuya denominación y presentación se correspondan con este ítem. | N58: Pendiente de valorización | P58: =IF(O58="","",O58*MAX(I58,J58)) | Q58: Pendiente | R58: Sin decidir
A59: 623 | B59: Salta | C59: Descartable | F59: 202 | G59: Pervinox 100 ml | H59: volumen 100 ml | I59: 54 | J59: 0 | M59: No se encontró en SAP ningún material cuya denominación y presentación se correspondan con este ítem. | N59: Pendiente de valorización | P59: =IF(O59="","",O59*MAX(I59,J59)) | Q59: Pendiente | R59: Sin decidir
A60: 633 | B60: Salta | C60: Medicamento | F60: 210 | G60: Rosuvastatina Comprimidos x 40mg | H60: concentración 40 mg · forma comprimido | I60: 10 | J60: 0 | M60: No se encontró en SAP ningún material cuya denominación y presentación se correspondan con este ítem. | N60: Pendiente de valorización | P60: =IF(O60="","",O60*MAX(I60,J60)) | Q60: Pendiente | R60: Sin decidir
A61: 635 | B61: Salta | C61: Medicamento | F61: 213 | G61: Salbutamol 100 mcg Inhal. Aer. x 200 Dosis + aplic. | H61: concentración 0,1 mg · forma aerosol · cantidad sin unidad 200 | I61: 19 | J61: 0 | M61: No se encontró en SAP ningún material cuya denominación y presentación se correspondan con este ítem. | N61: Pendiente de valorización | P61: =IF(O61="","",O61*MAX(I61,J61)) | Q61: Pendiente | R61: Sin decidir
A62: 687 | B62: Salta | C62: Medicamento | F62: 251 | G62: Vitamina K 1amp=10mlx10mg | H62: concentración 10 mg · forma ampolla · modelo K1 · cantidad sin unidad 10 | I62: 10 | J62: 0 | M62: No se encontró en SAP ningún material cuya denominación y presentación se correspondan con este ítem. | N62: Pendiente de valorización | P62: =IF(O62="","",O62*MAX(I62,J62)) | Q62: Pendiente | R62: Sin decidir
A63: TOTAL | I63: =SUBTOTAL(109,I5:I62) | J63: =SUBTOTAL(109,J5:J62) | P63: =SUBTOTAL(109,P5:P62)

Sheet C Propuestas de baja
A1: Materiales de SAP sin correspondencia física
A2: PROPUESTA de baja, sujeta a revisión y aprobación. No ejecuta nada en SAP. Provisional mientras queden casos en revisión.
A4: Nº | B4: Base | C4: Tipo | D4: Código SAP | E4: Descripción en SAP | F4: Código inventario físico | G4: Nomenclatura del inventario físico | H4: Presentación | I4: Cantidad física · UNIDADES | J4: Stock SAP · UNIDADES | K4: Atributos verificados | L4: Confianza | M4: Justificación | N4: Estado de valorización | O4: VU de referencia SAP · $ | P4: Valor de referencia SAP · $ | Q4: Estado de revisión | R4: Decisión registrada | S4: Revisor | T4: Observaciones
A5: 688 | B5: San Juan | C5: Descartable | D5: 2001555 | E5: SONDA T/K-27 | I5: 0 | J5: 4107 | M5: Ningún ítem del inventario físico de esta base se identificó con este material. Tampoco se identificó en las otras bases relevadas. Atención: aparece como posible equivalencia en un caso pendiente de revisión. Conviene resolver ese caso antes de proponer la baja. | N5: Pendiente de valorización | O5: 787.19267 | P5: =IF(O5="","",O5*MAX(I5,J5)) | Q5: Pendiente | R5: Sin decidir
A6: 689 | B6: San Juan | C6: Descartable | D6: 2000158 | E6: GUANTES DE EXAMINACIÓN TALLE M | I6: 0 | J6: 3090 | M6: Ningún ítem del inventario físico de esta base se identificó con este material. Tampoco se identificó en las otras bases relevadas. | N6: Pendiente de valorización | O6: 160.62188 | P6: =IF(O6="","",O6*MAX(I6,J6)) | Q6: Pendiente | R6: Sin decidir
A7: 690 | B7: Neuquén | C7: Descartable | D7: 2000158 | E7: GUANTES DE EXAMINACIÓN TALLE M | I7: 0 | J7: 83584 | M7: Ningún ítem del inventario físico de esta base se identificó con este material. Tampoco se identificó en las otras bases relevadas. | N7: Pendiente de valorización | O7: 33.319065 | P7: =IF(O7="","",O7*MAX(I7,J7)) | Q7: Pendiente | R7: Sin decidir
A8: 691 | B8: Salta | C8: Descartable | D8: 2000158 | E8: GUANTES DE EXAMINACIÓN TALLE M | I8: 0 | J8: 1 | M8: Ningún ítem del inventario físico de esta base se identificó con este material. Tampoco se identificó en las otras bases relevadas. | N8: Pendiente de valorización | O8: 5400 | P8: =IF(O8="","",O8*MAX(I8,J8)) | Q8: Pendiente | R8: Sin decidir
A9: 692 | B9: San Juan | C9: Descartable | D9: 2000363 | E9: MASCARA PARA O2 ADULTO CON RESERVORIO | I9: 0 | J9: 2912 | M9: Ningún ítem del inventario físico de esta base se identificó con este material. Tampoco se identificó en las otras bases relevadas. Atención: aparece como posible equivalencia en un caso pendiente de revisión. Conviene resolver ese caso antes de proponer la baja. | N9: Pendiente de valorización | O9: 1594.028 | P9: =IF(O9="","",O9*MAX(I9,J9)) | Q9: Pendiente | R9: Sin decidir
A10: 693 | B10: Neuquén | C10: Descartable | D10: 2000363 | E10: MASCARA PARA O2 ADULTO CON RESERVORIO | I10: 0 | J10: 1578 | M10: Ningún ítem del inventario físico de esta base se identificó con este material. Tampoco se identificó en las otras bases relevadas. Atención: aparece como posible equivalencia en un caso pendiente de revisión. Conviene resolver ese caso antes de proponer la baja. | N10: Pendiente de valorización | O10: 1368.8268 | P10: =IF(O10="","",O10*MAX(I10,J10)) | Q10: Pendiente | R10: Sin decidir
A11: 694 | B11: Salta | C11: Descartable | D11: 2000363 | E11: MASCARA PARA O2 ADULTO CON RESERVORIO | I11: 0 | J11: 200 | M11: Ningún ítem del inventario físico de esta base se identificó con este material. Tampoco se identificó en las otras bases relevadas. Atención: aparece como posible equivalencia en un caso pendiente de revisión. Conviene resolver ese caso antes de proponer la baja. | N11: Pendiente de valorización | O11: 1168.985 | P11: =IF(O11="","",O11*MAX(I11,J11)) | Q11: Pendiente | R11: Sin decidir
A12: 695 | B12: San Juan | C12: Descartable | D12: 2000011 | E12: BAJALENGUAS DE MADERA | I12: 0 | J12: 2636 | M12: Ningún ítem del inventario físico de esta base se identificó con este material. Tampoco se identificó en las otras bases relevadas. Atención: aparece como posible equivalencia en un caso pendiente de revisión. Conviene resolver ese caso antes de proponer la baja. | N12: Pendiente de valorización | O12: 33.512045 | P12: =IF(O12="","",O12*MAX(I12,J12)) | Q12: Pendiente | R12: Sin decidir
A13: 696 | B13: Neuquén | C13: Descartable | D13: 2000011 | E13: BAJALENGUAS DE MADERA | I13: 0 | J13: 11160 | M13: Ningún ítem del inventario físico de esta base se identificó con este material. Tampoco se identificó en las otras bases relevadas. | N13: Pendiente de valorización | O13: 15.933322 | P13: =IF(O13="","",O13*MAX(I13,J13)) | Q13: Pendiente | R13: Sin decidir
A14: 697 | B14: Salta | C14: Descartable | D14: 2000011 | E14: BAJALENGUAS DE MADERA | I14: 0 | J14: 1017 | M14: Ningún ítem del inventario físico de esta base se identificó con este material. Tampoco se identificó en las otras bases relevadas. Atención: aparece como posible equivalencia en un caso pendiente de revisión. Conviene resolver ese caso antes de proponer la baja. | N14: Pendiente de valorización | O14: 50.022006 | P14: =IF(O14="","",O14*MAX(I14,J14)) | Q14: Pendiente | R14: Sin decidir
A15: 698 | B15: Neuquén | C15: Descartable | D15: 2000270 | E15: GUANTES DE EXAMINACION TALLE S | I15: 0 | J15: 15007 | M15: Ningún ítem del inventario físico de esta base se identificó con este material. Sí está identificado en San Juan, así que el código está en uso: la baja sería sólo del stock de esta base, no del material. | N15: Pendiente de valorización | O15: 13.341774 | P15: =IF(O15="","",O15*MAX(I15,J15)) | Q15: Pendiente | R15: Sin decidir
A16: 699 | B16: Salta | C16: Descartable | D16: 2000270 | E16: GUANTES DE EXAMINACION TALLE S | I16: 0 | J16: 20 | M16: Ningún ítem del inventario físico de esta base se identificó con este material. Sí está identificado en San Juan, así que el código está en uso: la baja sería sólo del stock de esta base, no del material. | N16: Pendiente de valorización | O16: 4642.161 | P16: =IF(O16="","",O16*MAX(I16,J16)) | Q16: Pendiente | R16: Sin decidir
... A807: 1839 | B807: Salta | C807: Medicamento | D807: 1000009 | E807: DIFENHIDRAMINA 10MG AMPOLLA DE 1 ML(Park | I807: 0 | J807: 50 | M807: Ningún ítem del inventario físico de esta base se identificó con este material. Tampoco se identificó en las otras bases relevadas. | N807: Pendiente de valorización | O807: 717.0618 | P807: =IF(O807="","",O807*MAX(I807,J807)) | Q807: Pendiente | R807: Sin decidir
A808: 1840 | B808: Neuquén | C808: Medicamento | D808: 1000024 | E808: GASA FURACINADA AL 0.2% | I808: 0 | J808: 0 | M808: Ningún ítem del inventario físico de esta base se identificó con este material. Tampoco se identificó en las otras bases relevadas. | N808: Pendiente de valorización | P808: =IF(O808="","",O808*MAX(I808,J808)) | Q808: Pendiente | R808: Sin decidir
A809: 1841 | B809: Neuquén | C809: Medicamento | D809: 1000110 | E809: SOLUCION FISIOLOGICA DE 5ML AMPOLLA | I809: 0 | J809: 0 | M809: Ningún ítem del inventario físico de esta base se identificó con este material. Tampoco se identificó en las otras bases relevadas. | N809: Pendiente de valorización | P809: =IF(O809="","",O809*MAX(I809,J809)) | Q809: Pendiente | R809: Sin decidir
A810: 1842 | B810: Neuquén | C810: Medicamento | D810: 1000176 | E810: CURA PLUS COMPRIMIDO | I810: 0 | J810: 0 | M810: Ningún ítem del inventario físico de esta base se identificó con este material. Tampoco se identificó en las otras bases relevadas. | N810: Pendiente de valorización | P810: =IF(O810="","",O810*MAX(I810,J810)) | Q810: Pendiente | R810: Sin decidir
A811: 1843 | B811: Neuquén | C811: Medicamento | D811: 1000180 | E811: HISTAMINO CORTEROID L COMPRIMIDO | I811: 0 | J811: 0 | M811: Ningún ítem del inventario físico de esta base se identificó con este material. Tampoco se identificó en las otras bases relevadas. | N811: Pendiente de valorización | P811: =IF(O811="","",O811*MAX(I811,J811)) | Q811: Pendiente | R811: Sin decidir
A812: 1844 | B812: Neuquén | C812: Medicamento | D812: 1000186 | E812: XYLOPROCTO POMADA CREMA | I812: 0 | J812: 0 | M812: Ningún ítem del inventario físico de esta base se identificó con este material. Tampoco se identificó en las otras bases relevadas. | N812: Pendiente de valorización | P812: =IF(O812="","",O812*MAX(I812,J812)) | Q812: Pendiente | R812: Sin decidir
A813: 1845 | B813: Neuquén | C813: Medicamento | D813: 1000188 | E813: MYLANTA SUSPENSIÓN SOLUCION | I813: 0 | J813: 0 | M813: Ningún ítem del inventario físico de esta base se identificó con este material. Tampoco se identificó en las otras bases relevadas. | N813: Pendiente de valorización | P813: =IF(O813="","",O813*MAX(I813,J813)) | Q813: Pendiente | R813: Sin decidir
A814: 1846 | B814: Neuquén | C814: Medicamento | D814: 1000191 | E814: GOTAS LUBRICANTES GLICERINA 1% 10ML | I814: 0 | J814: 0 | M814: Ningún ítem del inventario físico de esta base se identificó con este material. Tampoco se identificó en las otras bases relevadas. | N814: Pendiente de valorización | P814: =IF(O814="","",O814*MAX(I814,J814)) | Q814: Pendiente | R814: Sin decidir
A815: 1847 | B815: Neuquén | C815: Medicamento | D815: 1000203 | E815: GLUCONATO DE CA +2 AMPOLLAS | I815: 0 | J815: 0 | M815: Ningún ítem del inventario físico de esta base se identificó con este material. Tampoco se identificó en las otras bases relevadas. | N815: Pendiente de valorización | P815: =IF(O815="","",O815*MAX(I815,J815)) | Q815: Pendiente | R815: Sin decidir
A816: 1848 | B816: Neuquén | C816: Medicamento | D816: 1000352 | E816: DICLOFENAC SÓDICO 75 mg (DIOXAFLEX 75) | I816: 0 | J816: 0 | M816: Ningún ítem del inventario físico de esta base se identificó con este material. Tampoco se identificó en las otras bases relevadas. | N816: Pendiente de valorización | P816: =IF(O816="","",O816*MAX(I816,J816)) | Q816: Pendiente | R816: Sin decidir
A817: 1849 | B817: Neuquén | C817: Descartable | D817: 2000017 | E817: ESTETOSCOPIO PEDIATRICO | I817: 0 | J817: 0 | M817: Ningún ítem del inventario físico de esta base se identificó con este material. Tampoco se identificó en las otras bases relevadas. | N817: Pendiente de valorización | P817: =IF(O817="","",O817*MAX(I817,J817)) | Q817: Pendiente | R817: Sin decidir
A818: 1850 | B818: Neuquén | C818: Descartable | D818: 2000036 | E818: TENSIOMETRO PEDIATRICO | I818: 0 | J818: 0 | M818: Ningún ítem del inventario físico de esta base se identificó con este material. Tampoco se identificó en las otras bases relevadas. Atención: aparece como posible equivalencia en un caso pendiente de revisión. Conviene resolver ese caso antes de proponer la baja. | N818: Pendiente de valorización | P818: =IF(O818="","",O818*MAX(I818,J818)) | Q818: Pendiente | R818: Sin decidir
A819: 1851 | B819: Neuquén | C819: Descartable | D819: 2000044 | E819: AGUJA PERICRANEAL 21G T/BUTTERFLY | I819: 0 | J819: 0 | M819: Ningún ítem del inventario físico de esta base se identificó con este material. Tampoco se identificó en las otras bases relevadas. | N819: Pendiente de valorización | P819: =IF(O819="","",O819*MAX(I819,J819)) | Q819: Pendiente | R819: Sin decidir
... A829: 1861 | B829: Neuquén | C829: Descartable | D829: 2000901 | E829: GASA ESTERIL 20X20CM | I829: 0 | J829: 0 | M829: Ningún ítem del inventario físico de esta base se identificó con este material. Tampoco se identificó en las otras bases relevadas. | N829: Pendiente de valorización | P829: =IF(O829="","",O829*MAX(I829,J829)) | Q829: Pendiente | R829: Sin decidir
A830: 1864 | B830: Salta | C830: Medicamento | D830: 1000722 | E830: CARAMELOS ANTI FECOFAR | I830: 0 | J830: 1503 | M830: Ningún ítem del inventario físico de esta base se identificó con este material. Tampoco se identificó en las otras bases relevadas. | N830: Pendiente de valorización | O830: 212.75 | P830: =IF(O830="","",O830*MAX(I830,J830)) | Q830: Pendiente | R830: Sin decidir
A831: 1865 | B831: Salta | C831: Medicamento | D831: 1000373 | E831: DICLOFENAC 50MG COMPRIMIDO | I831: 0 | J831: 405 | M831: Ningún ítem del inventario físico de esta base se identificó con este material. Tampoco se identificó en las otras bases relevadas. Atención: aparece como posible equivalencia en un caso pendiente de revisión. Conviene resolver ese caso antes de proponer la baja. | N831: Pendiente de valorización | O831: 22.489309 | P831: =IF(O831="","",O831*MAX(I831,J831)) | Q831: Pendiente | R831: Sin decidir
A832: 1866 | B832: Salta | C832: Medicamento | D832: 1005273 | E832: DEXALERGIN 10MG COMP | I832: 0 | J832: 200 | M832: Ningún ítem del inventario físico de esta base se identificó con este material. Tampoco se identificó en las otras bases relevadas. | N832: Pendiente de valorización | O832: 73.6 | P832: =IF(O832="","",O832*MAX(I832,J832)) | Q832: Pendiente | R832: Sin decidir
A833: 1867 | B833: Salta | C833: Medicamento | D833: 1005334 | E833: LORATADINA 2 MG COMP | I833: 0 | J833: 200 | M833: Ningún ítem del inventario físico de esta base se identificó con este material. Tampoco se identificó en las otras bases relevadas. | N833: Pendiente de valorización | O833: 48.31 | P833: =IF(O833="","",O833*MAX(I833,J833)) | Q833: Pendiente | R833: Sin decidir
A834: 1868 | B834: Salta | C834: Medicamento | D834: 1001231 | E834: HIOSCINA 20 MG AMP cjax100 | I834: 0 | J834: 100 | M834: Ningún ítem del inventario físico de esta base se identificó con este material. Tampoco se identificó en las otras bases relevadas. Atención: aparece como posible equivalencia en un caso pendiente de revisión. Conviene resolver ese caso antes de proponer la baja. | N834: Pendiente de valorización | O834: 567.6 | P834: =IF(O834="","",O834*MAX(I834,J834)) | Q834: Pendiente | R834: Sin decidir
A835: 1869 | B835: Salta | C835: Descartable | D835: 2001334 | E835: TELA ADHE MICROPOROSA HIPOALER 5CM | I835: 0 | J835: 72 | M835: Ningún ítem del inventario físico de esta base se identificó con este material. Tampoco se identificó en las otras bases relevadas. | N835: Pendiente de valorización | O835: 506.64778 | P835: =IF(O835="","",O835*MAX(I835,J835)) | Q835: Pendiente | R835: Sin decidir
A836: 1870 | B836: Salta | C836: Medicamento | D836: 1000571 | E836: ACEMUK 600MG | I836: 0 | J836: 60 | M836: Ningún ítem del inventario físico de esta base se identificó con este material. Tampoco se identificó en las otras bases relevadas. Atención: aparece como posible equivalencia en un caso pendiente de revisión. Conviene resolver ese caso antes de proponer la baja. | N836: Pendiente de valorización | O836: 1146.7 | P836: =IF(O836="","",O836*MAX(I836,J836)) | Q836: Pendiente | R836: Sin decidir
A837: 1871 | B837: Salta | C837: Medicamento | D837: 1000484 | E837: PENICILINA G BENZATINICA 2.400.000 U.I | I837: 0 | J837: 75 | M837: Ningún ítem del inventario físico de esta base se identificó con este material. Tampoco se identificó en las otras bases relevadas. Atención: aparece como posible equivalencia en un caso pendiente de revisión. Conviene resolver ese caso antes de proponer la baja. | N837: Pendiente de valorización | O837: 3853.9467 | P837: =IF(O837="","",O837*MAX(I837,J837)) | Q837: Pendiente | R837: Sin decidir
A838: 1872 | B838: Salta | C838: Medicamento | D838: 1000635 | E838: TRAMADOL 50MG AMPOLLA | I838: 0 | J838: 50 | M838: Ningún ítem del inventario físico de esta base se identificó con este material. Tampoco se identificó en las otras bases relevadas. | N838: Pendiente de valorización | O838: 977.5 | P838: =IF(O838="","",O838*MAX(I838,J838)) | Q838: Pendiente | R838: Sin decidir
A839: 1873 | B839: Salta | C839: Medicamento | D839: 1001265 | E839: REPELENTE LOCION SPRAY 100ML | I839: 0 | J839: 50 | M839: Ningún ítem del inventario físico de esta base se identificó con este material. Tampoco se identificó en las otras bases relevadas. | N839: Pendiente de valorización | O839: 1151.24 | P839: =IF(O839="","",O839*MAX(I839,J839)) | Q839: Pendiente | R839: Sin decidir
A840: 1874 | B840: Salta | C840: Descartable | D840: 2001116 | E840: MICRONEBULIZADOR PEDIATRICO C/ MASC | I840: 0 | J840: 50 | M840: Ningún ítem del inventario físico de esta base se identificó con este material. Tampoco se identificó en las otras bases relevadas. | N840: Pendiente de valorización | O840: 1835.68 | P840: =IF(O840="","",O840*MAX(I840,J840)) | Q840: Pendiente | R840: Sin decidir
A841: 1875 | B841: Salta | C841: Descartable | D841: 2001853 | E841: JERINGA 60 ML PICO LUER SLIP | I841: 0 | J841: 50 | M841: Ningún ítem del inventario físico de esta base se identificó con este material. Tampoco se identificó en las otras bases relevadas. | N841: Pendiente de valorización | O841: 177.9618 | P841: =IF(O841="","",O841*MAX(I841,J841)) | Q841: Pendiente | R841: Sin decidir
... A898: 1990 | B898: Salta | C898: Descartable | D898: 2001450 | E898: TAMBOR DE ACERO INOXIDABLE | I898: 0 | J898: 1 | M898: Ningún ítem del inventario físico de esta base se identificó con este material. Tampoco se identificó en las otras bases relevadas. | N898: Pendiente de valorización | O898: 36756 | P898: =IF(O898="","",O898*MAX(I898,J898)) | Q898: Pendiente | R898: Sin decidir
A899: TOTAL | I899: =SUBTOTAL(109,I5:I898) | J899: =SUBTOTAL(109,J5:J898) | P899: =SUBTOTAL(109,P5:P898)

Sheet D A revisar
A1: Casos que requieren revisión
A2: Coincidencias parciales, diferencias de presentación, varios códigos posibles o nomenclatura insuficiente. No se resuelven automáticamente.
A4: Nº | B4: Base | C4: Tipo | D4: Código SAP | E4: Descripción en SAP | F4: Código inventario físico | G4: Nomenclatura del inventario físico | H4: Presentación | I4: Cantidad física · UNIDADES | J4: Stock SAP · UNIDADES | K4: Atributos verificados | L4: Confianza | M4: Justificación | N4: Estado de valorización | O4: VU de referencia SAP · $ | P4: Valor de referencia SAP · $ | Q4: Estado de revisión | R4: Decisión registrada | S4: Revisor | T4: Observaciones
A5: 5 | B5: San Juan | C5: Medicamento | E5: ACIDO ACETILSALICILICO 100MG | F5: MED4 | G5: Acido Acetil Salicílico Comp x 100 mg | H5: concentración 100 mg · forma comprimido | I5: 100 | J5: 0 | K5: concentración | M5: Candidato 1001237 «ACIDO ACETILSALICILICO 100MG». Denominación: 62% del nombre del inventario explicado por el texto de SAP y 94% a la inversa. Atributos verificados: concentración. La coincidencia de denominación no alcanza para dar la identificación por confirmada. | N5: Pendiente de valorización | P5: =IF(O5="","",O5*MAX(I5,J5)) | Q5: Pendiente | R5: Sin decidir
A6: 20 | B6: San Juan | C6: Medicamento | F6: MED186 | G6: amiodarona 200mg comp | H6: concentración 200 mg · forma comprimido | I6: 20 | J6: 0 | M6: El candidato más parecido es 1000005 «AMIODARONA 150MG AMPOLLA DE 3 ML INYEC», pero difiere en concentración, forma farmacéutica. No se asigna el código: una diferencia de presentación significa que no es el mismo material. | N6: Pendiente de valorización | P6: =IF(O6="","",O6*MAX(I6,J6)) | Q6: Pendiente | R6: Sin decidir
A7: 21 | B7: San Juan | C7: Medicamento | F7: MED14 | G7: Amoxicilina + Clavulanato Comp x 1 mg | H7: concentración 1 mg · forma comprimido | I7: 371 | J7: 0 | M7: El candidato más parecido es 1005299 «AMOXICILINA +AC. CLAVULONICO 1GR COMP», pero difiere en concentración. No se asigna el código: una diferencia de presentación significa que no es el mismo material. | N7: Pendiente de valorización | P7: =IF(O7="","",O7*MAX(I7,J7)) | Q7: Pendiente | R7: Sin decidir
A8: 22 | B8: San Juan | C8: Medicamento | F8: MED156 | G8: Antigripal comp | H8: forma comprimido | I8: 60 | J8: 0 | K8: forma farmacéutica | M8: Candidato 1001216 «TAVINEX ANTIGRIPAL COMP.». Denominación: 100% del nombre del inventario explicado por el texto de SAP y 48% a la inversa. Atributos verificados: forma farmacéutica. Pero 1001297 «PULMONIX ANTIGRIP 20 COMP» es igual de plausible. Hay que elegir cuál corresponde. | N8: Pendiente de valorización | P8: =IF(O8="","",O8*MAX(I8,J8)) | Q8: Pendiente | R8: Sin decidir
A9: 23 | B9: San Juan | C9: Descartable | E9: APOSITO NO ESTERIL (G+A) 10X20CM | F9: DESC21 | G9: Apositos estériles | I9: 160 | J9: 0 | M9: Candidato 2000095 «APOSITO NO ESTERIL (G+A) 10X20CM». Denominación: 52% del nombre del inventario explicado por el texto de SAP y 42% a la inversa. Sap declara la presentación y el inventario físico no, así que la equivalencia no puede confirmarse con la información disponible. | N9: Pendiente de valorización | P9: =IF(O9="","",O9*MAX(I9,J9)) | Q9: Pendiente | R9: Sin decidir
A10: 26 | B10: San Juan | C10: Descartable | E10: BAJALENGUAS DE MADERA | F10: DESC22 | G10: Bajalenguas x 1 ud | I10: 1800 | J10: 0 | M10: Candidato 2000011 «BAJALENGUAS DE MADERA». Denominación: 100% del nombre del inventario explicado por el texto de SAP y 48% a la inversa. La coincidencia de denominación no alcanza para dar la identificación por confirmada. | N10: Pendiente de valorización | P10: =IF(O10="","",O10*MAX(I10,J10)) | Q10: Pendiente | R10: Sin decidir
A11: 27 | B11: San Juan | C11: Descartable | E11: VALVULA ESPIRATORIA | F11: DESC24 | G11: Barbijos N95 c/válvula | I11: 10 | J11: 0 | M11: Candidato 2001024 «VALVULA ESPIRATORIA». Denominación: 33% del nombre del inventario explicado por el texto de SAP y 48% a la inversa. La coincidencia de denominación no alcanza para dar la identificación por confirmada. | N11: Pendiente de valorización | P11: =IF(O11="","",O11*MAX(I11,J11)) | Q11: Pendiente | R11: Sin decidir
A12: 28 | B12: San Juan | C12: Descartable | E12: TIJERA QUIRURGICA | F12: DESC25 | G12: Barbijos quirúrgicos x 1 ud | I12: 350 | J12: 0 | M12: Candidato 2001378 «TIJERA QUIRURGICA». Denominación: 46% del nombre del inventario explicado por el texto de SAP y 47% a la inversa. La coincidencia de denominación no alcanza para dar la identificación por confirmada. | N12: Pendiente de valorización | P12: =IF(O12="","",O12*MAX(I12,J12)) | Q12: Pendiente | R12: Sin decidir
A13: 29 | B13: San Juan | C13: Descartable | E13: BOLSA COLECTORA DE ORINA X 2000 ML | F13: DESC26 | G13: Bolsa Colectora de orina T/K-207 | H13: modelo K207 | I13: 3 | J13: 0 | M13: Candidato 2000100 «BOLSA COLECTORA DE ORINA X 2000 ML». Denominación: 100% del nombre del inventario explicado por el texto de SAP y 100% a la inversa. El inventario físico declara la presentación y SAP no, así que la equivalencia no puede confirmarse con la información disponible. | N13: Pendiente de valorización | P13: =IF(O13="","",O13*MAX(I13,J13)) | Q13: Pendiente | R13: Sin decidir
A14: 30 | B14: San Juan | C14: Descartable | E14: MASCARA PARA O2 ADULTO CON RESERVORIO | F14: DESC27 | G14: Bolsa de Resucitación manual (tipo Ambú) con reservorio adulto | H14: población adulto | I14: 6 | J14: 0 | K14: población | M14: Candidato 2000363 «MASCARA PARA O2 ADULTO CON RESERVORIO». Denominación: 39% del nombre del inventario explicado por el texto de SAP y 68% a la inversa. Atributos verificados: población. La coincidencia de denominación no alcanza para dar la identificación por confirmada. | N14: Pendiente de valorización | P14: =IF(O14="","",O14*MAX(I14,J14)) | Q14: Pendiente | R14: Sin decidir
A15: 31 | B15: San Juan | C15: Descartable | E15: BRAZALETE ADULTO | F15: DESC285 | G15: Brazalete para Tensiómetro | I15: 2 | J15: 0 | M15: Candidato 2001483 «BRAZALETE ADULTO». Denominación: 54% del nombre del inventario explicado por el texto de SAP y 59% a la inversa. Sap declara la presentación y el inventario físico no, así que la equivalencia no puede confirmarse con la información disponible. | N15: Pendiente de valorización | P15: =IF(O15="","",O15*MAX(I15,J15)) | Q15: Pendiente | R15: Sin decidir
A16: 34 | B16: San Juan | C16: Descartable | E16: CANULA NASAL O2T SIL 100% COD 230-09 PED | F16: DESC36 | G16: Canula nasal | I16: 1316 | J16: 0 | M16: Candidato 2000103 «CANULA NASAL O2T SIL 100% COD 230-09 PED». Denominación: 100% del nombre del inventario explicado por el texto de SAP y 30% a la inversa. Sap declara la presentación y el inventario físico no, así que la equivalencia no puede confirmarse con la información disponible. | N16: Pendiente de valorización | P16: =IF(O16="","",O16*MAX(I16,J16)) | Q16: Pendiente | R16: Sin decidir
A17: 35 | B17: San Juan | C17: Descartable | E17: KIT CANULAS OROFARINGEAS (TUBOS DE MAYO) | F17: DESC280 | G17: Canula Orofaringea N° 8 | H17: calibre N° 8 | I17: 3 | J17: 0 | M17: Candidato 2000659 «KIT CANULAS OROFARINGEAS (TUBOS DE MAYO)». Denominación: 90% del nombre del inventario explicado por el texto de SAP y 63% a la inversa. El inventario físico declara la presentación y SAP no, así que la equivalencia no puede confirmarse con la información disponible. | N17: Pendiente de valorización | P17: =IF(O17="","",O17*MAX(I17,J17)) | Q17: Pendiente | R17: Sin decidir
A18: 36 | B18: San Juan | C18: Medicamento | E18: PULMONIX ANTIGRIP 20 COMP | F18: MED30 | G18: Caramelos antigripales con benzocaina 20.7mg | H18: concentración 20,7 mg | I18: 351 | J18: 0 | M18: Candidato 1001297 «PULMONIX ANTIGRIP 20 COMP». Denominación: 31% del nombre del inventario explicado por el texto de SAP y 45% a la inversa. El inventario físico declara la presentación y SAP no, así que la equivalencia no puede confirmarse con la información disponible. | N18: Pendiente de valorización | P18: =IF(O18="","",O18*MAX(I18,J18)) | Q18: Pendiente | R18: Sin decidir
A19: 37 | B19: San Juan | C19: Descartable | E19: ANTIPARRA DE PLASTICO | F19: DESC281 | G19: Chata Plástica | I19: 5 | J19: 0 | M19: Candidato 2000010 «ANTIPARRA DE PLASTICO». Denominación: 45% del nombre del inventario explicado por el texto de SAP y 45% a la inversa. La coincidencia de denominación no alcanza para dar la identificación por confirmada. | N19: Pendiente de valorización | P19: =IF(O19="","",O19*MAX(I19,J19)) | Q19: Pendiente | R19: Sin decidir
A20: 40 | B20: San Juan | C20: Medicamento | E20: DEXAMETASONA 8MG/2ML AMP(DESCONTINUADO) | F20: MED35 | G20: Ciprofloxacina + Dexametasona 0,1% / 0,03 % Gotas oftal x 5ml | H20: concentración 0,03%, 0,1% · forma gotas · volumen 5 ml | I20: 3 | J20: 0 | K20: forma farmacéutica | M20: Candidato 1000478 «DEXAMETASONA 8MG/2ML AMP(DESCONTINUADO)». Denominación: 27% del nombre del inventario explicado por el texto de SAP y 100% a la inversa. Atributos verificados: forma farmacéutica. La coincidencia de denominación no alcanza para dar la identificación por confirmada. | N20: Pendiente de valorización | P20: =IF(O20="","",O20*MAX(I20,J20)) | Q20: Pendiente | R20: Sin decidir
A21: 42 | B21: San Juan | C21: Medicamento | F21: MED40 | G21: Clindamicina 300 mg (FM) comp | H21: concentración 300 mg · forma comprimido | I21: 4 | J21: 0 | M21: El candidato más parecido es 1000567 «CLINDAMICINA 100MG», pero difiere en concentración. No se asigna el código: una diferencia de presentación significa que no es el mismo material. | N21: Pendiente de valorización | P21: =IF(O21="","",O21*MAX(I21,J21)) | Q21: Pendiente | R21: Sin decidir
A22: 43 | B22: San Juan | C22: Descartable | E22: REGULADOR DE FLUJO | F22: DESC50 | G22: Collar regulable | I22: 1 | J22: 0 | M22: Candidato 2001234 «REGULADOR DE FLUJO». Denominación: 50% del nombre del inventario explicado por el texto de SAP y 42% a la inversa. La coincidencia de denominación no alcanza para dar la identificación por confirmada. | N22: Pendiente de valorización | P22: =IF(O22="","",O22*MAX(I22,J22)) | Q22: Pendiente | R22: Sin decidir
A23: 44 | B23: San Juan | C23: Descartable | E23: CURITAS TELA ELASTICA | F23: DESC52 | G23: Curitas x 1 ud | I23: 192 | J23: 0 | M23: Candidato 2000532 «CURITAS TELA ELASTICA». Denominación: 100% del nombre del inventario explicado por el texto de SAP y 36% a la inversa. La coincidencia de denominación no alcanza para dar la identificación por confirmada. | N23: Pendiente de valorización | P23: =IF(O23="","",O23*MAX(I23,J23)) | Q23: Pendiente | R23: Sin decidir
A24: 45 | B24: San Juan | C24: Descartable | E24: DESCARTADOR GRANDE MODELO E7 | F24: DESC54 | G24: Descartador Grande | I24: 4 | J24: 0 | M24: Candidato 2001114 «DESCARTADOR GRANDE MODELO E7». Denominación: 100% del nombre del inventario explicado por el texto de SAP y 63% a la inversa. La coincidencia de denominación no alcanza para dar la identificación por confirmada. | N24: Pendiente de valorización | P24: =IF(O24="","",O24*MAX(I24,J24)) | Q24: Pendiente | R24: Sin decidir
A25: 46 | B25: San Juan | C25: Medicamento | F25: MED55 | G25: Dexametasona 8mg Amp x 2 ml | H25: concentración 8 mg · forma ampolla · volumen 2 ml | I25: 100 | J25: 0 | K25: forma farmacéutica | M25: Candidato 1000478 «DEXAMETASONA 8MG/2ML AMP(DESCONTINUADO)». Denominación: 100% del nombre del inventario explicado por el texto de SAP y 100% a la inversa. Atributos verificados: forma farmacéutica. Pero 1000094 «DEXAMETASONA INY 4MG/ML AMPOLLA» es igual de plausible. Hay que elegir cuál corresponde. | N25: Pendiente de valorización | P25: =IF(O25="","",O25*MAX(I25,J25)) | Q25: Pendiente | R25: Sin decidir
